Workbook

Sheet BITACORA
A1: RECEPCION Y CONTROL: MADERA EN TUCO
A3: FECHA DE PARTIDA | B3: FECHA DE RECEPCION EN PLANTA | C3: PLACA | D3: RESPONSABLE | E3: PUNTO DE PARTIDA | F3: DETALLE | G3: ID | H3: ESTIMADO (TICKET) | I3: DATO REAL (DATO ASERRADO) | J3: PRECIO $ (VALOR A PAGAR) | K3: COSTO $ | L3: SALDO | M3: ESTADO $ | N3: OBSERVACION
A4: 44321 | B4: 44321 | C4: HBA0270 | D4: ANAGUANO GALARRAGA FAUSTO | E4: VARIOS | F4: PROVEEDOR | G4: 1 | I4: 110 | J4: 100 | K4: 0.90909091 | L4: 0 | M4: CANCELADO | N4: 27 TUCOS EN CAMIONETA
A5: 44321 | B5: 44321 | C5: XBE343 | D5: BRAVO BRAVO MILTON GABRIEL | E5: VARIOS | F5: PROVEEDOR | G5: 2 | I5: 320 | J5: 200 | K5: 0.625 | L5: 0 | M5: CANCELADO | N5: CAMIONETADA COMPRADA EN $200 PAGO EN EFECTIVO
A6: 44321 | B6: 44321 | C6: HBC6496 | D6: VELIZ ZAMBRANO JAIME GREGORIO | E6: RIO FRIO | F6: BOSQUE | G6: 3 | I6: 83 | J6: 0 | K6: 0 | L6: 0 | N6: 13 TUCOS GRUESOS EN BUEN ESTADO Y UNO FINO. Completado con madera aserrada.
A7: 44323 | B7: 44323 | C7: NBF0031 | D7: VELIZ ZAMBRANO JAIME GREGORIO | E7: RIO FRIO | F7: BOSQUE | G7: 4 | I7: 3090 | J7: 0 | K7: 0 | L7: 0 | N7: 5 FILAS. LAS ULTIMAS FILAS NO VINIERON COMPLETAS. PERO BUEN GROSOR, POCA MADERA FINA
A8: 44322 | B8: 44322 | C8: NBF0031 | D8: VELIZ ZAMBRANO JAIME GREGORIO | E8: RIO FRIO | F8: BOSQUE | G8: 5 | I8: 3385 | J8: 0 | K8: 0 | L8: 0 | N8: 5 FILAS COMPLETAS HASTA ARRIBA. MADERA DE BUEN GROSOR. ULTIMA FILA CON MADERA UN POCO MAS FINA.
A9: 44323 | B9: 44323 | C9: HBC6496 | D9: VELIZ ZAMBRANO JAIME GREGORIO | E9: RIO FRIO | F9: BOSQUE | G9: 6 | I9: 1125 | J9: 0 | K9: 0 | L9: 0 | N9: 2 CAMIONETADAS
A10: 44323 | B10: 44323 | C10: PPA1778 | D10: VELIZ ZAMBRANO JAIME GREGORIO | E10: RIO FRIO | F10: BOSQUE | G10: 7 | I10: 407 | J10: 0 | K10: 0 | L10: 0 | N10: CAMIONETADA V6
A11: 44323 | B11: 44323 | C11: PPA1778 | D11: VELIZ ZAMBRANO JAIME GREGORIO | E11: RIO FRIO | F11: BOSQUE | G11: 8 | I11: 408 | J11: 0 | K11: 0 | L11: 0 | N11: CAMIONETADA V6
A12: 44323 | B12: 44323 | C12: NBF0031 | D12: VELIZ ZAMBRANO JAIME GREGORIO | E12: RIO FRIO | F12: BOSQUE | G12: 9 | I12: 1505 | J12: 0 | K12: 0 | L12: 0 | N12: POCA MADERA
A13: 44323 | B13: 44323 | C13: HBA0270 | D13: VELIZ ZAMBRANO JAIME GREGORIO | E13: RIO FRIO | F13: BOSQUE | G13: 10 | I13: 481 | J13: 0 | K13: 0 | L13: 0 | N13: CAMIONETADA V6
A14: 44326 | B14: 44326 | C14: PPA1778 | D14: VELIZ ZAMBRANO JAIME GREGORIO | E14: RIO FRIO | F14: BOSQUE | G14: 11 | I14: 478 | J14: 0 | K14: 0 | L14: 0 | N14: CAMIONETADA V6
A15: 44327 | B15: 44327 | C15: HBC6496 | D15: VELIZ ZAMBRANO JAIME GREGORIO | E15: RIO FRIO | F15: BOSQUE | G15: 13 | I15: 484 | J15: 0 | K15: 0 | L15: 0 | N15: CAMIONETADA V6
A16: 44327 | B16: 44327 | C16: RBA9146 | D16: VELIZ ZAMBRANO JAIME GREGORIO | E16: RIO FRIO | F16: BOSQUE | G16: 14 | I16: 410 | J16: 0 | K16: 0 | L16: 0 | N16: VAMIONETADA V6
A17: 44327 | B17: 44327 | C17: PPA1778 | D17: VELIZ ZAMBRANO JAIME GREGORIO | E17: RIO FRIO | F17: BOSQUE | G17: 15 | I17: 369 | J17: 0 | K17: 0 | L17: 0 | N17: CAMIONETADA MADERA LARGA
... A19: 44327 | B19: 44327 | C19: HBC6496 | D19: VELIZ ZAMBRANO JAIME GREGORIO | E19: RIO FRIO | F19: BOSQUE | G19: 17 | I19: 408 | J19: 0 | K19: 0 | L19: 0 | N19: VAMIONETADA V6
A20: 44327 | B20: 44327 | C20: PVL0706 | D20: AGUILAR ALVARES PATRICIO ESTUARDO | E20: VARIOS | F20: PROVEEDOR | G20: 18 | H20: 3600 | I20: 3522 | J20: 3000 | K20: 0.85178876 | L20: 0 | M20: CANCELADO | N20: GH 5 FILAS. MADERA GRUESA, PERO CON GRAN PORCENTAJE DE MADERA PESADA.
A21: 44327 | B21: 44327 | C21: PFB0399 | D21: VELIZ ZAMBRANO JAIME GREGORIO | E21: RIO FRIO | F21: BOSQUE | G21: 19 | I21: 401 | J21: 0 | K21: 0 | L21: 0 | N21: VAMIONETADA V6
A22: 44328 | B22: 44328 | D22: MADERA DE PLANTA | E22: FINCA EN PLANTA | F22: FINCA | G22: 20 | I22: 33 | J22: 0 | K22: 0 | L22: 0 | N22: 1 PATA TRAS PARQUEADERO
A23: 44328 | B23: 44328 | C23: NBF0031 | D23: VELIZ ZAMBRANO JAIME GREGORIO | E23: RIO FRIO | F23: BOSQUE | G23: 21 | I23: 2290 | J23: 0 | K23: 0 | L23: 0
A24: 44328 | B24: 44328 | C24: HGC420 | D24: MENDOZA GUARDERAS JORGE MANUEL | E24: VARIOS | F24: PROVEEDOR | G24: 22 | I24: 300 | J24: 225 | K24: 0.75 | L24: 0 | M24: CANCELADO | N24: CAMIONETADA
A25: 44330 | B25: 44330 | C25: PVL602 | D25: OLGUIN QUINATOA JAVIER ANTONIO | E25: VARIOS | F25: PROVEEDOR | G25: 23 | I25: 1205 | J25: 870 | K25: 0.7219917 | L25: 0 | M25: CANCELADO | N25: 4 FILAS MADERA 60% FINA 40% PROMEDIO PAGADO CON CHEQUE
A26: 44330 | B26: 44330 | C26: PBS1430 | D26: DOMINGUEZ CHIRIBOGA JORGE VICENTE | E26: VARIOS | F26: PROVEEDOR | G26: 24 | I26: 2061 | J26: 1400 | K26: 0.6792819 | L26: 0 | M26: CANCELADO | N26: VOLQUETA 4 FILAS. 20% MADERA FINA 80% MADERA PROMEDIO GRUESA PERO EN BUENE STADO
A27: 44330 | B27: 44330 | C27: PVH243 | D27: NAPA CAICEDO HENRRY JULIAN | E27: VARIOS | F27: PROVEEDOR | G27: 25 | I27: 65 | J27: 45 | K27: 0.69230769 | L27: 0 | M27: CANCELADO | N27: TROOPER CON 35 TUCOS MEDIANOS. PAGADOS EN EFECTIVO
A28: 44330 | B28: 44330 | C28: PVL602 | D28: OLGUIN QUINATOA JAVIER ANTONIO | E28: VARIOS | F28: PROVEEDOR | G28: 26 | I28: 1677 | J28: 870 | K28: 0.51878354 | L28: 0 | M28: CANCELADO | N28: 4 FILAS MADERA 70% FINA 30% PROMEDIO
A29: 44332 | B29: 44332 | C29: PBI0064 | D29: APOLO DIAS SEGUNDO PETER | E29: VARIOS | F29: PROVEEDOR | G29: 27 | I29: 2464 | J29: 2100 | K29: 0.85227273 | L29: 0 | M29: CANCELADO | N29: FC 4 FILAS MADERA GRUESA, 80 % LIVIANA
A30: 44332 | B30: 44332 | C30: PQF0935 | D30: APOLO DIAS SEGUNDO PETER | E30: VARIOS | F30: PROVEEDOR | G30: 28 | I30: 2314 | J30: 2100 | K30: 0.90751945 | L30: 0 | M30: CANCELADO | N30: FC 4 FILAS MADERA GRUESA, 80 % LIVIANA
A31: 44333 | B31: 44333 | C31: PLV602 | D31: OLGUIN QUINATOA JAVIER ANTONIO | E31: VARIOS | F31: PROVEEDOR | G31: 29 | I31: 941 | J31: 600 | K31: 0.63761955 | L31: 0 | M31: CANCELADO | N31: 3 FILAS 80% MADERA FINA
A32: 44333 | B32: 44333 | C32: PCP5161 | D32: MENDOZA GUARDERAS JORGE MANUEL | E32: VARIOS | F32: PROVEEDOR | G32: 30 | H32: 350 | I32: 316 | J32: 245 | K32: 0.77531646 | L32: 0 | M32: CANCELADO | N32: CAMIONETADA
A33: 44333 | B33: 44333 | C33: PPA1778 | D33: MENDOZA GUARDERAS JORGE MANUEL | E33: VARIOS | F33: PROVEEDOR | G33: 31 | H33: 350 | I33: 251 | J33: 195 | K33: 0.77689243 | L33: 0 | M33: CANCELADO | N33: CAMIONETADA
A34: 44334 | B34: 44334 | C34: PCP5161 | D34: MENDOZA GUARDERAS JORGE MANUEL | E34: VARIOS | F34: PROVEEDOR | G34: 32 | H34: 350 | I34: 244 | J34: 190 | K34: 0.77868852 | L34: 0 | M34: CANCELADO | N34: CAMIONETADA
A35: 44334 | B35: 44334 | C35: PPA1778 | D35: MENDOZA GUARDERAS JORGE MANUEL | E35: VARIOS | F35: PROVEEDOR | G35: 33 | H35: 350 | I35: 344 | J35: 268 | K35: 0.77906977 | L35: 0 | M35: CANCELADO | N35: CAMIONETADA
A36: 44334 | B36: 44334 | C36: PPA1778 | D36: MENDOZA GUARDERAS JORGE MANUEL | E36: VARIOS | F36: PROVEEDOR | G36: 34 | H36: 350 | I36: 125 | J36: 95 | K36: 0.76 | L36: 0 | M36: CANCELADO | N36: POCOS TUCOS
A37: 44334 | B37: 44334 | C37: PBI0064 | D37: APOLO DIAS SEGUNDO PETER | E37: VARIOS | F37: PROVEEDOR | G37: 35 | I37: 2586 | J37: 2100 | K37: 0.81206497 | L37: 0 | M37: CANCELADO | N37: FC 4 FILAS MADERA GRUESA, 80 % LIVIANA
A38: 44334 | B38: 44334 | C38: PQX0247 | D38: APOLO DIAS SEGUNDO PETER | E38: VARIOS | F38: PROVEEDOR | G38: 36 | I38: 3051 | J38: 2590 | K38: 0.848902 | L38: 0 | M38: CANCELADO | N38: GD 4 FILAS MAS RELLLENO POSTERIOR DE 12 TUCOS MADERA GRUESA 75% LIVIANA
A39: 44335 | B39: 44335 | C39: NBF0031 | D39: COBEÑA QUINTERO RICARDO | E39: RIO FRIO ETAPA 2 | F39: BOSQUE | G39: 37 | I39: 3115 | J39: 0 | K39: 0 | L39: 0 | N39: 5 FILAS COMPLETAS HASTA ARRIBA. MADERA DE BUEN GROSOR.
A40: 44335 | B40: 44335 | C40: HBC6496 | D40: COBEÑA QUINTERO RICARDO | E40: RIO FRIO ETAPA 2 | F40: BOSQUE | G40: 38 | H40: 250 | I40: 1144 | J40: 0 | K40: 0 | L40: 0 | N40: 3 CAMIONETADAS
A41: 44335 | B41: 44335 | C41: MPA1139 | D41: BRAVO SOLORZANO ANIBAL ORLEY | E41: VARIOS | F41: PROVEEDOR | G41: 39 | H41: 180 | I41: 247 | J41: 200 | K41: 0.8097166 | L41: 200 | M41: PENDIENTE | N41: CAMIONETADA COMPRADA EN PLANTA CON 85% DE MADERA FINA
A42: 44335 | B42: 44335 | C42: OBT260 | D42: OLMEDO VELEZ LIWINTONG AUGUSTO | E42: VARIOS | F42: PROVEEDOR | G42: 40 | H42: 80 | I42: 103 | J42: 50 | K42: 0.48543689 | L42: 0 | M42: CANCELADO | N42: 16 TUCOS DE 3 PALMOS
A43: 44335 | B43: 44335 | C43: RBA9146 | D43: COBEÑA QUINTERO RICARDO | E43: RIO FRIO ETAPA 2 | F43: BOSQUE | G43: 41 | H43: 350 | I43: 428 | J43: 0 | K43: 0 | L43: 0 | N43: CAMIONETADA
A44: 44335 | B44: 44335 | C44: HBC6496 | D44: COBEÑA QUINTERO RICARDO | E44: RIO FRIO ETAPA 2 | F44: BOSQUE | G44: 42 | H44: 350 | I44: 425 | J44: 0 | K44: - | L44: 0 | N44: CAMIONETADA
A45: 44335 | B45: 44335 | C45: PJOO176 | D45: SARI UZHO GUILLERMO FRANCEL | E45: VARIOS | F45: PROVEEDOR | G45: 43 | H45: 1300 | I45: 1215 | J45: 1650 | K45: 1.3580247 | L45: 0 | M45: CANCELADO | N45: CAMION FC CON MADERA LARGA 60% MADERA GRUESA
A46: 44335 | B46: 44335 | C46: HBC6496 | D46: COBEÑA QUINTERO RICARDO | E46: RIO FRIO ETAPA 2 | F46: BOSQUE | G46: 44 | H46: 90 | I46: 219 | J46: 0 | K46: 0 | L46: 0 | N46: CAMIONETA CON 20 TUCOS DE BUEN GROSOR COMPLETADA CON MADERA ASERRADA
A47: 44335 | B47: 44335 | C47: PBI0064 | D47: APOLO DIAS SEGUNDO PETER | E47: VARIOS | F47: PROVEEDOR | G47: 45 | H47: 1900 | I47: 2586 | J47: 2100 | K47: 0.81206497 | L47: 0 | M47: CANCELADO | N47: FC 4 FILAS MADERA GRUESA, 80 % LIVIANA
A48: 44336 | B48: 44336 | C48: NBF0031 | D48: BASURTO SACON ANDRES FERNANDO | E48: TACHINA | F48: ACOPIO | G48: 46 | H48: 3000 | I48: 3297 | J48: 0 | K48: 0 | L48: 0 | N48: 5 FILAS COMPLETAS , 30% MADERA GURESA , LA PRIMERA FILA CASI EN SU MAYORIA VINO CON MADERA LARGA
A49: 44336 | B49: 44336 | C49: PJB0751 | D49: GONZALEZ DEMERA HOLGER ANTONIO | E49: VARIOS | F49: PROVEEDOR | G49: 47 | H49: 200 | I49: 341 | J49: 230 | K49: 0.6744868 | L49: 0 | M49: CANCELADO | N49: CAMIONETA COMPRADA EN PLANTA CON 50 % MADERA GRUESA
A50: 44337 | B50: 44337 | C50: JAA1395 | D50: APOLO DIAS SEGUNDO PETER | E50: VARIOS | F50: PROVEEDOR | G50: 55 | H50: 2300 | I50: 2252 | J50: 2100 | K50: 0.93250444 | L50: 0 | M50: CANCELADO | N50: FC DE 4 FILAS MADERA GRUESA UN 75% LIVIANA
A51: 44336 | B51: 44336 | C51: HBC6496 | D51: COBEÑA QUINTERO RICARDO | E51: RIO FRIO ETAPA 2 | F51: BOSQUE | G51: 49 | H51: 250 | I51: 386 | J51: 0 | K51: - | L51: 0 | N51: CAMIONETADA
A52: 44336 | B52: 44336 | C52: GLN358 | D52: COBEÑA QUINTERO RICARDO | E52: RIO FRIO ETAPA 2 | F52: BOSQUE | G52: 50 | H52: 250 | I52: 360 | J52: 0 | K52: - | L52: 0 | N52: CAMIONETADA
A53: 44336 | B53: 44336 | C53: HBC6496 | D53: COBEÑA QUINTERO RICARDO | E53: RIO FRIO ETAPA 2 | F53: BOSQUE | G53: 51 | H53: 250 | I53: 405 | J53: 0 | K53: - | L53: 0 | N53: CAMIONETADA
A54: 44338 | B54: 44338 | C54: PQK0247 | D54: APOLO DIAS SEGUNDO PETER | E54: VARIOS | F54: PROVEEDOR | G54: 62 | H54: 2500 | I54: 2533 | J54: 2400 | K54: 0.94749309 | L54: 0 | M54: CANCELADO | N54: GD 4 FILAS MADERA GRUESA 75% LIVIANA
A55: 44337 | B55: 44337 | C55: NBF0031 | D55: BASURTO SACON ANDRES FERNANDO | E55: TACHINA | F55: ACOPIO | G55: 53 | H55: 1900 | I55: 2456 | J55: 0 | K55: - | L55: 0 | N55: 2 FILAS DE MADERA LARGAR (2.60) Y LA MITAD DE UNA FILA CORTA (1.30) MADERA GRUESA UN 70%
A56: 44337 | B56: 44337 | C56: PIB0064 | D56: APOLO DIAS SEGUNDO PETER | E56: VARIOS | F56: PROVEEDOR | G56: 54 | H56: 2300 | I56: 2531 | J56: 2100 | K56: 0.82971158 | L56: 0 | M56: CANCELADO | N56: FC DE 4 FILAS MADERA GRUESA UN 80% LIVIANA
A57: 44339 | B57: 44339 | C57: PLU0117 | D57: APOLO DIAS SEGUNDO PETER | E57: VARIOS | F57: PROVEEDOR | G57: 73 | H57: 2300 | I57: 2350 | J57: 2100 | K57: 0.89361702 | L57: 0 | M57: CANCELADO | N57: 4 FILAS
A58: 44337 | B58: 44337 | C58: XBV236 | D58: SARANGO ROJAS HOMER ROMENL | E58: VARIOS | F58: PROVEEDOR | G58: 56 | H58: 1500 | I58: 1644 | J58: 1250 | K58: 0.76034063 | L58: 0 | M58: CANCELADO | N58: FC DE 4 FILAS NO COMPLETO CON UN 70% DE MADERA GRUESA
A59: 44337 | B59: 44337 | C59: HBC6496 | D59: COBEÑA QUINTERO RICARDO | E59: RIO FRIO ETAPA 2 | F59: BOSQUE | G59: 57 | H59: 850 | I59: 1468 | J59: 0 | K59: - | L59: 0 | N59: 3 CAMIONETADAS
A60: 44337 | B60: 44337 | C60: PIB9540 | D60: MACIAS MENDOZA DANIEL JOSE | E60: VARIOS | F60: PROVEEDOR | G60: 58 | H60: 650 | I60: 512 | J60: 550 | K60: 1.0742188 | L60: 0 | M60: CANCELADO | N60: 1 FILA COMPLETA DE MADERA Y LA MITAD DE OTRA . MADERA GRUESO UN 85% EN BUEN ESTADO
A61: 44337 | B61: 44337 | C61: HAA3807 | D61: APOLO DIAS SEGUNDO PETER | E61: VARIOS | F61: PROVEEDOR | G61: 59 | H61: 2300 | I61: 2626 | J61: 2100 | K61: 0.79969535 | L61: 0 | M61: CANCELADO | N61: FC DE 4 FILAS MADERA GRUESA UN 75% LIVIANA
A62: 44337 | B62: 44337 | C62: PBS1430 | D62: DOMINGUEZ CHIRIBOGA JORGE VICENTE | E62: VARIOS | F62: PROVEEDOR | G62: 60 | H62: 1600 | I62: 1741 | J62: 1300 | K62: 0.7466973 | L62: 0 | M62: CANCELADO | N62: VOLQUETA 4 FILAS. 35% MADERA FINA 65% MADERA PROMEDIO GRUESA PERO EN BUENE ESTADO
A63: 44338 | B63: 44338 | C63: PTG021 | D63: SOLORZANO VELEZ LUIS ANDRES | E63: VARIOS | F63: PROVEEDOR | G63: 61 | H63: 150 | I63: 165 | J63: 135 | K63: 0.81818182 | L63: 0 | M63: CANCELADO | N63: CAMIONETADA POR ASERRADA
A64: 44339 | B64: 44339 | C64: PQX0247 | D64: APOLO DIAS SEGUNDO PETER | E64: VARIOS | F64: PROVEEDOR | G64: 76 | H64: 2600 | I64: 2341 | J64: 2400 | K64: 1.0252029 | L64: 0 | M64: CANCELADO | N64: 4 FILAS
A65: 44338 | B65: 44338 | C65: RBA9146 | D65: MUENTES CORNEJO LUIS GONZAGA | E65: BOSQUE PUERTO NUEVO | F65: BOSQUE | G65: 63 | H65: 250 | I65: 439 | J65: 0 | K65: - | L65: 0 | N65: CAMIONETADA
A66: 44338 | B66: 44338 | C66: RBA9146 | D66: MUENTES CORNEJO LUIS GONZAGA | E66: BOSQUE PUERTO NUEVO | F66: BOSQUE | G66: 64 | H66: 250 | I66: 400 | J66: 0 | K66: - | L66: 0 | N66: CAMIONETADA
A67: 44338 | B67: 44338 | C67: PTG021 | D67: MUENTES CORNEJO LUIS GONZAGA | E67: BOSQUE PUERTO NUEVO | F67: BOSQUE | G67: 65 | H67: 250 | I67: 346 | J67: 0 | K67: - | L67: 0 | N67: CAMIONETADA
A68: 44338 | B68: 44338 | C68: HBC6496 | D68: MUENTES CORNEJO LUIS GONZAGA | E68: BOSQUE PUERTO NUEVO | F68: BOSQUE | G68: 66 | H68: 250 | I68: 440 | J68: 0 | K68: - | L68: 0 | N68: CAMIONETADA
A69: 44338 | B69: 44338 | C69: HBC6496 | D69: MUENTES CORNEJO LUIS GONZAGA | E69: BOSQUE PUERTO NUEVO | F69: BOSQUE | G69: 67 | H69: 250 | I69: 383 | J69: 0 | K69: - | L69: 0 | N69: CAMIONETADA
A70: 44338 | B70: 44338 | C70: MCW0186 | D70: ARIAS LARA MARCOS VINICIO | E70: TRES VIAS | F70: ACOPIO | G70: 68 | H70: 1500 | I70: 1794 | J70: 0 | K70: - | L70: 0 | N70: FC DE 4 FILAS COMPLETAS CON UN 80% DE MADERA FINA
A71: 44338 | B71: 44338 | C71: GLN358 | D71: COBEÑA QUINTERO RICARDO | E71: RIO FRIO ETAPA 2 | F71: BOSQUE | G71: 69 | H71: 250 | I71: 383 | J71: 0 | K71: - | L71: 0 | N71: CAMIONETADA
A72: 44340 | B72: 44340 | C72: PAC2557 | D72: APOLO DIAS SEGUNDO PETER | E72: VARIOS | F72: PROVEEDOR | G72: 83 | H72: 2600 | I72: 2513 | J72: 2400 | K72: 0.95503382 | L72: 0 | M72: CANCELADO | N72: GD DE 4 FILAS
A73: 44338 | B73: 44338 | C73: RBA9146 | D73: MUENTES CORNEJO LUIS GONZAGA | E73: BOSQUE PUERTO NUEVO | F73: BOSQUE | G73: 71 | H73: 250 | I73: 432 | J73: 0 | K73: - | L73: 0 | N73: CAMIONETADA
A74: 44338 | B74: 44338 | C74: PTG021 | D74: MUENTES CORNEJO LUIS GONZAGA | E74: BOSQUE PUERTO NUEVO | F74: BOSQUE | G74: 72 | H74: 250 | I74: 402 | J74: 0 | K74: 0 | L74: 0 | N74: CAMIONETADA
A75: 44341 | B75: 44341 | C75: PIB0064 | D75: APOLO DIAS SEGUNDO PETER | E75: VARIOS | F75: PROVEEDOR | G75: 94 | I75: 2135 | J75: 2100 | K75: 0.98360656 | L75: 0 | M75: CANCELADO | N75: FC 4 FILAS MADERA DE BUEN GROSOR PROVENIENTE DEL PUYO
A76: 44339 | B76: 44339 | C76: MBA2960 | D76: MOLINA LOZADA JONTHAN FERNANDO | E76: VARIOS | F76: PROVEEDOR | G76: 74 | H76: 3800 | I76: 3531 | J76: 3750 | K76: 1.0620221 | L76: 0 | M76: CANCELADO | N76: 6 FILAS MADERA PROMEDIO FINA.
A77: 44339 | B77: 44339 | C77: HBC6496 | D77: COBEÑA QUINTERO RICARDO | E77: RIO FRIO ETAPA 2 | F77: BOSQUE | G77: 75 | H77: 1000 | I77: 1128 | J77: 0 | K77: 0 | L77: 0 | N77: 3 CAMIONETADAS
A78: 44342 | B78: 44342 | C78: PQK0247 | D78: APOLO DIAS SEGUNDO PETER | E78: VARIOS | F78: PROVEEDOR | G78: 100 | I78: 2676 | J78: 2400 | K78: 0.89686099 | L78: 0 | M78: CANCELADO | N78: GD CON MADERA DE BUEN GROSOR PROVENIENTE DE EL PUYO
A79: 44344 | B79: 44344 | C79: PQX0247 | D79: APOLO DIAS SEGUNDO PETER | E79: VARIOS | F79: PROVEEDOR | G79: 117 | H79: 2500 | I79: 2532 | J79: 2400 | K79: 0.9478673 | L79: 0 | M79: CANCELADO | N79: GD 4 FILAS
A80: 44345 | B80: 44345 | C80: HAA3807 | D80: APOLO DIAS SEGUNDO PETER | E80: VARIOS | F80: PROVEEDOR | G80: 123 | H80: 2200 | I80: 2136 | J80: 2100 | K80: 0.98314607 | L80: 0 | M80: CANCELADO | N80: FC 4 FILAS MADERA EN BUEN ESTADO
A81: 44340 | B81: 44340 | C81: TAL0556 | D81: BASURTO SACON ANDRES FERNANDO | E81: TACHINA | F81: ACOPIO | G81: 79 | H81: 2000 | I81: 2213 | J81: 0 | K81: - | L81: 0 | N81: 5 FILAS, 85% MADERA LARGA, MADERA PROMEDIO.
A82: 44340 | B82: 44340 | C82: PIB0552 | D82: JIMENEZ FERNANDEZ ITALO PATROCIÑO | E82: VARIOS | F82: PROVEEDOR | G82: 80 | H82: 3000 | I82: 3155 | J82: 2750 | K82: 0.87163233 | L82: 0 | M82: CANCELADO | N82: 5 FILAS , MADERA 80% GRUESA
A83: 44338 | B83: 44338 | C83: MDJ0016 | D83: ARTEAGA JOSE | E83: VARIOS | F83: PROVEEDOR | G83: 70 | H83: 1900 | I83: 1920 | J83: 1800 | K83: 0.9375 | L83: 0 | M83: CANCELADO | N83: FC DE 4 FILAS CON 50% MADERA FINA
A84: 44340 | B84: 44340 | C84: XBV236 | D84: SARANGO ROJAS HOMER ROMENL | E84: VARIOS | F84: PROVEEDOR | G84: 82 | H84: 1600 | I84: 1859 | J84: 1400 | K84: 0.75309306 | L84: 0 | M84: CANCELADO | N84: 4 FILAS
A85: 44336 | B85: 44336 | C85: PBS1430 | D85: DOMINGUEZ CHIRIBOGA JORGE VICENTE | E85: VARIOS | F85: PROVEEDOR | G85: 52 | H85: 2000 | I85: 1678 | J85: 1500 | K85: 0.89392133 | L85: 0 | M85: CANCELADO | N85: VOLQUETA 4 FILAS. 35% MADERA FINA 65% MADERA PROMEDIO GRUESA PERO EN BUENE ESTADO
A86: 44340 | B86: 44340 | C86: HBC6496 | D86: COBEÑA QUINTERO RICARDO | E86: RIO FRIO ETAPA 2 | F86: BOSQUE | G86: 84 | H86: 250 | I86: 291 | J86: 0 | K86: 0 | L86: 0 | N86: CAMIONETADA
A87: 44344 | B87: 44344 | C87: PBT2250 | D87: FARIAS FARIAS HOLGER DARLING | E87: VARIOS | F87: PROVEEDOR | G87: 115 | H87: 2500 | I87: 2023 | J87: 2000 | K87: 0.98863075 | L87: 0 | M87: CANCELADO | N87: MULA TIPO PLATAFORMA, MADERA LARGA. CALIFICADA COMO GD
A88: 44340 | B88: 44340 | C88: HBC6496 | D88: COBEÑA QUINTERO RICARDO | E88: RIO FRIO ETAPA 2 | F88: BOSQUE | G88: 86 | H88: 350 | I88: 1161 | J88: 0 | K88: 0 | L88: 0 | N88: 3 CAMIONETADAS
A89: 44340 | B89: 44340 | C89: HCI0401 | D89: JIMENEZ FERNANDEZ ITALO PATROCIÑO | E89: VARIOS | F89: PROVEEDOR | G89: 81 | H89: 2900 | I89: 3106 | J89: 2750 | K89: 0.88538313 | L89: 0 | M89: CANCELADO | N89: 5 FILAS , MADERA 60% GRUESA
A90: 44341 | B90: 44341 | C90: TAL0556 | D90: BASURTO SACON ANDRES FERNANDO | E90: TACHINA | F90: ACOPIO | G90: 88 | H90: 1900 | I90: 2404 | J90: 0 | K90: 0 | L90: 0 | N90: 5 FILAS, MADERA DE TACHINA Y CHUMUNDE
A91: 44341 | B91: 44341 | C91: JAA3375 | D91: ARIAS LARA MARCOS VINICIO | E91: TRES VIAS | F91: ACOPIO | G91: 89 | H91: 1900 | I91: 2117 | J91: 0 | K91: 0 | L91: 0 | N91: 4 FILAS
A92: 44341 | B92: 44341 | C92: MAA7143 | D92: ZAMBRANO FERRIN CARLOS ANDRES | E92: VARIOS | F92: PROVEEDOR | G92: 90 | H92: 1300 | I92: 1344 | J92: 1000 | K92: 0.74404762 | L92: 0 | M92: CANCELADO | N92: FC 4 FILAS, MADERA FINA Y CON % DE MADERA DAÑADA
A93: 44341 | B93: 44341 | C93: PTG021 | D93: COBEÑA QUINTERO RICARDO | E93: RIO FRIO ETAPA 2 | F93: BOSQUE | G93: 91 | H93: 350 | I93: 401 | J93: 0 | K93: 0 | L93: 0 | N93: CAMIONETADA
A94: 44341 | B94: 44341 | C94: LBF191 | D94: PARRALES MORALES LEONARDO RAUL | E94: VARIOS | F94: PROVEEDOR | G94: 92 | H94: 350 | I94: 360 | J94: 270 | K94: 0.75 | L94: 0 | M94: CANCELADO | N94: CAMIONETADA, NISSAN JR MADERA DE BUEN GROSOR
A95: 44341 | B95: 44341 | C95: PTG021 | D95: COBEÑA QUINTERO RICARDO | E95: RIO FRIO ETAPA 2 | F95: BOSQUE | G95: 93 | H95: 1050 | I95: 1096 | J95: 0 | K95: 0 | L95: 0 | N95: 3 CAMIONETADAS
A96: 44343 | B96: 44343 | C96: PIB0552 | D96: JIMENEZ FERNANDEZ ITALO PATROCIÑO | E96: VARIOS | F96: PROVEEDOR | G96: 107 | H96: 2900 | I96: 3032 | J96: 2700 | K96: 0.89050132 | L96: 0 | M96: CANCELADO | N96: GH DE 5 FILAS
A97: 44341 | B97: 44341 | C97: SAA1395 | D97: APOLO DIAS SEGUNDO PETER | E97: VARIOS | F97: PROVEEDOR | G97: 95 | I97: 2567 | J97: 2100 | K97: 0.81807557 | L97: 0 | M97: CANCELADO | N97: FC 4 FILAS MADERA DE BUEN GROSOR PROVENIENTE DEL PUYO
A98: 44340 | B98: 44340 | C98: TDK0034 | D98: MOLINA LOZADA JONTHAN FERNANDO | E98: VARIOS | F98: PROVEEDOR | G98: 78 | H98: 1600 | I98: 1833 | J98: 1650 | K98: 0.90016367 | L98: 0 | M98: CANCELADO | N98: 4 FILAS FC
A99: 44342 | B99: 44342 | C99: JAA3375 | D99: ARIAS LARA MARCOS VINICIO | E99: TRES VIAS | F99: ACOPIO | G99: 97 | H99: 1800 | I99: 2158 | J99: 0 | K99: 0 | L99: 0 | N99: 4 FILAS
A100: 44342 | B100: 44342 | C100: TAL0556 | D100: BASURTO SACON ANDRES FERNANDO | E100: TACHINA | F100: ACOPIO | G100: 98 | H100: 2500 | I100: 2750 | J100: 0 | K100: 0 | L100: 0 | N100: 5 FILAS
A101: 44342 | B101: 44342 | C101: HBC6496 | D101: MUENTES CORNEJO LUIS GONZAGA | E101: BOSQUE PUERTO NUEVO | F101: BOSQUE | G101: 99 | I101: 412 | J101: 0 | K101: 0 | L101: 0 | N101: CAMIONETADA
A102: 44341 | B102: 44341 | C102: QAD2355 | D102: MOLINA LOZADA JONTHAN FERNANDO | E102: VARIOS | F102: PROVEEDOR | G102: 96 | I102: 3614 | J102: 3500 | K102: 0.968456 | L102: 0 | M102: CANCELADO | N102: FM DE 6 FILAS. MADERA CON UN 80% DE MADERA FINA
...

Sheet LISTAS
C1: DATO ENVIADO | D1: ASERRADO | F1: SUMA | G1: =SUM(G2:G5) -> 247600 | H1: =SUM(H2:H5) -> 307221
A2: MES | B2: MAYO | C2: =SUMIFS(BITACORA!$H$4:$H$7322,BITACORA!$B$4:$B$7322,">="&$B$3,BITACORA!$B$4:$B$7322,"<="&$B$4) -> 247600 | D2: =SUMIFS(BITACORA!$I$4:$I$7322,BITACORA!$B$4:$B$7322,">="&$B$3,BITACORA!$B$4:$B$7322,"<="&$B$4) -> 307221 | F2: BOSQUE | G2: =SUM(C33:C41) -> 13740 | H2: =SUM(D33:D41) -> 38697
A3: FECHA DE INICIO | B3: 44321 | F3: FINCA | G3: =SUM(C24:C30) -> 800 | H3: =SUM(D24:D30) -> 33
A4: FECHA DE CORTE | B4: 44377 | F4: ACOPIO | G4: =SUM(C7:C21) -> 67900 | H4: =SUM(D7:D21) -> 67917
F5: PROVEEDOR | G5: =SUM(C44:C1004) -> 165160 | H5: =SUM(D44:D1004) -> 200574
A6: RESPONSABLE | B6: PUNTO DE PARTIDA | C6: BFT ENVIADO | D6: BFT ASERRADO | G6: BFT ENVIADO | H6: BFT RECIBIDO
A7: BASURTO SACON ANDRES FERNANDO | B7: TACHINA | C7: =SUMIFS(BITACORA!$H$4:$H$7322,BITACORA!$D$4:$D$7322,$A$7:$A$100,BITACORA!$E$4:$E$7322,$B$7:$B$100,BITACORA!$B$4:$B$7322,">="&$B$3,BITACORA!$B$4:$B$7322,"<="&$B$4) -> 13800 | D7: =SUMIFS(BITACORA!$I$4:$I$7322,BITACORA!$D$4:$D$7322,$A$7:$A$100,BITACORA!$E$4:$E$7322,$B$7:$B$100,BITACORA!$B$4:$B$7322,">="&$B$3,BITACORA!$B$4:$B$7322,"<="&$B$4) -> 15797 | E7: ACOPIOS
A8: ARIAS LARA MARCOS VINICIO | B8: TRES VIAS | C8: =SUMIFS(BITACORA!$H$4:$H$7322,BITACORA!$D$4:$D$7322,$A$7:$A$100,BITACORA!$E$4:$E$7322,$B$7:$B$100,BITACORA!$B$4:$B$7322,">="&$B$3,BITACORA!$B$4:$B$7322,"<="&$B$4) -> 32400 | D8: =SUMIFS(BITACORA!$I$4:$I$7322,BITACORA!$D$4:$D$7322,$A$7:$A$100,BITACORA!$E$4:$E$7322,$B$7:$B$100,BITACORA!$B$4:$B$7322,">="&$B$3,BITACORA!$B$4:$B$7322,"<="&$B$4) -> 30831
A9: ZAMBRANO ZAMBRANO JEFFERSON VITERILO | B9: QUININDE | C9: =SUMIFS(BITACORA!$H$4:$H$7322,BITACORA!$D$4:$D$7322,$A$7:$A$100,BITACORA!$E$4:$E$7322,$B$7:$B$100,BITACORA!$B$4:$B$7322,">="&$B$3,BITACORA!$B$4:$B$7322,"<="&$B$4) -> 12200 | D9: =SUMIFS(BITACORA!$I$4:$I$7322,BITACORA!$D$4:$D$7322,$A$7:$A$100,BITACORA!$E$4:$E$7322,$B$7:$B$100,BITACORA!$B$4:$B$7322,">="&$B$3,BITACORA!$B$4:$B$7322,"<="&$B$4) -> 10934
A10: COBEÑA QUINTERO RICARDO | B10: TAISHA | C10: =SUMIFS(BITACORA!$H$4:$H$7322,BITACORA!$D$4:$D$7322,$A$7:$A$100,BITACORA!$E$4:$E$7322,$B$7:$B$100,BITACORA!$B$4:$B$7322,">="&$B$3,BITACORA!$B$4:$B$7322,"<="&$B$4) -> 6000 | D10: =SUMIFS(BITACORA!$I$4:$I$7322,BITACORA!$D$4:$D$7322,$A$7:$A$100,BITACORA!$E$4:$E$7322,$B$7:$B$100,BITACORA!$B$4:$B$7322,">="&$B$3,BITACORA!$B$4:$B$7322,"<="&$B$4) -> 6187
A11: COBEÑA QUINTERO RICARDO | B11: ARAJUNO | C11: =SUMIFS(BITACORA!$H$4:$H$7322,BITACORA!$D$4:$D$7322,$A$7:$A$100,BITACORA!$E$4:$E$7322,$B$7:$B$100,BITACORA!$B$4:$B$7322,">="&$B$3,BITACORA!$B$4:$B$7322,"<="&$B$4) -> 3500 | D11: =SUMIFS(BITACORA!$I$4:$I$7322,BITACORA!$D$4:$D$7322,$A$7:$A$100,BITACORA!$E$4:$E$7322,$B$7:$B$100,BITACORA!$B$4:$B$7322,">="&$B$3,BITACORA!$B$4:$B$7322,"<="&$B$4) -> 4168
C12: =SUMIFS(BITACORA!$H$4:$H$7322,BITACORA!$D$4:$D$7322,$A$7:$A$100,BITACORA!$E$4:$E$7322,$B$7:$B$100,BITACORA!$B$4:$B$7322,">="&$B$3,BITACORA!$B$4:$B$7322,"<="&$B$4) -> 0 | D12: =SUMIFS(BITACORA!$I$4:$I$7322,BITACORA!$D$4:$D$7322,$A$7:$A$100,BITACORA!$E$4:$E$7322,$B$7:$B$100,BITACORA!$B$4:$B$7322,">="&$B$3,BITACORA!$B$4:$B$7322,"<="&$B$4) -> 0
C13: =SUMIFS(BITACORA!$H$4:$H$7322,BITACORA!$D$4:$D$7322,$A$7:$A$100,BITACORA!$E$4:$E$7322,$B$7:$B$100,BITACORA!$B$4:$B$7322,">="&$B$3,BITACORA!$B$4:$B$7322,"<="&$B$4) -> 0 | D13: =SUMIFS(BITACORA!$I$4:$I$7322,BITACORA!$D$4:$D$7322,$A$7:$A$100,BITACORA!$E$4:$E$7322,$B$7:$B$100,BITACORA!$B$4:$B$7322,">="&$B$3,BITACORA!$B$4:$B$7322,"<="&$B$4) -> 0
C14: =SUMIFS(BITACORA!$H$4:$H$7322,BITACORA!$D$4:$D$7322,$A$7:$A$100,BITACORA!$E$4:$E$7322,$B$7:$B$100,BITACORA!$B$4:$B$7322,">="&$B$3,BITACORA!$B$4:$B$7322,"<="&$B$4) -> 0 | D14: =SUMIFS(BITACORA!$I$4:$I$7322,BITACORA!$D$4:$D$7322,$A$7:$A$100,BITACORA!$E$4:$E$7322,$B$7:$B$100,BITACORA!$B$4:$B$7322,">="&$B$3,BITACORA!$B$4:$B$7322,"<="&$B$4) -> 0
C15: =SUMIFS(BITACORA!$H$4:$H$7322,BITACORA!$D$4:$D$7322,$A$7:$A$100,BITACORA!$E$4:$E$7322,$B$7:$B$100,BITACORA!$B$4:$B$7322,">="&$B$3,BITACORA!$B$4:$B$7322,"<="&$B$4) -> 0 | D15: =SUMIFS(BITACORA!$I$4:$I$7322,BITACORA!$D$4:$D$7322,$A$7:$A$100,BITACORA!$E$4:$E$7322,$B$7:$B$100,BITACORA!$B$4:$B$7322,">="&$B$3,BITACORA!$B$4:$B$7322,"<="&$B$4) -> 0
C16: =SUMIFS(BITACORA!$H$4:$H$7322,BITACORA!$D$4:$D$7322,$A$7:$A$100,BITACORA!$E$4:$E$7322,$B$7:$B$100,BITACORA!$B$4:$B$7322,">="&$B$3,BITACORA!$B$4:$B$7322,"<="&$B$4) -> 0 | D16: =SUMIFS(BITACORA!$I$4:$I$7322,BITACORA!$D$4:$D$7322,$A$7:$A$100,BITACORA!$E$4:$E$7322,$B$7:$B$100,BITACORA!$B$4:$B$7322,">="&$B$3,BITACORA!$B$4:$B$7322,"<="&$B$4) -> 0
C17: =SUMIFS(BITACORA!$H$4:$H$7322,BITACORA!$D$4:$D$7322,$A$7:$A$100,BITACORA!$E$4:$E$7322,$B$7:$B$100,BITACORA!$B$4:$B$7322,">="&$B$3,BITACORA!$B$4:$B$7322,"<="&$B$4) -> 0 | D17: =SUMIFS(BITACORA!$I$4:$I$7322,BITACORA!$D$4:$D$7322,$A$7:$A$100,BITACORA!$E$4:$E$7322,$B$7:$B$100,BITACORA!$B$4:$B$7322,">="&$B$3,BITACORA!$B$4:$B$7322,"<="&$B$4) -> 0
C18: =SUMIFS(BITACORA!$H$4:$H$7322,BITACORA!$D$4:$D$7322,$A$7:$A$100,BITACORA!$E$4:$E$7322,$B$7:$B$100,BITACORA!$B$4:$B$7322,">="&$B$3,BITACORA!$B$4:$B$7322,"<="&$B$4) -> 0 | D18: =SUMIFS(BITACORA!$I$4:$I$7322,BITACORA!$D$4:$D$7322,$A$7:$A$100,BITACORA!$E$4:$E$7322,$B$7:$B$100,BITACORA!$B$4:$B$7322,">="&$B$3,BITACORA!$B$4:$B$7322,"<="&$B$4) -> 0
C19: =SUMIFS(BITACORA!$H$4:$H$7322,BITACORA!$D$4:$D$7322,$A$7:$A$100,BITACORA!$E$4:$E$7322,$B$7:$B$100,BITACORA!$B$4:$B$7322,">="&$B$3,BITACORA!$B$4:$B$7322,"<="&$B$4) -> 0 | D19: =SUMIFS(BITACORA!$I$4:$I$7322,BITACORA!$D$4:$D$7322,$A$7:$A$100,BITACORA!$E$4:$E$7322,$B$7:$B$100,BITACORA!$B$4:$B$7322,">="&$B$3,BITACORA!$B$4:$B$7322,"<="&$B$4) -> 0
C20: =SUMIFS(BITACORA!$H$4:$H$7322,BITACORA!$D$4:$D$7322,$A$7:$A$100,BITACORA!$E$4:$E$7322,$B$7:$B$100,BITACORA!$B$4:$B$7322,">="&$B$3,BITACORA!$B$4:$B$7322,"<="&$B$4) -> 0 | D20: =SUMIFS(BITACORA!$I$4:$I$7322,BITACORA!$D$4:$D$7322,$A$7:$A$100,BITACORA!$E$4:$E$7322,$B$7:$B$100,BITACORA!$B$4:$B$7322,">="&$B$3,BITACORA!$B$4:$B$7322,"<="&$B$4) -> 0
C21: =SUMIFS(BITACORA!$H$4:$H$7322,BITACORA!$D$4:$D$7322,$A$7:$A$100,BITACORA!$E$4:$E$7322,$B$7:$B$100,BITACORA!$B$4:$B$7322,">="&$B$3,BITACORA!$B$4:$B$7322,"<="&$B$4) -> 0 | D21: =SUMIFS(BITACORA!$I$4:$I$7322,BITACORA!$D$4:$D$7322,$A$7:$A$100,BITACORA!$E$4:$E$7322,$B$7:$B$100,BITACORA!$B$4:$B$7322,">="&$B$3,BITACORA!$B$4:$B$7322,"<="&$B$4) -> 0
A24: MADERA DE PLANTA | B24: FINCA EN PLANTA | C24: =SUMIFS(BITACORA!$H$4:$H$7322,BITACORA!$D$4:$D$7322,$A$7:$A$100,BITACORA!$E$4:$E$7322,$B$7:$B$100,BITACORA!$B$4:$B$7322,">="&$B$3,BITACORA!$B$4:$B$7322,"<="&$B$4) -> 0 | D24: =SUMIFS(BITACORA!$I$4:$I$7322,BITACORA!$D$4:$D$7322,$A$7:$A$100,BITACORA!$E$4:$E$7322,$B$7:$B$100,BITACORA!$B$4:$B$7322,">="&$B$3,BITACORA!$B$4:$B$7322,"<="&$B$4) -> 33 | E24: FINCA
A25: MUENTES CORNEJO JAVIER EDWIN | B25: LA SANDIA | C25: =SUMIFS(BITACORA!$H$4:$H$7322,BITACORA!$D$4:$D$7322,$A$7:$A$100,BITACORA!$E$4:$E$7322,$B$7:$B$100,BITACORA!$B$4:$B$7322,">="&$B$3,BITACORA!$B$4:$B$7322,"<="&$B$4) -> 800 | D25: =SUMIFS(BITACORA!$I$4:$I$7322,BITACORA!$D$4:$D$7322,$A$7:$A$100,BITACORA!$E$4:$E$7322,$B$7:$B$100,BITACORA!$B$4:$B$7322,">="&$B$3,BITACORA!$B$4:$B$7322,"<="&$B$4) -> 0
C26: =SUMIFS(BITACORA!$H$4:$H$7322,BITACORA!$D$4:$D$7322,$A$7:$A$100,BITACORA!$E$4:$E$7322,$B$7:$B$100,BITACORA!$B$4:$B$7322,">="&$B$3,BITACORA!$B$4:$B$7322,"<="&$B$4) -> 0 | D26: =SUMIFS(BITACORA!$I$4:$I$7322,BITACORA!$D$4:$D$7322,$A$7:$A$100,BITACORA!$E$4:$E$7322,$B$7:$B$100,BITACORA!$B$4:$B$7322,">="&$B$3,BITACORA!$B$4:$B$7322,"<="&$B$4) -> 0
C27: =SUMIFS(BITACORA!$H$4:$H$7322,BITACORA!$D$4:$D$7322,$A$7:$A$100,BITACORA!$E$4:$E$7322,$B$7:$B$100,BITACORA!$B$4:$B$7322,">="&$B$3,BITACORA!$B$4:$B$7322,"<="&$B$4) -> 0 | D27: =SUMIFS(BITACORA!$I$4:$I$7322,BITACORA!$D$4:$D$7322,$A$7:$A$100,BITACORA!$E$4:$E$7322,$B$7:$B$100,BITACORA!$B$4:$B$7322,">="&$B$3,BITACORA!$B$4:$B$7322,"<="&$B$4) -> 0
C28: =SUMIFS(BITACORA!$H$4:$H$7322,BITACORA!$D$4:$D$7322,$A$7:$A$100,BITACORA!$E$4:$E$7322,$B$7:$B$100,BITACORA!$B$4:$B$7322,">="&$B$3,BITACORA!$B$4:$B$7322,"<="&$B$4) -> 0 | D28: =SUMIFS(BITACORA!$I$4:$I$7322,BITACORA!$D$4:$D$7322,$A$7:$A$100,BITACORA!$E$4:$E$7322,$B$7:$B$100,BITACORA!$B$4:$B$7322,">="&$B$3,BITACORA!$B$4:$B$7322,"<="&$B$4) -> 0
C29: =SUMIFS(BITACORA!$H$4:$H$7322,BITACORA!$D$4:$D$7322,$A$7:$A$100,BITACORA!$E$4:$E$7322,$B$7:$B$100,BITACORA!$B$4:$B$7322,">="&$B$3,BITACORA!$B$4:$B$7322,"<="&$B$4) -> 0 | D29: =SUMIFS(BITACORA!$I$4:$I$7322,BITACORA!$D$4:$D$7322,$A$7:$A$100,BITACORA!$E$4:$E$7322,$B$7:$B$100,BITACORA!$B$4:$B$7322,">="&$B$3,BITACORA!$B$4:$B$7322,"<="&$B$4) -> 0
C30: =SUMIFS(BITACORA!$H$4:$H$7322,BITACORA!$D$4:$D$7322,$A$7:$A$100,BITACORA!$E$4:$E$7322,$B$7:$B$100,BITACORA!$B$4:$B$7322,">="&$B$3,BITACORA!$B$4:$B$7322,"<="&$B$4) -> 0 | D30: =SUMIFS(BITACORA!$I$4:$I$7322,BITACORA!$D$4:$D$7322,$A$7:$A$100,BITACORA!$E$4:$E$7322,$B$7:$B$100,BITACORA!$B$4:$B$7322,">="&$B$3,BITACORA!$B$4:$B$7322,"<="&$B$4) -> 0
A33: VELIZ ZAMBRANO JAIME GREGORIO | B33: RIO FRIO | C33: =SUMIFS(BITACORA!$H$4:$H$7322,BITACORA!$D$4:$D$7322,$A$7:$A$100,BITACORA!$E$4:$E$7322,$B$7:$B$100,BITACORA!$B$4:$B$7322,">="&$B$3,BITACORA!$B$4:$B$7322,"<="&$B$4) -> 0 | D33: =SUMIFS(BITACORA!$I$4:$I$7322,BITACORA!$D$4:$D$7322,$A$7:$A$100,BITACORA!$E$4:$E$7322,$B$7:$B$100,BITACORA!$B$4:$B$7322,">="&$B$3,BITACORA!$B$4:$B$7322,"<="&$B$4) -> 15779 | E33: BOSQUE
A34: COBEÑA QUINTERO RICARDO | B34: RIO FRIO ETAPA 2 | C34: =SUMIFS(BITACORA!$H$4:$H$7322,BITACORA!$D$4:$D$7322,$A$7:$A$100,BITACORA!$E$4:$E$7322,$B$7:$B$100,BITACORA!$B$4:$B$7322,">="&$B$3,BITACORA!$B$4:$B$7322,"<="&$B$4) -> 5890 | D34: =SUMIFS(BITACORA!$I$4:$I$7322,BITACORA!$D$4:$D$7322,$A$7:$A$100,BITACORA!$E$4:$E$7322,$B$7:$B$100,BITACORA!$B$4:$B$7322,">="&$B$3,BITACORA!$B$4:$B$7322,"<="&$B$4) -> 12410
A35: MUENTES CORNEJO LUIS GONZAGA | B35: BOSQUE PUERTO NUEVO | C35: =SUMIFS(BITACORA!$H$4:$H$7322,BITACORA!$D$4:$D$7322,$A$7:$A$100,BITACORA!$E$4:$E$7322,$B$7:$B$100,BITACORA!$B$4:$B$7322,">="&$B$3,BITACORA!$B$4:$B$7322,"<="&$B$4) -> 7850 | D35: =SUMIFS(BITACORA!$I$4:$I$7322,BITACORA!$D$4:$D$7322,$A$7:$A$100,BITACORA!$E$4:$E$7322,$B$7:$B$100,BITACORA!$B$4:$B$7322,">="&$B$3,BITACORA!$B$4:$B$7322,"<="&$B$4) -> 10508
C36: =SUMIFS(BITACORA!$H$4:$H$7322,BITACORA!$D$4:$D$7322,$A$7:$A$100,BITACORA!$E$4:$E$7322,$B$7:$B$100,BITACORA!$B$4:$B$7322,">="&$B$3,BITACORA!$B$4:$B$7322,"<="&$B$4) -> 0 | D36: =SUMIFS(BITACORA!$I$4:$I$7322,BITACORA!$D$4:$D$7322,$A$7:$A$100,BITACORA!$E$4:$E$7322,$B$7:$B$100,BITACORA!$B$4:$B$7322,">="&$B$3,BITACORA!$B$4:$B$7322,"<="&$B$4) -> 0
C37: =SUMIFS(BITACORA!$H$4:$H$7322,BITACORA!$D$4:$D$7322,$A$7:$A$100,BITACORA!$E$4:$E$7322,$B$7:$B$100,BITACORA!$B$4:$B$7322,">="&$B$3,BITACORA!$B$4:$B$7322,"<="&$B$4) -> 0 | D37: =SUMIFS(BITACORA!$I$4:$I$7322,BITACORA!$D$4:$D$7322,$A$7:$A$100,BITACORA!$E$4:$E$7322,$B$7:$B$100,BITACORA!$B$4:$B$7322,">="&$B$3,BITACORA!$B$4:$B$7322,"<="&$B$4) -> 0
C38: =SUMIFS(BITACORA!$H$4:$H$7322,BITACORA!$D$4:$D$7322,$A$7:$A$100,BITACORA!$E$4:$E$7322,$B$7:$B$100,BITACORA!$B$4:$B$7322,">="&$B$3,BITACORA!$B$4:$B$7322,"<="&$B$4) -> 0 | D38: =SUMIFS(BITACORA!$I$4:$I$7322,BITACORA!$D$4:$D$7322,$A$7:$A$100,BITACORA!$E$4:$E$7322,$B$7:$B$100,BITACORA!$B$4:$B$7322,">="&$B$3,BITACORA!$B$4:$B$7322,"<="&$B$4) -> 0
C39: =SUMIFS(BITACORA!$H$4:$H$7322,BITACORA!$D$4:$D$7322,$A$7:$A$100,BITACORA!$E$4:$E$7322,$B$7:$B$100,BITACORA!$B$4:$B$7322,">="&$B$3,BITACORA!$B$4:$B$7322,"<="&$B$4) -> 0 | D39: =SUMIFS(BITACORA!$I$4:$I$7322,BITACORA!$D$4:$D$7322,$A$7:$A$100,BITACORA!$E$4:$E$7322,$B$7:$B$100,BITACORA!$B$4:$B$7322,">="&$B$3,BITACORA!$B$4:$B$7322,"<="&$B$4) -> 0
C40: =SUMIFS(BITACORA!$H$4:$H$7322,BITACORA!$D$4:$D$7322,$A$7:$A$100,BITACORA!$E$4:$E$7322,$B$7:$B$100,BITACORA!$B$4:$B$7322,">="&$B$3,BITACORA!$B$4:$B$7322,"<="&$B$4) -> 0 | D40: =SUMIFS(BITACORA!$I$4:$I$7322,BITACORA!$D$4:$D$7322,$A$7:$A$100,BITACORA!$E$4:$E$7322,$B$7:$B$100,BITACORA!$B$4:$B$7322,">="&$B$3,BITACORA!$B$4:$B$7322,"<="&$B$4) -> 0
C41: =SUMIFS(BITACORA!$H$4:$H$7322,BITACORA!$D$4:$D$7322,$A$7:$A$100,BITACORA!$E$4:$E$7322,$B$7:$B$100,BITACORA!$B$4:$B$7322,">="&$B$3,BITACORA!$B$4:$B$7322,"<="&$B$4) -> 0 | D41: =SUMIFS(BITACORA!$I$4:$I$7322,BITACORA!$D$4:$D$7322,$A$7:$A$100,BITACORA!$E$4:$E$7322,$B$7:$B$100,BITACORA!$B$4:$B$7322,">="&$B$3,BITACORA!$B$4:$B$7322,"<="&$B$4) -> 0
A44: ANAGUANO GALARRAGA FAUSTO | B44: VARIOS | C44: =SUMIFS(BITACORA!$H$4:$H$7322,BITACORA!$D$4:$D$7322,$A$7:$A$100,BITACORA!$E$4:$E$7322,$B$7:$B$100,BITACORA!$B$4:$B$7322,">="&$B$3,BITACORA!$B$4:$B$7322,"<="&$B$4) -> 0 | D44: =SUMIFS(BITACORA!$I$4:$I$7322,BITACORA!$D$4:$D$7322,$A$7:$A$100,BITACORA!$E$4:$E$7322,$B$7:$B$100,BITACORA!$B$4:$B$7322,">="&$B$3,BITACORA!$B$4:$B$7322,"<="&$B$4) -> 110 | E44: PROVEEDORES
A45: BRAVO BRAVO MILTON GABRIEL | B45: VARIOS | C45: =SUMIFS(BITACORA!$H$4:$H$7322,BITACORA!$D$4:$D$7322,$A$7:$A$100,BITACORA!$E$4:$E$7322,$B$7:$B$100,BITACORA!$B$4:$B$7322,">="&$B$3,BITACORA!$B$4:$B$7322,"<="&$B$4) -> 0 | D45: =SUMIFS(BITACORA!$I$4:$I$7322,BITACORA!$D$4:$D$7322,$A$7:$A$100,BITACORA!$E$4:$E$7322,$B$7:$B$100,BITACORA!$B$4:$B$7322,">="&$B$3,BITACORA!$B$4:$B$7322,"<="&$B$4) -> 320
A46: DOMINGUEZ CHIRIBOGA JORGE VICENTE | B46: VARIOS | C46: =SUMIFS(BITACORA!$H$4:$H$7322,BITACORA!$D$4:$D$7322,$A$7:$A$100,BITACORA!$E$4:$E$7322,$B$7:$B$100,BITACORA!$B$4:$B$7322,">="&$B$3,BITACORA!$B$4:$B$7322,"<="&$B$4) -> 3600 | D46: =SUMIFS(BITACORA!$I$4:$I$7322,BITACORA!$D$4:$D$7322,$A$7:$A$100,BITACORA!$E$4:$E$7322,$B$7:$B$100,BITACORA!$B$4:$B$7322,">="&$B$3,BITACORA!$B$4:$B$7322,"<="&$B$4) -> 5480
A47: AGUILAR ALVARES PATRICIO ESTUARDO | B47: VARIOS | C47: =SUMIFS(BITACORA!$H$4:$H$7322,BITACORA!$D$4:$D$7322,$A$7:$A$100,BITACORA!$E$4:$E$7322,$B$7:$B$100,BITACORA!$B$4:$B$7322,">="&$B$3,BITACORA!$B$4:$B$7322,"<="&$B$4) -> 3600 | D47: =SUMIFS(BITACORA!$I$4:$I$7322,BITACORA!$D$4:$D$7322,$A$7:$A$100,BITACORA!$E$4:$E$7322,$B$7:$B$100,BITACORA!$B$4:$B$7322,">="&$B$3,BITACORA!$B$4:$B$7322,"<="&$B$4) -> 3522
A48: MENDOZA GUARDERAS JORGE MANUEL | B48: VARIOS | C48: =SUMIFS(BITACORA!$H$4:$H$7322,BITACORA!$D$4:$D$7322,$A$7:$A$100,BITACORA!$E$4:$E$7322,$B$7:$B$100,BITACORA!$B$4:$B$7322,">="&$B$3,BITACORA!$B$4:$B$7322,"<="&$B$4) -> 1750 | D48: =SUMIFS(BITACORA!$I$4:$I$7322,BITACORA!$D$4:$D$7322,$A$7:$A$100,BITACORA!$E$4:$E$7322,$B$7:$B$100,BITACORA!$B$4:$B$7322,">="&$B$3,BITACORA!$B$4:$B$7322,"<="&$B$4) -> 1580
A49: OLGUIN QUINATOA JAVIER ANTONIO | B49: VARIOS | C49: =SUMIFS(BITACORA!$H$4:$H$7322,BITACORA!$D$4:$D$7322,$A$7:$A$100,BITACORA!$E$4:$E$7322,$B$7:$B$100,BITACORA!$B$4:$B$7322,">="&$B$3,BITACORA!$B$4:$B$7322,"<="&$B$4) -> 0 | D49: =SUMIFS(BITACORA!$I$4:$I$7322,BITACORA!$D$4:$D$7322,$A$7:$A$100,BITACORA!$E$4:$E$7322,$B$7:$B$100,BITACORA!$B$4:$B$7322,">="&$B$3,BITACORA!$B$4:$B$7322,"<="&$B$4) -> 3823
A50: NAPA CAICEDO HENRRY JULIAN | B50: VARIOS | C50: =SUMIFS(BITACORA!$H$4:$H$7322,BITACORA!$D$4:$D$7322,$A$7:$A$100,BITACORA!$E$4:$E$7322,$B$7:$B$100,BITACORA!$B$4:$B$7322,">="&$B$3,BITACORA!$B$4:$B$7322,"<="&$B$4) -> 0 | D50: =SUMIFS(BITACORA!$I$4:$I$7322,BITACORA!$D$4:$D$7322,$A$7:$A$100,BITACORA!$E$4:$E$7322,$B$7:$B$100,BITACORA!$B$4:$B$7322,">="&$B$3,BITACORA!$B$4:$B$7322,"<="&$B$4) -> 65
A51: APOLO DIAS SEGUNDO PETER | B51: VARIOS | C51: =SUMIFS(BITACORA!$H$4:$H$7322,BITACORA!$D$4:$D$7322,$A$7:$A$100,BITACORA!$E$4:$E$7322,$B$7:$B$100,BITACORA!$B$4:$B$7322,">="&$B$3,BITACORA!$B$4:$B$7322,"<="&$B$4) -> 69600 | D51: =SUMIFS(BITACORA!$I$4:$I$7322,BITACORA!$D$4:$D$7322,$A$7:$A$100,BITACORA!$E$4:$E$7322,$B$7:$B$100,BITACORA!$B$4:$B$7322,">="&$B$3,BITACORA!$B$4:$B$7322,"<="&$B$4) -> 91052
A52: FARIAS FARIAS HOLGER DARLING | B52: VARIOS | C52: =SUMIFS(BITACORA!$H$4:$H$7322,BITACORA!$D$4:$D$7322,$A$7:$A$100,BITACORA!$E$4:$E$7322,$B$7:$B$100,BITACORA!$B$4:$B$7322,">="&$B$3,BITACORA!$B$4:$B$7322,"<="&$B$4) -> 2500 | D52: =SUMIFS(BITACORA!$I$4:$I$7322,BITACORA!$D$4:$D$7322,$A$7:$A$100,BITACORA!$E$4:$E$7322,$B$7:$B$100,BITACORA!$B$4:$B$7322,">="&$B$3,BITACORA!$B$4:$B$7322,"<="&$B$4) -> 2023
A53: BRAVO SOLORZANO ANIBAL ORLEY | B53: VARIOS | C53: =SUMIFS(BITACORA!$H$4:$H$7322,BITACORA!$D$4:$D$7322,$A$7:$A$100,BITACORA!$E$4:$E$7322,$B$7:$B$100,BITACORA!$B$4:$B$7322,">="&$B$3,BITACORA!$B$4:$B$7322,"<="&$B$4) -> 180 | D53: =SUMIFS(BITACORA!$I$4:$I$7322,BITACORA!$D$4:$D$7322,$A$7:$A$100,BITACORA!$E$4:$E$7322,$B$7:$B$100,BITACORA!$B$4:$B$7322,">="&$B$3,BITACORA!$B$4:$B$7322,"<="&$B$4) -> 247
C54: =SUMIFS(BITACORA!$H$4:$H$7322,BITACORA!$D$4:$D$7322,$A$7:$A$100,BITACORA!$E$4:$E$7322,$B$7:$B$100,BITACORA!$B$4:$B$7322,">="&$B$3,BITACORA!$B$4:$B$7322,"<="&$B$4) -> 0 | D54: =SUMIFS(BITACORA!$I$4:$I$7322,BITACORA!$D$4:$D$7322,$A$7:$A$100,BITACORA!$E$4:$E$7322,$B$7:$B$100,BITACORA!$B$4:$B$7322,">="&$B$3,BITACORA!$B$4:$B$7322,"<="&$B$4) -> 0
A55: OLMEDO VELEZ LIWINTONG AUGUSTO | B55: VARIOS | C55: =SUMIFS(BITACORA!$H$4:$H$7322,BITACORA!$D$4:$D$7322,$A$7:$A$100,BITACORA!$E$4:$E$7322,$B$7:$B$100,BITACORA!$B$4:$B$7322,">="&$B$3,BITACORA!$B$4:$B$7322,"<="&$B$4) -> 80 | D55: =SUMIFS(BITACORA!$I$4:$I$7322,BITACORA!$D$4:$D$7322,$A$7:$A$100,BITACORA!$E$4:$E$7322,$B$7:$B$100,BITACORA!$B$4:$B$7322,">="&$B$3,BITACORA!$B$4:$B$7322,"<="&$B$4) -> 103
A56: SARI UZHO GUILLERMO FRANCEL | B56: VARIOS | C56: =SUMIFS(BITACORA!$H$4:$H$7322,BITACORA!$D$4:$D$7322,$A$7:$A$100,BITACORA!$E$4:$E$7322,$B$7:$B$100,BITACORA!$B$4:$B$7322,">="&$B$3,BITACORA!$B$4:$B$7322,"<="&$B$4) -> 2700 | D56: =SUMIFS(BITACORA!$I$4:$I$7322,BITACORA!$D$4:$D$7322,$A$7:$A$100,BITACORA!$E$4:$E$7322,$B$7:$B$100,BITACORA!$B$4:$B$7322,">="&$B$3,BITACORA!$B$4:$B$7322,"<="&$B$4) -> 4982
A57: GONZALEZ DEMERA HOLGER ANTONIO | B57: VARIOS | C57: =SUMIFS(BITACORA!$H$4:$H$7322,BITACORA!$D$4:$D$7322,$A$7:$A$100,BITACORA!$E$4:$E$7322,$B$7:$B$100,BITACORA!$B$4:$B$7322,">="&$B$3,BITACORA!$B$4:$B$7322,"<="&$B$4) -> 200 | D57: =SUMIFS(BITACORA!$I$4:$I$7322,BITACORA!$D$4:$D$7322,$A$7:$A$100,BITACORA!$E$4:$E$7322,$B$7:$B$100,BITACORA!$B$4:$B$7322,">="&$B$3,BITACORA!$B$4:$B$7322,"<="&$B$4) -> 341
A58: SARANGO ROJAS HOMER ROMENL | B58: VARIOS | C58: =SUMIFS(BITACORA!$H$4:$H$7322,BITACORA!$D$4:$D$7322,$A$7:$A$100,BITACORA!$E$4:$E$7322,$B$7:$B$100,BITACORA!$B$4:$B$7322,">="&$B$3,BITACORA!$B$4:$B$7322,"<="&$B$4) -> 19500 | D58: =SUMIFS(BITACORA!$I$4:$I$7322,BITACORA!$D$4:$D$7322,$A$7:$A$100,BITACORA!$E$4:$E$7322,$B$7:$B$100,BITACORA!$B$4:$B$7322,">="&$B$3,BITACORA!$B$4:$B$7322,"<="&$B$4) -> 20537
A59: MACIAS MENDOZA DANIEL JOSE | B59: VARIOS | C59: =SUMIFS(BITACORA!$H$4:$H$7322,BITACORA!$D$4:$D$7322,$A$7:$A$100,BITACORA!$E$4:$E$7322,$B$7:$B$100,BITACORA!$B$4:$B$7322,">="&$B$3,BITACORA!$B$4:$B$7322,"<="&$B$4) -> 650 | D59: =SUMIFS(BITACORA!$I$4:$I$7322,BITACORA!$D$4:$D$7322,$A$7:$A$100,BITACORA!$E$4:$E$7322,$B$7:$B$100,BITACORA!$B$4:$B$7322,">="&$B$3,BITACORA!$B$4:$B$7322,"<="&$B$4) -> 512
A60: SOLORZANO VELEZ LUIS ANDRES | B60: VARIOS | C60: =SUMIFS(BITACORA!$H$4:$H$7322,BITACORA!$D$4:$D$7322,$A$7:$A$100,BITACORA!$E$4:$E$7322,$B$7:$B$100,BITACORA!$B$4:$B$7322,">="&$B$3,BITACORA!$B$4:$B$7322,"<="&$B$4) -> 150 | D60: =SUMIFS(BITACORA!$I$4:$I$7322,BITACORA!$D$4:$D$7322,$A$7:$A$100,BITACORA!$E$4:$E$7322,$B$7:$B$100,BITACORA!$B$4:$B$7322,">="&$B$3,BITACORA!$B$4:$B$7322,"<="&$B$4) -> 165
A61: ARTEAGA JOSE | B61: VARIOS | C61: =SUMIFS(BITACORA!$H$4:$H$7322,BITACORA!$D$4:$D$7322,$A$7:$A$100,BITACORA!$E$4:$E$7322,$B$7:$B$100,BITACORA!$B$4:$B$7322,">="&$B$3,BITACORA!$B$4:$B$7322,"<="&$B$4) -> 1900 | D61: =SUMIFS(BITACORA!$I$4:$I$7322,BITACORA!$D$4:$D$7322,$A$7:$A$100,BITACORA!$E$4:$E$7322,$B$7:$B$100,BITACORA!$B$4:$B$7322,">="&$B$3,BITACORA!$B$4:$B$7322,"<="&$B$4) -> 1920
A62: MOLINA LOZADA JONTHAN FERNANDO | B62: VARIOS | C62: =SUMIFS(BITACORA!$H$4:$H$7322,BITACORA!$D$4:$D$7322,$A$7:$A$100,BITACORA!$E$4:$E$7322,$B$7:$B$100,BITACORA!$B$4:$B$7322,">="&$B$3,BITACORA!$B$4:$B$7322,"<="&$B$4) -> 19400 | D62: =SUMIFS(BITACORA!$I$4:$I$7322,BITACORA!$D$4:$D$7322,$A$7:$A$100,BITACORA!$E$4:$E$7322,$B$7:$B$100,BITACORA!$B$4:$B$7322,">="&$B$3,BITACORA!$B$4:$B$7322,"<="&$B$4) -> 22946
A63: QUIROZ MUÑOZ YIMI QURINO | B63: VARIOS | C63: =SUMIFS(BITACORA!$H$4:$H$7322,BITACORA!$D$4:$D$7322,$A$7:$A$100,BITACORA!$E$4:$E$7322,$B$7:$B$100,BITACORA!$B$4:$B$7322,">="&$B$3,BITACORA!$B$4:$B$7322,"<="&$B$4) -> 3300 | D63: =SUMIFS(BITACORA!$I$4:$I$7322,BITACORA!$D$4:$D$7322,$A$7:$A$100,BITACORA!$E$4:$E$7322,$B$7:$B$100,BITACORA!$B$4:$B$7322,">="&$B$3,BITACORA!$B$4:$B$7322,"<="&$B$4) -> 3351
A64: JIMENEZ FERNANDEZ ITALO PATROCIÑO | B64: VARIOS | C64: =SUMIFS(BITACORA!$H$4:$H$7322,BITACORA!$D$4:$D$7322,$A$7:$A$100,BITACORA!$E$4:$E$7322,$B$7:$B$100,BITACORA!$B$4:$B$7322,">="&$B$3,BITACORA!$B$4:$B$7322,"<="&$B$4) -> 8800 | D64: =SUMIFS(BITACORA!$I$4:$I$7322,BITACORA!$D$4:$D$7322,$A$7:$A$100,BITACORA!$E$4:$E$7322,$B$7:$B$100,BITACORA!$B$4:$B$7322,">="&$B$3,BITACORA!$B$4:$B$7322,"<="&$B$4) -> 9293
A65: PABLO ARTURO SANCHEZ MENDOZA | B65: VARIOS | C65: =SUMIFS(BITACORA!$H$4:$H$7322,BITACORA!$D$4:$D$7322,$A$7:$A$100,BITACORA!$E$4:$E$7322,$B$7:$B$100,BITACORA!$B$4:$B$7322,">="&$B$3,BITACORA!$B$4:$B$7322,"<="&$B$4) -> 100 | D65: =SUMIFS(BITACORA!$I$4:$I$7322,BITACORA!$D$4:$D$7322,$A$7:$A$100,BITACORA!$E$4:$E$7322,$B$7:$B$100,BITACORA!$B$4:$B$7322,">="&$B$3,BITACORA!$B$4:$B$7322,"<="&$B$4) -> 98
A66: ZAMBRANO FERRIN CARLOS ANDRES | B66: VARIOS | C66: =SUMIFS(BITACORA!$H$4:$H$7322,BITACORA!$D$4:$D$7322,$A$7:$A$100,BITACORA!$E$4:$E$7322,$B$7:$B$100,BITACORA!$B$4:$B$7322,">="&$B$3,BITACORA!$B$4:$B$7322,"<="&$B$4) -> 1390 | D66: =SUMIFS(BITACORA!$I$4:$I$7322,BITACORA!$D$4:$D$7322,$A$7:$A$100,BITACORA!$E$4:$E$7322,$B$7:$B$100,BITACORA!$B$4:$B$7322,">="&$B$3,BITACORA!$B$4:$B$7322,"<="&$B$4) -> 1454
... A92: NEXAR MUÑOZ ROLDAN | B92: VARIOS | C92: =SUMIFS(BITACORA!$H$4:$H$7322,BITACORA!$D$4:$D$7322,$A$7:$A$100,BITACORA!$E$4:$E$7322,$B$7:$B$100,BITACORA!$B$4:$B$7322,">="&$B$3,BITACORA!$B$4:$B$7322,"<="&$B$4) -> 320 | D92: =SUMIFS(BITACORA!$I$4:$I$7322,BITACORA!$D$4:$D$7322,$A$7:$A$100,BITACORA!$E$4:$E$7322,$B$7:$B$100,BITACORA!$B$4:$B$7322,">="&$B$3,BITACORA!$B$4:$B$7322,"<="&$B$4) -> 0
C93: =SUMIFS(BITACORA!$H$4:$H$7322,BITACORA!$D$4:$D$7322,$A$7:$A$100,BITACORA!$E$4:$E$7322,$B$7:$B$100,BITACORA!$B$4:$B$7322,">="&$B$3,BITACORA!$B$4:$B$7322,"<="&$B$4) -> 0 | D93: =SUMIFS(BITACORA!$I$4:$I$7322,BITACORA!$D$4:$D$7322,$A$7:$A$100,BITACORA!$E$4:$E$7322,$B$7:$B$100,BITACORA!$B$4:$B$7322,">="&$B$3,BITACORA!$B$4:$B$7322,"<="&$B$4) -> 0
C94: =SUMIFS(BITACORA!$H$4:$H$7322,BITACORA!$D$4:$D$7322,$A$7:$A$100,BITACORA!$E$4:$E$7322,$B$7:$B$100,BITACORA!$B$4:$B$7322,">="&$B$3,BITACORA!$B$4:$B$7322,"<="&$B$4) -> 0 | D94: =SUMIFS(BITACORA!$I$4:$I$7322,BITACORA!$D$4:$D$7322,$A$7:$A$100,BITACORA!$E$4:$E$7322,$B$7:$B$100,BITACORA!$B$4:$B$7322,">="&$B$3,BITACORA!$B$4:$B$7322,"<="&$B$4) -> 0
C95: =SUMIFS(BITACORA!$H$4:$H$7322,BITACORA!$D$4:$D$7322,$A$7:$A$100,BITACORA!$E$4:$E$7322,$B$7:$B$100,BITACORA!$B$4:$B$7322,">="&$B$3,BITACORA!$B$4:$B$7322,"<="&$B$4) -> 0 | D95: =SUMIFS(BITACORA!$I$4:$I$7322,BITACORA!$D$4:$D$7322,$A$7:$A$100,BITACORA!$E$4:$E$7322,$B$7:$B$100,BITACORA!$B$4:$B$7322,">="&$B$3,BITACORA!$B$4:$B$7322,"<="&$B$4) -> 0
C96: =SUMIFS(BITACORA!$H$4:$H$7322,BITACORA!$D$4:$D$7322,$A$7:$A$100,BITACORA!$E$4:$E$7322,$B$7:$B$100,BITACORA!$B$4:$B$7322,">="&$B$3,BITACORA!$B$4:$B$7322,"<="&$B$4) -> 0 | D96: =SUMIFS(BITACORA!$I$4:$I$7322,BITACORA!$D$4:$D$7322,$A$7:$A$100,BITACORA!$E$4:$E$7322,$B$7:$B$100,BITACORA!$B$4:$B$7322,">="&$B$3,BITACORA!$B$4:$B$7322,"<="&$B$4) -> 0
C97: =SUMIFS(BITACORA!$H$4:$H$7322,BITACORA!$D$4:$D$7322,$A$7:$A$100,BITACORA!$E$4:$E$7322,$B$7:$B$100,BITACORA!$B$4:$B$7322,">="&$B$3,BITACORA!$B$4:$B$7322,"<="&$B$4) -> 0 | D97: =SUMIFS(BITACORA!$I$4:$I$7322,BITACORA!$D$4:$D$7322,$A$7:$A$100,BITACORA!$E$4:$E$7322,$B$7:$B$100,BITACORA!$B$4:$B$7322,">="&$B$3,BITACORA!$B$4:$B$7322,"<="&$B$4) -> 0
C98: =SUMIFS(BITACORA!$H$4:$H$7322,BITACORA!$D$4:$D$7322,$A$7:$A$100,BITACORA!$E$4:$E$7322,$B$7:$B$100,BITACORA!$B$4:$B$7322,">="&$B$3,BITACORA!$B$4:$B$7322,"<="&$B$4) -> 0 | D98: =SUMIFS(BITACORA!$I$4:$I$7322,BITACORA!$D$4:$D$7322,$A$7:$A$100,BITACORA!$E$4:$E$7322,$B$7:$B$100,BITACORA!$B$4:$B$7322,">="&$B$3,BITACORA!$B$4:$B$7322,"<="&$B$4) -> 0
C99: =SUMIFS(BITACORA!$H$4:$H$7322,BITACORA!$D$4:$D$7322,$A$7:$A$100,BITACORA!$E$4:$E$7322,$B$7:$B$100,BITACORA!$B$4:$B$7322,">="&$B$3,BITACORA!$B$4:$B$7322,"<="&$B$4) -> 0 | D99: =SUMIFS(BITACORA!$I$4:$I$7322,BITACORA!$D$4:$D$7322,$A$7:$A$100,BITACORA!$E$4:$E$7322,$B$7:$B$100,BITACORA!$B$4:$B$7322,">="&$B$3,BITACORA!$B$4:$B$7322,"<="&$B$4) -> 0
C100: =SUMIFS(BITACORA!$H$4:$H$7322,BITACORA!$D$4:$D$7322,$A$7:$A$100,BITACORA!$E$4:$E$7322,$B$7:$B$100,BITACORA!$B$4:$B$7322,">="&$B$3,BITACORA!$B$4:$B$7322,"<="&$B$4) -> 0 | D100: =SUMIFS(BITACORA!$I$4:$I$7322,BITACORA!$D$4:$D$7322,$A$7:$A$100,BITACORA!$E$4:$E$7322,$B$7:$B$100,BITACORA!$B$4:$B$7322,">="&$B$3,BITACORA!$B$4:$B$7322,"<="&$B$4) -> 0
C101: =SUMIFS(BITACORA!$H$4:$H$7322,BITACORA!$D$4:$D$7322,$A$7:$A$100,BITACORA!$E$4:$E$7322,$B$7:$B$100,BITACORA!$B$4:$B$7322,">="&$B$3,BITACORA!$B$4:$B$7322,"<="&$B$4) -> 0 | D101: =SUMIFS(BITACORA!$I$4:$I$7322,BITACORA!$D$4:$D$7322,$A$7:$A$100,BITACORA!$E$4:$E$7322,$B$7:$B$100,BITACORA!$B$4:$B$7322,">="&$B$3,BITACORA!$B$4:$B$7322,"<="&$B$4) -> 0
C102: =SUMIFS(BITACORA!$H$4:$H$7322,BITACORA!$D$4:$D$7322,$A$7:$A$100,BITACORA!$E$4:$E$7322,$B$7:$B$100,BITACORA!$B$4:$B$7322,">="&$B$3,BITACORA!$B$4:$B$7322,"<="&$B$4) -> 0 | D102: =SUMIFS(BITACORA!$I$4:$I$7322,BITACORA!$D$4:$D$7322,$A$7:$A$100,BITACORA!$E$4:$E$7322,$B$7:$B$100,BITACORA!$B$4:$B$7322,">="&$B$3,BITACORA!$B$4:$B$7322,"<="&$B$4) -> 0
C103: =SUMIFS(BITACORA!$H$4:$H$7322,BITACORA!$D$4:$D$7322,$A$7:$A$100,BITACORA!$E$4:$E$7322,$B$7:$B$100,BITACORA!$B$4:$B$7322,">="&$B$3,BITACORA!$B$4:$B$7322,"<="&$B$4) -> 0 | D103: =SUMIFS(BITACORA!$I$4:$I$7322,BITACORA!$D$4:$D$7322,$A$7:$A$100,BITACORA!$E$4:$E$7322,$B$7:$B$100,BITACORA!$B$4:$B$7322,">="&$B$3,BITACORA!$B$4:$B$7322,"<="&$B$4) -> 0
C104: =SUMIFS(BITACORA!$H$4:$H$7322,BITACORA!$D$4:$D$7322,$A$7:$A$100,BITACORA!$E$4:$E$7322,$B$7:$B$100,BITACORA!$B$4:$B$7322,">="&$B$3,BITACORA!$B$4:$B$7322,"<="&$B$4) -> 0 | D104: =SUMIFS(BITACORA!$I$4:$I$7322,BITACORA!$D$4:$D$7322,$A$7:$A$100,BITACORA!$E$4:$E$7322,$B$7:$B$100,BITACORA!$B$4:$B$7322,">="&$B$3,BITACORA!$B$4:$B$7322,"<="&$B$4) -> 0
... C160: =SUMIFS(BITACORA!$H$4:$H$7322,BITACORA!$D$4:$D$7322,$A$7:$A$100,BITACORA!$E$4:$E$7322,$B$7:$B$100,BITACORA!$B$4:$B$7322,">="&$B$3,BITACORA!$B$4:$B$7322,"<="&$B$4) -> 0 | D160: =SUMIFS(BITACORA!$I$4:$I$7322,BITACORA!$D$4:$D$7322,$A$7:$A$100,BITACORA!$E$4:$E$7322,$B$7:$B$100,BITACORA!$B$4:$B$7322,">="&$B$3,BITACORA!$B$4:$B$7322,"<="&$B$4) -> 0

Sheet FLETES (#) MAYO
A1: MES | B1: ABRIL | C1: =COUNTIFS(BITACORA!B4:B7322,">="&B3,BITACORA!B4:B7322,"<="&B4) -> 138 | E1: TOTAL DE VIAJES FLETADOS | F1: =SUM(D7:D504) -> 18
D2: 3
A3: FECHA DE INICIO | B3: 44317 | D3: 4 | E3: 170 | F3: 180
A4: FECHA DE CORTE | B4: 44347 | D4: 5 | E4: 190 | F4: 200
D5: 6
A6: =IFERROR(__xludf.DUMMYFUNCTION("IMPORTRANGE(""https://docs.google.com/spreadsheets/d/1utvdjsQjm2nB6A8-WaesD8IPx5qFCLXNwJxEgiS8wno/edit?usp=sharing"",""TRANSPORTISTAS!A1:C500"")"),"TRANSPORTISTA") -> TRANSPORTISTA | B6: =IFERROR(__xludf.DUMMYFUNCTION("""COMPUTED_VALUE"""),"PLACA DEL VEHICULO") -> PLACA DEL VEHICULO | C6: =IFERROR(__xludf.DUMMYFUNCTION("""COMPUTED_VALUE"""),"CAPACIDAD (FILAS)") -> CAPACIDAD (FILAS) | D6: TOTAL DE VIAJES | E6: =LISTAS!$B7 -> TACHINA | F6: =LISTAS!$B8 -> TRES VIAS | G6: =LISTAS!$B9 -> QUININDE | H6: =LISTAS!$B10 -> TAISHA | I6: =LISTAS!$B11 -> ARAJUNO | J6: =LISTAS!$B12 -> 0 | K6: =LISTAS!$B13 -> 0 | L6: =LISTAS!$B14 -> 0 | M6: =LISTAS!$B15 -> 0 | N6: =LISTAS!$B16 -> 0 | O6: =LISTAS!$B17 -> 0 | P6: =LISTAS!$B18 -> 0 | Q6: =LISTAS!$B19 -> 0 | R6: =LISTAS!$B20 -> 0 | S6: =LISTAS!$B21 -> 0 | T6: =LISTAS!$B22 -> 0 | U6: =LISTAS!$B23 -> 0 | V6: =LISTAS!$B24 -> FINCA EN PLANTA | W6: =LISTAS!$B25 -> LA SANDIA | X6: =LISTAS!$B26 -> 0 | Y6: =LISTAS!$B27 -> 0 | Z6: =LISTAS!$B28 -> 0 | AA6: =LISTAS!$B29 -> 0 | AB6: =LISTAS!$B30 -> 0 | AC6: =LISTAS!$B31 -> 0 | AD6: =LISTAS!$B32 -> 0 | AE6: =LISTAS!$B33 -> RIO FRIO | AF6: =LISTAS!$B34 -> RIO FRIO ETAPA 2 | AG6: =LISTAS!$B35 -> BOSQUE PUERTO NUEVO | AH6: =LISTAS!$B36 -> 0 | AI6: =LISTAS!$B37 -> 0 | AJ6: =LISTAS!$B38 -> 0 | AK6: =LISTAS!$B39 -> 0 | AL6: =LISTAS!$B40 -> 0 | AM6: =LISTAS!$B41 -> 0
A7: =IFERROR(__xludf.DUMMYFUNCTION("""COMPUTED_VALUE"""),"Klever Enrique Moreira Cedeño") -> Klever Enrique Moreira Cedeño | B7: =IFERROR(__xludf.DUMMYFUNCTION("""COMPUTED_VALUE"""),"JAR4061") -> JAR4061 | C7: =IFERROR(__xludf.DUMMYFUNCTION("""COMPUTED_VALUE"""),3) -> 3 | D7: =SUM(E7:AM7) -> 0 | E7: =COUNTIFS(BITACORA!$C$4:$C$7322,$B$7:$B$501,BITACORA!$E$4:$E$7322,$E$6:$AM$6,BITACORA!$B$4:$B$7322,">="&$B$3,BITACORA!$B$4:$B$7322,"<="&$B$4) -> 0 | F7: =COUNTIFS(BITACORA!$C$4:$C$7322,$B$7:$B$501,BITACORA!$E$4:$E$7322,$E$6:$AM$6,BITACORA!$B$4:$B$7322,">="&$B$3,BITACORA!$B$4:$B$7322,"<="&$B$4) -> 0 | G7: =COUNTIFS(BITACORA!$C$4:$C$7322,$B$7:$B$501,BITACORA!$E$4:$E$7322,$E$6:$AM$6,BITACORA!$B$4:$B$7322,">="&$B$3,BITACORA!$B$4:$B$7322,"<="&$B$4) -> 0 | H7: =COUNTIFS(BITACORA!$C$4:$C$7322,$B$7:$B$501,BITACORA!$E$4:$E$7322,$E$6:$AM$6,BITACORA!$B$4:$B$7322,">="&$B$3,BITACORA!$B$4:$B$7322,"<="&$B$4) -> 0 | I7: =COUNTIFS(BITACORA!$C$4:$C$7322,$B$7:$B$501,BITACORA!$E$4:$E$7322,$E$6:$AM$6,BITACORA!$B$4:$B$7322,">="&$B$3,BITACORA!$B$4:$B$7322,"<="&$B$4) -> 0 | J7: =COUNTIFS(BITACORA!$C$4:$C$7322,$B$7:$B$501,BITACORA!$E$4:$E$7322,$E$6:$AM$6,BITACORA!$B$4:$B$7322,">="&$B$3,BITACORA!$B$4:$B$7322,"<="&$B$4) -> 0 | K7: =COUNTIFS(BITACORA!$C$4:$C$7322,$B$7:$B$501,BITACORA!$E$4:$E$7322,$E$6:$AM$6,BITACORA!$B$4:$B$7322,">="&$B$3,BITACORA!$B$4:$B$7322,"<="&$B$4) -> 0 | L7: =COUNTIFS(BITACORA!$C$4:$C$7322,$B$7:$B$501,BITACORA!$E$4:$E$7322,$E$6:$AM$6,BITACORA!$B$4:$B$7322,">="&$B$3,BITACORA!$B$4:$B$7322,"<="&$B$4) -> 0 | ... AM7: =COUNTIFS(BITACORA!$C$4:$C$7322,$B$7:$B$501,BITACORA!$E$4:$E$7322,$E$6:$AM$6,BITACORA!$B$4:$B$7322,">="&$B$3,BITACORA!$B$4:$B$7322,"<="&$B$4) -> 0
A8: =IFERROR(__xludf.DUMMYFUNCTION("""COMPUTED_VALUE"""),"Ricardo Coveña Quintero") -> Ricardo Coveña Quintero | B8: =IFERROR(__xludf.DUMMYFUNCTION("""COMPUTED_VALUE"""),"PPX0724") -> PPX0724 | C8: =IFERROR(__xludf.DUMMYFUNCTION("""COMPUTED_VALUE"""),3) -> 3 | D8: =SUM(E8:AM8) -> 0 | E8: =COUNTIFS(BITACORA!$C$4:$C$7322,$B$7:$B$501,BITACORA!$E$4:$E$7322,$E$6:$AM$6,BITACORA!$B$4:$B$7322,">="&$B$3,BITACORA!$B$4:$B$7322,"<="&$B$4) -> 0 | F8: =COUNTIFS(BITACORA!$C$4:$C$7322,$B$7:$B$501,BITACORA!$E$4:$E$7322,$E$6:$AM$6,BITACORA!$B$4:$B$7322,">="&$B$3,BITACORA!$B$4:$B$7322,"<="&$B$4) -> 0 | G8: =COUNTIFS(BITACORA!$C$4:$C$7322,$B$7:$B$501,BITACORA!$E$4:$E$7322,$E$6:$AM$6,BITACORA!$B$4:$B$7322,">="&$B$3,BITACORA!$B$4:$B$7322,"<="&$B$4) -> 0 | H8: =COUNTIFS(BITACORA!$C$4:$C$7322,$B$7:$B$501,BITACORA!$E$4:$E$7322,$E$6:$AM$6,BITACORA!$B$4:$B$7322,">="&$B$3,BITACORA!$B$4:$B$7322,"<="&$B$4) -> 0 | I8: =COUNTIFS(BITACORA!$C$4:$C$7322,$B$7:$B$501,BITACORA!$E$4:$E$7322,$E$6:$AM$6,BITACORA!$B$4:$B$7322,">="&$B$3,BITACORA!$B$4:$B$7322,"<="&$B$4) -> 0 | J8: =COUNTIFS(BITACORA!$C$4:$C$7322,$B$7:$B$501,BITACORA!$E$4:$E$7322,$E$6:$AM$6,BITACORA!$B$4:$B$7322,">="&$B$3,BITACORA!$B$4:$B$7322,"<="&$B$4) -> 0 | K8: =COUNTIFS(BITACORA!$C$4:$C$7322,$B$7:$B$501,BITACORA!$E$4:$E$7322,$E$6:$AM$6,BITACORA!$B$4:$B$7322,">="&$B$3,BITACORA!$B$4:$B$7322,"<="&$B$4) -> 0 | L8: =COUNTIFS(BITACORA!$C$4:$C$7322,$B$7:$B$501,BITACORA!$E$4:$E$7322,$E$6:$AM$6,BITACORA!$B$4:$B$7322,">="&$B$3,BITACORA!$B$4:$B$7322,"<="&$B$4) -> 0 | ... AM8: =COUNTIFS(BITACORA!$C$4:$C$7322,$B$7:$B$501,BITACORA!$E$4:$E$7322,$E$6:$AM$6,BITACORA!$B$4:$B$7322,">="&$B$3,BITACORA!$B$4:$B$7322,"<="&$B$4) -> 0
A9: =IFERROR(__xludf.DUMMYFUNCTION("""COMPUTED_VALUE"""),"Cesar Octavio Aguilar Loor") -> Cesar Octavio Aguilar Loor | B9: =IFERROR(__xludf.DUMMYFUNCTION("""COMPUTED_VALUE"""),"MCW0186") -> MCW0186 | C9: =IFERROR(__xludf.DUMMYFUNCTION("""COMPUTED_VALUE"""),4) -> 4 | D9: =SUM(E9:AM9) -> 1 | E9: =COUNTIFS(BITACORA!$C$4:$C$7322,$B$7:$B$501,BITACORA!$E$4:$E$7322,$E$6:$AM$6,BITACORA!$B$4:$B$7322,">="&$B$3,BITACORA!$B$4:$B$7322,"<="&$B$4) -> 0 | F9: =COUNTIFS(BITACORA!$C$4:$C$7322,$B$7:$B$501,BITACORA!$E$4:$E$7322,$E$6:$AM$6,BITACORA!$B$4:$B$7322,">="&$B$3,BITACORA!$B$4:$B$7322,"<="&$B$4) -> 1 | G9: =COUNTIFS(BITACORA!$C$4:$C$7322,$B$7:$B$501,BITACORA!$E$4:$E$7322,$E$6:$AM$6,BITACORA!$B$4:$B$7322,">="&$B$3,BITACORA!$B$4:$B$7322,"<="&$B$4) -> 0 | H9: =COUNTIFS(BITACORA!$C$4:$C$7322,$B$7:$B$501,BITACORA!$E$4:$E$7322,$E$6:$AM$6,BITACORA!$B$4:$B$7322,">="&$B$3,BITACORA!$B$4:$B$7322,"<="&$B$4) -> 0 | I9: =COUNTIFS(BITACORA!$C$4:$C$7322,$B$7:$B$501,BITACORA!$E$4:$E$7322,$E$6:$AM$6,BITACORA!$B$4:$B$7322,">="&$B$3,BITACORA!$B$4:$B$7322,"<="&$B$4) -> 0 | J9: =COUNTIFS(BITACORA!$C$4:$C$7322,$B$7:$B$501,BITACORA!$E$4:$E$7322,$E$6:$AM$6,BITACORA!$B$4:$B$7322,">="&$B$3,BITACORA!$B$4:$B$7322,"<="&$B$4) -> 0 | K9: =COUNTIFS(BITACORA!$C$4:$C$7322,$B$7:$B$501,BITACORA!$E$4:$E$7322,$E$6:$AM$6,BITACORA!$B$4:$B$7322,">="&$B$3,BITACORA!$B$4:$B$7322,"<="&$B$4) -> 0 | L9: =COUNTIFS(BITACORA!$C$4:$C$7322,$B$7:$B$501,BITACORA!$E$4:$E$7322,$E$6:$AM$6,BITACORA!$B$4:$B$7322,">="&$B$3,BITACORA!$B$4:$B$7322,"<="&$B$4) -> 0 | ... AM9: =COUNTIFS(BITACORA!$C$4:$C$7322,$B$7:$B$501,BITACORA!$E$4:$E$7322,$E$6:$AM$6,BITACORA!$B$4:$B$7322,">="&$B$3,BITACORA!$B$4:$B$7322,"<="&$B$4) -> 0
A10: =IFERROR(__xludf.DUMMYFUNCTION("""COMPUTED_VALUE"""),"Jonathan Jehova Vera Mendoza") -> Jonathan Jehova Vera Mendoza | B10: =IFERROR(__xludf.DUMMYFUNCTION("""COMPUTED_VALUE"""),"JAA3367") -> JAA3367 | C10: =IFERROR(__xludf.DUMMYFUNCTION("""COMPUTED_VALUE"""),4) -> 4 | D10: =SUM(E10:AM10) -> 0 | E10: =COUNTIFS(BITACORA!$C$4:$C$7322,$B$7:$B$501,BITACORA!$E$4:$E$7322,$E$6:$AM$6,BITACORA!$B$4:$B$7322,">="&$B$3,BITACORA!$B$4:$B$7322,"<="&$B$4) -> 0 | F10: =COUNTIFS(BITACORA!$C$4:$C$7322,$B$7:$B$501,BITACORA!$E$4:$E$7322,$E$6:$AM$6,BITACORA!$B$4:$B$7322,">="&$B$3,BITACORA!$B$4:$B$7322,"<="&$B$4) -> 0 | G10: =COUNTIFS(BITACORA!$C$4:$C$7322,$B$7:$B$501,BITACORA!$E$4:$E$7322,$E$6:$AM$6,BITACORA!$B$4:$B$7322,">="&$B$3,BITACORA!$B$4:$B$7322,"<="&$B$4) -> 0 | H10: =COUNTIFS(BITACORA!$C$4:$C$7322,$B$7:$B$501,BITACORA!$E$4:$E$7322,$E$6:$AM$6,BITACORA!$B$4:$B$7322,">="&$B$3,BITACORA!$B$4:$B$7322,"<="&$B$4) -> 0 | I10: =COUNTIFS(BITACORA!$C$4:$C$7322,$B$7:$B$501,BITACORA!$E$4:$E$7322,$E$6:$AM$6,BITACORA!$B$4:$B$7322,">="&$B$3,BITACORA!$B$4:$B$7322,"<="&$B$4) -> 0 | J10: =COUNTIFS(BITACORA!$C$4:$C$7322,$B$7:$B$501,BITACORA!$E$4:$E$7322,$E$6:$AM$6,BITACORA!$B$4:$B$7322,">="&$B$3,BITACORA!$B$4:$B$7322,"<="&$B$4) -> 0 | K10: =COUNTIFS(BITACORA!$C$4:$C$7322,$B$7:$B$501,BITACORA!$E$4:$E$7322,$E$6:$AM$6,BITACORA!$B$4:$B$7322,">="&$B$3,BITACORA!$B$4:$B$7322,"<="&$B$4) -> 0 | L10: =COUNTIFS(BITACORA!$C$4:$C$7322,$B$7:$B$501,BITACORA!$E$4:$E$7322,$E$6:$AM$6,BITACORA!$B$4:$B$7322,">="&$B$3,BITACORA!$B$4:$B$7322,"<="&$B$4) -> 0 | ... AM10: =COUNTIFS(BITACORA!$C$4:$C$7322,$B$7:$B$501,BITACORA!$E$4:$E$7322,$E$6:$AM$6,BITACORA!$B$4:$B$7322,">="&$B$3,BITACORA!$B$4:$B$7322,"<="&$B$4) -> 0
A11: =IFERROR(__xludf.DUMMYFUNCTION("""COMPUTED_VALUE"""),"Emerson Fabricio Moreira Alcivar") -> Emerson Fabricio Moreira Alcivar | B11: =IFERROR(__xludf.DUMMYFUNCTION("""COMPUTED_VALUE"""),"JAA3375") -> JAA3375 | C11: =IFERROR(__xludf.DUMMYFUNCTION("""COMPUTED_VALUE"""),4) -> 4 | D11: =SUM(E11:AM11) -> 3 | E11: =COUNTIFS(BITACORA!$C$4:$C$7322,$B$7:$B$501,BITACORA!$E$4:$E$7322,$E$6:$AM$6,BITACORA!$B$4:$B$7322,">="&$B$3,BITACORA!$B$4:$B$7322,"<="&$B$4) -> 0 | F11: =COUNTIFS(BITACORA!$C$4:$C$7322,$B$7:$B$501,BITACORA!$E$4:$E$7322,$E$6:$AM$6,BITACORA!$B$4:$B$7322,">="&$B$3,BITACORA!$B$4:$B$7322,"<="&$B$4) -> 3 | G11: =COUNTIFS(BITACORA!$C$4:$C$7322,$B$7:$B$501,BITACORA!$E$4:$E$7322,$E$6:$AM$6,BITACORA!$B$4:$B$7322,">="&$B$3,BITACORA!$B$4:$B$7322,"<="&$B$4) -> 0 | H11: =COUNTIFS(BITACORA!$C$4:$C$7322,$B$7:$B$501,BITACORA!$E$4:$E$7322,$E$6:$AM$6,BITACORA!$B$4:$B$7322,">="&$B$3,BITACORA!$B$4:$B$7322,"<="&$B$4) -> 0 | I11: =COUNTIFS(BITACORA!$C$4:$C$7322,$B$7:$B$501,BITACORA!$E$4:$E$7322,$E$6:$AM$6,BITACORA!$B$4:$B$7322,">="&$B$3,BITACORA!$B$4:$B$7322,"<="&$B$4) -> 0 | J11: =COUNTIFS(BITACORA!$C$4:$C$7322,$B$7:$B$501,BITACORA!$E$4:$E$7322,$E$6:$AM$6,BITACORA!$B$4:$B$7322,">="&$B$3,BITACORA!$B$4:$B$7322,"<="&$B$4) -> 0 | K11: =COUNTIFS(BITACORA!$C$4:$C$7322,$B$7:$B$501,BITACORA!$E$4:$E$7322,$E$6:$AM$6,BITACORA!$B$4:$B$7322,">="&$B$3,BITACORA!$B$4:$B$7322,"<="&$B$4) -> 0 | L11: =COUNTIFS(BITACORA!$C$4:$C$7322,$B$7:$B$501,BITACORA!$E$4:$E$7322,$E$6:$AM$6,BITACORA!$B$4:$B$7322,">="&$B$3,BITACORA!$B$4:$B$7322,"<="&$B$4) -> 0 | ... AM11: =COUNTIFS(BITACORA!$C$4:$C$7322,$B$7:$B$501,BITACORA!$E$4:$E$7322,$E$6:$AM$6,BITACORA!$B$4:$B$7322,">="&$B$3,BITACORA!$B$4:$B$7322,"<="&$B$4) -> 0
A12: =IFERROR(__xludf.DUMMYFUNCTION("""COMPUTED_VALUE"""),"Cedeño Barveran Marcelo German") -> Cedeño Barveran Marcelo German | B12: =IFERROR(__xludf.DUMMYFUNCTION("""COMPUTED_VALUE"""),"MAP0286") -> MAP0286 | C12: =IFERROR(__xludf.DUMMYFUNCTION("""COMPUTED_VALUE"""),4) -> 4 | D12: =SUM(E12:AM12) -> 0 | E12: =COUNTIFS(BITACORA!$C$4:$C$7322,$B$7:$B$501,BITACORA!$E$4:$E$7322,$E$6:$AM$6,BITACORA!$B$4:$B$7322,">="&$B$3,BITACORA!$B$4:$B$7322,"<="&$B$4) -> 0 | F12: =COUNTIFS(BITACORA!$C$4:$C$7322,$B$7:$B$501,BITACORA!$E$4:$E$7322,$E$6:$AM$6,BITACORA!$B$4:$B$7322,">="&$B$3,BITACORA!$B$4:$B$7322,"<="&$B$4) -> 0 | G12: =COUNTIFS(BITACORA!$C$4:$C$7322,$B$7:$B$501,BITACORA!$E$4:$E$7322,$E$6:$AM$6,BITACORA!$B$4:$B$7322,">="&$B$3,BITACORA!$B$4:$B$7322,"<="&$B$4) -> 0 | H12: =COUNTIFS(BITACORA!$C$4:$C$7322,$B$7:$B$501,BITACORA!$E$4:$E$7322,$E$6:$AM$6,BITACORA!$B$4:$B$7322,">="&$B$3,BITACORA!$B$4:$B$7322,"<="&$B$4) -> 0 | I12: =COUNTIFS(BITACORA!$C$4:$C$7322,$B$7:$B$501,BITACORA!$E$4:$E$7322,$E$6:$AM$6,BITACORA!$B$4:$B$7322,">="&$B$3,BITACORA!$B$4:$B$7322,"<="&$B$4) -> 0 | J12: =COUNTIFS(BITACORA!$C$4:$C$7322,$B$7:$B$501,BITACORA!$E$4:$E$7322,$E$6:$AM$6,BITACORA!$B$4:$B$7322,">="&$B$3,BITACORA!$B$4:$B$7322,"<="&$B$4) -> 0 | K12: =COUNTIFS(BITACORA!$C$4:$C$7322,$B$7:$B$501,BITACORA!$E$4:$E$7322,$E$6:$AM$6,BITACORA!$B$4:$B$7322,">="&$B$3,BITACORA!$B$4:$B$7322,"<="&$B$4) -> 0 | L12: =COUNTIFS(BITACORA!$C$4:$C$7322,$B$7:$B$501,BITACORA!$E$4:$E$7322,$E$6:$AM$6,BITACORA!$B$4:$B$7322,">="&$B$3,BITACORA!$B$4:$B$7322,"<="&$B$4) -> 0 | ... AM12: =COUNTIFS(BITACORA!$C$4:$C$7322,$B$7:$B$501,BITACORA!$E$4:$E$7322,$E$6:$AM$6,BITACORA!$B$4:$B$7322,">="&$B$3,BITACORA!$B$4:$B$7322,"<="&$B$4) -> 0
A13: =IFERROR(__xludf.DUMMYFUNCTION("""COMPUTED_VALUE"""),"Jonathan Alejandro Diaz Montes") -> Jonathan Alejandro Diaz Montes | B13: =IFERROR(__xludf.DUMMYFUNCTION("""COMPUTED_VALUE"""),"PQX0243") -> PQX0243 | C13: =IFERROR(__xludf.DUMMYFUNCTION("""COMPUTED_VALUE"""),4) -> 4 | D13: =SUM(E13:AM13) -> 0 | E13: =COUNTIFS(BITACORA!$C$4:$C$7322,$B$7:$B$501,BITACORA!$E$4:$E$7322,$E$6:$AM$6,BITACORA!$B$4:$B$7322,">="&$B$3,BITACORA!$B$4:$B$7322,"<="&$B$4) -> 0 | F13: =COUNTIFS(BITACORA!$C$4:$C$7322,$B$7:$B$501,BITACORA!$E$4:$E$7322,$E$6:$AM$6,BITACORA!$B$4:$B$7322,">="&$B$3,BITACORA!$B$4:$B$7322,"<="&$B$4) -> 0 | G13: =COUNTIFS(BITACORA!$C$4:$C$7322,$B$7:$B$501,BITACORA!$E$4:$E$7322,$E$6:$AM$6,BITACORA!$B$4:$B$7322,">="&$B$3,BITACORA!$B$4:$B$7322,"<="&$B$4) -> 0 | H13: =COUNTIFS(BITACORA!$C$4:$C$7322,$B$7:$B$501,BITACORA!$E$4:$E$7322,$E$6:$AM$6,BITACORA!$B$4:$B$7322,">="&$B$3,BITACORA!$B$4:$B$7322,"<="&$B$4) -> 0 | I13: =COUNTIFS(BITACORA!$C$4:$C$7322,$B$7:$B$501,BITACORA!$E$4:$E$7322,$E$6:$AM$6,BITACORA!$B$4:$B$7322,">="&$B$3,BITACORA!$B$4:$B$7322,"<="&$B$4) -> 0 | J13: =COUNTIFS(BITACORA!$C$4:$C$7322,$B$7:$B$501,BITACORA!$E$4:$E$7322,$E$6:$AM$6,BITACORA!$B$4:$B$7322,">="&$B$3,BITACORA!$B$4:$B$7322,"<="&$B$4) -> 0 | K13: =COUNTIFS(BITACORA!$C$4:$C$7322,$B$7:$B$501,BITACORA!$E$4:$E$7322,$E$6:$AM$6,BITACORA!$B$4:$B$7322,">="&$B$3,BITACORA!$B$4:$B$7322,"<="&$B$4) -> 0 | L13: =COUNTIFS(BITACORA!$C$4:$C$7322,$B$7:$B$501,BITACORA!$E$4:$E$7322,$E$6:$AM$6,BITACORA!$B$4:$B$7322,">="&$B$3,BITACORA!$B$4:$B$7322,"<="&$B$4) -> 0 | ... AM13: =COUNTIFS(BITACORA!$C$4:$C$7322,$B$7:$B$501,BITACORA!$E$4:$E$7322,$E$6:$AM$6,BITACORA!$B$4:$B$7322,">="&$B$3,BITACORA!$B$4:$B$7322,"<="&$B$4) -> 0
A14: =IFERROR(__xludf.DUMMYFUNCTION("""COMPUTED_VALUE"""),"Freddy Amador Napa Rosado") -> Freddy Amador Napa Rosado | B14: =IFERROR(__xludf.DUMMYFUNCTION("""COMPUTED_VALUE"""),"PIB0529") -> PIB0529 | C14: =IFERROR(__xludf.DUMMYFUNCTION("""COMPUTED_VALUE"""),4) -> 4 | D14: =SUM(E14:AM14) -> 0 | E14: =COUNTIFS(BITACORA!$C$4:$C$7322,$B$7:$B$501,BITACORA!$E$4:$E$7322,$E$6:$AM$6,BITACORA!$B$4:$B$7322,">="&$B$3,BITACORA!$B$4:$B$7322,"<="&$B$4) -> 0 | F14: =COUNTIFS(BITACORA!$C$4:$C$7322,$B$7:$B$501,BITACORA!$E$4:$E$7322,$E$6:$AM$6,BITACORA!$B$4:$B$7322,">="&$B$3,BITACORA!$B$4:$B$7322,"<="&$B$4) -> 0 | G14: =COUNTIFS(BITACORA!$C$4:$C$7322,$B$7:$B$501,BITACORA!$E$4:$E$7322,$E$6:$AM$6,BITACORA!$B$4:$B$7322,">="&$B$3,BITACORA!$B$4:$B$7322,"<="&$B$4) -> 0 | H14: =COUNTIFS(BITACORA!$C$4:$C$7322,$B$7:$B$501,BITACORA!$E$4:$E$7322,$E$6:$AM$6,BITACORA!$B$4:$B$7322,">="&$B$3,BITACORA!$B$4:$B$7322,"<="&$B$4) -> 0 | I14: =COUNTIFS(BITACORA!$C$4:$C$7322,$B$7:$B$501,BITACORA!$E$4:$E$7322,$E$6:$AM$6,BITACORA!$B$4:$B$7322,">="&$B$3,BITACORA!$B$4:$B$7322,"<="&$B$4) -> 0 | J14: =COUNTIFS(BITACORA!$C$4:$C$7322,$B$7:$B$501,BITACORA!$E$4:$E$7322,$E$6:$AM$6,BITACORA!$B$4:$B$7322,">="&$B$3,BITACORA!$B$4:$B$7322,"<="&$B$4) -> 0 | K14: =COUNTIFS(BITACORA!$C$4:$C$7322,$B$7:$B$501,BITACORA!$E$4:$E$7322,$E$6:$AM$6,BITACORA!$B$4:$B$7322,">="&$B$3,BITACORA!$B$4:$B$7322,"<="&$B$4) -> 0 | L14: =COUNTIFS(BITACORA!$C$4:$C$7322,$B$7:$B$501,BITACORA!$E$4:$E$7322,$E$6:$AM$6,BITACORA!$B$4:$B$7322,">="&$B$3,BITACORA!$B$4:$B$7322,"<="&$B$4) -> 0 | ... AM14: =COUNTIFS(BITACORA!$C$4:$C$7322,$B$7:$B$501,BITACORA!$E$4:$E$7322,$E$6:$AM$6,BITACORA!$B$4:$B$7322,">="&$B$3,BITACORA!$B$4:$B$7322,"<="&$B$4) -> 0
A15: =IFERROR(__xludf.DUMMYFUNCTION("""COMPUTED_VALUE"""),"Diego Adrian Mendoza Velez") -> Diego Adrian Mendoza Velez | B15: =IFERROR(__xludf.DUMMYFUNCTION("""COMPUTED_VALUE"""),"JAA3376") -> JAA3376 | C15: =IFERROR(__xludf.DUMMYFUNCTION("""COMPUTED_VALUE"""),4) -> 4 | D15: =SUM(E15:AM15) -> 0 | E15: =COUNTIFS(BITACORA!$C$4:$C$7322,$B$7:$B$501,BITACORA!$E$4:$E$7322,$E$6:$AM$6,BITACORA!$B$4:$B$7322,">="&$B$3,BITACORA!$B$4:$B$7322,"<="&$B$4) -> 0 | F15: =COUNTIFS(BITACORA!$C$4:$C$7322,$B$7:$B$501,BITACORA!$E$4:$E$7322,$E$6:$AM$6,BITACORA!$B$4:$B$7322,">="&$B$3,BITACORA!$B$4:$B$7322,"<="&$B$4) -> 0 | G15: =COUNTIFS(BITACORA!$C$4:$C$7322,$B$7:$B$501,BITACORA!$E$4:$E$7322,$E$6:$AM$6,BITACORA!$B$4:$B$7322,">="&$B$3,BITACORA!$B$4:$B$7322,"<="&$B$4) -> 0 | H15: =COUNTIFS(BITACORA!$C$4:$C$7322,$B$7:$B$501,BITACORA!$E$4:$E$7322,$E$6:$AM$6,BITACORA!$B$4:$B$7322,">="&$B$3,BITACORA!$B$4:$B$7322,"<="&$B$4) -> 0 | I15: =COUNTIFS(BITACORA!$C$4:$C$7322,$B$7:$B$501,BITACORA!$E$4:$E$7322,$E$6:$AM$6,BITACORA!$B$4:$B$7322,">="&$B$3,BITACORA!$B$4:$B$7322,"<="&$B$4) -> 0 | J15: =COUNTIFS(BITACORA!$C$4:$C$7322,$B$7:$B$501,BITACORA!$E$4:$E$7322,$E$6:$AM$6,BITACORA!$B$4:$B$7322,">="&$B$3,BITACORA!$B$4:$B$7322,"<="&$B$4) -> 0 | K15: =COUNTIFS(BITACORA!$C$4:$C$7322,$B$7:$B$501,BITACORA!$E$4:$E$7322,$E$6:$AM$6,BITACORA!$B$4:$B$7322,">="&$B$3,BITACORA!$B$4:$B$7322,"<="&$B$4) -> 0 | L15: =COUNTIFS(BITACORA!$C$4:$C$7322,$B$7:$B$501,BITACORA!$E$4:$E$7322,$E$6:$AM$6,BITACORA!$B$4:$B$7322,">="&$B$3,BITACORA!$B$4:$B$7322,"<="&$B$4) -> 0 | ... AM15: =COUNTIFS(BITACORA!$C$4:$C$7322,$B$7:$B$501,BITACORA!$E$4:$E$7322,$E$6:$AM$6,BITACORA!$B$4:$B$7322,">="&$B$3,BITACORA!$B$4:$B$7322,"<="&$B$4) -> 0
A16: =IFERROR(__xludf.DUMMYFUNCTION("""COMPUTED_VALUE"""),"Oscar Jose Loor Basurto") -> Oscar Jose Loor Basurto | B16: =IFERROR(__xludf.DUMMYFUNCTION("""COMPUTED_VALUE"""),"PJB0702") -> PJB0702 | C16: =IFERROR(__xludf.DUMMYFUNCTION("""COMPUTED_VALUE"""),4) -> 4 | D16: =SUM(E16:AM16) -> 0 | E16: =COUNTIFS(BITACORA!$C$4:$C$7322,$B$7:$B$501,BITACORA!$E$4:$E$7322,$E$6:$AM$6,BITACORA!$B$4:$B$7322,">="&$B$3,BITACORA!$B$4:$B$7322,"<="&$B$4) -> 0 | F16: =COUNTIFS(BITACORA!$C$4:$C$7322,$B$7:$B$501,BITACORA!$E$4:$E$7322,$E$6:$AM$6,BITACORA!$B$4:$B$7322,">="&$B$3,BITACORA!$B$4:$B$7322,"<="&$B$4) -> 0 | G16: =COUNTIFS(BITACORA!$C$4:$C$7322,$B$7:$B$501,BITACORA!$E$4:$E$7322,$E$6:$AM$6,BITACORA!$B$4:$B$7322,">="&$B$3,BITACORA!$B$4:$B$7322,"<="&$B$4) -> 0 | H16: =COUNTIFS(BITACORA!$C$4:$C$7322,$B$7:$B$501,BITACORA!$E$4:$E$7322,$E$6:$AM$6,BITACORA!$B$4:$B$7322,">="&$B$3,BITACORA!$B$4:$B$7322,"<="&$B$4) -> 0 | I16: =COUNTIFS(BITACORA!$C$4:$C$7322,$B$7:$B$501,BITACORA!$E$4:$E$7322,$E$6:$AM$6,BITACORA!$B$4:$B$7322,">="&$B$3,BITACORA!$B$4:$B$7322,"<="&$B$4) -> 0 | J16: =COUNTIFS(BITACORA!$C$4:$C$7322,$B$7:$B$501,BITACORA!$E$4:$E$7322,$E$6:$AM$6,BITACORA!$B$4:$B$7322,">="&$B$3,BITACORA!$B$4:$B$7322,"<="&$B$4) -> 0 | K16: =COUNTIFS(BITACORA!$C$4:$C$7322,$B$7:$B$501,BITACORA!$E$4:$E$7322,$E$6:$AM$6,BITACORA!$B$4:$B$7322,">="&$B$3,BITACORA!$B$4:$B$7322,"<="&$B$4) -> 0 | L16: =COUNTIFS(BITACORA!$C$4:$C$7322,$B$7:$B$501,BITACORA!$E$4:$E$7322,$E$6:$AM$6,BITACORA!$B$4:$B$7322,">="&$B$3,BITACORA!$B$4:$B$7322,"<="&$B$4) -> 0 | ... AM16: =COUNTIFS(BITACORA!$C$4:$C$7322,$B$7:$B$501,BITACORA!$E$4:$E$7322,$E$6:$AM$6,BITACORA!$B$4:$B$7322,">="&$B$3,BITACORA!$B$4:$B$7322,"<="&$B$4) -> 0
A17: =IFERROR(__xludf.DUMMYFUNCTION("""COMPUTED_VALUE"""),"Angulo Saltos Marlon Fabian") -> Angulo Saltos Marlon Fabian | B17: =IFERROR(__xludf.DUMMYFUNCTION("""COMPUTED_VALUE"""),"GKX0511") -> GKX0511 | C17: =IFERROR(__xludf.DUMMYFUNCTION("""COMPUTED_VALUE"""),4) -> 4 | D17: =SUM(E17:AM17) -> 0 | E17: =COUNTIFS(BITACORA!$C$4:$C$7322,$B$7:$B$501,BITACORA!$E$4:$E$7322,$E$6:$AM$6,BITACORA!$B$4:$B$7322,">="&$B$3,BITACORA!$B$4:$B$7322,"<="&$B$4) -> 0 | F17: =COUNTIFS(BITACORA!$C$4:$C$7322,$B$7:$B$501,BITACORA!$E$4:$E$7322,$E$6:$AM$6,BITACORA!$B$4:$B$7322,">="&$B$3,BITACORA!$B$4:$B$7322,"<="&$B$4) -> 0 | G17: =COUNTIFS(BITACORA!$C$4:$C$7322,$B$7:$B$501,BITACORA!$E$4:$E$7322,$E$6:$AM$6,BITACORA!$B$4:$B$7322,">="&$B$3,BITACORA!$B$4:$B$7322,"<="&$B$4) -> 0 | H17: =COUNTIFS(BITACORA!$C$4:$C$7322,$B$7:$B$501,BITACORA!$E$4:$E$7322,$E$6:$AM$6,BITACORA!$B$4:$B$7322,">="&$B$3,BITACORA!$B$4:$B$7322,"<="&$B$4) -> 0 | I17: =COUNTIFS(BITACORA!$C$4:$C$7322,$B$7:$B$501,BITACORA!$E$4:$E$7322,$E$6:$AM$6,BITACORA!$B$4:$B$7322,">="&$B$3,BITACORA!$B$4:$B$7322,"<="&$B$4) -> 0 | J17: =COUNTIFS(BITACORA!$C$4:$C$7322,$B$7:$B$501,BITACORA!$E$4:$E$7322,$E$6:$AM$6,BITACORA!$B$4:$B$7322,">="&$B$3,BITACORA!$B$4:$B$7322,"<="&$B$4) -> 0 | K17: =COUNTIFS(BITACORA!$C$4:$C$7322,$B$7:$B$501,BITACORA!$E$4:$E$7322,$E$6:$AM$6,BITACORA!$B$4:$B$7322,">="&$B$3,BITACORA!$B$4:$B$7322,"<="&$B$4) -> 0 | L17: =COUNTIFS(BITACORA!$C$4:$C$7322,$B$7:$B$501,BITACORA!$E$4:$E$7322,$E$6:$AM$6,BITACORA!$B$4:$B$7322,">="&$B$3,BITACORA!$B$4:$B$7322,"<="&$B$4) -> 0 | ... AM17: =COUNTIFS(BITACORA!$C$4:$C$7322,$B$7:$B$501,BITACORA!$E$4:$E$7322,$E$6:$AM$6,BITACORA!$B$4:$B$7322,">="&$B$3,BITACORA!$B$4:$B$7322,"<="&$B$4) -> 0
A18: =IFERROR(__xludf.DUMMYFUNCTION("""COMPUTED_VALUE"""),"Enner Eliezer Cevallos Burgos") -> Enner Eliezer Cevallos Burgos | B18: =IFERROR(__xludf.DUMMYFUNCTION("""COMPUTED_VALUE"""),"PZI0105") -> PZI0105 | C18: =IFERROR(__xludf.DUMMYFUNCTION("""COMPUTED_VALUE"""),5) -> 5 | D18: =SUM(E18:AM18) -> 1 | E18: =COUNTIFS(BITACORA!$C$4:$C$7322,$B$7:$B$501,BITACORA!$E$4:$E$7322,$E$6:$AM$6,BITACORA!$B$4:$B$7322,">="&$B$3,BITACORA!$B$4:$B$7322,"<="&$B$4) -> 0 | F18: =COUNTIFS(BITACORA!$C$4:$C$7322,$B$7:$B$501,BITACORA!$E$4:$E$7322,$E$6:$AM$6,BITACORA!$B$4:$B$7322,">="&$B$3,BITACORA!$B$4:$B$7322,"<="&$B$4) -> 1 | G18: =COUNTIFS(BITACORA!$C$4:$C$7322,$B$7:$B$501,BITACORA!$E$4:$E$7322,$E$6:$AM$6,BITACORA!$B$4:$B$7322,">="&$B$3,BITACORA!$B$4:$B$7322,"<="&$B$4) -> 0 | H18: =COUNTIFS(BITACORA!$C$4:$C$7322,$B$7:$B$501,BITACORA!$E$4:$E$7322,$E$6:$AM$6,BITACORA!$B$4:$B$7322,">="&$B$3,BITACORA!$B$4:$B$7322,"<="&$B$4) -> 0 | I18: =COUNTIFS(BITACORA!$C$4:$C$7322,$B$7:$B$501,BITACORA!$E$4:$E$7322,$E$6:$AM$6,BITACORA!$B$4:$B$7322,">="&$B$3,BITACORA!$B$4:$B$7322,"<="&$B$4) -> 0 | J18: =COUNTIFS(BITACORA!$C$4:$C$7322,$B$7:$B$501,BITACORA!$E$4:$E$7322,$E$6:$AM$6,BITACORA!$B$4:$B$7322,">="&$B$3,BITACORA!$B$4:$B$7322,"<="&$B$4) -> 0 | K18: =COUNTIFS(BITACORA!$C$4:$C$7322,$B$7:$B$501,BITACORA!$E$4:$E$7322,$E$6:$AM$6,BITACORA!$B$4:$B$7322,">="&$B$3,BITACORA!$B$4:$B$7322,"<="&$B$4) -> 0 | L18: =COUNTIFS(BITACORA!$C$4:$C$7322,$B$7:$B$501,BITACORA!$E$4:$E$7322,$E$6:$AM$6,BITACORA!$B$4:$B$7322,">="&$B$3,BITACORA!$B$4:$B$7322,"<="&$B$4) -> 0 | ... AM18: =COUNTIFS(BITACORA!$C$4:$C$7322,$B$7:$B$501,BITACORA!$E$4:$E$7322,$E$6:$AM$6,BITACORA!$B$4:$B$7322,">="&$B$3,BITACORA!$B$4:$B$7322,"<="&$B$4) -> 0
A19: =IFERROR(__xludf.DUMMYFUNCTION("""COMPUTED_VALUE"""),"Luis Javier Jaramillo Vera") -> Luis Javier Jaramillo Vera | B19: =IFERROR(__xludf.DUMMYFUNCTION("""COMPUTED_VALUE"""),"HAJ0694") -> HAJ0694 | C19: =IFERROR(__xludf.DUMMYFUNCTION("""COMPUTED_VALUE"""),5) -> 5 | D19: =SUM(E19:AM19) -> 0 | E19: =COUNTIFS(BITACORA!$C$4:$C$7322,$B$7:$B$501,BITACORA!$E$4:$E$7322,$E$6:$AM$6,BITACORA!$B$4:$B$7322,">="&$B$3,BITACORA!$B$4:$B$7322,"<="&$B$4) -> 0 | F19: =COUNTIFS(BITACORA!$C$4:$C$7322,$B$7:$B$501,BITACORA!$E$4:$E$7322,$E$6:$AM$6,BITACORA!$B$4:$B$7322,">="&$B$3,BITACORA!$B$4:$B$7322,"<="&$B$4) -> 0 | G19: =COUNTIFS(BITACORA!$C$4:$C$7322,$B$7:$B$501,BITACORA!$E$4:$E$7322,$E$6:$AM$6,BITACORA!$B$4:$B$7322,">="&$B$3,BITACORA!$B$4:$B$7322,"<="&$B$4) -> 0 | H19: =COUNTIFS(BITACORA!$C$4:$C$7322,$B$7:$B$501,BITACORA!$E$4:$E$7322,$E$6:$AM$6,BITACORA!$B$4:$B$7322,">="&$B$3,BITACORA!$B$4:$B$7322,"<="&$B$4) -> 0 | I19: =COUNTIFS(BITACORA!$C$4:$C$7322,$B$7:$B$501,BITACORA!$E$4:$E$7322,$E$6:$AM$6,BITACORA!$B$4:$B$7322,">="&$B$3,BITACORA!$B$4:$B$7322,"<="&$B$4) -> 0 | J19: =COUNTIFS(BITACORA!$C$4:$C$7322,$B$7:$B$501,BITACORA!$E$4:$E$7322,$E$6:$AM$6,BITACORA!$B$4:$B$7322,">="&$B$3,BITACORA!$B$4:$B$7322,"<="&$B$4) -> 0 | K19: =COUNTIFS(BITACORA!$C$4:$C$7322,$B$7:$B$501,BITACORA!$E$4:$E$7322,$E$6:$AM$6,BITACORA!$B$4:$B$7322,">="&$B$3,BITACORA!$B$4:$B$7322,"<="&$B$4) -> 0 | L19: =COUNTIFS(BITACORA!$C$4:$C$7322,$B$7:$B$501,BITACORA!$E$4:$E$7322,$E$6:$AM$6,BITACORA!$B$4:$B$7322,">="&$B$3,BITACORA!$B$4:$B$7322,"<="&$B$4) -> 0 | ... AM19: =COUNTIFS(BITACORA!$C$4:$C$7322,$B$7:$B$501,BITACORA!$E$4:$E$7322,$E$6:$AM$6,BITACORA!$B$4:$B$7322,">="&$B$3,BITACORA!$B$4:$B$7322,"<="&$B$4) -> 0
A20: =IFERROR(__xludf.DUMMYFUNCTION("""COMPUTED_VALUE"""),"Gabriel Rolando Muentes Cornejo") -> Gabriel Rolando Muentes Cornejo | B20: =IFERROR(__xludf.DUMMYFUNCTION("""COMPUTED_VALUE"""),"BAC0784") -> BAC0784 | C20: =IFERROR(__xludf.DUMMYFUNCTION("""COMPUTED_VALUE"""),5) -> 5 | D20: =SUM(E20:AM20) -> 0 | E20: =COUNTIFS(BITACORA!$C$4:$C$7322,$B$7:$B$501,BITACORA!$E$4:$E$7322,$E$6:$AM$6,BITACORA!$B$4:$B$7322,">="&$B$3,BITACORA!$B$4:$B$7322,"<="&$B$4) -> 0 | F20: =COUNTIFS(BITACORA!$C$4:$C$7322,$B$7:$B$501,BITACORA!$E$4:$E$7322,$E$6:$AM$6,BITACORA!$B$4:$B$7322,">="&$B$3,BITACORA!$B$4:$B$7322,"<="&$B$4) -> 0 | G20: =COUNTIFS(BITACORA!$C$4:$C$7322,$B$7:$B$501,BITACORA!$E$4:$E$7322,$E$6:$AM$6,BITACORA!$B$4:$B$7322,">="&$B$3,BITACORA!$B$4:$B$7322,"<="&$B$4) -> 0 | H20: =COUNTIFS(BITACORA!$C$4:$C$7322,$B$7:$B$501,BITACORA!$E$4:$E$7322,$E$6:$AM$6,BITACORA!$B$4:$B$7322,">="&$B$3,BITACORA!$B$4:$B$7322,"<="&$B$4) -> 0 | I20: =COUNTIFS(BITACORA!$C$4:$C$7322,$B$7:$B$501,BITACORA!$E$4:$E$7322,$E$6:$AM$6,BITACORA!$B$4:$B$7322,">="&$B$3,BITACORA!$B$4:$B$7322,"<="&$B$4) -> 0 | J20: =COUNTIFS(BITACORA!$C$4:$C$7322,$B$7:$B$501,BITACORA!$E$4:$E$7322,$E$6:$AM$6,BITACORA!$B$4:$B$7322,">="&$B$3,BITACORA!$B$4:$B$7322,"<="&$B$4) -> 0 | K20: =COUNTIFS(BITACORA!$C$4:$C$7322,$B$7:$B$501,BITACORA!$E$4:$E$7322,$E$6:$AM$6,BITACORA!$B$4:$B$7322,">="&$B$3,BITACORA!$B$4:$B$7322,"<="&$B$4) -> 0 | L20: =COUNTIFS(BITACORA!$C$4:$C$7322,$B$7:$B$501,BITACORA!$E$4:$E$7322,$E$6:$AM$6,BITACORA!$B$4:$B$7322,">="&$B$3,BITACORA!$B$4:$B$7322,"<="&$B$4) -> 0 | ... AM20: =COUNTIFS(BITACORA!$C$4:$C$7322,$B$7:$B$501,BITACORA!$E$4:$E$7322,$E$6:$AM$6,BITACORA!$B$4:$B$7322,">="&$B$3,BITACORA!$B$4:$B$7322,"<="&$B$4) -> 0
A21: =IFERROR(__xludf.DUMMYFUNCTION("""COMPUTED_VALUE"""),"Nexar Celestino Vargas Intrigo") -> Nexar Celestino Vargas Intrigo | B21: =IFERROR(__xludf.DUMMYFUNCTION("""COMPUTED_VALUE"""),"MAA4517") -> MAA4517 | C21: =IFERROR(__xludf.DUMMYFUNCTION("""COMPUTED_VALUE"""),5) -> 5 | D21: =SUM(E21:AM21) -> 0 | E21: =COUNTIFS(BITACORA!$C$4:$C$7322,$B$7:$B$501,BITACORA!$E$4:$E$7322,$E$6:$AM$6,BITACORA!$B$4:$B$7322,">="&$B$3,BITACORA!$B$4:$B$7322,"<="&$B$4) -> 0 | F21: =COUNTIFS(BITACORA!$C$4:$C$7322,$B$7:$B$501,BITACORA!$E$4:$E$7322,$E$6:$AM$6,BITACORA!$B$4:$B$7322,">="&$B$3,BITACORA!$B$4:$B$7322,"<="&$B$4) -> 0 | G21: =COUNTIFS(BITACORA!$C$4:$C$7322,$B$7:$B$501,BITACORA!$E$4:$E$7322,$E$6:$AM$6,BITACORA!$B$4:$B$7322,">="&$B$3,BITACORA!$B$4:$B$7322,"<="&$B$4) -> 0 | H21: =COUNTIFS(BITACORA!$C$4:$C$7322,$B$7:$B$501,BITACORA!$E$4:$E$7322,$E$6:$AM$6,BITACORA!$B$4:$B$7322,">="&$B$3,BITACORA!$B$4:$B$7322,"<="&$B$4) -> 0 | I21: =COUNTIFS(BITACORA!$C$4:$C$7322,$B$7:$B$501,BITACORA!$E$4:$E$7322,$E$6:$AM$6,BITACORA!$B$4:$B$7322,">="&$B$3,BITACORA!$B$4:$B$7322,"<="&$B$4) -> 0 | J21: =COUNTIFS(BITACORA!$C$4:$C$7322,$B$7:$B$501,BITACORA!$E$4:$E$7322,$E$6:$AM$6,BITACORA!$B$4:$B$7322,">="&$B$3,BITACORA!$B$4:$B$7322,"<="&$B$4) -> 0 | K21: =COUNTIFS(BITACORA!$C$4:$C$7322,$B$7:$B$501,BITACORA!$E$4:$E$7322,$E$6:$AM$6,BITACORA!$B$4:$B$7322,">="&$B$3,BITACORA!$B$4:$B$7322,"<="&$B$4) -> 0 | L21: =COUNTIFS(BITACORA!$C$4:$C$7322,$B$7:$B$501,BITACORA!$E$4:$E$7322,$E$6:$AM$6,BITACORA!$B$4:$B$7322,">="&$B$3,BITACORA!$B$4:$B$7322,"<="&$B$4) -> 0 | ... AM21: =COUNTIFS(BITACORA!$C$4:$C$7322,$B$7:$B$501,BITACORA!$E$4:$E$7322,$E$6:$AM$6,BITACORA!$B$4:$B$7322,">="&$B$3,BITACORA!$B$4:$B$7322,"<="&$B$4) -> 0
A22: =IFERROR(__xludf.DUMMYFUNCTION("""COMPUTED_VALUE"""),"Edison Gabriel Aules Sanchez") -> Edison Gabriel Aules Sanchez | B22: =IFERROR(__xludf.DUMMYFUNCTION("""COMPUTED_VALUE"""),"ABB2285") -> ABB2285 | C22: =IFERROR(__xludf.DUMMYFUNCTION("""COMPUTED_VALUE"""),5) -> 5 | D22: =SUM(E22:AM22) -> 0 | E22: =COUNTIFS(BITACORA!$C$4:$C$7322,$B$7:$B$501,BITACORA!$E$4:$E$7322,$E$6:$AM$6,BITACORA!$B$4:$B$7322,">="&$B$3,BITACORA!$B$4:$B$7322,"<="&$B$4) -> 0 | F22: =COUNTIFS(BITACORA!$C$4:$C$7322,$B$7:$B$501,BITACORA!$E$4:$E$7322,$E$6:$AM$6,BITACORA!$B$4:$B$7322,">="&$B$3,BITACORA!$B$4:$B$7322,"<="&$B$4) -> 0 | G22: =COUNTIFS(BITACORA!$C$4:$C$7322,$B$7:$B$501,BITACORA!$E$4:$E$7322,$E$6:$AM$6,BITACORA!$B$4:$B$7322,">="&$B$3,BITACORA!$B$4:$B$7322,"<="&$B$4) -> 0 | H22: =COUNTIFS(BITACORA!$C$4:$C$7322,$B$7:$B$501,BITACORA!$E$4:$E$7322,$E$6:$AM$6,BITACORA!$B$4:$B$7322,">="&$B$3,BITACORA!$B$4:$B$7322,"<="&$B$4) -> 0 | I22: =COUNTIFS(BITACORA!$C$4:$C$7322,$B$7:$B$501,BITACORA!$E$4:$E$7322,$E$6:$AM$6,BITACORA!$B$4:$B$7322,">="&$B$3,BITACORA!$B$4:$B$7322,"<="&$B$4) -> 0 | J22: =COUNTIFS(BITACORA!$C$4:$C$7322,$B$7:$B$501,BITACORA!$E$4:$E$7322,$E$6:$AM$6,BITACORA!$B$4:$B$7322,">="&$B$3,BITACORA!$B$4:$B$7322,"<="&$B$4) -> 0 | K22: =COUNTIFS(BITACORA!$C$4:$C$7322,$B$7:$B$501,BITACORA!$E$4:$E$7322,$E$6:$AM$6,BITACORA!$B$4:$B$7322,">="&$B$3,BITACORA!$B$4:$B$7322,"<="&$B$4) -> 0 | L22: =COUNTIFS(BITACORA!$C$4:$C$7322,$B$7:$B$501,BITACORA!$E$4:$E$7322,$E$6:$AM$6,BITACORA!$B$4:$B$7322,">="&$B$3,BITACORA!$B$4:$B$7322,"<="&$B$4) -> 0 | ... AM22: =COUNTIFS(BITACORA!$C$4:$C$7322,$B$7:$B$501,BITACORA!$E$4:$E$7322,$E$6:$AM$6,BITACORA!$B$4:$B$7322,">="&$B$3,BITACORA!$B$4:$B$7322,"<="&$B$4) -> 0
A23: =IFERROR(__xludf.DUMMYFUNCTION("""COMPUTED_VALUE"""),"Byron Gregorio Garcia Tumbaco") -> Byron Gregorio Garcia Tumbaco | B23: =IFERROR(__xludf.DUMMYFUNCTION("""COMPUTED_VALUE"""),"XBA6758") -> XBA6758 | C23: =IFERROR(__xludf.DUMMYFUNCTION("""COMPUTED_VALUE"""),5) -> 5 | D23: =SUM(E23:AM23) -> 0 | E23: =COUNTIFS(BITACORA!$C$4:$C$7322,$B$7:$B$501,BITACORA!$E$4:$E$7322,$E$6:$AM$6,BITACORA!$B$4:$B$7322,">="&$B$3,BITACORA!$B$4:$B$7322,"<="&$B$4) -> 0 | F23: =COUNTIFS(BITACORA!$C$4:$C$7322,$B$7:$B$501,BITACORA!$E$4:$E$7322,$E$6:$AM$6,BITACORA!$B$4:$B$7322,">="&$B$3,BITACORA!$B$4:$B$7322,"<="&$B$4) -> 0 | G23: =COUNTIFS(BITACORA!$C$4:$C$7322,$B$7:$B$501,BITACORA!$E$4:$E$7322,$E$6:$AM$6,BITACORA!$B$4:$B$7322,">="&$B$3,BITACORA!$B$4:$B$7322,"<="&$B$4) -> 0 | H23: =COUNTIFS(BITACORA!$C$4:$C$7322,$B$7:$B$501,BITACORA!$E$4:$E$7322,$E$6:$AM$6,BITACORA!$B$4:$B$7322,">="&$B$3,BITACORA!$B$4:$B$7322,"<="&$B$4) -> 0 | I23: =COUNTIFS(BITACORA!$C$4:$C$7322,$B$7:$B$501,BITACORA!$E$4:$E$7322,$E$6:$AM$6,BITACORA!$B$4:$B$7322,">="&$B$3,BITACORA!$B$4:$B$7322,"<="&$B$4) -> 0 | J23: =COUNTIFS(BITACORA!$C$4:$C$7322,$B$7:$B$501,BITACORA!$E$4:$E$7322,$E$6:$AM$6,BITACORA!$B$4:$B$7322,">="&$B$3,BITACORA!$B$4:$B$7322,"<="&$B$4) -> 0 | K23: =COUNTIFS(BITACORA!$C$4:$C$7322,$B$7:$B$501,BITACORA!$E$4:$E$7322,$E$6:$AM$6,BITACORA!$B$4:$B$7322,">="&$B$3,BITACORA!$B$4:$B$7322,"<="&$B$4) -> 0 | L23: =COUNTIFS(BITACORA!$C$4:$C$7322,$B$7:$B$501,BITACORA!$E$4:$E$7322,$E$6:$AM$6,BITACORA!$B$4:$B$7322,">="&$B$3,BITACORA!$B$4:$B$7322,"<="&$B$4) -> 0 | ... AM23: =COUNTIFS(BITACORA!$C$4:$C$7322,$B$7:$B$501,BITACORA!$E$4:$E$7322,$E$6:$AM$6,BITACORA!$B$4:$B$7322,">="&$B$3,BITACORA!$B$4:$B$7322,"<="&$B$4) -> 0
A24: =IFERROR(__xludf.DUMMYFUNCTION("""COMPUTED_VALUE"""),"Byron Gregorio Garcia Tumbaco") -> Byron Gregorio Garcia Tumbaco | B24: =IFERROR(__xludf.DUMMYFUNCTION("""COMPUTED_VALUE"""),"QAA1814") -> QAA1814 | C24: =IFERROR(__xludf.DUMMYFUNCTION("""COMPUTED_VALUE"""),6) -> 6 | D24: =SUM(E24:AM24) -> 0 | E24: =COUNTIFS(BITACORA!$C$4:$C$7322,$B$7:$B$501,BITACORA!$E$4:$E$7322,$E$6:$AM$6,BITACORA!$B$4:$B$7322,">="&$B$3,BITACORA!$B$4:$B$7322,"<="&$B$4) -> 0 | F24: =COUNTIFS(BITACORA!$C$4:$C$7322,$B$7:$B$501,BITACORA!$E$4:$E$7322,$E$6:$AM$6,BITACORA!$B$4:$B$7322,">="&$B$3,BITACORA!$B$4:$B$7322,"<="&$B$4) -> 0 | G24: =COUNTIFS(BITACORA!$C$4:$C$7322,$B$7:$B$501,BITACORA!$E$4:$E$7322,$E$6:$AM$6,BITACORA!$B$4:$B$7322,">="&$B$3,BITACORA!$B$4:$B$7322,"<="&$B$4) -> 0 | H24: =COUNTIFS(BITACORA!$C$4:$C$7322,$B$7:$B$501,BITACORA!$E$4:$E$7322,$E$6:$AM$6,BITACORA!$B$4:$B$7322,">="&$B$3,BITACORA!$B$4:$B$7322,"<="&$B$4) -> 0 | I24: =COUNTIFS(BITACORA!$C$4:$C$7322,$B$7:$B$501,BITACORA!$E$4:$E$7322,$E$6:$AM$6,BITACORA!$B$4:$B$7322,">="&$B$3,BITACORA!$B$4:$B$7322,"<="&$B$4) -> 0 | J24: =COUNTIFS(BITACORA!$C$4:$C$7322,$B$7:$B$501,BITACORA!$E$4:$E$7322,$E$6:$AM$6,BITACORA!$B$4:$B$7322,">="&$B$3,BITACORA!$B$4:$B$7322,"<="&$B$4) -> 0 | K24: =COUNTIFS(BITACORA!$C$4:$C$7322,$B$7:$B$501,BITACORA!$E$4:$E$7322,$E$6:$AM$6,BITACORA!$B$4:$B$7322,">="&$B$3,BITACORA!$B$4:$B$7322,"<="&$B$4) -> 0 | L24: =COUNTIFS(BITACORA!$C$4:$C$7322,$B$7:$B$501,BITACORA!$E$4:$E$7322,$E$6:$AM$6,BITACORA!$B$4:$B$7322,">="&$B$3,BITACORA!$B$4:$B$7322,"<="&$B$4) -> 0 | ... AM24: =COUNTIFS(BITACORA!$C$4:$C$7322,$B$7:$B$501,BITACORA!$E$4:$E$7322,$E$6:$AM$6,BITACORA!$B$4:$B$7322,">="&$B$3,BITACORA!$B$4:$B$7322,"<="&$B$4) -> 0
A25: =IFERROR(__xludf.DUMMYFUNCTION("""COMPUTED_VALUE"""),"Miguel Angel Quishpe Gordon") -> Miguel Angel Quishpe Gordon | B25: =IFERROR(__xludf.DUMMYFUNCTION("""COMPUTED_VALUE"""),"PYP0743") -> PYP0743 | C25: =IFERROR(__xludf.DUMMYFUNCTION("""COMPUTED_VALUE"""),5) -> 5 | D25: =SUM(E25:AM25) -> 0 | E25: =COUNTIFS(BITACORA!$C$4:$C$7322,$B$7:$B$501,BITACORA!$E$4:$E$7322,$E$6:$AM$6,BITACORA!$B$4:$B$7322,">="&$B$3,BITACORA!$B$4:$B$7322,"<="&$B$4) -> 0 | F25: =COUNTIFS(BITACORA!$C$4:$C$7322,$B$7:$B$501,BITACORA!$E$4:$E$7322,$E$6:$AM$6,BITACORA!$B$4:$B$7322,">="&$B$3,BITACORA!$B$4:$B$7322,"<="&$B$4) -> 0 | G25: =COUNTIFS(BITACORA!$C$4:$C$7322,$B$7:$B$501,BITACORA!$E$4:$E$7322,$E$6:$AM$6,BITACORA!$B$4:$B$7322,">="&$B$3,BITACORA!$B$4:$B$7322,"<="&$B$4) -> 0 | H25: =COUNTIFS(BITACORA!$C$4:$C$7322,$B$7:$B$501,BITACORA!$E$4:$E$7322,$E$6:$AM$6,BITACORA!$B$4:$B$7322,">="&$B$3,BITACORA!$B$4:$B$7322,"<="&$B$4) -> 0 | I25: =COUNTIFS(BITACORA!$C$4:$C$7322,$B$7:$B$501,BITACORA!$E$4:$E$7322,$E$6:$AM$6,BITACORA!$B$4:$B$7322,">="&$B$3,BITACORA!$B$4:$B$7322,"<="&$B$4) -> 0 | J25: =COUNTIFS(BITACORA!$C$4:$C$7322,$B$7:$B$501,BITACORA!$E$4:$E$7322,$E$6:$AM$6,BITACORA!$B$4:$B$7322,">="&$B$3,BITACORA!$B$4:$B$7322,"<="&$B$4) -> 0 | K25: =COUNTIFS(BITACORA!$C$4:$C$7322,$B$7:$B$501,BITACORA!$E$4:$E$7322,$E$6:$AM$6,BITACORA!$B$4:$B$7322,">="&$B$3,BITACORA!$B$4:$B$7322,"<="&$B$4) -> 0 | L25: =COUNTIFS(BITACORA!$C$4:$C$7322,$B$7:$B$501,BITACORA!$E$4:$E$7322,$E$6:$AM$6,BITACORA!$B$4:$B$7322,">="&$B$3,BITACORA!$B$4:$B$7322,"<="&$B$4) -> 0 | ... AM25: =COUNTIFS(BITACORA!$C$4:$C$7322,$B$7:$B$501,BITACORA!$E$4:$E$7322,$E$6:$AM$6,BITACORA!$B$4:$B$7322,">="&$B$3,BITACORA!$B$4:$B$7322,"<="&$B$4) -> 0
A26: =IFERROR(__xludf.DUMMYFUNCTION("""COMPUTED_VALUE"""),"Miguel Angel Quishpe Gordon") -> Miguel Angel Quishpe Gordon | B26: =IFERROR(__xludf.DUMMYFUNCTION("""COMPUTED_VALUE"""),"IAE0151") -> IAE0151 | C26: =IFERROR(__xludf.DUMMYFUNCTION("""COMPUTED_VALUE"""),6) -> 6 | D26: =SUM(E26:AM26) -> 0 | E26: =COUNTIFS(BITACORA!$C$4:$C$7322,$B$7:$B$501,BITACORA!$E$4:$E$7322,$E$6:$AM$6,BITACORA!$B$4:$B$7322,">="&$B$3,BITACORA!$B$4:$B$7322,"<="&$B$4) -> 0 | F26: =COUNTIFS(BITACORA!$C$4:$C$7322,$B$7:$B$501,BITACORA!$E$4:$E$7322,$E$6:$AM$6,BITACORA!$B$4:$B$7322,">="&$B$3,BITACORA!$B$4:$B$7322,"<="&$B$4) -> 0 | G26: =COUNTIFS(BITACORA!$C$4:$C$7322,$B$7:$B$501,BITACORA!$E$4:$E$7322,$E$6:$AM$6,BITACORA!$B$4:$B$7322,">="&$B$3,BITACORA!$B$4:$B$7322,"<="&$B$4) -> 0 | H26: =COUNTIFS(BITACORA!$C$4:$C$7322,$B$7:$B$501,BITACORA!$E$4:$E$7322,$E$6:$AM$6,BITACORA!$B$4:$B$7322,">="&$B$3,BITACORA!$B$4:$B$7322,"<="&$B$4) -> 0 | I26: =COUNTIFS(BITACORA!$C$4:$C$7322,$B$7:$B$501,BITACORA!$E$4:$E$7322,$E$6:$AM$6,BITACORA!$B$4:$B$7322,">="&$B$3,BITACORA!$B$4:$B$7322,"<="&$B$4) -> 0 | J26: =COUNTIFS(BITACORA!$C$4:$C$7322,$B$7:$B$501,BITACORA!$E$4:$E$7322,$E$6:$AM$6,BITACORA!$B$4:$B$7322,">="&$B$3,BITACORA!$B$4:$B$7322,"<="&$B$4) -> 0 | K26: =COUNTIFS(BITACORA!$C$4:$C$7322,$B$7:$B$501,BITACORA!$E$4:$E$7322,$E$6:$AM$6,BITACORA!$B$4:$B$7322,">="&$B$3,BITACORA!$B$4:$B$7322,"<="&$B$4) -> 0 | L26: =COUNTIFS(BITACORA!$C$4:$C$7322,$B$7:$B$501,BITACORA!$E$4:$E$7322,$E$6:$AM$6,BITACORA!$B$4:$B$7322,">="&$B$3,BITACORA!$B$4:$B$7322,"<="&$B$4) -> 0 | ... AM26: =COUNTIFS(BITACORA!$C$4:$C$7322,$B$7:$B$501,BITACORA!$E$4:$E$7322,$E$6:$AM$6,BITACORA!$B$4:$B$7322,">="&$B$3,BITACORA!$B$4:$B$7322,"<="&$B$4) -> 0
A27: =IFERROR(__xludf.DUMMYFUNCTION("""COMPUTED_VALUE"""),"Cesar Luis Muentes Cornejo") -> Cesar Luis Muentes Cornejo | B27: =IFERROR(__xludf.DUMMYFUNCTION("""COMPUTED_VALUE"""),"OAH0651") -> OAH0651 | C27: =IFERROR(__xludf.DUMMYFUNCTION("""COMPUTED_VALUE"""),5) -> 5 | D27: =SUM(E27:AM27) -> 0 | E27: =COUNTIFS(BITACORA!$C$4:$C$7322,$B$7:$B$501,BITACORA!$E$4:$E$7322,$E$6:$AM$6,BITACORA!$B$4:$B$7322,">="&$B$3,BITACORA!$B$4:$B$7322,"<="&$B$4) -> 0 | F27: =COUNTIFS(BITACORA!$C$4:$C$7322,$B$7:$B$501,BITACORA!$E$4:$E$7322,$E$6:$AM$6,BITACORA!$B$4:$B$7322,">="&$B$3,BITACORA!$B$4:$B$7322,"<="&$B$4) -> 0 | G27: =COUNTIFS(BITACORA!$C$4:$C$7322,$B$7:$B$501,BITACORA!$E$4:$E$7322,$E$6:$AM$6,BITACORA!$B$4:$B$7322,">="&$B$3,BITACORA!$B$4:$B$7322,"<="&$B$4) -> 0 | H27: =COUNTIFS(BITACORA!$C$4:$C$7322,$B$7:$B$501,BITACORA!$E$4:$E$7322,$E$6:$AM$6,BITACORA!$B$4:$B$7322,">="&$B$3,BITACORA!$B$4:$B$7322,"<="&$B$4) -> 0 | I27: =COUNTIFS(BITACORA!$C$4:$C$7322,$B$7:$B$501,BITACORA!$E$4:$E$7322,$E$6:$AM$6,BITACORA!$B$4:$B$7322,">="&$B$3,BITACORA!$B$4:$B$7322,"<="&$B$4) -> 0 | J27: =COUNTIFS(BITACORA!$C$4:$C$7322,$B$7:$B$501,BITACORA!$E$4:$E$7322,$E$6:$AM$6,BITACORA!$B$4:$B$7322,">="&$B$3,BITACORA!$B$4:$B$7322,"<="&$B$4) -> 0 | K27: =COUNTIFS(BITACORA!$C$4:$C$7322,$B$7:$B$501,BITACORA!$E$4:$E$7322,$E$6:$AM$6,BITACORA!$B$4:$B$7322,">="&$B$3,BITACORA!$B$4:$B$7322,"<="&$B$4) -> 0 | L27: =COUNTIFS(BITACORA!$C$4:$C$7322,$B$7:$B$501,BITACORA!$E$4:$E$7322,$E$6:$AM$6,BITACORA!$B$4:$B$7322,">="&$B$3,BITACORA!$B$4:$B$7322,"<="&$B$4) -> 0 | ... AM27: =COUNTIFS(BITACORA!$C$4:$C$7322,$B$7:$B$501,BITACORA!$E$4:$E$7322,$E$6:$AM$6,BITACORA!$B$4:$B$7322,">="&$B$3,BITACORA!$B$4:$B$7322,"<="&$B$4) -> 0
A28: =IFERROR(__xludf.DUMMYFUNCTION("""COMPUTED_VALUE"""),"Luis Gonzaga Muentes Napa") -> Luis Gonzaga Muentes Napa | B28: =IFERROR(__xludf.DUMMYFUNCTION("""COMPUTED_VALUE"""),"XBE0343") -> XBE0343 | C28: =IFERROR(__xludf.DUMMYFUNCTION("""COMPUTED_VALUE"""),5) -> 5 | D28: =SUM(E28:AM28) -> 0 | E28: =COUNTIFS(BITACORA!$C$4:$C$7322,$B$7:$B$501,BITACORA!$E$4:$E$7322,$E$6:$AM$6,BITACORA!$B$4:$B$7322,">="&$B$3,BITACORA!$B$4:$B$7322,"<="&$B$4) -> 0 | F28: =COUNTIFS(BITACORA!$C$4:$C$7322,$B$7:$B$501,BITACORA!$E$4:$E$7322,$E$6:$AM$6,BITACORA!$B$4:$B$7322,">="&$B$3,BITACORA!$B$4:$B$7322,"<="&$B$4) -> 0 | G28: =COUNTIFS(BITACORA!$C$4:$C$7322,$B$7:$B$501,BITACORA!$E$4:$E$7322,$E$6:$AM$6,BITACORA!$B$4:$B$7322,">="&$B$3,BITACORA!$B$4:$B$7322,"<="&$B$4) -> 0 | H28: =COUNTIFS(BITACORA!$C$4:$C$7322,$B$7:$B$501,BITACORA!$E$4:$E$7322,$E$6:$AM$6,BITACORA!$B$4:$B$7322,">="&$B$3,BITACORA!$B$4:$B$7322,"<="&$B$4) -> 0 | I28: =COUNTIFS(BITACORA!$C$4:$C$7322,$B$7:$B$501,BITACORA!$E$4:$E$7322,$E$6:$AM$6,BITACORA!$B$4:$B$7322,">="&$B$3,BITACORA!$B$4:$B$7322,"<="&$B$4) -> 0 | J28: =COUNTIFS(BITACORA!$C$4:$C$7322,$B$7:$B$501,BITACORA!$E$4:$E$7322,$E$6:$AM$6,BITACORA!$B$4:$B$7322,">="&$B$3,BITACORA!$B$4:$B$7322,"<="&$B$4) -> 0 | K28: =COUNTIFS(BITACORA!$C$4:$C$7322,$B$7:$B$501,BITACORA!$E$4:$E$7322,$E$6:$AM$6,BITACORA!$B$4:$B$7322,">="&$B$3,BITACORA!$B$4:$B$7322,"<="&$B$4) -> 0 | L28: =COUNTIFS(BITACORA!$C$4:$C$7322,$B$7:$B$501,BITACORA!$E$4:$E$7322,$E$6:$AM$6,BITACORA!$B$4:$B$7322,">="&$B$3,BITACORA!$B$4:$B$7322,"<="&$B$4) -> 0 | ... AM28: =COUNTIFS(BITACORA!$C$4:$C$7322,$B$7:$B$501,BITACORA!$E$4:$E$7322,$E$6:$AM$6,BITACORA!$B$4:$B$7322,">="&$B$3,BITACORA!$B$4:$B$7322,"<="&$B$4) -> 0
A29: =IFERROR(__xludf.DUMMYFUNCTION("""COMPUTED_VALUE"""),"Luis Gonzaga Muentes Napa") -> Luis Gonzaga Muentes Napa | B29: =IFERROR(__xludf.DUMMYFUNCTION("""COMPUTED_VALUE"""),"BAC0784") -> BAC0784 | C29: =IFERROR(__xludf.DUMMYFUNCTION("""COMPUTED_VALUE"""),5) -> 5 | D29: =SUM(E29:AM29) -> 0 | E29: =COUNTIFS(BITACORA!$C$4:$C$7322,$B$7:$B$501,BITACORA!$E$4:$E$7322,$E$6:$AM$6,BITACORA!$B$4:$B$7322,">="&$B$3,BITACORA!$B$4:$B$7322,"<="&$B$4) -> 0 | F29: =COUNTIFS(BITACORA!$C$4:$C$7322,$B$7:$B$501,BITACORA!$E$4:$E$7322,$E$6:$AM$6,BITACORA!$B$4:$B$7322,">="&$B$3,BITACORA!$B$4:$B$7322,"<="&$B$4) -> 0 | G29: =COUNTIFS(BITACORA!$C$4:$C$7322,$B$7:$B$501,BITACORA!$E$4:$E$7322,$E$6:$AM$6,BITACORA!$B$4:$B$7322,">="&$B$3,BITACORA!$B$4:$B$7322,"<="&$B$4) -> 0 | H29: =COUNTIFS(BITACORA!$C$4:$C$7322,$B$7:$B$501,BITACORA!$E$4:$E$7322,$E$6:$AM$6,BITACORA!$B$4:$B$7322,">="&$B$3,BITACORA!$B$4:$B$7322,"<="&$B$4) -> 0 | I29: =COUNTIFS(BITACORA!$C$4:$C$7322,$B$7:$B$501,BITACORA!$E$4:$E$7322,$E$6:$AM$6,BITACORA!$B$4:$B$7322,">="&$B$3,BITACORA!$B$4:$B$7322,"<="&$B$4) -> 0 | J29: =COUNTIFS(BITACORA!$C$4:$C$7322,$B$7:$B$501,BITACORA!$E$4:$E$7322,$E$6:$AM$6,BITACORA!$B$4:$B$7322,">="&$B$3,BITACORA!$B$4:$B$7322,"<="&$B$4) -> 0 | K29: =COUNTIFS(BITACORA!$C$4:$C$7322,$B$7:$B$501,BITACORA!$E$4:$E$7322,$E$6:$AM$6,BITACORA!$B$4:$B$7322,">="&$B$3,BITACORA!$B$4:$B$7322,"<="&$B$4) -> 0 | L29: =COUNTIFS(BITACORA!$C$4:$C$7322,$B$7:$B$501,BITACORA!$E$4:$E$7322,$E$6:$AM$6,BITACORA!$B$4:$B$7322,">="&$B$3,BITACORA!$B$4:$B$7322,"<="&$B$4) -> 0 | ... AM29: =COUNTIFS(BITACORA!$C$4:$C$7322,$B$7:$B$501,BITACORA!$E$4:$E$7322,$E$6:$AM$6,BITACORA!$B$4:$B$7322,">="&$B$3,BITACORA!$B$4:$B$7322,"<="&$B$4) -> 0
A30: =IFERROR(__xludf.DUMMYFUNCTION("""COMPUTED_VALUE"""),"Walter Ivan Cadena Saldariega") -> Walter Ivan Cadena Saldariega | B30: =IFERROR(__xludf.DUMMYFUNCTION("""COMPUTED_VALUE"""),"NBF0031") -> NBF0031 | C30: =IFERROR(__xludf.DUMMYFUNCTION("""COMPUTED_VALUE"""),5) -> 5 | D30: =SUM(E30:AM30) -> 9 | E30: =COUNTIFS(BITACORA!$C$4:$C$7322,$B$7:$B$501,BITACORA!$E$4:$E$7322,$E$6:$AM$6,BITACORA!$B$4:$B$7322,">="&$B$3,BITACORA!$B$4:$B$7322,"<="&$B$4) -> 2 | F30: =COUNTIFS(BITACORA!$C$4:$C$7322,$B$7:$B$501,BITACORA!$E$4:$E$7322,$E$6:$AM$6,BITACORA!$B$4:$B$7322,">="&$B$3,BITACORA!$B$4:$B$7322,"<="&$B$4) -> 1 | G30: =COUNTIFS(BITACORA!$C$4:$C$7322,$B$7:$B$501,BITACORA!$E$4:$E$7322,$E$6:$AM$6,BITACORA!$B$4:$B$7322,">="&$B$3,BITACORA!$B$4:$B$7322,"<="&$B$4) -> 0 | H30: =COUNTIFS(BITACORA!$C$4:$C$7322,$B$7:$B$501,BITACORA!$E$4:$E$7322,$E$6:$AM$6,BITACORA!$B$4:$B$7322,">="&$B$3,BITACORA!$B$4:$B$7322,"<="&$B$4) -> 0 | I30: =COUNTIFS(BITACORA!$C$4:$C$7322,$B$7:$B$501,BITACORA!$E$4:$E$7322,$E$6:$AM$6,BITACORA!$B$4:$B$7322,">="&$B$3,BITACORA!$B$4:$B$7322,"<="&$B$4) -> 0 | J30: =COUNTIFS(BITACORA!$C$4:$C$7322,$B$7:$B$501,BITACORA!$E$4:$E$7322,$E$6:$AM$6,BITACORA!$B$4:$B$7322,">="&$B$3,BITACORA!$B$4:$B$7322,"<="&$B$4) -> 0 | K30: =COUNTIFS(BITACORA!$C$4:$C$7322,$B$7:$B$501,BITACORA!$E$4:$E$7322,$E$6:$AM$6,BITACORA!$B$4:$B$7322,">="&$B$3,BITACORA!$B$4:$B$7322,"<="&$B$4) -> 0 | L30: =COUNTIFS(BITACORA!$C$4:$C$7322,$B$7:$B$501,BITACORA!$E$4:$E$7322,$E$6:$AM$6,BITACORA!$B$4:$B$7322,">="&$B$3,BITACORA!$B$4:$B$7322,"<="&$B$4) -> 0 | ... AM30: =COUNTIFS(BITACORA!$C$4:$C$7322,$B$7:$B$501,BITACORA!$E$4:$E$7322,$E$6:$AM$6,BITACORA!$B$4:$B$7322,">="&$B$3,BITACORA!$B$4:$B$7322,"<="&$B$4) -> 0
A31: =IFERROR(__xludf.DUMMYFUNCTION("""COMPUTED_VALUE"""),"Cristhian Raul Bravo Zambrano") -> Cristhian Raul Bravo Zambrano | B31: =IFERROR(__xludf.DUMMYFUNCTION("""COMPUTED_VALUE"""),"EBF166") -> EBF166 | C31: =IFERROR(__xludf.DUMMYFUNCTION("""COMPUTED_VALUE"""),5) -> 5 | D31: =SUM(E31:AM31) -> 0 | E31: =COUNTIFS(BITACORA!$C$4:$C$7322,$B$7:$B$501,BITACORA!$E$4:$E$7322,$E$6:$AM$6,BITACORA!$B$4:$B$7322,">="&$B$3,BITACORA!$B$4:$B$7322,"<="&$B$4) -> 0 | F31: =COUNTIFS(BITACORA!$C$4:$C$7322,$B$7:$B$501,BITACORA!$E$4:$E$7322,$E$6:$AM$6,BITACORA!$B$4:$B$7322,">="&$B$3,BITACORA!$B$4:$B$7322,"<="&$B$4) -> 0 | G31: =COUNTIFS(BITACORA!$C$4:$C$7322,$B$7:$B$501,BITACORA!$E$4:$E$7322,$E$6:$AM$6,BITACORA!$B$4:$B$7322,">="&$B$3,BITACORA!$B$4:$B$7322,"<="&$B$4) -> 0 | H31: =COUNTIFS(BITACORA!$C$4:$C$7322,$B$7:$B$501,BITACORA!$E$4:$E$7322,$E$6:$AM$6,BITACORA!$B$4:$B$7322,">="&$B$3,BITACORA!$B$4:$B$7322,"<="&$B$4) -> 0 | I31: =COUNTIFS(BITACORA!$C$4:$C$7322,$B$7:$B$501,BITACORA!$E$4:$E$7322,$E$6:$AM$6,BITACORA!$B$4:$B$7322,">="&$B$3,BITACORA!$B$4:$B$7322,"<="&$B$4) -> 0 | J31: =COUNTIFS(BITACORA!$C$4:$C$7322,$B$7:$B$501,BITACORA!$E$4:$E$7322,$E$6:$AM$6,BITACORA!$B$4:$B$7322,">="&$B$3,BITACORA!$B$4:$B$7322,"<="&$B$4) -> 0 | K31: =COUNTIFS(BITACORA!$C$4:$C$7322,$B$7:$B$501,BITACORA!$E$4:$E$7322,$E$6:$AM$6,BITACORA!$B$4:$B$7322,">="&$B$3,BITACORA!$B$4:$B$7322,"<="&$B$4) -> 0 | L31: =COUNTIFS(BITACORA!$C$4:$C$7322,$B$7:$B$501,BITACORA!$E$4:$E$7322,$E$6:$AM$6,BITACORA!$B$4:$B$7322,">="&$B$3,BITACORA!$B$4:$B$7322,"<="&$B$4) -> 0 | ... AM31: =COUNTIFS(BITACORA!$C$4:$C$7322,$B$7:$B$501,BITACORA!$E$4:$E$7322,$E$6:$AM$6,BITACORA!$B$4:$B$7322,">="&$B$3,BITACORA!$B$4:$B$7322,"<="&$B$4) -> 0
A32: =IFERROR(__xludf.DUMMYFUNCTION("""COMPUTED_VALUE"""),"Freddy Alexamder Morales Zambrano") -> Freddy Alexamder Morales Zambrano | B32: =IFERROR(__xludf.DUMMYFUNCTION("""COMPUTED_VALUE"""),"PZS0487") -> PZS0487 | C32: =IFERROR(__xludf.DUMMYFUNCTION("""COMPUTED_VALUE"""),5) -> 5 | D32: =SUM(E32:AM32) -> 0 | E32: =COUNTIFS(BITACORA!$C$4:$C$7322,$B$7:$B$501,BITACORA!$E$4:$E$7322,$E$6:$AM$6,BITACORA!$B$4:$B$7322,">="&$B$3,BITACORA!$B$4:$B$7322,"<="&$B$4) -> 0 | F32: =COUNTIFS(BITACORA!$C$4:$C$7322,$B$7:$B$501,BITACORA!$E$4:$E$7322,$E$6:$AM$6,BITACORA!$B$4:$B$7322,">="&$B$3,BITACORA!$B$4:$B$7322,"<="&$B$4) -> 0 | G32: =COUNTIFS(BITACORA!$C$4:$C$7322,$B$7:$B$501,BITACORA!$E$4:$E$7322,$E$6:$AM$6,BITACORA!$B$4:$B$7322,">="&$B$3,BITACORA!$B$4:$B$7322,"<="&$B$4) -> 0 | H32: =COUNTIFS(BITACORA!$C$4:$C$7322,$B$7:$B$501,BITACORA!$E$4:$E$7322,$E$6:$AM$6,BITACORA!$B$4:$B$7322,">="&$B$3,BITACORA!$B$4:$B$7322,"<="&$B$4) -> 0 | I32: =COUNTIFS(BITACORA!$C$4:$C$7322,$B$7:$B$501,BITACORA!$E$4:$E$7322,$E$6:$AM$6,BITACORA!$B$4:$B$7322,">="&$B$3,BITACORA!$B$4:$B$7322,"<="&$B$4) -> 0 | J32: =COUNTIFS(BITACORA!$C$4:$C$7322,$B$7:$B$501,BITACORA!$E$4:$E$7322,$E$6:$AM$6,BITACORA!$B$4:$B$7322,">="&$B$3,BITACORA!$B$4:$B$7322,"<="&$B$4) -> 0 | K32: =COUNTIFS(BITACORA!$C$4:$C$7322,$B$7:$B$501,BITACORA!$E$4:$E$7322,$E$6:$AM$6,BITACORA!$B$4:$B$7322,">="&$B$3,BITACORA!$B$4:$B$7322,"<="&$B$4) -> 0 | L32: =COUNTIFS(BITACORA!$C$4:$C$7322,$B$7:$B$501,BITACORA!$E$4:$E$7322,$E$6:$AM$6,BITACORA!$B$4:$B$7322,">="&$B$3,BITACORA!$B$4:$B$7322,"<="&$B$4) -> 0 | ... AM32: =COUNTIFS(BITACORA!$C$4:$C$7322,$B$7:$B$501,BITACORA!$E$4:$E$7322,$E$6:$AM$6,BITACORA!$B$4:$B$7322,">="&$B$3,BITACORA!$B$4:$B$7322,"<="&$B$4) -> 0
A33: =IFERROR(__xludf.DUMMYFUNCTION("""COMPUTED_VALUE"""),"Raul Neptali Velez Velez (Darwin Tigre)") -> Raul Neptali Velez Velez (Darwin Tigre) | B33: =IFERROR(__xludf.DUMMYFUNCTION("""COMPUTED_VALUE"""),"TBA7675") -> TBA7675 | C33: =IFERROR(__xludf.DUMMYFUNCTION("""COMPUTED_VALUE"""),5) -> 5 | D33: =SUM(E33:AM33) -> 0 | E33: =COUNTIFS(BITACORA!$C$4:$C$7322,$B$7:$B$501,BITACORA!$E$4:$E$7322,$E$6:$AM$6,BITACORA!$B$4:$B$7322,">="&$B$3,BITACORA!$B$4:$B$7322,"<="&$B$4) -> 0 | F33: =COUNTIFS(BITACORA!$C$4:$C$7322,$B$7:$B$501,BITACORA!$E$4:$E$7322,$E$6:$AM$6,BITACORA!$B$4:$B$7322,">="&$B$3,BITACORA!$B$4:$B$7322,"<="&$B$4) -> 0 | G33: =COUNTIFS(BITACORA!$C$4:$C$7322,$B$7:$B$501,BITACORA!$E$4:$E$7322,$E$6:$AM$6,BITACORA!$B$4:$B$7322,">="&$B$3,BITACORA!$B$4:$B$7322,"<="&$B$4) -> 0 | H33: =COUNTIFS(BITACORA!$C$4:$C$7322,$B$7:$B$501,BITACORA!$E$4:$E$7322,$E$6:$AM$6,BITACORA!$B$4:$B$7322,">="&$B$3,BITACORA!$B$4:$B$7322,"<="&$B$4) -> 0 | I33: =COUNTIFS(BITACORA!$C$4:$C$7322,$B$7:$B$501,BITACORA!$E$4:$E$7322,$E$6:$AM$6,BITACORA!$B$4:$B$7322,">="&$B$3,BITACORA!$B$4:$B$7322,"<="&$B$4) -> 0 | J33: =COUNTIFS(BITACORA!$C$4:$C$7322,$B$7:$B$501,BITACORA!$E$4:$E$7322,$E$6:$AM$6,BITACORA!$B$4:$B$7322,">="&$B$3,BITACORA!$B$4:$B$7322,"<="&$B$4) -> 0 | K33: =COUNTIFS(BITACORA!$C$4:$C$7322,$B$7:$B$501,BITACORA!$E$4:$E$7322,$E$6:$AM$6,BITACORA!$B$4:$B$7322,">="&$B$3,BITACORA!$B$4:$B$7322,"<="&$B$4) -> 0 | L33: =COUNTIFS(BITACORA!$C$4:$C$7322,$B$7:$B$501,BITACORA!$E$4:$E$7322,$E$6:$AM$6,BITACORA!$B$4:$B$7322,">="&$B$3,BITACORA!$B$4:$B$7322,"<="&$B$4) -> 0 | ... AM33: =COUNTIFS(BITACORA!$C$4:$C$7322,$B$7:$B$501,BITACORA!$E$4:$E$7322,$E$6:$AM$6,BITACORA!$B$4:$B$7322,">="&$B$3,BITACORA!$B$4:$B$7322,"<="&$B$4) -> 0
A34: =IFERROR(__xludf.DUMMYFUNCTION("""COMPUTED_VALUE"""),"Luis Alberto Mendoza Basurto (Darwin Tigre)") -> Luis Alberto Mendoza Basurto (Darwin Tigre) | B34: =IFERROR(__xludf.DUMMYFUNCTION("""COMPUTED_VALUE"""),"TAL0556") -> TAL0556 | C34: =IFERROR(__xludf.DUMMYFUNCTION("""COMPUTED_VALUE"""),5) -> 5 | D34: =SUM(E34:AM34) -> 3 | E34: =COUNTIFS(BITACORA!$C$4:$C$7322,$B$7:$B$501,BITACORA!$E$4:$E$7322,$E$6:$AM$6,BITACORA!$B$4:$B$7322,">="&$B$3,BITACORA!$B$4:$B$7322,"<="&$B$4) -> 3 | F34: =COUNTIFS(BITACORA!$C$4:$C$7322,$B$7:$B$501,BITACORA!$E$4:$E$7322,$E$6:$AM$6,BITACORA!$B$4:$B$7322,">="&$B$3,BITACORA!$B$4:$B$7322,"<="&$B$4) -> 0 | G34: =COUNTIFS(BITACORA!$C$4:$C$7322,$B$7:$B$501,BITACORA!$E$4:$E$7322,$E$6:$AM$6,BITACORA!$B$4:$B$7322,">="&$B$3,BITACORA!$B$4:$B$7322,"<="&$B$4) -> 0 | H34: =COUNTIFS(BITACORA!$C$4:$C$7322,$B$7:$B$501,BITACORA!$E$4:$E$7322,$E$6:$AM$6,BITACORA!$B$4:$B$7322,">="&$B$3,BITACORA!$B$4:$B$7322,"<="&$B$4) -> 0 | I34: =COUNTIFS(BITACORA!$C$4:$C$7322,$B$7:$B$501,BITACORA!$E$4:$E$7322,$E$6:$AM$6,BITACORA!$B$4:$B$7322,">="&$B$3,BITACORA!$B$4:$B$7322,"<="&$B$4) -> 0 | J34: =COUNTIFS(BITACORA!$C$4:$C$7322,$B$7:$B$501,BITACORA!$E$4:$E$7322,$E$6:$AM$6,BITACORA!$B$4:$B$7322,">="&$B$3,BITACORA!$B$4:$B$7322,"<="&$B$4) -> 0 | K34: =COUNTIFS(BITACORA!$C$4:$C$7322,$B$7:$B$501,BITACORA!$E$4:$E$7322,$E$6:$AM$6,BITACORA!$B$4:$B$7322,">="&$B$3,BITACORA!$B$4:$B$7322,"<="&$B$4) -> 0 | L34: =COUNTIFS(BITACORA!$C$4:$C$7322,$B$7:$B$501,BITACORA!$E$4:$E$7322,$E$6:$AM$6,BITACORA!$B$4:$B$7322,">="&$B$3,BITACORA!$B$4:$B$7322,"<="&$B$4) -> 0 | ... AM34: =COUNTIFS(BITACORA!$C$4:$C$7322,$B$7:$B$501,BITACORA!$E$4:$E$7322,$E$6:$AM$6,BITACORA!$B$4:$B$7322,">="&$B$3,BITACORA!$B$4:$B$7322,"<="&$B$4) -> 0
A35: =IFERROR(__xludf.DUMMYFUNCTION("""COMPUTED_VALUE"""),"Javier Mendoza guarderas (abogado)") -> Javier Mendoza guarderas (abogado) | B35: =IFERROR(__xludf.DUMMYFUNCTION("""COMPUTED_VALUE"""),"TCM0286") -> TCM0286 | C35: =IFERROR(__xludf.DUMMYFUNCTION("""COMPUTED_VALUE"""),5) -> 5 | D35: =SUM(E35:AM35) -> 1 | E35: =COUNTIFS(BITACORA!$C$4:$C$7322,$B$7:$B$501,BITACORA!$E$4:$E$7322,$E$6:$AM$6,BITACORA!$B$4:$B$7322,">="&$B$3,BITACORA!$B$4:$B$7322,"<="&$B$4) -> 1 | F35: =COUNTIFS(BITACORA!$C$4:$C$7322,$B$7:$B$501,BITACORA!$E$4:$E$7322,$E$6:$AM$6,BITACORA!$B$4:$B$7322,">="&$B$3,BITACORA!$B$4:$B$7322,"<="&$B$4) -> 0 | G35: =COUNTIFS(BITACORA!$C$4:$C$7322,$B$7:$B$501,BITACORA!$E$4:$E$7322,$E$6:$AM$6,BITACORA!$B$4:$B$7322,">="&$B$3,BITACORA!$B$4:$B$7322,"<="&$B$4) -> 0 | H35: =COUNTIFS(BITACORA!$C$4:$C$7322,$B$7:$B$501,BITACORA!$E$4:$E$7322,$E$6:$AM$6,BITACORA!$B$4:$B$7322,">="&$B$3,BITACORA!$B$4:$B$7322,"<="&$B$4) -> 0 | I35: =COUNTIFS(BITACORA!$C$4:$C$7322,$B$7:$B$501,BITACORA!$E$4:$E$7322,$E$6:$AM$6,BITACORA!$B$4:$B$7322,">="&$B$3,BITACORA!$B$4:$B$7322,"<="&$B$4) -> 0 | J35: =COUNTIFS(BITACORA!$C$4:$C$7322,$B$7:$B$501,BITACORA!$E$4:$E$7322,$E$6:$AM$6,BITACORA!$B$4:$B$7322,">="&$B$3,BITACORA!$B$4:$B$7322,"<="&$B$4) -> 0 | K35: =COUNTIFS(BITACORA!$C$4:$C$7322,$B$7:$B$501,BITACORA!$E$4:$E$7322,$E$6:$AM$6,BITACORA!$B$4:$B$7322,">="&$B$3,BITACORA!$B$4:$B$7322,"<="&$B$4) -> 0 | L35: =COUNTIFS(BITACORA!$C$4:$C$7322,$B$7:$B$501,BITACORA!$E$4:$E$7322,$E$6:$AM$6,BITACORA!$B$4:$B$7322,">="&$B$3,BITACORA!$B$4:$B$7322,"<="&$B$4) -> 0 | ... AM35: =COUNTIFS(BITACORA!$C$4:$C$7322,$B$7:$B$501,BITACORA!$E$4:$E$7322,$E$6:$AM$6,BITACORA!$B$4:$B$7322,">="&$B$3,BITACORA!$B$4:$B$7322,"<="&$B$4) -> 0
D36: =SUM(E36:AM36) -> 0 | E36: =COUNTIFS(BITACORA!$C$4:$C$7322,$B$7:$B$501,BITACORA!$E$4:$E$7322,$E$6:$AM$6,BITACORA!$B$4:$B$7322,">="&$B$3,BITACORA!$B$4:$B$7322,"<="&$B$4) -> 0 | F36: =COUNTIFS(BITACORA!$C$4:$C$7322,$B$7:$B$501,BITACORA!$E$4:$E$7322,$E$6:$AM$6,BITACORA!$B$4:$B$7322,">="&$B$3,BITACORA!$B$4:$B$7322,"<="&$B$4) -> 0 | G36: =COUNTIFS(BITACORA!$C$4:$C$7322,$B$7:$B$501,BITACORA!$E$4:$E$7322,$E$6:$AM$6,BITACORA!$B$4:$B$7322,">="&$B$3,BITACORA!$B$4:$B$7322,"<="&$B$4) -> 0 | H36: =COUNTIFS(BITACORA!$C$4:$C$7322,$B$7:$B$501,BITACORA!$E$4:$E$7322,$E$6:$AM$6,BITACORA!$B$4:$B$7322,">="&$B$3,BITACORA!$B$4:$B$7322,"<="&$B$4) -> 0 | I36: =COUNTIFS(BITACORA!$C$4:$C$7322,$B$7:$B$501,BITACORA!$E$4:$E$7322,$E$6:$AM$6,BITACORA!$B$4:$B$7322,">="&$B$3,BITACORA!$B$4:$B$7322,"<="&$B$4) -> 0 | J36: =COUNTIFS(BITACORA!$C$4:$C$7322,$B$7:$B$501,BITACORA!$E$4:$E$7322,$E$6:$AM$6,BITACORA!$B$4:$B$7322,">="&$B$3,BITACORA!$B$4:$B$7322,"<="&$B$4) -> 0 | K36: =COUNTIFS(BITACORA!$C$4:$C$7322,$B$7:$B$501,BITACORA!$E$4:$E$7322,$E$6:$AM$6,BITACORA!$B$4:$B$7322,">="&$B$3,BITACORA!$B$4:$B$7322,"<="&$B$4) -> 0 | L36: =COUNTIFS(BITACORA!$C$4:$C$7322,$B$7:$B$501,BITACORA!$E$4:$E$7322,$E$6:$AM$6,BITACORA!$B$4:$B$7322,">="&$B$3,BITACORA!$B$4:$B$7322,"<="&$B$4) -> 0 | ... AM36: =COUNTIFS(BITACORA!$C$4:$C$7322,$B$7:$B$501,BITACORA!$E$4:$E$7322,$E$6:$AM$6,BITACORA!$B$4:$B$7322,">="&$B$3,BITACORA!$B$4:$B$7322,"<="&$B$4) -> 0
D37: =SUM(E37:AM37) -> 0 | E37: =COUNTIFS(BITACORA!$C$4:$C$7322,$B$7:$B$501,BITACORA!$E$4:$E$7322,$E$6:$AM$6,BITACORA!$B$4:$B$7322,">="&$B$3,BITACORA!$B$4:$B$7322,"<="&$B$4) -> 0 | F37: =COUNTIFS(BITACORA!$C$4:$C$7322,$B$7:$B$501,BITACORA!$E$4:$E$7322,$E$6:$AM$6,BITACORA!$B$4:$B$7322,">="&$B$3,BITACORA!$B$4:$B$7322,"<="&$B$4) -> 0 | G37: =COUNTIFS(BITACORA!$C$4:$C$7322,$B$7:$B$501,BITACORA!$E$4:$E$7322,$E$6:$AM$6,BITACORA!$B$4:$B$7322,">="&$B$3,BITACORA!$B$4:$B$7322,"<="&$B$4) -> 0 | H37: =COUNTIFS(BITACORA!$C$4:$C$7322,$B$7:$B$501,BITACORA!$E$4:$E$7322,$E$6:$AM$6,BITACORA!$B$4:$B$7322,">="&$B$3,BITACORA!$B$4:$B$7322,"<="&$B$4) -> 0 | I37: =COUNTIFS(BITACORA!$C$4:$C$7322,$B$7:$B$501,BITACORA!$E$4:$E$7322,$E$6:$AM$6,BITACORA!$B$4:$B$7322,">="&$B$3,BITACORA!$B$4:$B$7322,"<="&$B$4) -> 0 | J37: =COUNTIFS(BITACORA!$C$4:$C$7322,$B$7:$B$501,BITACORA!$E$4:$E$7322,$E$6:$AM$6,BITACORA!$B$4:$B$7322,">="&$B$3,BITACORA!$B$4:$B$7322,"<="&$B$4) -> 0 | K37: =COUNTIFS(BITACORA!$C$4:$C$7322,$B$7:$B$501,BITACORA!$E$4:$E$7322,$E$6:$AM$6,BITACORA!$B$4:$B$7322,">="&$B$3,BITACORA!$B$4:$B$7322,"<="&$B$4) -> 0 | L37: =COUNTIFS(BITACORA!$C$4:$C$7322,$B$7:$B$501,BITACORA!$E$4:$E$7322,$E$6:$AM$6,BITACORA!$B$4:$B$7322,">="&$B$3,BITACORA!$B$4:$B$7322,"<="&$B$4) -> 0 | ... AM37: =COUNTIFS(BITACORA!$C$4:$C$7322,$B$7:$B$501,BITACORA!$E$4:$E$7322,$E$6:$AM$6,BITACORA!$B$4:$B$7322,">="&$B$3,BITACORA!$B$4:$B$7322,"<="&$B$4) -> 0
D38: =SUM(E38:AM38) -> 0 | E38: =COUNTIFS(BITACORA!$C$4:$C$7322,$B$7:$B$501,BITACORA!$E$4:$E$7322,$E$6:$AM$6,BITACORA!$B$4:$B$7322,">="&$B$3,BITACORA!$B$4:$B$7322,"<="&$B$4) -> 0 | F38: =COUNTIFS(BITACORA!$C$4:$C$7322,$B$7:$B$501,BITACORA!$E$4:$E$7322,$E$6:$AM$6,BITACORA!$B$4:$B$7322,">="&$B$3,BITACORA!$B$4:$B$7322,"<="&$B$4) -> 0 | G38: =COUNTIFS(BITACORA!$C$4:$C$7322,$B$7:$B$501,BITACORA!$E$4:$E$7322,$E$6:$AM$6,BITACORA!$B$4:$B$7322,">="&$B$3,BITACORA!$B$4:$B$7322,"<="&$B$4) -> 0 | H38: =COUNTIFS(BITACORA!$C$4:$C$7322,$B$7:$B$501,BITACORA!$E$4:$E$7322,$E$6:$AM$6,BITACORA!$B$4:$B$7322,">="&$B$3,BITACORA!$B$4:$B$7322,"<="&$B$4) -> 0 | I38: =COUNTIFS(BITACORA!$C$4:$C$7322,$B$7:$B$501,BITACORA!$E$4:$E$7322,$E$6:$AM$6,BITACORA!$B$4:$B$7322,">="&$B$3,BITACORA!$B$4:$B$7322,"<="&$B$4) -> 0 | J38: =COUNTIFS(BITACORA!$C$4:$C$7322,$B$7:$B$501,BITACORA!$E$4:$E$7322,$E$6:$AM$6,BITACORA!$B$4:$B$7322,">="&$B$3,BITACORA!$B$4:$B$7322,"<="&$B$4) -> 0 | K38: =COUNTIFS(BITACORA!$C$4:$C$7322,$B$7:$B$501,BITACORA!$E$4:$E$7322,$E$6:$AM$6,BITACORA!$B$4:$B$7322,">="&$B$3,BITACORA!$B$4:$B$7322,"<="&$B$4) -> 0 | L38: =COUNTIFS(BITACORA!$C$4:$C$7322,$B$7:$B$501,BITACORA!$E$4:$E$7322,$E$6:$AM$6,BITACORA!$B$4:$B$7322,">="&$B$3,BITACORA!$B$4:$B$7322,"<="&$B$4) -> 0 | ... AM38: =COUNTIFS(BITACORA!$C$4:$C$7322,$B$7:$B$501,BITACORA!$E$4:$E$7322,$E$6:$AM$6,BITACORA!$B$4:$B$7322,">="&$B$3,BITACORA!$B$4:$B$7322,"<="&$B$4) -> 0
D39: =SUM(E39:AM39) -> 0 | E39: =COUNTIFS(BITACORA!$C$4:$C$7322,$B$7:$B$501,BITACORA!$E$4:$E$7322,$E$6:$AM$6,BITACORA!$B$4:$B$7322,">="&$B$3,BITACORA!$B$4:$B$7322,"<="&$B$4) -> 0 | F39: =COUNTIFS(BITACORA!$C$4:$C$7322,$B$7:$B$501,BITACORA!$E$4:$E$7322,$E$6:$AM$6,BITACORA!$B$4:$B$7322,">="&$B$3,BITACORA!$B$4:$B$7322,"<="&$B$4) -> 0 | G39: =COUNTIFS(BITACORA!$C$4:$C$7322,$B$7:$B$501,BITACORA!$E$4:$E$7322,$E$6:$AM$6,BITACORA!$B$4:$B$7322,">="&$B$3,BITACORA!$B$4:$B$7322,"<="&$B$4) -> 0 | H39: =COUNTIFS(BITACORA!$C$4:$C$7322,$B$7:$B$501,BITACORA!$E$4:$E$7322,$E$6:$AM$6,BITACORA!$B$4:$B$7322,">="&$B$3,BITACORA!$B$4:$B$7322,"<="&$B$4) -> 0 | I39: =COUNTIFS(BITACORA!$C$4:$C$7322,$B$7:$B$501,BITACORA!$E$4:$E$7322,$E$6:$AM$6,BITACORA!$B$4:$B$7322,">="&$B$3,BITACORA!$B$4:$B$7322,"<="&$B$4) -> 0 | J39: =COUNTIFS(BITACORA!$C$4:$C$7322,$B$7:$B$501,BITACORA!$E$4:$E$7322,$E$6:$AM$6,BITACORA!$B$4:$B$7322,">="&$B$3,BITACORA!$B$4:$B$7322,"<="&$B$4) -> 0 | K39: =COUNTIFS(BITACORA!$C$4:$C$7322,$B$7:$B$501,BITACORA!$E$4:$E$7322,$E$6:$AM$6,BITACORA!$B$4:$B$7322,">="&$B$3,BITACORA!$B$4:$B$7322,"<="&$B$4) -> 0 | L39: =COUNTIFS(BITACORA!$C$4:$C$7322,$B$7:$B$501,BITACORA!$E$4:$E$7322,$E$6:$AM$6,BITACORA!$B$4:$B$7322,">="&$B$3,BITACORA!$B$4:$B$7322,"<="&$B$4) -> 0 | ... AM39: =COUNTIFS(BITACORA!$C$4:$C$7322,$B$7:$B$501,BITACORA!$E$4:$E$7322,$E$6:$AM$6,BITACORA!$B$4:$B$7322,">="&$B$3,BITACORA!$B$4:$B$7322,"<="&$B$4) -> 0
D40: =SUM(E40:AM40) -> 0 | E40: =COUNTIFS(BITACORA!$C$4:$C$7322,$B$7:$B$501,BITACORA!$E$4:$E$7322,$E$6:$AM$6,BITACORA!$B$4:$B$7322,">="&$B$3,BITACORA!$B$4:$B$7322,"<="&$B$4) -> 0 | F40: =COUNTIFS(BITACORA!$C$4:$C$7322,$B$7:$B$501,BITACORA!$E$4:$E$7322,$E$6:$AM$6,BITACORA!$B$4:$B$7322,">="&$B$3,BITACORA!$B$4:$B$7322,"<="&$B$4) -> 0 | G40: =COUNTIFS(BITACORA!$C$4:$C$7322,$B$7:$B$501,BITACORA!$E$4:$E$7322,$E$6:$AM$6,BITACORA!$B$4:$B$7322,">="&$B$3,BITACORA!$B$4:$B$7322,"<="&$B$4) -> 0 | H40: =COUNTIFS(BITACORA!$C$4:$C$7322,$B$7:$B$501,BITACORA!$E$4:$E$7322,$E$6:$AM$6,BITACORA!$B$4:$B$7322,">="&$B$3,BITACORA!$B$4:$B$7322,"<="&$B$4) -> 0 | I40: =COUNTIFS(BITACORA!$C$4:$C$7322,$B$7:$B$501,BITACORA!$E$4:$E$7322,$E$6:$AM$6,BITACORA!$B$4:$B$7322,">="&$B$3,BITACORA!$B$4:$B$7322,"<="&$B$4) -> 0 | J40: =COUNTIFS(BITACORA!$C$4:$C$7322,$B$7:$B$501,BITACORA!$E$4:$E$7322,$E$6:$AM$6,BITACORA!$B$4:$B$7322,">="&$B$3,BITACORA!$B$4:$B$7322,"<="&$B$4) -> 0 | K40: =COUNTIFS(BITACORA!$C$4:$C$7322,$B$7:$B$501,BITACORA!$E$4:$E$7322,$E$6:$AM$6,BITACORA!$B$4:$B$7322,">="&$B$3,BITACORA!$B$4:$B$7322,"<="&$B$4) -> 0 | L40: =COUNTIFS(BITACORA!$C$4:$C$7322,$B$7:$B$501,BITACORA!$E$4:$E$7322,$E$6:$AM$6,BITACORA!$B$4:$B$7322,">="&$B$3,BITACORA!$B$4:$B$7322,"<="&$B$4) -> 0 | ... AM40: =COUNTIFS(BITACORA!$C$4:$C$7322,$B$7:$B$501,BITACORA!$E$4:$E$7322,$E$6:$AM$6,BITACORA!$B$4:$B$7322,">="&$B$3,BITACORA!$B$4:$B$7322,"<="&$B$4) -> 0
D41: =SUM(E41:AM41) -> 0 | E41: =COUNTIFS(BITACORA!$C$4:$C$7322,$B$7:$B$501,BITACORA!$E$4:$E$7322,$E$6:$AM$6,BITACORA!$B$4:$B$7322,">="&$B$3,BITACORA!$B$4:$B$7322,"<="&$B$4) -> 0 | F41: =COUNTIFS(BITACORA!$C$4:$C$7322,$B$7:$B$501,BITACORA!$E$4:$E$7322,$E$6:$AM$6,BITACORA!$B$4:$B$7322,">="&$B$3,BITACORA!$B$4:$B$7322,"<="&$B$4) -> 0 | G41: =COUNTIFS(BITACORA!$C$4:$C$7322,$B$7:$B$501,BITACORA!$E$4:$E$7322,$E$6:$AM$6,BITACORA!$B$4:$B$7322,">="&$B$3,BITACORA!$B$4:$B$7322,"<="&$B$4) -> 0 | H41: =COUNTIFS(BITACORA!$C$4:$C$7322,$B$7:$B$501,BITACORA!$E$4:$E$7322,$E$6:$AM$6,BITACORA!$B$4:$B$7322,">="&$B$3,BITACORA!$B$4:$B$7322,"<="&$B$4) -> 0 | I41: =COUNTIFS(BITACORA!$C$4:$C$7322,$B$7:$B$501,BITACORA!$E$4:$E$7322,$E$6:$AM$6,BITACORA!$B$4:$B$7322,">="&$B$3,BITACORA!$B$4:$B$7322,"<="&$B$4) -> 0 | J41: =COUNTIFS(BITACORA!$C$4:$C$7322,$B$7:$B$501,BITACORA!$E$4:$E$7322,$E$6:$AM$6,BITACORA!$B$4:$B$7322,">="&$B$3,BITACORA!$B$4:$B$7322,"<="&$B$4) -> 0 | K41: =COUNTIFS(BITACORA!$C$4:$C$7322,$B$7:$B$501,BITACORA!$E$4:$E$7322,$E$6:$AM$6,BITACORA!$B$4:$B$7322,">="&$B$3,BITACORA!$B$4:$B$7322,"<="&$B$4) -> 0 | L41: =COUNTIFS(BITACORA!$C$4:$C$7322,$B$7:$B$501,BITACORA!$E$4:$E$7322,$E$6:$AM$6,BITACORA!$B$4:$B$7322,">="&$B$3,BITACORA!$B$4:$B$7322,"<="&$B$4) -> 0 | ... AM41: =COUNTIFS(BITACORA!$C$4:$C$7322,$B$7:$B$501,BITACORA!$E$4:$E$7322,$E$6:$AM$6,BITACORA!$B$4:$B$7322,">="&$B$3,BITACORA!$B$4:$B$7322,"<="&$B$4) -> 0
D42: =SUM(E42:AM42) -> 0 | E42: =COUNTIFS(BITACORA!$C$4:$C$7322,$B$7:$B$501,BITACORA!$E$4:$E$7322,$E$6:$AM$6,BITACORA!$B$4:$B$7322,">="&$B$3,BITACORA!$B$4:$B$7322,"<="&$B$4) -> 0 | F42: =COUNTIFS(BITACORA!$C$4:$C$7322,$B$7:$B$501,BITACORA!$E$4:$E$7322,$E$6:$AM$6,BITACORA!$B$4:$B$7322,">="&$B$3,BITACORA!$B$4:$B$7322,"<="&$B$4) -> 0 | G42: =COUNTIFS(BITACORA!$C$4:$C$7322,$B$7:$B$501,BITACORA!$E$4:$E$7322,$E$6:$AM$6,BITACORA!$B$4:$B$7322,">="&$B$3,BITACORA!$B$4:$B$7322,"<="&$B$4) -> 0 | H42: =COUNTIFS(BITACORA!$C$4:$C$7322,$B$7:$B$501,BITACORA!$E$4:$E$7322,$E$6:$AM$6,BITACORA!$B$4:$B$7322,">="&$B$3,BITACORA!$B$4:$B$7322,"<="&$B$4) -> 0 | I42: =COUNTIFS(BITACORA!$C$4:$C$7322,$B$7:$B$501,BITACORA!$E$4:$E$7322,$E$6:$AM$6,BITACORA!$B$4:$B$7322,">="&$B$3,BITACORA!$B$4:$B$7322,"<="&$B$4) -> 0 | J42: =COUNTIFS(BITACORA!$C$4:$C$7322,$B$7:$B$501,BITACORA!$E$4:$E$7322,$E$6:$AM$6,BITACORA!$B$4:$B$7322,">="&$B$3,BITACORA!$B$4:$B$7322,"<="&$B$4) -> 0 | K42: =COUNTIFS(BITACORA!$C$4:$C$7322,$B$7:$B$501,BITACORA!$E$4:$E$7322,$E$6:$AM$6,BITACORA!$B$4:$B$7322,">="&$B$3,BITACORA!$B$4:$B$7322,"<="&$B$4) -> 0 | L42: =COUNTIFS(BITACORA!$C$4:$C$7322,$B$7:$B$501,BITACORA!$E$4:$E$7322,$E$6:$AM$6,BITACORA!$B$4:$B$7322,">="&$B$3,BITACORA!$B$4:$B$7322,"<="&$B$4) -> 0 | ... AM42: =COUNTIFS(BITACORA!$C$4:$C$7322,$B$7:$B$501,BITACORA!$E$4:$E$7322,$E$6:$AM$6,BITACORA!$B$4:$B$7322,">="&$B$3,BITACORA!$B$4:$B$7322,"<="&$B$4) -> 0
D43: =SUM(E43:AM43) -> 0 | E43: =COUNTIFS(BITACORA!$C$4:$C$7322,$B$7:$B$501,BITACORA!$E$4:$E$7322,$E$6:$AM$6,BITACORA!$B$4:$B$7322,">="&$B$3,BITACORA!$B$4:$B$7322,"<="&$B$4) -> 0 | F43: =COUNTIFS(BITACORA!$C$4:$C$7322,$B$7:$B$501,BITACORA!$E$4:$E$7322,$E$6:$AM$6,BITACORA!$B$4:$B$7322,">="&$B$3,BITACORA!$B$4:$B$7322,"<="&$B$4) -> 0 | G43: =COUNTIFS(BITACORA!$C$4:$C$7322,$B$7:$B$501,BITACORA!$E$4:$E$7322,$E$6:$AM$6,BITACORA!$B$4:$B$7322,">="&$B$3,BITACORA!$B$4:$B$7322,"<="&$B$4) -> 0 | H43: =COUNTIFS(BITACORA!$C$4:$C$7322,$B$7:$B$501,BITACORA!$E$4:$E$7322,$E$6:$AM$6,BITACORA!$B$4:$B$7322,">="&$B$3,BITACORA!$B$4:$B$7322,"<="&$B$4) -> 0 | I43: =COUNTIFS(BITACORA!$C$4:$C$7322,$B$7:$B$501,BITACORA!$E$4:$E$7322,$E$6:$AM$6,BITACORA!$B$4:$B$7322,">="&$B$3,BITACORA!$B$4:$B$7322,"<="&$B$4) -> 0 | J43: =COUNTIFS(BITACORA!$C$4:$C$7322,$B$7:$B$501,BITACORA!$E$4:$E$7322,$E$6:$AM$6,BITACORA!$B$4:$B$7322,">="&$B$3,BITACORA!$B$4:$B$7322,"<="&$B$4) -> 0 | K43: =COUNTIFS(BITACORA!$C$4:$C$7322,$B$7:$B$501,BITACORA!$E$4:$E$7322,$E$6:$AM$6,BITACORA!$B$4:$B$7322,">="&$B$3,BITACORA!$B$4:$B$7322,"<="&$B$4) -> 0 | L43: =COUNTIFS(BITACORA!$C$4:$C$7322,$B$7:$B$501,BITACORA!$E$4:$E$7322,$E$6:$AM$6,BITACORA!$B$4:$B$7322,">="&$B$3,BITACORA!$B$4:$B$7322,"<="&$B$4) -> 0 | ... AM43: =COUNTIFS(BITACORA!$C$4:$C$7322,$B$7:$B$501,BITACORA!$E$4:$E$7322,$E$6:$AM$6,BITACORA!$B$4:$B$7322,">="&$B$3,BITACORA!$B$4:$B$7322,"<="&$B$4) -> 0
D44: =SUM(E44:AM44) -> 0 | E44: =COUNTIFS(BITACORA!$C$4:$C$7322,$B$7:$B$501,BITACORA!$E$4:$E$7322,$E$6:$AM$6,BITACORA!$B$4:$B$7322,">="&$B$3,BITACORA!$B$4:$B$7322,"<="&$B$4) -> 0 | F44: =COUNTIFS(BITACORA!$C$4:$C$7322,$B$7:$B$501,BITACORA!$E$4:$E$7322,$E$6:$AM$6,BITACORA!$B$4:$B$7322,">="&$B$3,BITACORA!$B$4:$B$7322,"<="&$B$4) -> 0 | G44: =COUNTIFS(BITACORA!$C$4:$C$7322,$B$7:$B$501,BITACORA!$E$4:$E$7322,$E$6:$AM$6,BITACORA!$B$4:$B$7322,">="&$B$3,BITACORA!$B$4:$B$7322,"<="&$B$4) -> 0 | H44: =COUNTIFS(BITACORA!$C$4:$C$7322,$B$7:$B$501,BITACORA!$E$4:$E$7322,$E$6:$AM$6,BITACORA!$B$4:$B$7322,">="&$B$3,BITACORA!$B$4:$B$7322,"<="&$B$4) -> 0 | I44: =COUNTIFS(BITACORA!$C$4:$C$7322,$B$7:$B$501,BITACORA!$E$4:$E$7322,$E$6:$AM$6,BITACORA!$B$4:$B$7322,">="&$B$3,BITACORA!$B$4:$B$7322,"<="&$B$4) -> 0 | J44: =COUNTIFS(BITACORA!$C$4:$C$7322,$B$7:$B$501,BITACORA!$E$4:$E$7322,$E$6:$AM$6,BITACORA!$B$4:$B$7322,">="&$B$3,BITACORA!$B$4:$B$7322,"<="&$B$4) -> 0 | K44: =COUNTIFS(BITACORA!$C$4:$C$7322,$B$7:$B$501,BITACORA!$E$4:$E$7322,$E$6:$AM$6,BITACORA!$B$4:$B$7322,">="&$B$3,BITACORA!$B$4:$B$7322,"<="&$B$4) -> 0 | L44: =COUNTIFS(BITACORA!$C$4:$C$7322,$B$7:$B$501,BITACORA!$E$4:$E$7322,$E$6:$AM$6,BITACORA!$B$4:$B$7322,">="&$B$3,BITACORA!$B$4:$B$7322,"<="&$B$4) -> 0 | ... AM44: =COUNTIFS(BITACORA!$C$4:$C$7322,$B$7:$B$501,BITACORA!$E$4:$E$7322,$E$6:$AM$6,BITACORA!$B$4:$B$7322,">="&$B$3,BITACORA!$B$4:$B$7322,"<="&$B$4) -> 0
D45: =SUM(E45:AM45) -> 0 | E45: =COUNTIFS(BITACORA!$C$4:$C$7322,$B$7:$B$501,BITACORA!$E$4:$E$7322,$E$6:$AM$6,BITACORA!$B$4:$B$7322,">="&$B$3,BITACORA!$B$4:$B$7322,"<="&$B$4) -> 0 | F45: =COUNTIFS(BITACORA!$C$4:$C$7322,$B$7:$B$501,BITACORA!$E$4:$E$7322,$E$6:$AM$6,BITACORA!$B$4:$B$7322,">="&$B$3,BITACORA!$B$4:$B$7322,"<="&$B$4) -> 0 | G45: =COUNTIFS(BITACORA!$C$4:$C$7322,$B$7:$B$501,BITACORA!$E$4:$E$7322,$E$6:$AM$6,BITACORA!$B$4:$B$7322,">="&$B$3,BITACORA!$B$4:$B$7322,"<="&$B$4) -> 0 | H45: =COUNTIFS(BITACORA!$C$4:$C$7322,$B$7:$B$501,BITACORA!$E$4:$E$7322,$E$6:$AM$6,BITACORA!$B$4:$B$7322,">="&$B$3,BITACORA!$B$4:$B$7322,"<="&$B$4) -> 0 | I45: =COUNTIFS(BITACORA!$C$4:$C$7322,$B$7:$B$501,BITACORA!$E$4:$E$7322,$E$6:$AM$6,BITACORA!$B$4:$B$7322,">="&$B$3,BITACORA!$B$4:$B$7322,"<="&$B$4) -> 0 | J45: =COUNTIFS(BITACORA!$C$4:$C$7322,$B$7:$B$501,BITACORA!$E$4:$E$7322,$E$6:$AM$6,BITACORA!$B$4:$B$7322,">="&$B$3,BITACORA!$B$4:$B$7322,"<="&$B$4) -> 0 | K45: =COUNTIFS(BITACORA!$C$4:$C$7322,$B$7:$B$501,BITACORA!$E$4:$E$7322,$E$6:$AM$6,BITACORA!$B$4:$B$7322,">="&$B$3,BITACORA!$B$4:$B$7322,"<="&$B$4) -> 0 | L45: =COUNTIFS(BITACORA!$C$4:$C$7322,$B$7:$B$501,BITACORA!$E$4:$E$7322,$E$6:$AM$6,BITACORA!$B$4:$B$7322,">="&$B$3,BITACORA!$B$4:$B$7322,"<="&$B$4) -> 0 | ... AM45: =COUNTIFS(BITACORA!$C$4:$C$7322,$B$7:$B$501,BITACORA!$E$4:$E$7322,$E$6:$AM$6,BITACORA!$B$4:$B$7322,">="&$B$3,BITACORA!$B$4:$B$7322,"<="&$B$4) -> 0
D46: =SUM(E46:AM46) -> 0 | E46: =COUNTIFS(BITACORA!$C$4:$C$7322,$B$7:$B$501,BITACORA!$E$4:$E$7322,$E$6:$AM$6,BITACORA!$B$4:$B$7322,">="&$B$3,BITACORA!$B$4:$B$7322,"<="&$B$4) -> 0 | F46: =COUNTIFS(BITACORA!$C$4:$C$7322,$B$7:$B$501,BITACORA!$E$4:$E$7322,$E$6:$AM$6,BITACORA!$B$4:$B$7322,">="&$B$3,BITACORA!$B$4:$B$7322,"<="&$B$4) -> 0 | G46: =COUNTIFS(BITACORA!$C$4:$C$7322,$B$7:$B$501,BITACORA!$E$4:$E$7322,$E$6:$AM$6,BITACORA!$B$4:$B$7322,">="&$B$3,BITACORA!$B$4:$B$7322,"<="&$B$4) -> 0 | H46: =COUNTIFS(BITACORA!$C$4:$C$7322,$B$7:$B$501,BITACORA!$E$4:$E$7322,$E$6:$AM$6,BITACORA!$B$4:$B$7322,">="&$B$3,BITACORA!$B$4:$B$7322,"<="&$B$4) -> 0 | I46: =COUNTIFS(BITACORA!$C$4:$C$7322,$B$7:$B$501,BITACORA!$E$4:$E$7322,$E$6:$AM$6,BITACORA!$B$4:$B$7322,">="&$B$3,BITACORA!$B$4:$B$7322,"<="&$B$4) -> 0 | J46: =COUNTIFS(BITACORA!$C$4:$C$7322,$B$7:$B$501,BITACORA!$E$4:$E$7322,$E$6:$AM$6,BITACORA!$B$4:$B$7322,">="&$B$3,BITACORA!$B$4:$B$7322,"<="&$B$4) -> 0 | K46: =COUNTIFS(BITACORA!$C$4:$C$7322,$B$7:$B$501,BITACORA!$E$4:$E$7322,$E$6:$AM$6,BITACORA!$B$4:$B$7322,">="&$B$3,BITACORA!$B$4:$B$7322,"<="&$B$4) -> 0 | L46: =COUNTIFS(BITACORA!$C$4:$C$7322,$B$7:$B$501,BITACORA!$E$4:$E$7322,$E$6:$AM$6,BITACORA!$B$4:$B$7322,">="&$B$3,BITACORA!$B$4:$B$7322,"<="&$B$4) -> 0 | ... AM46: =COUNTIFS(BITACORA!$C$4:$C$7322,$B$7:$B$501,BITACORA!$E$4:$E$7322,$E$6:$AM$6,BITACORA!$B$4:$B$7322,">="&$B$3,BITACORA!$B$4:$B$7322,"<="&$B$4) -> 0
D47: =SUM(E47:AM47) -> 0 | E47: =COUNTIFS(BITACORA!$C$4:$C$7322,$B$7:$B$501,BITACORA!$E$4:$E$7322,$E$6:$AM$6,BITACORA!$B$4:$B$7322,">="&$B$3,BITACORA!$B$4:$B$7322,"<="&$B$4) -> 0 | F47: =COUNTIFS(BITACORA!$C$4:$C$7322,$B$7:$B$501,BITACORA!$E$4:$E$7322,$E$6:$AM$6,BITACORA!$B$4:$B$7322,">="&$B$3,BITACORA!$B$4:$B$7322,"<="&$B$4) -> 0 | G47: =COUNTIFS(BITACORA!$C$4:$C$7322,$B$7:$B$501,BITACORA!$E$4:$E$7322,$E$6:$AM$6,BITACORA!$B$4:$B$7322,">="&$B$3,BITACORA!$B$4:$B$7322,"<="&$B$4) -> 0 | H47: =COUNTIFS(BITACORA!$C$4:$C$7322,$B$7:$B$501,BITACORA!$E$4:$E$7322,$E$6:$AM$6,BITACORA!$B$4:$B$7322,">="&$B$3,BITACORA!$B$4:$B$7322,"<="&$B$4) -> 0 | I47: =COUNTIFS(BITACORA!$C$4:$C$7322,$B$7:$B$501,BITACORA!$E$4:$E$7322,$E$6:$AM$6,BITACORA!$B$4:$B$7322,">="&$B$3,BITACORA!$B$4:$B$7322,"<="&$B$4) -> 0 | J47: =COUNTIFS(BITACORA!$C$4:$C$7322,$B$7:$B$501,BITACORA!$E$4:$E$7322,$E$6:$AM$6,BITACORA!$B$4:$B$7322,">="&$B$3,BITACORA!$B$4:$B$7322,"<="&$B$4) -> 0 | K47: =COUNTIFS(BITACORA!$C$4:$C$7322,$B$7:$B$501,BITACORA!$E$4:$E$7322,$E$6:$AM$6,BITACORA!$B$4:$B$7322,">="&$B$3,BITACORA!$B$4:$B$7322,"<="&$B$4) -> 0 | L47: =COUNTIFS(BITACORA!$C$4:$C$7322,$B$7:$B$501,BITACORA!$E$4:$E$7322,$E$6:$AM$6,BITACORA!$B$4:$B$7322,">="&$B$3,BITACORA!$B$4:$B$7322,"<="&$B$4) -> 0 | ... AM47: =COUNTIFS(BITACORA!$C$4:$C$7322,$B$7:$B$501,BITACORA!$E$4:$E$7322,$E$6:$AM$6,BITACORA!$B$4:$B$7322,">="&$B$3,BITACORA!$B$4:$B$7322,"<="&$B$4) -> 0
... D504: =SUM(E504:AM504) -> 0 | E504: =COUNTIFS(BITACORA!$C$4:$C$7322,$B$7:$B$501,BITACORA!$E$4:$E$7322,$E$6:$AM$6,BITACORA!$B$4:$B$7322,">="&$B$3,BITACORA!$B$4:$B$7322,"<="&$B$4) -> 0 | F504: =COUNTIFS(BITACORA!$C$4:$C$7322,$B$7:$B$501,BITACORA!$E$4:$E$7322,$E$6:$AM$6,BITACORA!$B$4:$B$7322,">="&$B$3,BITACORA!$B$4:$B$7322,"<="&$B$4) -> 0 | G504: =COUNTIFS(BITACORA!$C$4:$C$7322,$B$7:$B$501,BITACORA!$E$4:$E$7322,$E$6:$AM$6,BITACORA!$B$4:$B$7322,">="&$B$3,BITACORA!$B$4:$B$7322,"<="&$B$4) -> 0 | H504: =COUNTIFS(BITACORA!$C$4:$C$7322,$B$7:$B$501,BITACORA!$E$4:$E$7322,$E$6:$AM$6,BITACORA!$B$4:$B$7322,">="&$B$3,BITACORA!$B$4:$B$7322,"<="&$B$4) -> 0 | I504: =COUNTIFS(BITACORA!$C$4:$C$7322,$B$7:$B$501,BITACORA!$E$4:$E$7322,$E$6:$AM$6,BITACORA!$B$4:$B$7322,">="&$B$3,BITACORA!$B$4:$B$7322,"<="&$B$4) -> 0 | J504: =COUNTIFS(BITACORA!$C$4:$C$7322,$B$7:$B$501,BITACORA!$E$4:$E$7322,$E$6:$AM$6,BITACORA!$B$4:$B$7322,">="&$B$3,BITACORA!$B$4:$B$7322,"<="&$B$4) -> 0 | K504: =COUNTIFS(BITACORA!$C$4:$C$7322,$B$7:$B$501,BITACORA!$E$4:$E$7322,$E$6:$AM$6,BITACORA!$B$4:$B$7322,">="&$B$3,BITACORA!$B$4:$B$7322,"<="&$B$4) -> 0 | L504: =COUNTIFS(BITACORA!$C$4:$C$7322,$B$7:$B$501,BITACORA!$E$4:$E$7322,$E$6:$AM$6,BITACORA!$B$4:$B$7322,">="&$B$3,BITACORA!$B$4:$B$7322,"<="&$B$4) -> 0 | ... AM504: =COUNTIFS(BITACORA!$C$4:$C$7322,$B$7:$B$501,BITACORA!$E$4:$E$7322,$E$6:$AM$6,BITACORA!$B$4:$B$7322,">="&$B$3,BITACORA!$B$4:$B$7322,"<="&$B$4) -> 0
D506: TRANSPORTISTAS EXTERNOS
B507: HBA0270
B508: XBE343
B509: PVL0706
B510: PPA1778
B511: HBC6496
B512: PCP5161
B513: RBA9146
B514: HGC420
B515: JAA2389
B516: PFB0399
B517: PVL602
B518: PBS1430
... B582: MCJ947

Sheet FLETES ($) JUNIO
A1: MES | B1: ABRIL | C1: =COUNTIFS(BITACORA!B4:B7322,">="&B3,BITACORA!B4:B7322,"<="&B4) -> 70 | E1: TOTAL $ VIAJES FLETADOS | F1: =SUM(D7:D504) -> #REF!
D2: 3 | E2: =#REF! -> #REF! | F2: =#REF! -> #REF! | G2: =#REF! -> #REF! | H2: =#REF! -> #REF! | I2: =#REF! -> #REF! | J2: =#REF! -> #REF! | K2: =#REF! -> #REF! | L2: =#REF! -> #REF! | ... AM2: =#REF! -> #REF!
A3: FECHA DE INICIO | B3: 44348 | D3: 4 | E3: =#REF! -> #REF! | F3: =#REF! -> #REF! | G3: =#REF! -> #REF! | H3: =#REF! -> #REF! | I3: =#REF! -> #REF! | J3: =#REF! -> #REF! | K3: =#REF! -> #REF! | L3: =#REF! -> #REF! | ... AM3: =#REF! -> #REF!
A4: FECHA DE CORTE | B4: 44377 | D4: 5 | E4: =#REF! -> #REF! | F4: =#REF! -> #REF! | G4: =#REF! -> #REF! | H4: =#REF! -> #REF! | I4: =#REF! -> #REF! | J4: =#REF! -> #REF! | K4: =#REF! -> #REF! | L4: =#REF! -> #REF! | ... AM4: =#REF! -> #REF!
D5: 6 | E5: =#REF! -> #REF! | F5: =#REF! -> #REF! | G5: =#REF! -> #REF! | H5: =#REF! -> #REF! | I5: =#REF! -> #REF! | J5: =#REF! -> #REF! | K5: =#REF! -> #REF! | L5: =#REF! -> #REF! | ... AM5: =#REF! -> #REF!
A6: =IFERROR(__xludf.DUMMYFUNCTION("IMPORTRANGE(""https://docs.google.com/spreadsheets/d/1utvdjsQjm2nB6A8-WaesD8IPx5qFCLXNwJxEgiS8wno/edit?usp=sharing"",""TRANSPORTISTAS!A1:C500"")"),"TRANSPORTISTA") -> TRANSPORTISTA | B6: =IFERROR(__xludf.DUMMYFUNCTION("""COMPUTED_VALUE"""),"PLACA DEL VEHICULO") -> PLACA DEL VEHICULO | C6: =IFERROR(__xludf.DUMMYFUNCTION("""COMPUTED_VALUE"""),"CAPACIDAD (FILAS)") -> CAPACIDAD (FILAS) | D6: TOTAL $ DE VIAJES | E6: =LISTAS!$B7 -> TACHINA | F6: =LISTAS!$B8 -> TRES VIAS | G6: =LISTAS!$B9 -> QUININDE | H6: =LISTAS!$B10 -> TAISHA | I6: =LISTAS!$B11 -> ARAJUNO | J6: =LISTAS!$B12 -> 0 | K6: =LISTAS!$B13 -> 0 | L6: =LISTAS!$B14 -> 0 | M6: =LISTAS!$B15 -> 0 | N6: =LISTAS!$B16 -> 0 | O6: =LISTAS!$B17 -> 0 | P6: =LISTAS!$B18 -> 0 | Q6: =LISTAS!$B19 -> 0 | R6: =LISTAS!$B20 -> 0 | S6: =LISTAS!$B21 -> 0 | T6: =LISTAS!$B22 -> 0 | U6: =LISTAS!$B23 -> 0 | V6: =LISTAS!$B24 -> FINCA EN PLANTA | W6: =LISTAS!$B25 -> LA SANDIA | X6: =LISTAS!$B26 -> 0 | Y6: =LISTAS!$B27 -> 0 | Z6: =LISTAS!$B28 -> 0 | AA6: =LISTAS!$B29 -> 0 | AB6: =LISTAS!$B30 -> 0 | AC6: =LISTAS!$B31 -> 0 | AD6: =LISTAS!$B32 -> 0 | AE6: =LISTAS!$B33 -> RIO FRIO | AF6: =LISTAS!$B34 -> RIO FRIO ETAPA 2 | AG6: =LISTAS!$B35 -> BOSQUE PUERTO NUEVO | AH6: =LISTAS!$B36 -> 0 | AI6: =LISTAS!$B37 -> 0 | AJ6: =LISTAS!$B38 -> 0 | AK6: =LISTAS!$B39 -> 0 | AL6: =LISTAS!$B40 -> 0 | AM6: =LISTAS!$B41 -> 0
A7: =IFERROR(__xludf.DUMMYFUNCTION("""COMPUTED_VALUE"""),"Klever Enrique Moreira Cedeño") -> Klever Enrique Moreira Cedeño | B7: =IFERROR(__xludf.DUMMYFUNCTION("""COMPUTED_VALUE"""),"JAR4061") -> JAR4061 | C7: =IFERROR(__xludf.DUMMYFUNCTION("""COMPUTED_VALUE"""),3) -> 3 | D7: =SUM(E7:AM7) -> #REF! | E7: =IF($C7=$D$2,#REF!*E$2,IF($C7=$D$3,#REF!*E$3,IF($C7=$D$4,#REF!*E$4,IF($C7=$D$5,#REF!*E$5,0)))) -> #REF! | F7: =IF($C7=$D$2,#REF!*F$2,IF($C7=$D$3,#REF!*F$3,IF($C7=$D$4,#REF!*F$4,IF($C7=$D$5,#REF!*F$5,0)))) -> #REF! | G7: =IF($C7=$D$2,#REF!*G$2,IF($C7=$D$3,#REF!*G$3,IF($C7=$D$4,#REF!*G$4,IF($C7=$D$5,#REF!*G$5,0)))) -> #REF! | H7: =IF($C7=$D$2,#REF!*H$2,IF($C7=$D$3,#REF!*H$3,IF($C7=$D$4,#REF!*H$4,IF($C7=$D$5,#REF!*H$5,0)))) -> #REF! | I7: =IF($C7=$D$2,#REF!*I$2,IF($C7=$D$3,#REF!*I$3,IF($C7=$D$4,#REF!*I$4,IF($C7=$D$5,#REF!*I$5,0)))) -> #REF! | J7: =IF($C7=$D$2,#REF!*J$2,IF($C7=$D$3,#REF!*J$3,IF($C7=$D$4,#REF!*J$4,IF($C7=$D$5,#REF!*J$5,0)))) -> #REF! | K7: =IF($C7=$D$2,#REF!*K$2,IF($C7=$D$3,#REF!*K$3,IF($C7=$D$4,#REF!*K$4,IF($C7=$D$5,#REF!*K$5,0)))) -> #REF! | L7: =IF($C7=$D$2,#REF!*L$2,IF($C7=$D$3,#REF!*L$3,IF($C7=$D$4,#REF!*L$4,IF($C7=$D$5,#REF!*L$5,0)))) -> #REF! | ... AM7: =IF($C7=$D$2,#REF!*AM$2,IF($C7=$D$3,#REF!*AM$3,IF($C7=$D$4,#REF!*AM$4,IF($C7=$D$5,#REF!*AM$5,0)))) -> #REF!
A8: =IFERROR(__xludf.DUMMYFUNCTION("""COMPUTED_VALUE"""),"Ricardo Coveña Quintero") -> Ricardo Coveña Quintero | B8: =IFERROR(__xludf.DUMMYFUNCTION("""COMPUTED_VALUE"""),"PPX0724") -> PPX0724 | C8: =IFERROR(__xludf.DUMMYFUNCTION("""COMPUTED_VALUE"""),3) -> 3 | D8: =SUM(E8:AM8) -> #REF! | E8: =IF($C8=$D$2,#REF!*E$2,IF($C8=$D$3,#REF!*E$3,IF($C8=$D$4,#REF!*E$4,IF($C8=$D$5,#REF!*E$5,0)))) -> #REF! | F8: =IF($C8=$D$2,#REF!*F$2,IF($C8=$D$3,#REF!*F$3,IF($C8=$D$4,#REF!*F$4,IF($C8=$D$5,#REF!*F$5,0)))) -> #REF! | G8: =IF($C8=$D$2,#REF!*G$2,IF($C8=$D$3,#REF!*G$3,IF($C8=$D$4,#REF!*G$4,IF($C8=$D$5,#REF!*G$5,0)))) -> #REF! | H8: =IF($C8=$D$2,#REF!*H$2,IF($C8=$D$3,#REF!*H$3,IF($C8=$D$4,#REF!*H$4,IF($C8=$D$5,#REF!*H$5,0)))) -> #REF! | I8: =IF($C8=$D$2,#REF!*I$2,IF($C8=$D$3,#REF!*I$3,IF($C8=$D$4,#REF!*I$4,IF($C8=$D$5,#REF!*I$5,0)))) -> #REF! | J8: =IF($C8=$D$2,#REF!*J$2,IF($C8=$D$3,#REF!*J$3,IF($C8=$D$4,#REF!*J$4,IF($C8=$D$5,#REF!*J$5,0)))) -> #REF! | K8: =IF($C8=$D$2,#REF!*K$2,IF($C8=$D$3,#REF!*K$3,IF($C8=$D$4,#REF!*K$4,IF($C8=$D$5,#REF!*K$5,0)))) -> #REF! | L8: =IF($C8=$D$2,#REF!*L$2,IF($C8=$D$3,#REF!*L$3,IF($C8=$D$4,#REF!*L$4,IF($C8=$D$5,#REF!*L$5,0)))) -> #REF! | ... AM8: =IF($C8=$D$2,#REF!*AM$2,IF($C8=$D$3,#REF!*AM$3,IF($C8=$D$4,#REF!*AM$4,IF($C8=$D$5,#REF!*AM$5,0)))) -> #REF!
A9: =IFERROR(__xludf.DUMMYFUNCTION("""COMPUTED_VALUE"""),"Cesar Octavio Aguilar Loor") -> Cesar Octavio Aguilar Loor | B9: =IFERROR(__xludf.DUMMYFUNCTION("""COMPUTED_VALUE"""),"MCW0186") -> MCW0186 | C9: =IFERROR(__xludf.DUMMYFUNCTION("""COMPUTED_VALUE"""),4) -> 4 | D9: =SUM(E9:AM9) -> #REF! | E9: =IF($C9=$D$2,#REF!*E$2,IF($C9=$D$3,#REF!*E$3,IF($C9=$D$4,#REF!*E$4,IF($C9=$D$5,#REF!*E$5,0)))) -> #REF! | F9: =IF($C9=$D$2,#REF!*F$2,IF($C9=$D$3,#REF!*F$3,IF($C9=$D$4,#REF!*F$4,IF($C9=$D$5,#REF!*F$5,0)))) -> #REF! | G9: =IF($C9=$D$2,#REF!*G$2,IF($C9=$D$3,#REF!*G$3,IF($C9=$D$4,#REF!*G$4,IF($C9=$D$5,#REF!*G$5,0)))) -> #REF! | H9: =IF($C9=$D$2,#REF!*H$2,IF($C9=$D$3,#REF!*H$3,IF($C9=$D$4,#REF!*H$4,IF($C9=$D$5,#REF!*H$5,0)))) -> #REF! | I9: =IF($C9=$D$2,#REF!*I$2,IF($C9=$D$3,#REF!*I$3,IF($C9=$D$4,#REF!*I$4,IF($C9=$D$5,#REF!*I$5,0)))) -> #REF! | J9: =IF($C9=$D$2,#REF!*J$2,IF($C9=$D$3,#REF!*J$3,IF($C9=$D$4,#REF!*J$4,IF($C9=$D$5,#REF!*J$5,0)))) -> #REF! | K9: =IF($C9=$D$2,#REF!*K$2,IF($C9=$D$3,#REF!*K$3,IF($C9=$D$4,#REF!*K$4,IF($C9=$D$5,#REF!*K$5,0)))) -> #REF! | L9: =IF($C9=$D$2,#REF!*L$2,IF($C9=$D$3,#REF!*L$3,IF($C9=$D$4,#REF!*L$4,IF($C9=$D$5,#REF!*L$5,0)))) -> #REF! | ... AM9: =IF($C9=$D$2,#REF!*AM$2,IF($C9=$D$3,#REF!*AM$3,IF($C9=$D$4,#REF!*AM$4,IF($C9=$D$5,#REF!*AM$5,0)))) -> #REF!
A10: =IFERROR(__xludf.DUMMYFUNCTION("""COMPUTED_VALUE"""),"Jonathan Jehova Vera Mendoza") -> Jonathan Jehova Vera Mendoza | B10: =IFERROR(__xludf.DUMMYFUNCTION("""COMPUTED_VALUE"""),"JAA3367") -> JAA3367 | C10: =IFERROR(__xludf.DUMMYFUNCTION("""COMPUTED_VALUE"""),4) -> 4 | D10: =SUM(E10:AM10) -> #REF! | E10: =IF($C10=$D$2,#REF!*E$2,IF($C10=$D$3,#REF!*E$3,IF($C10=$D$4,#REF!*E$4,IF($C10=$D$5,#REF!*E$5,0)))) -> #REF! | F10: =IF($C10=$D$2,#REF!*F$2,IF($C10=$D$3,#REF!*F$3,IF($C10=$D$4,#REF!*F$4,IF($C10=$D$5,#REF!*F$5,0)))) -> #REF! | G10: =IF($C10=$D$2,#REF!*G$2,IF($C10=$D$3,#REF!*G$3,IF($C10=$D$4,#REF!*G$4,IF($C10=$D$5,#REF!*G$5,0)))) -> #REF! | H10: =IF($C10=$D$2,#REF!*H$2,IF($C10=$D$3,#REF!*H$3,IF($C10=$D$4,#REF!*H$4,IF($C10=$D$5,#REF!*H$5,0)))) -> #REF! | I10: =IF($C10=$D$2,#REF!*I$2,IF($C10=$D$3,#REF!*I$3,IF($C10=$D$4,#REF!*I$4,IF($C10=$D$5,#REF!*I$5,0)))) -> #REF! | J10: =IF($C10=$D$2,#REF!*J$2,IF($C10=$D$3,#REF!*J$3,IF($C10=$D$4,#REF!*J$4,IF($C10=$D$5,#REF!*J$5,0)))) -> #REF! | K10: =IF($C10=$D$2,#REF!*K$2,IF($C10=$D$3,#REF!*K$3,IF($C10=$D$4,#REF!*K$4,IF($C10=$D$5,#REF!*K$5,0)))) -> #REF! | L10: =IF($C10=$D$2,#REF!*L$2,IF($C10=$D$3,#REF!*L$3,IF($C10=$D$4,#REF!*L$4,IF($C10=$D$5,#REF!*L$5,0)))) -> #REF! | ... AM10: =IF($C10=$D$2,#REF!*AM$2,IF($C10=$D$3,#REF!*AM$3,IF($C10=$D$4,#REF!*AM$4,IF($C10=$D$5,#REF!*AM$5,0)))) -> #REF!
A11: =IFERROR(__xludf.DUMMYFUNCTION("""COMPUTED_VALUE"""),"Emerson Fabricio Moreira Alcivar") -> Emerson Fabricio Moreira Alcivar | B11: =IFERROR(__xludf.DUMMYFUNCTION("""COMPUTED_VALUE"""),"JAA3375") -> JAA3375 | C11: =IFERROR(__xludf.DUMMYFUNCTION("""COMPUTED_VALUE"""),4) -> 4 | D11: =SUM(E11:AM11) -> #REF! | E11: =IF($C11=$D$2,#REF!*E$2,IF($C11=$D$3,#REF!*E$3,IF($C11=$D$4,#REF!*E$4,IF($C11=$D$5,#REF!*E$5,0)))) -> #REF! | F11: =IF($C11=$D$2,#REF!*F$2,IF($C11=$D$3,#REF!*F$3,IF($C11=$D$4,#REF!*F$4,IF($C11=$D$5,#REF!*F$5,0)))) -> #REF! | G11: =IF($C11=$D$2,#REF!*G$2,IF($C11=$D$3,#REF!*G$3,IF($C11=$D$4,#REF!*G$4,IF($C11=$D$5,#REF!*G$5,0)))) -> #REF! | H11: =IF($C11=$D$2,#REF!*H$2,IF($C11=$D$3,#REF!*H$3,IF($C11=$D$4,#REF!*H$4,IF($C11=$D$5,#REF!*H$5,0)))) -> #REF! | I11: =IF($C11=$D$2,#REF!*I$2,IF($C11=$D$3,#REF!*I$3,IF($C11=$D$4,#REF!*I$4,IF($C11=$D$5,#REF!*I$5,0)))) -> #REF! | J11: =IF($C11=$D$2,#REF!*J$2,IF($C11=$D$3,#REF!*J$3,IF($C11=$D$4,#REF!*J$4,IF($C11=$D$5,#REF!*J$5,0)))) -> #REF! | K11: =IF($C11=$D$2,#REF!*K$2,IF($C11=$D$3,#REF!*K$3,IF($C11=$D$4,#REF!*K$4,IF($C11=$D$5,#REF!*K$5,0)))) -> #REF! | L11: =IF($C11=$D$2,#REF!*L$2,IF($C11=$D$3,#REF!*L$3,IF($C11=$D$4,#REF!*L$4,IF($C11=$D$5,#REF!*L$5,0)))) -> #REF! | ... AM11: =IF($C11=$D$2,#REF!*AM$2,IF($C11=$D$3,#REF!*AM$3,IF($C11=$D$4,#REF!*AM$4,IF($C11=$D$5,#REF!*AM$5,0)))) -> #REF!
A12: =IFERROR(__xludf.DUMMYFUNCTION("""COMPUTED_VALUE"""),"Cedeño Barveran Marcelo German") -> Cedeño Barveran Marcelo German | B12: =IFERROR(__xludf.DUMMYFUNCTION("""COMPUTED_VALUE"""),"MAP0286") -> MAP0286 | C12: =IFERROR(__xludf.DUMMYFUNCTION("""COMPUTED_VALUE"""),4) -> 4 | D12: =SUM(E12:AM12) -> #REF! | E12: =IF($C12=$D$2,#REF!*E$2,IF($C12=$D$3,#REF!*E$3,IF($C12=$D$4,#REF!*E$4,IF($C12=$D$5,#REF!*E$5,0)))) -> #REF! | F12: =IF($C12=$D$2,#REF!*F$2,IF($C12=$D$3,#REF!*F$3,IF($C12=$D$4,#REF!*F$4,IF($C12=$D$5,#REF!*F$5,0)))) -> #REF! | G12: =IF($C12=$D$2,#REF!*G$2,IF($C12=$D$3,#REF!*G$3,IF($C12=$D$4,#REF!*G$4,IF($C12=$D$5,#REF!*G$5,0)))) -> #REF! | H12: =IF($C12=$D$2,#REF!*H$2,IF($C12=$D$3,#REF!*H$3,IF($C12=$D$4,#REF!*H$4,IF($C12=$D$5,#REF!*H$5,0)))) -> #REF! | I12: =IF($C12=$D$2,#REF!*I$2,IF($C12=$D$3,#REF!*I$3,IF($C12=$D$4,#REF!*I$4,IF($C12=$D$5,#REF!*I$5,0)))) -> #REF! | J12: =IF($C12=$D$2,#REF!*J$2,IF($C12=$D$3,#REF!*J$3,IF($C12=$D$4,#REF!*J$4,IF($C12=$D$5,#REF!*J$5,0)))) -> #REF! | K12: =IF($C12=$D$2,#REF!*K$2,IF($C12=$D$3,#REF!*K$3,IF($C12=$D$4,#REF!*K$4,IF($C12=$D$5,#REF!*K$5,0)))) -> #REF! | L12: =IF($C12=$D$2,#REF!*L$2,IF($C12=$D$3,#REF!*L$3,IF($C12=$D$4,#REF!*L$4,IF($C12=$D$5,#REF!*L$5,0)))) -> #REF! | ... AM12: =IF($C12=$D$2,#REF!*AM$2,IF($C12=$D$3,#REF!*AM$3,IF($C12=$D$4,#REF!*AM$4,IF($C12=$D$5,#REF!*AM$5,0)))) -> #REF!
A13: =IFERROR(__xludf.DUMMYFUNCTION("""COMPUTED_VALUE"""),"Jonathan Alejandro Diaz Montes") -> Jonathan Alejandro Diaz Montes | B13: =IFERROR(__xludf.DUMMYFUNCTION("""COMPUTED_VALUE"""),"PQX0243") -> PQX0243 | C13: =IFERROR(__xludf.DUMMYFUNCTION("""COMPUTED_VALUE"""),4) -> 4 | D13: =SUM(E13:AM13) -> #REF! | E13: =IF($C13=$D$2,#REF!*E$2,IF($C13=$D$3,#REF!*E$3,IF($C13=$D$4,#REF!*E$4,IF($C13=$D$5,#REF!*E$5,0)))) -> #REF! | F13: =IF($C13=$D$2,#REF!*F$2,IF($C13=$D$3,#REF!*F$3,IF($C13=$D$4,#REF!*F$4,IF($C13=$D$5,#REF!*F$5,0)))) -> #REF! | G13: =IF($C13=$D$2,#REF!*G$2,IF($C13=$D$3,#REF!*G$3,IF($C13=$D$4,#REF!*G$4,IF($C13=$D$5,#REF!*G$5,0)))) -> #REF! | H13: =IF($C13=$D$2,#REF!*H$2,IF($C13=$D$3,#REF!*H$3,IF($C13=$D$4,#REF!*H$4,IF($C13=$D$5,#REF!*H$5,0)))) -> #REF! | I13: =IF($C13=$D$2,#REF!*I$2,IF($C13=$D$3,#REF!*I$3,IF($C13=$D$4,#REF!*I$4,IF($C13=$D$5,#REF!*I$5,0)))) -> #REF! | J13: =IF($C13=$D$2,#REF!*J$2,IF($C13=$D$3,#REF!*J$3,IF($C13=$D$4,#REF!*J$4,IF($C13=$D$5,#REF!*J$5,0)))) -> #REF! | K13: =IF($C13=$D$2,#REF!*K$2,IF($C13=$D$3,#REF!*K$3,IF($C13=$D$4,#REF!*K$4,IF($C13=$D$5,#REF!*K$5,0)))) -> #REF! | L13: =IF($C13=$D$2,#REF!*L$2,IF($C13=$D$3,#REF!*L$3,IF($C13=$D$4,#REF!*L$4,IF($C13=$D$5,#REF!*L$5,0)))) -> #REF! | ... AM13: =IF($C13=$D$2,#REF!*AM$2,IF($C13=$D$3,#REF!*AM$3,IF($C13=$D$4,#REF!*AM$4,IF($C13=$D$5,#REF!*AM$5,0)))) -> #REF!
A14: =IFERROR(__xludf.DUMMYFUNCTION("""COMPUTED_VALUE"""),"Freddy Amador Napa Rosado") -> Freddy Amador Napa Rosado | B14: =IFERROR(__xludf.DUMMYFUNCTION("""COMPUTED_VALUE"""),"PIB0529") -> PIB0529 | C14: =IFERROR(__xludf.DUMMYFUNCTION("""COMPUTED_VALUE"""),4) -> 4 | D14: =SUM(E14:AM14) -> #REF! | E14: =IF($C14=$D$2,#REF!*E$2,IF($C14=$D$3,#REF!*E$3,IF($C14=$D$4,#REF!*E$4,IF($C14=$D$5,#REF!*E$5,0)))) -> #REF! | F14: =IF($C14=$D$2,#REF!*F$2,IF($C14=$D$3,#REF!*F$3,IF($C14=$D$4,#REF!*F$4,IF($C14=$D$5,#REF!*F$5,0)))) -> #REF! | G14: =IF($C14=$D$2,#REF!*G$2,IF($C14=$D$3,#REF!*G$3,IF($C14=$D$4,#REF!*G$4,IF($C14=$D$5,#REF!*G$5,0)))) -> #REF! | H14: =IF($C14=$D$2,#REF!*H$2,IF($C14=$D$3,#REF!*H$3,IF($C14=$D$4,#REF!*H$4,IF($C14=$D$5,#REF!*H$5,0)))) -> #REF! | I14: =IF($C14=$D$2,#REF!*I$2,IF($C14=$D$3,#REF!*I$3,IF($C14=$D$4,#REF!*I$4,IF($C14=$D$5,#REF!*I$5,0)))) -> #REF! | J14: =IF($C14=$D$2,#REF!*J$2,IF($C14=$D$3,#REF!*J$3,IF($C14=$D$4,#REF!*J$4,IF($C14=$D$5,#REF!*J$5,0)))) -> #REF! | K14: =IF($C14=$D$2,#REF!*K$2,IF($C14=$D$3,#REF!*K$3,IF($C14=$D$4,#REF!*K$4,IF($C14=$D$5,#REF!*K$5,0)))) -> #REF! | L14: =IF($C14=$D$2,#REF!*L$2,IF($C14=$D$3,#REF!*L$3,IF($C14=$D$4,#REF!*L$4,IF($C14=$D$5,#REF!*L$5,0)))) -> #REF! | ... AM14: =IF($C14=$D$2,#REF!*AM$2,IF($C14=$D$3,#REF!*AM$3,IF($C14=$D$4,#REF!*AM$4,IF($C14=$D$5,#REF!*AM$5,0)))) -> #REF!
A15: =IFERROR(__xludf.DUMMYFUNCTION("""COMPUTED_VALUE"""),"Diego Adrian Mendoza Velez") -> Diego Adrian Mendoza Velez | B15: =IFERROR(__xludf.DUMMYFUNCTION("""COMPUTED_VALUE"""),"JAA3376") -> JAA3376 | C15: =IFERROR(__xludf.DUMMYFUNCTION("""COMPUTED_VALUE"""),4) -> 4 | D15: =SUM(E15:AM15) -> #REF! | E15: =IF($C15=$D$2,#REF!*E$2,IF($C15=$D$3,#REF!*E$3,IF($C15=$D$4,#REF!*E$4,IF($C15=$D$5,#REF!*E$5,0)))) -> #REF! | F15: =IF($C15=$D$2,#REF!*F$2,IF($C15=$D$3,#REF!*F$3,IF($C15=$D$4,#REF!*F$4,IF($C15=$D$5,#REF!*F$5,0)))) -> #REF! | G15: =IF($C15=$D$2,#REF!*G$2,IF($C15=$D$3,#REF!*G$3,IF($C15=$D$4,#REF!*G$4,IF($C15=$D$5,#REF!*G$5,0)))) -> #REF! | H15: =IF($C15=$D$2,#REF!*H$2,IF($C15=$D$3,#REF!*H$3,IF($C15=$D$4,#REF!*H$4,IF($C15=$D$5,#REF!*H$5,0)))) -> #REF! | I15: =IF($C15=$D$2,#REF!*I$2,IF($C15=$D$3,#REF!*I$3,IF($C15=$D$4,#REF!*I$4,IF($C15=$D$5,#REF!*I$5,0)))) -> #REF! | J15: =IF($C15=$D$2,#REF!*J$2,IF($C15=$D$3,#REF!*J$3,IF($C15=$D$4,#REF!*J$4,IF($C15=$D$5,#REF!*J$5,0)))) -> #REF! | K15: =IF($C15=$D$2,#REF!*K$2,IF($C15=$D$3,#REF!*K$3,IF($C15=$D$4,#REF!*K$4,IF($C15=$D$5,#REF!*K$5,0)))) -> #REF! | L15: =IF($C15=$D$2,#REF!*L$2,IF($C15=$D$3,#REF!*L$3,IF($C15=$D$4,#REF!*L$4,IF($C15=$D$5,#REF!*L$5,0)))) -> #REF! | ... AM15: =IF($C15=$D$2,#REF!*AM$2,IF($C15=$D$3,#REF!*AM$3,IF($C15=$D$4,#REF!*AM$4,IF($C15=$D$5,#REF!*AM$5,0)))) -> #REF!
A16: =IFERROR(__xludf.DUMMYFUNCTION("""COMPUTED_VALUE"""),"Oscar Jose Loor Basurto") -> Oscar Jose Loor Basurto | B16: =IFERROR(__xludf.DUMMYFUNCTION("""COMPUTED_VALUE"""),"PJB0702") -> PJB0702 | C16: =IFERROR(__xludf.DUMMYFUNCTION("""COMPUTED_VALUE"""),4) -> 4 | D16: =SUM(E16:AM16) -> #REF! | E16: =IF($C16=$D$2,#REF!*E$2,IF($C16=$D$3,#REF!*E$3,IF($C16=$D$4,#REF!*E$4,IF($C16=$D$5,#REF!*E$5,0)))) -> #REF! | F16: =IF($C16=$D$2,#REF!*F$2,IF($C16=$D$3,#REF!*F$3,IF($C16=$D$4,#REF!*F$4,IF($C16=$D$5,#REF!*F$5,0)))) -> #REF! | G16: =IF($C16=$D$2,#REF!*G$2,IF($C16=$D$3,#REF!*G$3,IF($C16=$D$4,#REF!*G$4,IF($C16=$D$5,#REF!*G$5,0)))) -> #REF! | H16: =IF($C16=$D$2,#REF!*H$2,IF($C16=$D$3,#REF!*H$3,IF($C16=$D$4,#REF!*H$4,IF($C16=$D$5,#REF!*H$5,0)))) -> #REF! | I16: =IF($C16=$D$2,#REF!*I$2,IF($C16=$D$3,#REF!*I$3,IF($C16=$D$4,#REF!*I$4,IF($C16=$D$5,#REF!*I$5,0)))) -> #REF! | J16: =IF($C16=$D$2,#REF!*J$2,IF($C16=$D$3,#REF!*J$3,IF($C16=$D$4,#REF!*J$4,IF($C16=$D$5,#REF!*J$5,0)))) -> #REF! | K16: =IF($C16=$D$2,#REF!*K$2,IF($C16=$D$3,#REF!*K$3,IF($C16=$D$4,#REF!*K$4,IF($C16=$D$5,#REF!*K$5,0)))) -> #REF! | L16: =IF($C16=$D$2,#REF!*L$2,IF($C16=$D$3,#REF!*L$3,IF($C16=$D$4,#REF!*L$4,IF($C16=$D$5,#REF!*L$5,0)))) -> #REF! | ... AM16: =IF($C16=$D$2,#REF!*AM$2,IF($C16=$D$3,#REF!*AM$3,IF($C16=$D$4,#REF!*AM$4,IF($C16=$D$5,#REF!*AM$5,0)))) -> #REF!
A17: =IFERROR(__xludf.DUMMYFUNCTION("""COMPUTED_VALUE"""),"Angulo Saltos Marlon Fabian") -> Angulo Saltos Marlon Fabian | B17: =IFERROR(__xludf.DUMMYFUNCTION("""COMPUTED_VALUE"""),"GKX0511") -> GKX0511 | C17: =IFERROR(__xludf.DUMMYFUNCTION("""COMPUTED_VALUE"""),4) -> 4 | D17: =SUM(E17:AM17) -> #REF! | E17: =IF($C17=$D$2,#REF!*E$2,IF($C17=$D$3,#REF!*E$3,IF($C17=$D$4,#REF!*E$4,IF($C17=$D$5,#REF!*E$5,0)))) -> #REF! | F17: =IF($C17=$D$2,#REF!*F$2,IF($C17=$D$3,#REF!*F$3,IF($C17=$D$4,#REF!*F$4,IF($C17=$D$5,#REF!*F$5,0)))) -> #REF! | G17: =IF($C17=$D$2,#REF!*G$2,IF($C17=$D$3,#REF!*G$3,IF($C17=$D$4,#REF!*G$4,IF($C17=$D$5,#REF!*G$5,0)))) -> #REF! | H17: =IF($C17=$D$2,#REF!*H$2,IF($C17=$D$3,#REF!*H$3,IF($C17=$D$4,#REF!*H$4,IF($C17=$D$5,#REF!*H$5,0)))) -> #REF! | I17: =IF($C17=$D$2,#REF!*I$2,IF($C17=$D$3,#REF!*I$3,IF($C17=$D$4,#REF!*I$4,IF($C17=$D$5,#REF!*I$5,0)))) -> #REF! | J17: =IF($C17=$D$2,#REF!*J$2,IF($C17=$D$3,#REF!*J$3,IF($C17=$D$4,#REF!*J$4,IF($C17=$D$5,#REF!*J$5,0)))) -> #REF! | K17: =IF($C17=$D$2,#REF!*K$2,IF($C17=$D$3,#REF!*K$3,IF($C17=$D$4,#REF!*K$4,IF($C17=$D$5,#REF!*K$5,0)))) -> #REF! | L17: =IF($C17=$D$2,#REF!*L$2,IF($C17=$D$3,#REF!*L$3,IF($C17=$D$4,#REF!*L$4,IF($C17=$D$5,#REF!*L$5,0)))) -> #REF! | ... AM17: =IF($C17=$D$2,#REF!*AM$2,IF($C17=$D$3,#REF!*AM$3,IF($C17=$D$4,#REF!*AM$4,IF($C17=$D$5,#REF!*AM$5,0)))) -> #REF!
A18: =IFERROR(__xludf.DUMMYFUNCTION("""COMPUTED_VALUE"""),"Enner Eliezer Cevallos Burgos") -> Enner Eliezer Cevallos Burgos | B18: =IFERROR(__xludf.DUMMYFUNCTION("""COMPUTED_VALUE"""),"PZI0105") -> PZI0105 | C18: =IFERROR(__xludf.DUMMYFUNCTION("""COMPUTED_VALUE"""),5) -> 5 | D18: =SUM(E18:AM18) -> #REF! | E18: =IF($C18=$D$2,#REF!*E$2,IF($C18=$D$3,#REF!*E$3,IF($C18=$D$4,#REF!*E$4,IF($C18=$D$5,#REF!*E$5,0)))) -> #REF! | F18: =IF($C18=$D$2,#REF!*F$2,IF($C18=$D$3,#REF!*F$3,IF($C18=$D$4,#REF!*F$4,IF($C18=$D$5,#REF!*F$5,0)))) -> #REF! | G18: =IF($C18=$D$2,#REF!*G$2,IF($C18=$D$3,#REF!*G$3,IF($C18=$D$4,#REF!*G$4,IF($C18=$D$5,#REF!*G$5,0)))) -> #REF! | H18: =IF($C18=$D$2,#REF!*H$2,IF($C18=$D$3,#REF!*H$3,IF($C18=$D$4,#REF!*H$4,IF($C18=$D$5,#REF!*H$5,0)))) -> #REF! | I18: =IF($C18=$D$2,#REF!*I$2,IF($C18=$D$3,#REF!*I$3,IF($C18=$D$4,#REF!*I$4,IF($C18=$D$5,#REF!*I$5,0)))) -> #REF! | J18: =IF($C18=$D$2,#REF!*J$2,IF($C18=$D$3,#REF!*J$3,IF($C18=$D$4,#REF!*J$4,IF($C18=$D$5,#REF!*J$5,0)))) -> #REF! | K18: =IF($C18=$D$2,#REF!*K$2,IF($C18=$D$3,#REF!*K$3,IF($C18=$D$4,#REF!*K$4,IF($C18=$D$5,#REF!*K$5,0)))) -> #REF! | L18: =IF($C18=$D$2,#REF!*L$2,IF($C18=$D$3,#REF!*L$3,IF($C18=$D$4,#REF!*L$4,IF($C18=$D$5,#REF!*L$5,0)))) -> #REF! | ... AM18: =IF($C18=$D$2,#REF!*AM$2,IF($C18=$D$3,#REF!*AM$3,IF($C18=$D$4,#REF!*AM$4,IF($C18=$D$5,#REF!*AM$5,0)))) -> #REF!
A19: =IFERROR(__xludf.DUMMYFUNCTION("""COMPUTED_VALUE"""),"Luis Javier Jaramillo Vera") -> Luis Javier Jaramillo Vera | B19: =IFERROR(__xludf.DUMMYFUNCTION("""COMPUTED_VALUE"""),"HAJ0694") -> HAJ0694 | C19: =IFERROR(__xludf.DUMMYFUNCTION("""COMPUTED_VALUE"""),5) -> 5 | D19: =SUM(E19:AM19) -> #REF! | E19: =IF($C19=$D$2,#REF!*E$2,IF($C19=$D$3,#REF!*E$3,IF($C19=$D$4,#REF!*E$4,IF($C19=$D$5,#REF!*E$5,0)))) -> #REF! | F19: =IF($C19=$D$2,#REF!*F$2,IF($C19=$D$3,#REF!*F$3,IF($C19=$D$4,#REF!*F$4,IF($C19=$D$5,#REF!*F$5,0)))) -> #REF! | G19: =IF($C19=$D$2,#REF!*G$2,IF($C19=$D$3,#REF!*G$3,IF($C19=$D$4,#REF!*G$4,IF($C19=$D$5,#REF!*G$5,0)))) -> #REF! | H19: =IF($C19=$D$2,#REF!*H$2,IF($C19=$D$3,#REF!*H$3,IF($C19=$D$4,#REF!*H$4,IF($C19=$D$5,#REF!*H$5,0)))) -> #REF! | I19: =IF($C19=$D$2,#REF!*I$2,IF($C19=$D$3,#REF!*I$3,IF($C19=$D$4,#REF!*I$4,IF($C19=$D$5,#REF!*I$5,0)))) -> #REF! | J19: =IF($C19=$D$2,#REF!*J$2,IF($C19=$D$3,#REF!*J$3,IF($C19=$D$4,#REF!*J$4,IF($C19=$D$5,#REF!*J$5,0)))) -> #REF! | K19: =IF($C19=$D$2,#REF!*K$2,IF($C19=$D$3,#REF!*K$3,IF($C19=$D$4,#REF!*K$4,IF($C19=$D$5,#REF!*K$5,0)))) -> #REF! | L19: =IF($C19=$D$2,#REF!*L$2,IF($C19=$D$3,#REF!*L$3,IF($C19=$D$4,#REF!*L$4,IF($C19=$D$5,#REF!*L$5,0)))) -> #REF! | ... AM19: =IF($C19=$D$2,#REF!*AM$2,IF($C19=$D$3,#REF!*AM$3,IF($C19=$D$4,#REF!*AM$4,IF($C19=$D$5,#REF!*AM$5,0)))) -> #REF!
A20: =IFERROR(__xludf.DUMMYFUNCTION("""COMPUTED_VALUE"""),"Gabriel Rolando Muentes Cornejo") -> Gabriel Rolando Muentes Cornejo | B20: =IFERROR(__xludf.DUMMYFUNCTION("""COMPUTED_VALUE"""),"BAC0784") -> BAC0784 | C20: =IFERROR(__xludf.DUMMYFUNCTION("""COMPUTED_VALUE"""),5) -> 5 | D20: =SUM(E20:AM20) -> #REF! | E20: =IF($C20=$D$2,#REF!*E$2,IF($C20=$D$3,#REF!*E$3,IF($C20=$D$4,#REF!*E$4,IF($C20=$D$5,#REF!*E$5,0)))) -> #REF! | F20: =IF($C20=$D$2,#REF!*F$2,IF($C20=$D$3,#REF!*F$3,IF($C20=$D$4,#REF!*F$4,IF($C20=$D$5,#REF!*F$5,0)))) -> #REF! | G20: =IF($C20=$D$2,#REF!*G$2,IF($C20=$D$3,#REF!*G$3,IF($C20=$D$4,#REF!*G$4,IF($C20=$D$5,#REF!*G$5,0)))) -> #REF! | H20: =IF($C20=$D$2,#REF!*H$2,IF($C20=$D$3,#REF!*H$3,IF($C20=$D$4,#REF!*H$4,IF($C20=$D$5,#REF!*H$5,0)))) -> #REF! | I20: =IF($C20=$D$2,#REF!*I$2,IF($C20=$D$3,#REF!*I$3,IF($C20=$D$4,#REF!*I$4,IF($C20=$D$5,#REF!*I$5,0)))) -> #REF! | J20: =IF($C20=$D$2,#REF!*J$2,IF($C20=$D$3,#REF!*J$3,IF($C20=$D$4,#REF!*J$4,IF($C20=$D$5,#REF!*J$5,0)))) -> #REF! | K20: =IF($C20=$D$2,#REF!*K$2,IF($C20=$D$3,#REF!*K$3,IF($C20=$D$4,#REF!*K$4,IF($C20=$D$5,#REF!*K$5,0)))) -> #REF! | L20: =IF($C20=$D$2,#REF!*L$2,IF($C20=$D$3,#REF!*L$3,IF($C20=$D$4,#REF!*L$4,IF($C20=$D$5,#REF!*L$5,0)))) -> #REF! | ... AM20: =IF($C20=$D$2,#REF!*AM$2,IF($C20=$D$3,#REF!*AM$3,IF($C20=$D$4,#REF!*AM$4,IF($C20=$D$5,#REF!*AM$5,0)))) -> #REF!
A21: =IFERROR(__xludf.DUMMYFUNCTION("""COMPUTED_VALUE"""),"Nexar Celestino Vargas Intrigo") -> Nexar Celestino Vargas Intrigo | B21: =IFERROR(__xludf.DUMMYFUNCTION("""COMPUTED_VALUE"""),"MAA4517") -> MAA4517 | C21: =IFERROR(__xludf.DUMMYFUNCTION("""COMPUTED_VALUE"""),5) -> 5 | D21: =SUM(E21:AM21) -> #REF! | E21: =IF($C21=$D$2,#REF!*E$2,IF($C21=$D$3,#REF!*E$3,IF($C21=$D$4,#REF!*E$4,IF($C21=$D$5,#REF!*E$5,0)))) -> #REF! | F21: =IF($C21=$D$2,#REF!*F$2,IF($C21=$D$3,#REF!*F$3,IF($C21=$D$4,#REF!*F$4,IF($C21=$D$5,#REF!*F$5,0)))) -> #REF! | G21: =IF($C21=$D$2,#REF!*G$2,IF($C21=$D$3,#REF!*G$3,IF($C21=$D$4,#REF!*G$4,IF($C21=$D$5,#REF!*G$5,0)))) -> #REF! | H21: =IF($C21=$D$2,#REF!*H$2,IF($C21=$D$3,#REF!*H$3,IF($C21=$D$4,#REF!*H$4,IF($C21=$D$5,#REF!*H$5,0)))) -> #REF! | I21: =IF($C21=$D$2,#REF!*I$2,IF($C21=$D$3,#REF!*I$3,IF($C21=$D$4,#REF!*I$4,IF($C21=$D$5,#REF!*I$5,0)))) -> #REF! | J21: =IF($C21=$D$2,#REF!*J$2,IF($C21=$D$3,#REF!*J$3,IF($C21=$D$4,#REF!*J$4,IF($C21=$D$5,#REF!*J$5,0)))) -> #REF! | K21: =IF($C21=$D$2,#REF!*K$2,IF($C21=$D$3,#REF!*K$3,IF($C21=$D$4,#REF!*K$4,IF($C21=$D$5,#REF!*K$5,0)))) -> #REF! | L21: =IF($C21=$D$2,#REF!*L$2,IF($C21=$D$3,#REF!*L$3,IF($C21=$D$4,#REF!*L$4,IF($C21=$D$5,#REF!*L$5,0)))) -> #REF! | ... AM21: =IF($C21=$D$2,#REF!*AM$2,IF($C21=$D$3,#REF!*AM$3,IF($C21=$D$4,#REF!*AM$4,IF($C21=$D$5,#REF!*AM$5,0)))) -> #REF!
A22: =IFERROR(__xludf.DUMMYFUNCTION("""COMPUTED_VALUE"""),"Edison Gabriel Aules Sanchez") -> Edison Gabriel Aules Sanchez | B22: =IFERROR(__xludf.DUMMYFUNCTION("""COMPUTED_VALUE"""),"ABB2285") -> ABB2285 | C22: =IFERROR(__xludf.DUMMYFUNCTION("""COMPUTED_VALUE"""),5) -> 5 | D22: =SUM(E22:AM22) -> #REF! | E22: =IF($C22=$D$2,#REF!*E$2,IF($C22=$D$3,#REF!*E$3,IF($C22=$D$4,#REF!*E$4,IF($C22=$D$5,#REF!*E$5,0)))) -> #REF! | F22: =IF($C22=$D$2,#REF!*F$2,IF($C22=$D$3,#REF!*F$3,IF($C22=$D$4,#REF!*F$4,IF($C22=$D$5,#REF!*F$5,0)))) -> #REF! | G22: =IF($C22=$D$2,#REF!*G$2,IF($C22=$D$3,#REF!*G$3,IF($C22=$D$4,#REF!*G$4,IF($C22=$D$5,#REF!*G$5,0)))) -> #REF! | H22: =IF($C22=$D$2,#REF!*H$2,IF($C22=$D$3,#REF!*H$3,IF($C22=$D$4,#REF!*H$4,IF($C22=$D$5,#REF!*H$5,0)))) -> #REF! | I22: =IF($C22=$D$2,#REF!*I$2,IF($C22=$D$3,#REF!*I$3,IF($C22=$D$4,#REF!*I$4,IF($C22=$D$5,#REF!*I$5,0)))) -> #REF! | J22: =IF($C22=$D$2,#REF!*J$2,IF($C22=$D$3,#REF!*J$3,IF($C22=$D$4,#REF!*J$4,IF($C22=$D$5,#REF!*J$5,0)))) -> #REF! | K22: =IF($C22=$D$2,#REF!*K$2,IF($C22=$D$3,#REF!*K$3,IF($C22=$D$4,#REF!*K$4,IF($C22=$D$5,#REF!*K$5,0)))) -> #REF! | L22: =IF($C22=$D$2,#REF!*L$2,IF($C22=$D$3,#REF!*L$3,IF($C22=$D$4,#REF!*L$4,IF($C22=$D$5,#REF!*L$5,0)))) -> #REF! | ... AM22: =IF($C22=$D$2,#REF!*AM$2,IF($C22=$D$3,#REF!*AM$3,IF($C22=$D$4,#REF!*AM$4,IF($C22=$D$5,#REF!*AM$5,0)))) -> #REF!
A23: =IFERROR(__xludf.DUMMYFUNCTION("""COMPUTED_VALUE"""),"Byron Gregorio Garcia Tumbaco") -> Byron Gregorio Garcia Tumbaco | B23: =IFERROR(__xludf.DUMMYFUNCTION("""COMPUTED_VALUE"""),"XBA6758") -> XBA6758 | C23: =IFERROR(__xludf.DUMMYFUNCTION("""COMPUTED_VALUE"""),5) -> 5 | D23: =SUM(E23:AM23) -> #REF! | E23: =IF($C23=$D$2,#REF!*E$2,IF($C23=$D$3,#REF!*E$3,IF($C23=$D$4,#REF!*E$4,IF($C23=$D$5,#REF!*E$5,0)))) -> #REF! | F23: =IF($C23=$D$2,#REF!*F$2,IF($C23=$D$3,#REF!*F$3,IF($C23=$D$4,#REF!*F$4,IF($C23=$D$5,#REF!*F$5,0)))) -> #REF! | G23: =IF($C23=$D$2,#REF!*G$2,IF($C23=$D$3,#REF!*G$3,IF($C23=$D$4,#REF!*G$4,IF($C23=$D$5,#REF!*G$5,0)))) -> #REF! | H23: =IF($C23=$D$2,#REF!*H$2,IF($C23=$D$3,#REF!*H$3,IF($C23=$D$4,#REF!*H$4,IF($C23=$D$5,#REF!*H$5,0)))) -> #REF! | I23: =IF($C23=$D$2,#REF!*I$2,IF($C23=$D$3,#REF!*I$3,IF($C23=$D$4,#REF!*I$4,IF($C23=$D$5,#REF!*I$5,0)))) -> #REF! | J23: =IF($C23=$D$2,#REF!*J$2,IF($C23=$D$3,#REF!*J$3,IF($C23=$D$4,#REF!*J$4,IF($C23=$D$5,#REF!*J$5,0)))) -> #REF! | K23: =IF($C23=$D$2,#REF!*K$2,IF($C23=$D$3,#REF!*K$3,IF($C23=$D$4,#REF!*K$4,IF($C23=$D$5,#REF!*K$5,0)))) -> #REF! | L23: =IF($C23=$D$2,#REF!*L$2,IF($C23=$D$3,#REF!*L$3,IF($C23=$D$4,#REF!*L$4,IF($C23=$D$5,#REF!*L$5,0)))) -> #REF! | ... AM23: =IF($C23=$D$2,#REF!*AM$2,IF($C23=$D$3,#REF!*AM$3,IF($C23=$D$4,#REF!*AM$4,IF($C23=$D$5,#REF!*AM$5,0)))) -> #REF!
A24: =IFERROR(__xludf.DUMMYFUNCTION("""COMPUTED_VALUE"""),"Byron Gregorio Garcia Tumbaco") -> Byron Gregorio Garcia Tumbaco | B24: =IFERROR(__xludf.DUMMYFUNCTION("""COMPUTED_VALUE"""),"QAA1814") -> QAA1814 | C24: =IFERROR(__xludf.DUMMYFUNCTION("""COMPUTED_VALUE"""),6) -> 6 | D24: =SUM(E24:AM24) -> #REF! | E24: =IF($C24=$D$2,#REF!*E$2,IF($C24=$D$3,#REF!*E$3,IF($C24=$D$4,#REF!*E$4,IF($C24=$D$5,#REF!*E$5,0)))) -> #REF! | F24: =IF($C24=$D$2,#REF!*F$2,IF($C24=$D$3,#REF!*F$3,IF($C24=$D$4,#REF!*F$4,IF($C24=$D$5,#REF!*F$5,0)))) -> #REF! | G24: =IF($C24=$D$2,#REF!*G$2,IF($C24=$D$3,#REF!*G$3,IF($C24=$D$4,#REF!*G$4,IF($C24=$D$5,#REF!*G$5,0)))) -> #REF! | H24: =IF($C24=$D$2,#REF!*H$2,IF($C24=$D$3,#REF!*H$3,IF($C24=$D$4,#REF!*H$4,IF($C24=$D$5,#REF!*H$5,0)))) -> #REF! | I24: =IF($C24=$D$2,#REF!*I$2,IF($C24=$D$3,#REF!*I$3,IF($C24=$D$4,#REF!*I$4,IF($C24=$D$5,#REF!*I$5,0)))) -> #REF! | J24: =IF($C24=$D$2,#REF!*J$2,IF($C24=$D$3,#REF!*J$3,IF($C24=$D$4,#REF!*J$4,IF($C24=$D$5,#REF!*J$5,0)))) -> #REF! | K24: =IF($C24=$D$2,#REF!*K$2,IF($C24=$D$3,#REF!*K$3,IF($C24=$D$4,#REF!*K$4,IF($C24=$D$5,#REF!*K$5,0)))) -> #REF! | L24: =IF($C24=$D$2,#REF!*L$2,IF($C24=$D$3,#REF!*L$3,IF($C24=$D$4,#REF!*L$4,IF($C24=$D$5,#REF!*L$5,0)))) -> #REF! | ... AM24: =IF($C24=$D$2,#REF!*AM$2,IF($C24=$D$3,#REF!*AM$3,IF($C24=$D$4,#REF!*AM$4,IF($C24=$D$5,#REF!*AM$5,0)))) -> #REF!
A25: =IFERROR(__xludf.DUMMYFUNCTION("""COMPUTED_VALUE"""),"Miguel Angel Quishpe Gordon") -> Miguel Angel Quishpe Gordon | B25: =IFERROR(__xludf.DUMMYFUNCTION("""COMPUTED_VALUE"""),"PYP0743") -> PYP0743 | C25: =IFERROR(__xludf.DUMMYFUNCTION("""COMPUTED_VALUE"""),5) -> 5 | D25: =SUM(E25:AM25) -> #REF! | E25: =IF($C25=$D$2,#REF!*E$2,IF($C25=$D$3,#REF!*E$3,IF($C25=$D$4,#REF!*E$4,IF($C25=$D$5,#REF!*E$5,0)))) -> #REF! | F25: =IF($C25=$D$2,#REF!*F$2,IF($C25=$D$3,#REF!*F$3,IF($C25=$D$4,#REF!*F$4,IF($C25=$D$5,#REF!*F$5,0)))) -> #REF! | G25: =IF($C25=$D$2,#REF!*G$2,IF($C25=$D$3,#REF!*G$3,IF($C25=$D$4,#REF!*G$4,IF($C25=$D$5,#REF!*G$5,0)))) -> #REF! | H25: =IF($C25=$D$2,#REF!*H$2,IF($C25=$D$3,#REF!*H$3,IF($C25=$D$4,#REF!*H$4,IF($C25=$D$5,#REF!*H$5,0)))) -> #REF! | I25: =IF($C25=$D$2,#REF!*I$2,IF($C25=$D$3,#REF!*I$3,IF($C25=$D$4,#REF!*I$4,IF($C25=$D$5,#REF!*I$5,0)))) -> #REF! | J25: =IF($C25=$D$2,#REF!*J$2,IF($C25=$D$3,#REF!*J$3,IF($C25=$D$4,#REF!*J$4,IF($C25=$D$5,#REF!*J$5,0)))) -> #REF! | K25: =IF($C25=$D$2,#REF!*K$2,IF($C25=$D$3,#REF!*K$3,IF($C25=$D$4,#REF!*K$4,IF($C25=$D$5,#REF!*K$5,0)))) -> #REF! | L25: =IF($C25=$D$2,#REF!*L$2,IF($C25=$D$3,#REF!*L$3,IF($C25=$D$4,#REF!*L$4,IF($C25=$D$5,#REF!*L$5,0)))) -> #REF! | ... AM25: =IF($C25=$D$2,#REF!*AM$2,IF($C25=$D$3,#REF!*AM$3,IF($C25=$D$4,#REF!*AM$4,IF($C25=$D$5,#REF!*AM$5,0)))) -> #REF!
A26: =IFERROR(__xludf.DUMMYFUNCTION("""COMPUTED_VALUE"""),"Miguel Angel Quishpe Gordon") -> Miguel Angel Quishpe Gordon | B26: =IFERROR(__xludf.DUMMYFUNCTION("""COMPUTED_VALUE"""),"IAE0151") -> IAE0151 | C26: =IFERROR(__xludf.DUMMYFUNCTION("""COMPUTED_VALUE"""),6) -> 6 | D26: =SUM(E26:AM26) -> #REF! | E26: =IF($C26=$D$2,#REF!*E$2,IF($C26=$D$3,#REF!*E$3,IF($C26=$D$4,#REF!*E$4,IF($C26=$D$5,#REF!*E$5,0)))) -> #REF! | F26: =IF($C26=$D$2,#REF!*F$2,IF($C26=$D$3,#REF!*F$3,IF($C26=$D$4,#REF!*F$4,IF($C26=$D$5,#REF!*F$5,0)))) -> #REF! | G26: =IF($C26=$D$2,#REF!*G$2,IF($C26=$D$3,#REF!*G$3,IF($C26=$D$4,#REF!*G$4,IF($C26=$D$5,#REF!*G$5,0)))) -> #REF! | H26: =IF($C26=$D$2,#REF!*H$2,IF($C26=$D$3,#REF!*H$3,IF($C26=$D$4,#REF!*H$4,IF($C26=$D$5,#REF!*H$5,0)))) -> #REF! | I26: =IF($C26=$D$2,#REF!*I$2,IF($C26=$D$3,#REF!*I$3,IF($C26=$D$4,#REF!*I$4,IF($C26=$D$5,#REF!*I$5,0)))) -> #REF! | J26: =IF($C26=$D$2,#REF!*J$2,IF($C26=$D$3,#REF!*J$3,IF($C26=$D$4,#REF!*J$4,IF($C26=$D$5,#REF!*J$5,0)))) -> #REF! | K26: =IF($C26=$D$2,#REF!*K$2,IF($C26=$D$3,#REF!*K$3,IF($C26=$D$4,#REF!*K$4,IF($C26=$D$5,#REF!*K$5,0)))) -> #REF! | L26: =IF($C26=$D$2,#REF!*L$2,IF($C26=$D$3,#REF!*L$3,IF($C26=$D$4,#REF!*L$4,IF($C26=$D$5,#REF!*L$5,0)))) -> #REF! | ... AM26: =IF($C26=$D$2,#REF!*AM$2,IF($C26=$D$3,#REF!*AM$3,IF($C26=$D$4,#REF!*AM$4,IF($C26=$D$5,#REF!*AM$5,0)))) -> #REF!
A27: =IFERROR(__xludf.DUMMYFUNCTION("""COMPUTED_VALUE"""),"Cesar Luis Muentes Cornejo") -> Cesar Luis Muentes Cornejo | B27: =IFERROR(__xludf.DUMMYFUNCTION("""COMPUTED_VALUE"""),"OAH0651") -> OAH0651 | C27: =IFERROR(__xludf.DUMMYFUNCTION("""COMPUTED_VALUE"""),5) -> 5 | D27: =SUM(E27:AM27) -> #REF! | E27: =IF($C27=$D$2,#REF!*E$2,IF($C27=$D$3,#REF!*E$3,IF($C27=$D$4,#REF!*E$4,IF($C27=$D$5,#REF!*E$5,0)))) -> #REF! | F27: =IF($C27=$D$2,#REF!*F$2,IF($C27=$D$3,#REF!*F$3,IF($C27=$D$4,#REF!*F$4,IF($C27=$D$5,#REF!*F$5,0)))) -> #REF! | G27: =IF($C27=$D$2,#REF!*G$2,IF($C27=$D$3,#REF!*G$3,IF($C27=$D$4,#REF!*G$4,IF($C27=$D$5,#REF!*G$5,0)))) -> #REF! | H27: =IF($C27=$D$2,#REF!*H$2,IF($C27=$D$3,#REF!*H$3,IF($C27=$D$4,#REF!*H$4,IF($C27=$D$5,#REF!*H$5,0)))) -> #REF! | I27: =IF($C27=$D$2,#REF!*I$2,IF($C27=$D$3,#REF!*I$3,IF($C27=$D$4,#REF!*I$4,IF($C27=$D$5,#REF!*I$5,0)))) -> #REF! | J27: =IF($C27=$D$2,#REF!*J$2,IF($C27=$D$3,#REF!*J$3,IF($C27=$D$4,#REF!*J$4,IF($C27=$D$5,#REF!*J$5,0)))) -> #REF! | K27: =IF($C27=$D$2,#REF!*K$2,IF($C27=$D$3,#REF!*K$3,IF($C27=$D$4,#REF!*K$4,IF($C27=$D$5,#REF!*K$5,0)))) -> #REF! | L27: =IF($C27=$D$2,#REF!*L$2,IF($C27=$D$3,#REF!*L$3,IF($C27=$D$4,#REF!*L$4,IF($C27=$D$5,#REF!*L$5,0)))) -> #REF! | ... AM27: =IF($C27=$D$2,#REF!*AM$2,IF($C27=$D$3,#REF!*AM$3,IF($C27=$D$4,#REF!*AM$4,IF($C27=$D$5,#REF!*AM$5,0)))) -> #REF!
A28: =IFERROR(__xludf.DUMMYFUNCTION("""COMPUTED_VALUE"""),"Luis Gonzaga Muentes Napa") -> Luis Gonzaga Muentes Napa | B28: =IFERROR(__xludf.DUMMYFUNCTION("""COMPUTED_VALUE"""),"XBE0343") -> XBE0343 | C28: =IFERROR(__xludf.DUMMYFUNCTION("""COMPUTED_VALUE"""),5) -> 5 | D28: =SUM(E28:AM28) -> #REF! | E28: =IF($C28=$D$2,#REF!*E$2,IF($C28=$D$3,#REF!*E$3,IF($C28=$D$4,#REF!*E$4,IF($C28=$D$5,#REF!*E$5,0)))) -> #REF! | F28: =IF($C28=$D$2,#REF!*F$2,IF($C28=$D$3,#REF!*F$3,IF($C28=$D$4,#REF!*F$4,IF($C28=$D$5,#REF!*F$5,0)))) -> #REF! | G28: =IF($C28=$D$2,#REF!*G$2,IF($C28=$D$3,#REF!*G$3,IF($C28=$D$4,#REF!*G$4,IF($C28=$D$5,#REF!*G$5,0)))) -> #REF! | H28: =IF($C28=$D$2,#REF!*H$2,IF($C28=$D$3,#REF!*H$3,IF($C28=$D$4,#REF!*H$4,IF($C28=$D$5,#REF!*H$5,0)))) -> #REF! | I28: =IF($C28=$D$2,#REF!*I$2,IF($C28=$D$3,#REF!*I$3,IF($C28=$D$4,#REF!*I$4,IF($C28=$D$5,#REF!*I$5,0)))) -> #REF! | J28: =IF($C28=$D$2,#REF!*J$2,IF($C28=$D$3,#REF!*J$3,IF($C28=$D$4,#REF!*J$4,IF($C28=$D$5,#REF!*J$5,0)))) -> #REF! | K28: =IF($C28=$D$2,#REF!*K$2,IF($C28=$D$3,#REF!*K$3,IF($C28=$D$4,#REF!*K$4,IF($C28=$D$5,#REF!*K$5,0)))) -> #REF! | L28: =IF($C28=$D$2,#REF!*L$2,IF($C28=$D$3,#REF!*L$3,IF($C28=$D$4,#REF!*L$4,IF($C28=$D$5,#REF!*L$5,0)))) -> #REF! | ... AM28: =IF($C28=$D$2,#REF!*AM$2,IF($C28=$D$3,#REF!*AM$3,IF($C28=$D$4,#REF!*AM$4,IF($C28=$D$5,#REF!*AM$5,0)))) -> #REF!
A29: =IFERROR(__xludf.DUMMYFUNCTION("""COMPUTED_VALUE"""),"Luis Gonzaga Muentes Napa") -> Luis Gonzaga Muentes Napa | B29: =IFERROR(__xludf.DUMMYFUNCTION("""COMPUTED_VALUE"""),"BAC0784") -> BAC0784 | C29: =IFERROR(__xludf.DUMMYFUNCTION("""COMPUTED_VALUE"""),5) -> 5 | D29: =SUM(E29:AM29) -> #REF! | E29: =IF($C29=$D$2,#REF!*E$2,IF($C29=$D$3,#REF!*E$3,IF($C29=$D$4,#REF!*E$4,IF($C29=$D$5,#REF!*E$5,0)))) -> #REF! | F29: =IF($C29=$D$2,#REF!*F$2,IF($C29=$D$3,#REF!*F$3,IF($C29=$D$4,#REF!*F$4,IF($C29=$D$5,#REF!*F$5,0)))) -> #REF! | G29: =IF($C29=$D$2,#REF!*G$2,IF($C29=$D$3,#REF!*G$3,IF($C29=$D$4,#REF!*G$4,IF($C29=$D$5,#REF!*G$5,0)))) -> #REF! | H29: =IF($C29=$D$2,#REF!*H$2,IF($C29=$D$3,#REF!*H$3,IF($C29=$D$4,#REF!*H$4,IF($C29=$D$5,#REF!*H$5,0)))) -> #REF! | I29: =IF($C29=$D$2,#REF!*I$2,IF($C29=$D$3,#REF!*I$3,IF($C29=$D$4,#REF!*I$4,IF($C29=$D$5,#REF!*I$5,0)))) -> #REF! | J29: =IF($C29=$D$2,#REF!*J$2,IF($C29=$D$3,#REF!*J$3,IF($C29=$D$4,#REF!*J$4,IF($C29=$D$5,#REF!*J$5,0)))) -> #REF! | K29: =IF($C29=$D$2,#REF!*K$2,IF($C29=$D$3,#REF!*K$3,IF($C29=$D$4,#REF!*K$4,IF($C29=$D$5,#REF!*K$5,0)))) -> #REF! | L29: =IF($C29=$D$2,#REF!*L$2,IF($C29=$D$3,#REF!*L$3,IF($C29=$D$4,#REF!*L$4,IF($C29=$D$5,#REF!*L$5,0)))) -> #REF! | ... AM29: =IF($C29=$D$2,#REF!*AM$2,IF($C29=$D$3,#REF!*AM$3,IF($C29=$D$4,#REF!*AM$4,IF($C29=$D$5,#REF!*AM$5,0)))) -> #REF!
A30: =IFERROR(__xludf.DUMMYFUNCTION("""COMPUTED_VALUE"""),"Walter Ivan Cadena Saldariega") -> Walter Ivan Cadena Saldariega | B30: =IFERROR(__xludf.DUMMYFUNCTION("""COMPUTED_VALUE"""),"NBF0031") -> NBF0031 | C30: =IFERROR(__xludf.DUMMYFUNCTION("""COMPUTED_VALUE"""),5) -> 5 | D30: =SUM(E30:AM30) -> #REF! | E30: =IF($C30=$D$2,#REF!*E$2,IF($C30=$D$3,#REF!*E$3,IF($C30=$D$4,#REF!*E$4,IF($C30=$D$5,#REF!*E$5,0)))) -> #REF! | F30: =IF($C30=$D$2,#REF!*F$2,IF($C30=$D$3,#REF!*F$3,IF($C30=$D$4,#REF!*F$4,IF($C30=$D$5,#REF!*F$5,0)))) -> #REF! | G30: =IF($C30=$D$2,#REF!*G$2,IF($C30=$D$3,#REF!*G$3,IF($C30=$D$4,#REF!*G$4,IF($C30=$D$5,#REF!*G$5,0)))) -> #REF! | H30: =IF($C30=$D$2,#REF!*H$2,IF($C30=$D$3,#REF!*H$3,IF($C30=$D$4,#REF!*H$4,IF($C30=$D$5,#REF!*H$5,0)))) -> #REF! | I30: =IF($C30=$D$2,#REF!*I$2,IF($C30=$D$3,#REF!*I$3,IF($C30=$D$4,#REF!*I$4,IF($C30=$D$5,#REF!*I$5,0)))) -> #REF! | J30: =IF($C30=$D$2,#REF!*J$2,IF($C30=$D$3,#REF!*J$3,IF($C30=$D$4,#REF!*J$4,IF($C30=$D$5,#REF!*J$5,0)))) -> #REF! | K30: =IF($C30=$D$2,#REF!*K$2,IF($C30=$D$3,#REF!*K$3,IF($C30=$D$4,#REF!*K$4,IF($C30=$D$5,#REF!*K$5,0)))) -> #REF! | L30: =IF($C30=$D$2,#REF!*L$2,IF($C30=$D$3,#REF!*L$3,IF($C30=$D$4,#REF!*L$4,IF($C30=$D$5,#REF!*L$5,0)))) -> #REF! | ... AM30: =IF($C30=$D$2,#REF!*AM$2,IF($C30=$D$3,#REF!*AM$3,IF($C30=$D$4,#REF!*AM$4,IF($C30=$D$5,#REF!*AM$5,0)))) -> #REF!
A31: =IFERROR(__xludf.DUMMYFUNCTION("""COMPUTED_VALUE"""),"Cristhian Raul Bravo Zambrano") -> Cristhian Raul Bravo Zambrano | B31: =IFERROR(__xludf.DUMMYFUNCTION("""COMPUTED_VALUE"""),"EBF166") -> EBF166 | C31: =IFERROR(__xludf.DUMMYFUNCTION("""COMPUTED_VALUE"""),5) -> 5 | D31: =SUM(E31:AM31) -> #REF! | E31: =IF($C31=$D$2,#REF!*E$2,IF($C31=$D$3,#REF!*E$3,IF($C31=$D$4,#REF!*E$4,IF($C31=$D$5,#REF!*E$5,0)))) -> #REF! | F31: =IF($C31=$D$2,#REF!*F$2,IF($C31=$D$3,#REF!*F$3,IF($C31=$D$4,#REF!*F$4,IF($C31=$D$5,#REF!*F$5,0)))) -> #REF! | G31: =IF($C31=$D$2,#REF!*G$2,IF($C31=$D$3,#REF!*G$3,IF($C31=$D$4,#REF!*G$4,IF($C31=$D$5,#REF!*G$5,0)))) -> #REF! | H31: =IF($C31=$D$2,#REF!*H$2,IF($C31=$D$3,#REF!*H$3,IF($C31=$D$4,#REF!*H$4,IF($C31=$D$5,#REF!*H$5,0)))) -> #REF! | I31: =IF($C31=$D$2,#REF!*I$2,IF($C31=$D$3,#REF!*I$3,IF($C31=$D$4,#REF!*I$4,IF($C31=$D$5,#REF!*I$5,0)))) -> #REF! | J31: =IF($C31=$D$2,#REF!*J$2,IF($C31=$D$3,#REF!*J$3,IF($C31=$D$4,#REF!*J$4,IF($C31=$D$5,#REF!*J$5,0)))) -> #REF! | K31: =IF($C31=$D$2,#REF!*K$2,IF($C31=$D$3,#REF!*K$3,IF($C31=$D$4,#REF!*K$4,IF($C31=$D$5,#REF!*K$5,0)))) -> #REF! | L31: =IF($C31=$D$2,#REF!*L$2,IF($C31=$D$3,#REF!*L$3,IF($C31=$D$4,#REF!*L$4,IF($C31=$D$5,#REF!*L$5,0)))) -> #REF! | ... AM31: =IF($C31=$D$2,#REF!*AM$2,IF($C31=$D$3,#REF!*AM$3,IF($C31=$D$4,#REF!*AM$4,IF($C31=$D$5,#REF!*AM$5,0)))) -> #REF!
A32: =IFERROR(__xludf.DUMMYFUNCTION("""COMPUTED_VALUE"""),"Freddy Alexamder Morales Zambrano") -> Freddy Alexamder Morales Zambrano | B32: =IFERROR(__xludf.DUMMYFUNCTION("""COMPUTED_VALUE"""),"PZS0487") -> PZS0487 | C32: =IFERROR(__xludf.DUMMYFUNCTION("""COMPUTED_VALUE"""),5) -> 5 | D32: =SUM(E32:AM32) -> #REF! | E32: =IF($C32=$D$2,#REF!*E$2,IF($C32=$D$3,#REF!*E$3,IF($C32=$D$4,#REF!*E$4,IF($C32=$D$5,#REF!*E$5,0)))) -> #REF! | F32: =IF($C32=$D$2,#REF!*F$2,IF($C32=$D$3,#REF!*F$3,IF($C32=$D$4,#REF!*F$4,IF($C32=$D$5,#REF!*F$5,0)))) -> #REF! | G32: =IF($C32=$D$2,#REF!*G$2,IF($C32=$D$3,#REF!*G$3,IF($C32=$D$4,#REF!*G$4,IF($C32=$D$5,#REF!*G$5,0)))) -> #REF! | H32: =IF($C32=$D$2,#REF!*H$2,IF($C32=$D$3,#REF!*H$3,IF($C32=$D$4,#REF!*H$4,IF($C32=$D$5,#REF!*H$5,0)))) -> #REF! | I32: =IF($C32=$D$2,#REF!*I$2,IF($C32=$D$3,#REF!*I$3,IF($C32=$D$4,#REF!*I$4,IF($C32=$D$5,#REF!*I$5,0)))) -> #REF! | J32: =IF($C32=$D$2,#REF!*J$2,IF($C32=$D$3,#REF!*J$3,IF($C32=$D$4,#REF!*J$4,IF($C32=$D$5,#REF!*J$5,0)))) -> #REF! | K32: =IF($C32=$D$2,#REF!*K$2,IF($C32=$D$3,#REF!*K$3,IF($C32=$D$4,#REF!*K$4,IF($C32=$D$5,#REF!*K$5,0)))) -> #REF! | L32: =IF($C32=$D$2,#REF!*L$2,IF($C32=$D$3,#REF!*L$3,IF($C32=$D$4,#REF!*L$4,IF($C32=$D$5,#REF!*L$5,0)))) -> #REF! | ... AM32: =IF($C32=$D$2,#REF!*AM$2,IF($C32=$D$3,#REF!*AM$3,IF($C32=$D$4,#REF!*AM$4,IF($C32=$D$5,#REF!*AM$5,0)))) -> #REF!
A33: =IFERROR(__xludf.DUMMYFUNCTION("""COMPUTED_VALUE"""),"Raul Neptali Velez Velez (Darwin Tigre)") -> Raul Neptali Velez Velez (Darwin Tigre) | B33: =IFERROR(__xludf.DUMMYFUNCTION("""COMPUTED_VALUE"""),"TBA7675") -> TBA7675 | C33: =IFERROR(__xludf.DUMMYFUNCTION("""COMPUTED_VALUE"""),5) -> 5 | D33: =SUM(E33:AM33) -> #REF! | E33: =IF($C33=$D$2,#REF!*E$2,IF($C33=$D$3,#REF!*E$3,IF($C33=$D$4,#REF!*E$4,IF($C33=$D$5,#REF!*E$5,0)))) -> #REF! | F33: =IF($C33=$D$2,#REF!*F$2,IF($C33=$D$3,#REF!*F$3,IF($C33=$D$4,#REF!*F$4,IF($C33=$D$5,#REF!*F$5,0)))) -> #REF! | G33: =IF($C33=$D$2,#REF!*G$2,IF($C33=$D$3,#REF!*G$3,IF($C33=$D$4,#REF!*G$4,IF($C33=$D$5,#REF!*G$5,0)))) -> #REF! | H33: =IF($C33=$D$2,#REF!*H$2,IF($C33=$D$3,#REF!*H$3,IF($C33=$D$4,#REF!*H$4,IF($C33=$D$5,#REF!*H$5,0)))) -> #REF! | I33: =IF($C33=$D$2,#REF!*I$2,IF($C33=$D$3,#REF!*I$3,IF($C33=$D$4,#REF!*I$4,IF($C33=$D$5,#REF!*I$5,0)))) -> #REF! | J33: =IF($C33=$D$2,#REF!*J$2,IF($C33=$D$3,#REF!*J$3,IF($C33=$D$4,#REF!*J$4,IF($C33=$D$5,#REF!*J$5,0)))) -> #REF! | K33: =IF($C33=$D$2,#REF!*K$2,IF($C33=$D$3,#REF!*K$3,IF($C33=$D$4,#REF!*K$4,IF($C33=$D$5,#REF!*K$5,0)))) -> #REF! | L33: =IF($C33=$D$2,#REF!*L$2,IF($C33=$D$3,#REF!*L$3,IF($C33=$D$4,#REF!*L$4,IF($C33=$D$5,#REF!*L$5,0)))) -> #REF! | ... AM33: =IF($C33=$D$2,#REF!*AM$2,IF($C33=$D$3,#REF!*AM$3,IF($C33=$D$4,#REF!*AM$4,IF($C33=$D$5,#REF!*AM$5,0)))) -> #REF!
A34: =IFERROR(__xludf.DUMMYFUNCTION("""COMPUTED_VALUE"""),"Luis Alberto Mendoza Basurto (Darwin Tigre)") -> Luis Alberto Mendoza Basurto (Darwin Tigre) | B34: =IFERROR(__xludf.DUMMYFUNCTION("""COMPUTED_VALUE"""),"TAL0556") -> TAL0556 | C34: =IFERROR(__xludf.DUMMYFUNCTION("""COMPUTED_VALUE"""),5) -> 5 | D34: =SUM(E34:AM34) -> #REF! | E34: =IF($C34=$D$2,#REF!*E$2,IF($C34=$D$3,#REF!*E$3,IF($C34=$D$4,#REF!*E$4,IF($C34=$D$5,#REF!*E$5,0)))) -> #REF! | F34: =IF($C34=$D$2,#REF!*F$2,IF($C34=$D$3,#REF!*F$3,IF($C34=$D$4,#REF!*F$4,IF($C34=$D$5,#REF!*F$5,0)))) -> #REF! | G34: =IF($C34=$D$2,#REF!*G$2,IF($C34=$D$3,#REF!*G$3,IF($C34=$D$4,#REF!*G$4,IF($C34=$D$5,#REF!*G$5,0)))) -> #REF! | H34: =IF($C34=$D$2,#REF!*H$2,IF($C34=$D$3,#REF!*H$3,IF($C34=$D$4,#REF!*H$4,IF($C34=$D$5,#REF!*H$5,0)))) -> #REF! | I34: =IF($C34=$D$2,#REF!*I$2,IF($C34=$D$3,#REF!*I$3,IF($C34=$D$4,#REF!*I$4,IF($C34=$D$5,#REF!*I$5,0)))) -> #REF! | J34: =IF($C34=$D$2,#REF!*J$2,IF($C34=$D$3,#REF!*J$3,IF($C34=$D$4,#REF!*J$4,IF($C34=$D$5,#REF!*J$5,0)))) -> #REF! | K34: =IF($C34=$D$2,#REF!*K$2,IF($C34=$D$3,#REF!*K$3,IF($C34=$D$4,#REF!*K$4,IF($C34=$D$5,#REF!*K$5,0)))) -> #REF! | L34: =IF($C34=$D$2,#REF!*L$2,IF($C34=$D$3,#REF!*L$3,IF($C34=$D$4,#REF!*L$4,IF($C34=$D$5,#REF!*L$5,0)))) -> #REF! | ... AM34: =IF($C34=$D$2,#REF!*AM$2,IF($C34=$D$3,#REF!*AM$3,IF($C34=$D$4,#REF!*AM$4,IF($C34=$D$5,#REF!*AM$5,0)))) -> #REF!
A35: =IFERROR(__xludf.DUMMYFUNCTION("""COMPUTED_VALUE"""),"Javier Mendoza guarderas (abogado)") -> Javier Mendoza guarderas (abogado) | B35: =IFERROR(__xludf.DUMMYFUNCTION("""COMPUTED_VALUE"""),"TCM0286") -> TCM0286 | C35: =IFERROR(__xludf.DUMMYFUNCTION("""COMPUTED_VALUE"""),5) -> 5 | D35: =SUM(E35:AM35) -> #REF! | E35: =IF($C35=$D$2,#REF!*E$2,IF($C35=$D$3,#REF!*E$3,IF($C35=$D$4,#REF!*E$4,IF($C35=$D$5,#REF!*E$5,0)))) -> #REF! | F35: =IF($C35=$D$2,#REF!*F$2,IF($C35=$D$3,#REF!*F$3,IF($C35=$D$4,#REF!*F$4,IF($C35=$D$5,#REF!*F$5,0)))) -> #REF! | G35: =IF($C35=$D$2,#REF!*G$2,IF($C35=$D$3,#REF!*G$3,IF($C35=$D$4,#REF!*G$4,IF($C35=$D$5,#REF!*G$5,0)))) -> #REF! | H35: =IF($C35=$D$2,#REF!*H$2,IF($C35=$D$3,#REF!*H$3,IF($C35=$D$4,#REF!*H$4,IF($C35=$D$5,#REF!*H$5,0)))) -> #REF! | I35: =IF($C35=$D$2,#REF!*I$2,IF($C35=$D$3,#REF!*I$3,IF($C35=$D$4,#REF!*I$4,IF($C35=$D$5,#REF!*I$5,0)))) -> #REF! | J35: =IF($C35=$D$2,#REF!*J$2,IF($C35=$D$3,#REF!*J$3,IF($C35=$D$4,#REF!*J$4,IF($C35=$D$5,#REF!*J$5,0)))) -> #REF! | K35: =IF($C35=$D$2,#REF!*K$2,IF($C35=$D$3,#REF!*K$3,IF($C35=$D$4,#REF!*K$4,IF($C35=$D$5,#REF!*K$5,0)))) -> #REF! | L35: =IF($C35=$D$2,#REF!*L$2,IF($C35=$D$3,#REF!*L$3,IF($C35=$D$4,#REF!*L$4,IF($C35=$D$5,#REF!*L$5,0)))) -> #REF! | ... AM35: =IF($C35=$D$2,#REF!*AM$2,IF($C35=$D$3,#REF!*AM$3,IF($C35=$D$4,#REF!*AM$4,IF($C35=$D$5,#REF!*AM$5,0)))) -> #REF!
D36: =SUM(E36:AM36) -> 0 | E36: =IF($C36=$D$2,#REF!*E$2,IF($C36=$D$3,#REF!*E$3,IF($C36=$D$4,#REF!*E$4,IF($C36=$D$5,#REF!*E$5,0)))) -> 0 | F36: =IF($C36=$D$2,#REF!*F$2,IF($C36=$D$3,#REF!*F$3,IF($C36=$D$4,#REF!*F$4,IF($C36=$D$5,#REF!*F$5,0)))) -> 0 | G36: =IF($C36=$D$2,#REF!*G$2,IF($C36=$D$3,#REF!*G$3,IF($C36=$D$4,#REF!*G$4,IF($C36=$D$5,#REF!*G$5,0)))) -> 0 | H36: =IF($C36=$D$2,#REF!*H$2,IF($C36=$D$3,#REF!*H$3,IF($C36=$D$4,#REF!*H$4,IF($C36=$D$5,#REF!*H$5,0)))) -> 0 | I36: =IF($C36=$D$2,#REF!*I$2,IF($C36=$D$3,#REF!*I$3,IF($C36=$D$4,#REF!*I$4,IF($C36=$D$5,#REF!*I$5,0)))) -> 0 | J36: =IF($C36=$D$2,#REF!*J$2,IF($C36=$D$3,#REF!*J$3,IF($C36=$D$4,#REF!*J$4,IF($C36=$D$5,#REF!*J$5,0)))) -> 0 | K36: =IF($C36=$D$2,#REF!*K$2,IF($C36=$D$3,#REF!*K$3,IF($C36=$D$4,#REF!*K$4,IF($C36=$D$5,#REF!*K$5,0)))) -> 0 | L36: =IF($C36=$D$2,#REF!*L$2,IF($C36=$D$3,#REF!*L$3,IF($C36=$D$4,#REF!*L$4,IF($C36=$D$5,#REF!*L$5,0)))) -> 0 | ... AM36: =IF($C36=$D$2,#REF!*AM$2,IF($C36=$D$3,#REF!*AM$3,IF($C36=$D$4,#REF!*AM$4,IF($C36=$D$5,#REF!*AM$5,0)))) -> 0
D37: =SUM(E37:AM37) -> 0 | E37: =IF($C37=$D$2,#REF!*E$2,IF($C37=$D$3,#REF!*E$3,IF($C37=$D$4,#REF!*E$4,IF($C37=$D$5,#REF!*E$5,0)))) -> 0 | F37: =IF($C37=$D$2,#REF!*F$2,IF($C37=$D$3,#REF!*F$3,IF($C37=$D$4,#REF!*F$4,IF($C37=$D$5,#REF!*F$5,0)))) -> 0 | G37: =IF($C37=$D$2,#REF!*G$2,IF($C37=$D$3,#REF!*G$3,IF($C37=$D$4,#REF!*G$4,IF($C37=$D$5,#REF!*G$5,0)))) -> 0 | H37: =IF($C37=$D$2,#REF!*H$2,IF($C37=$D$3,#REF!*H$3,IF($C37=$D$4,#REF!*H$4,IF($C37=$D$5,#REF!*H$5,0)))) -> 0 | I37: =IF($C37=$D$2,#REF!*I$2,IF($C37=$D$3,#REF!*I$3,IF($C37=$D$4,#REF!*I$4,IF($C37=$D$5,#REF!*I$5,0)))) -> 0 | J37: =IF($C37=$D$2,#REF!*J$2,IF($C37=$D$3,#REF!*J$3,IF($C37=$D$4,#REF!*J$4,IF($C37=$D$5,#REF!*J$5,0)))) -> 0 | K37: =IF($C37=$D$2,#REF!*K$2,IF($C37=$D$3,#REF!*K$3,IF($C37=$D$4,#REF!*K$4,IF($C37=$D$5,#REF!*K$5,0)))) -> 0 | L37: =IF($C37=$D$2,#REF!*L$2,IF($C37=$D$3,#REF!*L$3,IF($C37=$D$4,#REF!*L$4,IF($C37=$D$5,#REF!*L$5,0)))) -> 0 | ... AM37: =IF($C37=$D$2,#REF!*AM$2,IF($C37=$D$3,#REF!*AM$3,IF($C37=$D$4,#REF!*AM$4,IF($C37=$D$5,#REF!*AM$5,0)))) -> 0
D38: =SUM(E38:AM38) -> 0 | E38: =IF($C38=$D$2,#REF!*E$2,IF($C38=$D$3,#REF!*E$3,IF($C38=$D$4,#REF!*E$4,IF($C38=$D$5,#REF!*E$5,0)))) -> 0 | F38: =IF($C38=$D$2,#REF!*F$2,IF($C38=$D$3,#REF!*F$3,IF($C38=$D$4,#REF!*F$4,IF($C38=$D$5,#REF!*F$5,0)))) -> 0 | G38: =IF($C38=$D$2,#REF!*G$2,IF($C38=$D$3,#REF!*G$3,IF($C38=$D$4,#REF!*G$4,IF($C38=$D$5,#REF!*G$5,0)))) -> 0 | H38: =IF($C38=$D$2,#REF!*H$2,IF($C38=$D$3,#REF!*H$3,IF($C38=$D$4,#REF!*H$4,IF($C38=$D$5,#REF!*H$5,0)))) -> 0 | I38: =IF($C38=$D$2,#REF!*I$2,IF($C38=$D$3,#REF!*I$3,IF($C38=$D$4,#REF!*I$4,IF($C38=$D$5,#REF!*I$5,0)))) -> 0 | J38: =IF($C38=$D$2,#REF!*J$2,IF($C38=$D$3,#REF!*J$3,IF($C38=$D$4,#REF!*J$4,IF($C38=$D$5,#REF!*J$5,0)))) -> 0 | K38: =IF($C38=$D$2,#REF!*K$2,IF($C38=$D$3,#REF!*K$3,IF($C38=$D$4,#REF!*K$4,IF($C38=$D$5,#REF!*K$5,0)))) -> 0 | L38: =IF($C38=$D$2,#REF!*L$2,IF($C38=$D$3,#REF!*L$3,IF($C38=$D$4,#REF!*L$4,IF($C38=$D$5,#REF!*L$5,0)))) -> 0 | ... AM38: =IF($C38=$D$2,#REF!*AM$2,IF($C38=$D$3,#REF!*AM$3,IF($C38=$D$4,#REF!*AM$4,IF($C38=$D$5,#REF!*AM$5,0)))) -> 0
D39: =SUM(E39:AM39) -> 0 | E39: =IF($C39=$D$2,#REF!*E$2,IF($C39=$D$3,#REF!*E$3,IF($C39=$D$4,#REF!*E$4,IF($C39=$D$5,#REF!*E$5,0)))) -> 0 | F39: =IF($C39=$D$2,#REF!*F$2,IF($C39=$D$3,#REF!*F$3,IF($C39=$D$4,#REF!*F$4,IF($C39=$D$5,#REF!*F$5,0)))) -> 0 | G39: =IF($C39=$D$2,#REF!*G$2,IF($C39=$D$3,#REF!*G$3,IF($C39=$D$4,#REF!*G$4,IF($C39=$D$5,#REF!*G$5,0)))) -> 0 | H39: =IF($C39=$D$2,#REF!*H$2,IF($C39=$D$3,#REF!*H$3,IF($C39=$D$4,#REF!*H$4,IF($C39=$D$5,#REF!*H$5,0)))) -> 0 | I39: =IF($C39=$D$2,#REF!*I$2,IF($C39=$D$3,#REF!*I$3,IF($C39=$D$4,#REF!*I$4,IF($C39=$D$5,#REF!*I$5,0)))) -> 0 | J39: =IF($C39=$D$2,#REF!*J$2,IF($C39=$D$3,#REF!*J$3,IF($C39=$D$4,#REF!*J$4,IF($C39=$D$5,#REF!*J$5,0)))) -> 0 | K39: =IF($C39=$D$2,#REF!*K$2,IF($C39=$D$3,#REF!*K$3,IF($C39=$D$4,#REF!*K$4,IF($C39=$D$5,#REF!*K$5,0)))) -> 0 | L39: =IF($C39=$D$2,#REF!*L$2,IF($C39=$D$3,#REF!*L$3,IF($C39=$D$4,#REF!*L$4,IF($C39=$D$5,#REF!*L$5,0)))) -> 0 | ... AM39: =IF($C39=$D$2,#REF!*AM$2,IF($C39=$D$3,#REF!*AM$3,IF($C39=$D$4,#REF!*AM$4,IF($C39=$D$5,#REF!*AM$5,0)))) -> 0
D40: =SUM(E40:AM40) -> 0 | E40: =IF($C40=$D$2,#REF!*E$2,IF($C40=$D$3,#REF!*E$3,IF($C40=$D$4,#REF!*E$4,IF($C40=$D$5,#REF!*E$5,0)))) -> 0 | F40: =IF($C40=$D$2,#REF!*F$2,IF($C40=$D$3,#REF!*F$3,IF($C40=$D$4,#REF!*F$4,IF($C40=$D$5,#REF!*F$5,0)))) -> 0 | G40: =IF($C40=$D$2,#REF!*G$2,IF($C40=$D$3,#REF!*G$3,IF($C40=$D$4,#REF!*G$4,IF($C40=$D$5,#REF!*G$5,0)))) -> 0 | H40: =IF($C40=$D$2,#REF!*H$2,IF($C40=$D$3,#REF!*H$3,IF($C40=$D$4,#REF!*H$4,IF($C40=$D$5,#REF!*H$5,0)))) -> 0 | I40: =IF($C40=$D$2,#REF!*I$2,IF($C40=$D$3,#REF!*I$3,IF($C40=$D$4,#REF!*I$4,IF($C40=$D$5,#REF!*I$5,0)))) -> 0 | J40: =IF($C40=$D$2,#REF!*J$2,IF($C40=$D$3,#REF!*J$3,IF($C40=$D$4,#REF!*J$4,IF($C40=$D$5,#REF!*J$5,0)))) -> 0 | K40: =IF($C40=$D$2,#REF!*K$2,IF($C40=$D$3,#REF!*K$3,IF($C40=$D$4,#REF!*K$4,IF($C40=$D$5,#REF!*K$5,0)))) -> 0 | L40: =IF($C40=$D$2,#REF!*L$2,IF($C40=$D$3,#REF!*L$3,IF($C40=$D$4,#REF!*L$4,IF($C40=$D$5,#REF!*L$5,0)))) -> 0 | ... AM40: =IF($C40=$D$2,#REF!*AM$2,IF($C40=$D$3,#REF!*AM$3,IF($C40=$D$4,#REF!*AM$4,IF($C40=$D$5,#REF!*AM$5,0)))) -> 0
D41: =SUM(E41:AM41) -> 0 | E41: =IF($C41=$D$2,#REF!*E$2,IF($C41=$D$3,#REF!*E$3,IF($C41=$D$4,#REF!*E$4,IF($C41=$D$5,#REF!*E$5,0)))) -> 0 | F41: =IF($C41=$D$2,#REF!*F$2,IF($C41=$D$3,#REF!*F$3,IF($C41=$D$4,#REF!*F$4,IF($C41=$D$5,#REF!*F$5,0)))) -> 0 | G41: =IF($C41=$D$2,#REF!*G$2,IF($C41=$D$3,#REF!*G$3,IF($C41=$D$4,#REF!*G$4,IF($C41=$D$5,#REF!*G$5,0)))) -> 0 | H41: =IF($C41=$D$2,#REF!*H$2,IF($C41=$D$3,#REF!*H$3,IF($C41=$D$4,#REF!*H$4,IF($C41=$D$5,#REF!*H$5,0)))) -> 0 | I41: =IF($C41=$D$2,#REF!*I$2,IF($C41=$D$3,#REF!*I$3,IF($C41=$D$4,#REF!*I$4,IF($C41=$D$5,#REF!*I$5,0)))) -> 0 | J41: =IF($C41=$D$2,#REF!*J$2,IF($C41=$D$3,#REF!*J$3,IF($C41=$D$4,#REF!*J$4,IF($C41=$D$5,#REF!*J$5,0)))) -> 0 | K41: =IF($C41=$D$2,#REF!*K$2,IF($C41=$D$3,#REF!*K$3,IF($C41=$D$4,#REF!*K$4,IF($C41=$D$5,#REF!*K$5,0)))) -> 0 | L41: =IF($C41=$D$2,#REF!*L$2,IF($C41=$D$3,#REF!*L$3,IF($C41=$D$4,#REF!*L$4,IF($C41=$D$5,#REF!*L$5,0)))) -> 0 | ... AM41: =IF($C41=$D$2,#REF!*AM$2,IF($C41=$D$3,#REF!*AM$3,IF($C41=$D$4,#REF!*AM$4,IF($C41=$D$5,#REF!*AM$5,0)))) -> 0
D42: =SUM(E42:AM42) -> 0 | E42: =IF($C42=$D$2,#REF!*E$2,IF($C42=$D$3,#REF!*E$3,IF($C42=$D$4,#REF!*E$4,IF($C42=$D$5,#REF!*E$5,0)))) -> 0 | F42: =IF($C42=$D$2,#REF!*F$2,IF($C42=$D$3,#REF!*F$3,IF($C42=$D$4,#REF!*F$4,IF($C42=$D$5,#REF!*F$5,0)))) -> 0 | G42: =IF($C42=$D$2,#REF!*G$2,IF($C42=$D$3,#REF!*G$3,IF($C42=$D$4,#REF!*G$4,IF($C42=$D$5,#REF!*G$5,0)))) -> 0 | H42: =IF($C42=$D$2,#REF!*H$2,IF($C42=$D$3,#REF!*H$3,IF($C42=$D$4,#REF!*H$4,IF($C42=$D$5,#REF!*H$5,0)))) -> 0 | I42: =IF($C42=$D$2,#REF!*I$2,IF($C42=$D$3,#REF!*I$3,IF($C42=$D$4,#REF!*I$4,IF($C42=$D$5,#REF!*I$5,0)))) -> 0 | J42: =IF($C42=$D$2,#REF!*J$2,IF($C42=$D$3,#REF!*J$3,IF($C42=$D$4,#REF!*J$4,IF($C42=$D$5,#REF!*J$5,0)))) -> 0 | K42: =IF($C42=$D$2,#REF!*K$2,IF($C42=$D$3,#REF!*K$3,IF($C42=$D$4,#REF!*K$4,IF($C42=$D$5,#REF!*K$5,0)))) -> 0 | L42: =IF($C42=$D$2,#REF!*L$2,IF($C42=$D$3,#REF!*L$3,IF($C42=$D$4,#REF!*L$4,IF($C42=$D$5,#REF!*L$5,0)))) -> 0 | ... AM42: =IF($C42=$D$2,#REF!*AM$2,IF($C42=$D$3,#REF!*AM$3,IF($C42=$D$4,#REF!*AM$4,IF($C42=$D$5,#REF!*AM$5,0)))) -> 0
D43: =SUM(E43:AM43) -> 0 | E43: =IF($C43=$D$2,#REF!*E$2,IF($C43=$D$3,#REF!*E$3,IF($C43=$D$4,#REF!*E$4,IF($C43=$D$5,#REF!*E$5,0)))) -> 0 | F43: =IF($C43=$D$2,#REF!*F$2,IF($C43=$D$3,#REF!*F$3,IF($C43=$D$4,#REF!*F$4,IF($C43=$D$5,#REF!*F$5,0)))) -> 0 | G43: =IF($C43=$D$2,#REF!*G$2,IF($C43=$D$3,#REF!*G$3,IF($C43=$D$4,#REF!*G$4,IF($C43=$D$5,#REF!*G$5,0)))) -> 0 | H43: =IF($C43=$D$2,#REF!*H$2,IF($C43=$D$3,#REF!*H$3,IF($C43=$D$4,#REF!*H$4,IF($C43=$D$5,#REF!*H$5,0)))) -> 0 | I43: =IF($C43=$D$2,#REF!*I$2,IF($C43=$D$3,#REF!*I$3,IF($C43=$D$4,#REF!*I$4,IF($C43=$D$5,#REF!*I$5,0)))) -> 0 | J43: =IF($C43=$D$2,#REF!*J$2,IF($C43=$D$3,#REF!*J$3,IF($C43=$D$4,#REF!*J$4,IF($C43=$D$5,#REF!*J$5,0)))) -> 0 | K43: =IF($C43=$D$2,#REF!*K$2,IF($C43=$D$3,#REF!*K$3,IF($C43=$D$4,#REF!*K$4,IF($C43=$D$5,#REF!*K$5,0)))) -> 0 | L43: =IF($C43=$D$2,#REF!*L$2,IF($C43=$D$3,#REF!*L$3,IF($C43=$D$4,#REF!*L$4,IF($C43=$D$5,#REF!*L$5,0)))) -> 0 | ... AM43: =IF($C43=$D$2,#REF!*AM$2,IF($C43=$D$3,#REF!*AM$3,IF($C43=$D$4,#REF!*AM$4,IF($C43=$D$5,#REF!*AM$5,0)))) -> 0
D44: =SUM(E44:AM44) -> 0 | E44: =IF($C44=$D$2,#REF!*E$2,IF($C44=$D$3,#REF!*E$3,IF($C44=$D$4,#REF!*E$4,IF($C44=$D$5,#REF!*E$5,0)))) -> 0 | F44: =IF($C44=$D$2,#REF!*F$2,IF($C44=$D$3,#REF!*F$3,IF($C44=$D$4,#REF!*F$4,IF($C44=$D$5,#REF!*F$5,0)))) -> 0 | G44: =IF($C44=$D$2,#REF!*G$2,IF($C44=$D$3,#REF!*G$3,IF($C44=$D$4,#REF!*G$4,IF($C44=$D$5,#REF!*G$5,0)))) -> 0 | H44: =IF($C44=$D$2,#REF!*H$2,IF($C44=$D$3,#REF!*H$3,IF($C44=$D$4,#REF!*H$4,IF($C44=$D$5,#REF!*H$5,0)))) -> 0 | I44: =IF($C44=$D$2,#REF!*I$2,IF($C44=$D$3,#REF!*I$3,IF($C44=$D$4,#REF!*I$4,IF($C44=$D$5,#REF!*I$5,0)))) -> 0 | J44: =IF($C44=$D$2,#REF!*J$2,IF($C44=$D$3,#REF!*J$3,IF($C44=$D$4,#REF!*J$4,IF($C44=$D$5,#REF!*J$5,0)))) -> 0 | K44: =IF($C44=$D$2,#REF!*K$2,IF($C44=$D$3,#REF!*K$3,IF($C44=$D$4,#REF!*K$4,IF($C44=$D$5,#REF!*K$5,0)))) -> 0 | L44: =IF($C44=$D$2,#REF!*L$2,IF($C44=$D$3,#REF!*L$3,IF($C44=$D$4,#REF!*L$4,IF($C44=$D$5,#REF!*L$5,0)))) -> 0 | ... AM44: =IF($C44=$D$2,#REF!*AM$2,IF($C44=$D$3,#REF!*AM$3,IF($C44=$D$4,#REF!*AM$4,IF($C44=$D$5,#REF!*AM$5,0)))) -> 0
D45: =SUM(E45:AM45) -> 0 | E45: =IF($C45=$D$2,#REF!*E$2,IF($C45=$D$3,#REF!*E$3,IF($C45=$D$4,#REF!*E$4,IF($C45=$D$5,#REF!*E$5,0)))) -> 0 | F45: =IF($C45=$D$2,#REF!*F$2,IF($C45=$D$3,#REF!*F$3,IF($C45=$D$4,#REF!*F$4,IF($C45=$D$5,#REF!*F$5,0)))) -> 0 | G45: =IF($C45=$D$2,#REF!*G$2,IF($C45=$D$3,#REF!*G$3,IF($C45=$D$4,#REF!*G$4,IF($C45=$D$5,#REF!*G$5,0)))) -> 0 | H45: =IF($C45=$D$2,#REF!*H$2,IF($C45=$D$3,#REF!*H$3,IF($C45=$D$4,#REF!*H$4,IF($C45=$D$5,#REF!*H$5,0)))) -> 0 | I45: =IF($C45=$D$2,#REF!*I$2,IF($C45=$D$3,#REF!*I$3,IF($C45=$D$4,#REF!*I$4,IF($C45=$D$5,#REF!*I$5,0)))) -> 0 | J45: =IF($C45=$D$2,#REF!*J$2,IF($C45=$D$3,#REF!*J$3,IF($C45=$D$4,#REF!*J$4,IF($C45=$D$5,#REF!*J$5,0)))) -> 0 | K45: =IF($C45=$D$2,#REF!*K$2,IF($C45=$D$3,#REF!*K$3,IF($C45=$D$4,#REF!*K$4,IF($C45=$D$5,#REF!*K$5,0)))) -> 0 | L45: =IF($C45=$D$2,#REF!*L$2,IF($C45=$D$3,#REF!*L$3,IF($C45=$D$4,#REF!*L$4,IF($C45=$D$5,#REF!*L$5,0)))) -> 0 | ... AM45: =IF($C45=$D$2,#REF!*AM$2,IF($C45=$D$3,#REF!*AM$3,IF($C45=$D$4,#REF!*AM$4,IF($C45=$D$5,#REF!*AM$5,0)))) -> 0
D46: =SUM(E46:AM46) -> 0 | E46: =IF($C46=$D$2,#REF!*E$2,IF($C46=$D$3,#REF!*E$3,IF($C46=$D$4,#REF!*E$4,IF($C46=$D$5,#REF!*E$5,0)))) -> 0 | F46: =IF($C46=$D$2,#REF!*F$2,IF($C46=$D$3,#REF!*F$3,IF($C46=$D$4,#REF!*F$4,IF($C46=$D$5,#REF!*F$5,0)))) -> 0 | G46: =IF($C46=$D$2,#REF!*G$2,IF($C46=$D$3,#REF!*G$3,IF($C46=$D$4,#REF!*G$4,IF($C46=$D$5,#REF!*G$5,0)))) -> 0 | H46: =IF($C46=$D$2,#REF!*H$2,IF($C46=$D$3,#REF!*H$3,IF($C46=$D$4,#REF!*H$4,IF($C46=$D$5,#REF!*H$5,0)))) -> 0 | I46: =IF($C46=$D$2,#REF!*I$2,IF($C46=$D$3,#REF!*I$3,IF($C46=$D$4,#REF!*I$4,IF($C46=$D$5,#REF!*I$5,0)))) -> 0 | J46: =IF($C46=$D$2,#REF!*J$2,IF($C46=$D$3,#REF!*J$3,IF($C46=$D$4,#REF!*J$4,IF($C46=$D$5,#REF!*J$5,0)))) -> 0 | K46: =IF($C46=$D$2,#REF!*K$2,IF($C46=$D$3,#REF!*K$3,IF($C46=$D$4,#REF!*K$4,IF($C46=$D$5,#REF!*K$5,0)))) -> 0 | L46: =IF($C46=$D$2,#REF!*L$2,IF($C46=$D$3,#REF!*L$3,IF($C46=$D$4,#REF!*L$4,IF($C46=$D$5,#REF!*L$5,0)))) -> 0 | ... AM46: =IF($C46=$D$2,#REF!*AM$2,IF($C46=$D$3,#REF!*AM$3,IF($C46=$D$4,#REF!*AM$4,IF($C46=$D$5,#REF!*AM$5,0)))) -> 0
D47: =SUM(E47:AM47) -> 0 | E47: =IF($C47=$D$2,#REF!*E$2,IF($C47=$D$3,#REF!*E$3,IF($C47=$D$4,#REF!*E$4,IF($C47=$D$5,#REF!*E$5,0)))) -> 0 | F47: =IF($C47=$D$2,#REF!*F$2,IF($C47=$D$3,#REF!*F$3,IF($C47=$D$4,#REF!*F$4,IF($C47=$D$5,#REF!*F$5,0)))) -> 0 | G47: =IF($C47=$D$2,#REF!*G$2,IF($C47=$D$3,#REF!*G$3,IF($C47=$D$4,#REF!*G$4,IF($C47=$D$5,#REF!*G$5,0)))) -> 0 | H47: =IF($C47=$D$2,#REF!*H$2,IF($C47=$D$3,#REF!*H$3,IF($C47=$D$4,#REF!*H$4,IF($C47=$D$5,#REF!*H$5,0)))) -> 0 | I47: =IF($C47=$D$2,#REF!*I$2,IF($C47=$D$3,#REF!*I$3,IF($C47=$D$4,#REF!*I$4,IF($C47=$D$5,#REF!*I$5,0)))) -> 0 | J47: =IF($C47=$D$2,#REF!*J$2,IF($C47=$D$3,#REF!*J$3,IF($C47=$D$4,#REF!*J$4,IF($C47=$D$5,#REF!*J$5,0)))) -> 0 | K47: =IF($C47=$D$2,#REF!*K$2,IF($C47=$D$3,#REF!*K$3,IF($C47=$D$4,#REF!*K$4,IF($C47=$D$5,#REF!*K$5,0)))) -> 0 | L47: =IF($C47=$D$2,#REF!*L$2,IF($C47=$D$3,#REF!*L$3,IF($C47=$D$4,#REF!*L$4,IF($C47=$D$5,#REF!*L$5,0)))) -> 0 | ... AM47: =IF($C47=$D$2,#REF!*AM$2,IF($C47=$D$3,#REF!*AM$3,IF($C47=$D$4,#REF!*AM$4,IF($C47=$D$5,#REF!*AM$5,0)))) -> 0
... D504: =SUM(E504:AM504) -> 0 | E504: =IF($C504=$D$2,#REF!*E$2,IF($C504=$D$3,#REF!*E$3,IF($C504=$D$4,#REF!*E$4,IF($C504=$D$5,#REF!*E$5,0)))) -> 0 | F504: =IF($C504=$D$2,#REF!*F$2,IF($C504=$D$3,#REF!*F$3,IF($C504=$D$4,#REF!*F$4,IF($C504=$D$5,#REF!*F$5,0)))) -> 0 | G504: =IF($C504=$D$2,#REF!*G$2,IF($C504=$D$3,#REF!*G$3,IF($C504=$D$4,#REF!*G$4,IF($C504=$D$5,#REF!*G$5,0)))) -> 0 | H504: =IF($C504=$D$2,#REF!*H$2,IF($C504=$D$3,#REF!*H$3,IF($C504=$D$4,#REF!*H$4,IF($C504=$D$5,#REF!*H$5,0)))) -> 0 | I504: =IF($C504=$D$2,#REF!*I$2,IF($C504=$D$3,#REF!*I$3,IF($C504=$D$4,#REF!*I$4,IF($C504=$D$5,#REF!*I$5,0)))) -> 0 | J504: =IF($C504=$D$2,#REF!*J$2,IF($C504=$D$3,#REF!*J$3,IF($C504=$D$4,#REF!*J$4,IF($C504=$D$5,#REF!*J$5,0)))) -> 0 | K504: =IF($C504=$D$2,#REF!*K$2,IF($C504=$D$3,#REF!*K$3,IF($C504=$D$4,#REF!*K$4,IF($C504=$D$5,#REF!*K$5,0)))) -> 0 | L504: =IF($C504=$D$2,#REF!*L$2,IF($C504=$D$3,#REF!*L$3,IF($C504=$D$4,#REF!*L$4,IF($C504=$D$5,#REF!*L$5,0)))) -> 0 | ... AM504: =IF($C504=$D$2,#REF!*AM$2,IF($C504=$D$3,#REF!*AM$3,IF($C504=$D$4,#REF!*AM$4,IF($C504=$D$5,#REF!*AM$5,0)))) -> 0
D506: TRANSPORTISTAS EXTERNOS
B507: HBA0270
B508: XBE343
B509: PVL0706
B510: PPA1778
B511: HBC6496
B512: PCP5161
B513: RBA9146
B514: HGC420
B515: JAA2389
B516: PFB0399
B517: PVL602
B518: PBS1430
... B551: GQN0985

Sheet FLETES ($) MAYO
A1: MES | B1: ABRIL | C1: =COUNTIFS(BITACORA!B4:B7322,">="&B3,BITACORA!B4:B7322,"<="&B4) -> 138 | E1: TOTAL $ VIAJES FLETADOS | F1: =SUM(D7:D504) -> #REF!
D2: 3 | E2: =#REF! -> #REF! | F2: =#REF! -> #REF! | G2: =#REF! -> #REF! | H2: =#REF! -> #REF! | I2: =#REF! -> #REF! | J2: =#REF! -> #REF! | K2: =#REF! -> #REF! | L2: =#REF! -> #REF! | ... AM2: =#REF! -> #REF!
A3: FECHA DE INICIO | B3: 44317 | D3: 4 | E3: =#REF! -> #REF! | F3: =#REF! -> #REF! | G3: =#REF! -> #REF! | H3: =#REF! -> #REF! | I3: =#REF! -> #REF! | J3: =#REF! -> #REF! | K3: =#REF! -> #REF! | L3: =#REF! -> #REF! | ... AM3: =#REF! -> #REF!
A4: FECHA DE CORTE | B4: 44347 | D4: 5 | E4: =#REF! -> #REF! | F4: =#REF! -> #REF! | G4: =#REF! -> #REF! | H4: =#REF! -> #REF! | I4: =#REF! -> #REF! | J4: =#REF! -> #REF! | K4: =#REF! -> #REF! | L4: =#REF! -> #REF! | ... AM4: =#REF! -> #REF!
D5: 6 | E5: =#REF! -> #REF! | F5: =#REF! -> #REF! | G5: =#REF! -> #REF! | H5: =#REF! -> #REF! | I5: =#REF! -> #REF! | J5: =#REF! -> #REF! | K5: =#REF! -> #REF! | L5: =#REF! -> #REF! | ... AM5: =#REF! -> #REF!
A6: =IFERROR(__xludf.DUMMYFUNCTION("IMPORTRANGE(""https://docs.google.com/spreadsheets/d/1utvdjsQjm2nB6A8-WaesD8IPx5qFCLXNwJxEgiS8wno/edit?usp=sharing"",""TRANSPORTISTAS!A1:C500"")"),"TRANSPORTISTA") -> TRANSPORTISTA | B6: =IFERROR(__xludf.DUMMYFUNCTION("""COMPUTED_VALUE"""),"PLACA DEL VEHICULO") -> PLACA DEL VEHICULO | C6: =IFERROR(__xludf.DUMMYFUNCTION("""COMPUTED_VALUE"""),"CAPACIDAD (FILAS)") -> CAPACIDAD (FILAS) | D6: TOTAL $ DE VIAJES | E6: =LISTAS!$B7 -> TACHINA | F6: =LISTAS!$B8 -> TRES VIAS | G6: =LISTAS!$B9 -> QUININDE | H6: =LISTAS!$B10 -> TAISHA | I6: =LISTAS!$B11 -> ARAJUNO | J6: =LISTAS!$B12 -> 0 | K6: =LISTAS!$B13 -> 0 | L6: =LISTAS!$B14 -> 0 | M6: =LISTAS!$B15 -> 0 | N6: =LISTAS!$B16 -> 0 | O6: =LISTAS!$B17 -> 0 | P6: =LISTAS!$B18 -> 0 | Q6: =LISTAS!$B19 -> 0 | R6: =LISTAS!$B20 -> 0 | S6: =LISTAS!$B21 -> 0 | T6: =LISTAS!$B22 -> 0 | U6: =LISTAS!$B23 -> 0 | V6: =LISTAS!$B24 -> FINCA EN PLANTA | W6: =LISTAS!$B25 -> LA SANDIA | X6: =LISTAS!$B26 -> 0 | Y6: =LISTAS!$B27 -> 0 | Z6: =LISTAS!$B28 -> 0 | AA6: =LISTAS!$B29 -> 0 | AB6: =LISTAS!$B30 -> 0 | AC6: =LISTAS!$B31 -> 0 | AD6: =LISTAS!$B32 -> 0 | AE6: =LISTAS!$B33 -> RIO FRIO | AF6: =LISTAS!$B34 -> RIO FRIO ETAPA 2 | AG6: =LISTAS!$B35 -> BOSQUE PUERTO NUEVO | AH6: =LISTAS!$B36 -> 0 | AI6: =LISTAS!$B37 -> 0 | AJ6: =LISTAS!$B38 -> 0 | AK6: =LISTAS!$B39 -> 0 | AL6: =LISTAS!$B40 -> 0 | AM6: =LISTAS!$B41 -> 0
A7: =IFERROR(__xludf.DUMMYFUNCTION("""COMPUTED_VALUE"""),"Klever Enrique Moreira Cedeño") -> Klever Enrique Moreira Cedeño | B7: =IFERROR(__xludf.DUMMYFUNCTION("""COMPUTED_VALUE"""),"JAR4061") -> JAR4061 | C7: =IFERROR(__xludf.DUMMYFUNCTION("""COMPUTED_VALUE"""),3) -> 3 | D7: =SUM(E7:AM7) -> #REF! | E7: =IF($C7=$D$2,'FLETES (#) MAYO'!E7*E$2,IF($C7=$D$3,'FLETES (#) MAYO'!E7*E$3,IF($C7=$D$4,'FLETES (#) MAYO'!E7*E$4,IF($C7=$D$5,'FLETES (#) MAYO'!E7*E$5,0)))) -> #REF! | F7: =IF($C7=$D$2,'FLETES (#) MAYO'!F7*F$2,IF($C7=$D$3,'FLETES (#) MAYO'!F7*F$3,IF($C7=$D$4,'FLETES (#) MAYO'!F7*F$4,IF($C7=$D$5,'FLETES (#) MAYO'!F7*F$5,0)))) -> #REF! | G7: =IF($C7=$D$2,'FLETES (#) MAYO'!G7*G$2,IF($C7=$D$3,'FLETES (#) MAYO'!G7*G$3,IF($C7=$D$4,'FLETES (#) MAYO'!G7*G$4,IF($C7=$D$5,'FLETES (#) MAYO'!G7*G$5,0)))) -> #REF! | H7: =IF($C7=$D$2,'FLETES (#) MAYO'!H7*H$2,IF($C7=$D$3,'FLETES (#) MAYO'!H7*H$3,IF($C7=$D$4,'FLETES (#) MAYO'!H7*H$4,IF($C7=$D$5,'FLETES (#) MAYO'!H7*H$5,0)))) -> #REF! | I7: =IF($C7=$D$2,'FLETES (#) MAYO'!I7*I$2,IF($C7=$D$3,'FLETES (#) MAYO'!I7*I$3,IF($C7=$D$4,'FLETES (#) MAYO'!I7*I$4,IF($C7=$D$5,'FLETES (#) MAYO'!I7*I$5,0)))) -> #REF! | J7: =IF($C7=$D$2,'FLETES (#) MAYO'!J7*J$2,IF($C7=$D$3,'FLETES (#) MAYO'!J7*J$3,IF($C7=$D$4,'FLETES (#) MAYO'!J7*J$4,IF($C7=$D$5,'FLETES (#) MAYO'!J7*J$5,0)))) -> #REF! | K7: =IF($C7=$D$2,'FLETES (#) MAYO'!K7*K$2,IF($C7=$D$3,'FLETES (#) MAYO'!K7*K$3,IF($C7=$D$4,'FLETES (#) MAYO'!K7*K$4,IF($C7=$D$5,'FLETES (#) MAYO'!K7*K$5,0)))) -> #REF! | L7: =IF($C7=$D$2,'FLETES (#) MAYO'!L7*L$2,IF($C7=$D$3,'FLETES (#) MAYO'!L7*L$3,IF($C7=$D$4,'FLETES (#) MAYO'!L7*L$4,IF($C7=$D$5,'FLETES (#) MAYO'!L7*L$5,0)))) -> #REF! | ... AM7: =IF($C7=$D$2,'FLETES (#) MAYO'!AM7*AM$2,IF($C7=$D$3,'FLETES (#) MAYO'!AM7*AM$3,IF($C7=$D$4,'FLETES (#) MAYO'!AM7*AM$4,IF($C7=$D$5,'FLETES (#) MAYO'!AM7*AM$5,0)))) -> #REF!
A8: =IFERROR(__xludf.DUMMYFUNCTION("""COMPUTED_VALUE"""),"Ricardo Coveña Quintero") -> Ricardo Coveña Quintero | B8: =IFERROR(__xludf.DUMMYFUNCTION("""COMPUTED_VALUE"""),"PPX0724") -> PPX0724 | C8: =IFERROR(__xludf.DUMMYFUNCTION("""COMPUTED_VALUE"""),3) -> 3 | D8: =SUM(E8:AM8) -> #REF! | E8: =IF($C8=$D$2,'FLETES (#) MAYO'!E8*E$2,IF($C8=$D$3,'FLETES (#) MAYO'!E8*E$3,IF($C8=$D$4,'FLETES (#) MAYO'!E8*E$4,IF($C8=$D$5,'FLETES (#) MAYO'!E8*E$5,0)))) -> #REF! | F8: =IF($C8=$D$2,'FLETES (#) MAYO'!F8*F$2,IF($C8=$D$3,'FLETES (#) MAYO'!F8*F$3,IF($C8=$D$4,'FLETES (#) MAYO'!F8*F$4,IF($C8=$D$5,'FLETES (#) MAYO'!F8*F$5,0)))) -> #REF! | G8: =IF($C8=$D$2,'FLETES (#) MAYO'!G8*G$2,IF($C8=$D$3,'FLETES (#) MAYO'!G8*G$3,IF($C8=$D$4,'FLETES (#) MAYO'!G8*G$4,IF($C8=$D$5,'FLETES (#) MAYO'!G8*G$5,0)))) -> #REF! | H8: =IF($C8=$D$2,'FLETES (#) MAYO'!H8*H$2,IF($C8=$D$3,'FLETES (#) MAYO'!H8*H$3,IF($C8=$D$4,'FLETES (#) MAYO'!H8*H$4,IF($C8=$D$5,'FLETES (#) MAYO'!H8*H$5,0)))) -> #REF! | I8: =IF($C8=$D$2,'FLETES (#) MAYO'!I8*I$2,IF($C8=$D$3,'FLETES (#) MAYO'!I8*I$3,IF($C8=$D$4,'FLETES (#) MAYO'!I8*I$4,IF($C8=$D$5,'FLETES (#) MAYO'!I8*I$5,0)))) -> #REF! | J8: =IF($C8=$D$2,'FLETES (#) MAYO'!J8*J$2,IF($C8=$D$3,'FLETES (#) MAYO'!J8*J$3,IF($C8=$D$4,'FLETES (#) MAYO'!J8*J$4,IF($C8=$D$5,'FLETES (#) MAYO'!J8*J$5,0)))) -> #REF! | K8: =IF($C8=$D$2,'FLETES (#) MAYO'!K8*K$2,IF($C8=$D$3,'FLETES (#) MAYO'!K8*K$3,IF($C8=$D$4,'FLETES (#) MAYO'!K8*K$4,IF($C8=$D$5,'FLETES (#) MAYO'!K8*K$5,0)))) -> #REF! | L8: =IF($C8=$D$2,'FLETES (#) MAYO'!L8*L$2,IF($C8=$D$3,'FLETES (#) MAYO'!L8*L$3,IF($C8=$D$4,'FLETES (#) MAYO'!L8*L$4,IF($C8=$D$5,'FLETES (#) MAYO'!L8*L$5,0)))) -> #REF! | ... AM8: =IF($C8=$D$2,'FLETES (#) MAYO'!AM8*AM$2,IF($C8=$D$3,'FLETES (#) MAYO'!AM8*AM$3,IF($C8=$D$4,'FLETES (#) MAYO'!AM8*AM$4,IF($C8=$D$5,'FLETES (#) MAYO'!AM8*AM$5,0)))) -> #REF!
A9: =IFERROR(__xludf.DUMMYFUNCTION("""COMPUTED_VALUE"""),"Cesar Octavio Aguilar Loor") -> Cesar Octavio Aguilar Loor | B9: =IFERROR(__xludf.DUMMYFUNCTION("""COMPUTED_VALUE"""),"MCW0186") -> MCW0186 | C9: =IFERROR(__xludf.DUMMYFUNCTION("""COMPUTED_VALUE"""),4) -> 4 | D9: =SUM(E9:AM9) -> #REF! | E9: =IF($C9=$D$2,'FLETES (#) MAYO'!E9*E$2,IF($C9=$D$3,'FLETES (#) MAYO'!E9*E$3,IF($C9=$D$4,'FLETES (#) MAYO'!E9*E$4,IF($C9=$D$5,'FLETES (#) MAYO'!E9*E$5,0)))) -> #REF! | F9: =IF($C9=$D$2,'FLETES (#) MAYO'!F9*F$2,IF($C9=$D$3,'FLETES (#) MAYO'!F9*F$3,IF($C9=$D$4,'FLETES (#) MAYO'!F9*F$4,IF($C9=$D$5,'FLETES (#) MAYO'!F9*F$5,0)))) -> #REF! | G9: =IF($C9=$D$2,'FLETES (#) MAYO'!G9*G$2,IF($C9=$D$3,'FLETES (#) MAYO'!G9*G$3,IF($C9=$D$4,'FLETES (#) MAYO'!G9*G$4,IF($C9=$D$5,'FLETES (#) MAYO'!G9*G$5,0)))) -> #REF! | H9: =IF($C9=$D$2,'FLETES (#) MAYO'!H9*H$2,IF($C9=$D$3,'FLETES (#) MAYO'!H9*H$3,IF($C9=$D$4,'FLETES (#) MAYO'!H9*H$4,IF($C9=$D$5,'FLETES (#) MAYO'!H9*H$5,0)))) -> #REF! | I9: =IF($C9=$D$2,'FLETES (#) MAYO'!I9*I$2,IF($C9=$D$3,'FLETES (#) MAYO'!I9*I$3,IF($C9=$D$4,'FLETES (#) MAYO'!I9*I$4,IF($C9=$D$5,'FLETES (#) MAYO'!I9*I$5,0)))) -> #REF! | J9: =IF($C9=$D$2,'FLETES (#) MAYO'!J9*J$2,IF($C9=$D$3,'FLETES (#) MAYO'!J9*J$3,IF($C9=$D$4,'FLETES (#) MAYO'!J9*J$4,IF($C9=$D$5,'FLETES (#) MAYO'!J9*J$5,0)))) -> #REF! | K9: =IF($C9=$D$2,'FLETES (#) MAYO'!K9*K$2,IF($C9=$D$3,'FLETES (#) MAYO'!K9*K$3,IF($C9=$D$4,'FLETES (#) MAYO'!K9*K$4,IF($C9=$D$5,'FLETES (#) MAYO'!K9*K$5,0)))) -> #REF! | L9: =IF($C9=$D$2,'FLETES (#) MAYO'!L9*L$2,IF($C9=$D$3,'FLETES (#) MAYO'!L9*L$3,IF($C9=$D$4,'FLETES (#) MAYO'!L9*L$4,IF($C9=$D$5,'FLETES (#) MAYO'!L9*L$5,0)))) -> #REF! | ... AM9: =IF($C9=$D$2,'FLETES (#) MAYO'!AM9*AM$2,IF($C9=$D$3,'FLETES (#) MAYO'!AM9*AM$3,IF($C9=$D$4,'FLETES (#) MAYO'!AM9*AM$4,IF($C9=$D$5,'FLETES (#) MAYO'!AM9*AM$5,0)))) -> #REF!
A10: =IFERROR(__xludf.DUMMYFUNCTION("""COMPUTED_VALUE"""),"Jonathan Jehova Vera Mendoza") -> Jonathan Jehova Vera Mendoza | B10: =IFERROR(__xludf.DUMMYFUNCTION("""COMPUTED_VALUE"""),"JAA3367") -> JAA3367 | C10: =IFERROR(__xludf.DUMMYFUNCTION("""COMPUTED_VALUE"""),4) -> 4 | D10: =SUM(E10:AM10) -> #REF! | E10: =IF($C10=$D$2,'FLETES (#) MAYO'!E10*E$2,IF($C10=$D$3,'FLETES (#) MAYO'!E10*E$3,IF($C10=$D$4,'FLETES (#) MAYO'!E10*E$4,IF($C10=$D$5,'FLETES (#) MAYO'!E10*E$5,0)))) -> #REF! | F10: =IF($C10=$D$2,'FLETES (#) MAYO'!F10*F$2,IF($C10=$D$3,'FLETES (#) MAYO'!F10*F$3,IF($C10=$D$4,'FLETES (#) MAYO'!F10*F$4,IF($C10=$D$5,'FLETES (#) MAYO'!F10*F$5,0)))) -> #REF! | G10: =IF($C10=$D$2,'FLETES (#) MAYO'!G10*G$2,IF($C10=$D$3,'FLETES (#) MAYO'!G10*G$3,IF($C10=$D$4,'FLETES (#) MAYO'!G10*G$4,IF($C10=$D$5,'FLETES (#) MAYO'!G10*G$5,0)))) -> #REF! | H10: =IF($C10=$D$2,'FLETES (#) MAYO'!H10*H$2,IF($C10=$D$3,'FLETES (#) MAYO'!H10*H$3,IF($C10=$D$4,'FLETES (#) MAYO'!H10*H$4,IF($C10=$D$5,'FLETES (#) MAYO'!H10*H$5,0)))) -> #REF! | I10: =IF($C10=$D$2,'FLETES (#) MAYO'!I10*I$2,IF($C10=$D$3,'FLETES (#) MAYO'!I10*I$3,IF($C10=$D$4,'FLETES (#) MAYO'!I10*I$4,IF($C10=$D$5,'FLETES (#) MAYO'!I10*I$5,0)))) -> #REF! | J10: =IF($C10=$D$2,'FLETES (#) MAYO'!J10*J$2,IF($C10=$D$3,'FLETES (#) MAYO'!J10*J$3,IF($C10=$D$4,'FLETES (#) MAYO'!J10*J$4,IF($C10=$D$5,'FLETES (#) MAYO'!J10*J$5,0)))) -> #REF! | K10: =IF($C10=$D$2,'FLETES (#) MAYO'!K10*K$2,IF($C10=$D$3,'FLETES (#) MAYO'!K10*K$3,IF($C10=$D$4,'FLETES (#) MAYO'!K10*K$4,IF($C10=$D$5,'FLETES (#) MAYO'!K10*K$5,0)))) -> #REF! | L10: =IF($C10=$D$2,'FLETES (#) MAYO'!L10*L$2,IF($C10=$D$3,'FLETES (#) MAYO'!L10*L$3,IF($C10=$D$4,'FLETES (#) MAYO'!L10*L$4,IF($C10=$D$5,'FLETES (#) MAYO'!L10*L$5,0)))) -> #REF! | ... AM10: =IF($C10=$D$2,'FLETES (#) MAYO'!AM10*AM$2,IF($C10=$D$3,'FLETES (#) MAYO'!AM10*AM$3,IF($C10=$D$4,'FLETES (#) MAYO'!AM10*AM$4,IF($C10=$D$5,'FLETES (#) MAYO'!AM10*AM$5,0)))) -> #REF!
A11: =IFERROR(__xludf.DUMMYFUNCTION("""COMPUTED_VALUE"""),"Emerson Fabricio Moreira Alcivar") -> Emerson Fabricio Moreira Alcivar | B11: =IFERROR(__xludf.DUMMYFUNCTION("""COMPUTED_VALUE"""),"JAA3375") -> JAA3375 | C11: =IFERROR(__xludf.DUMMYFUNCTION("""COMPUTED_VALUE"""),4) -> 4 | D11: =SUM(E11:AM11) -> #REF! | E11: =IF($C11=$D$2,'FLETES (#) MAYO'!E11*E$2,IF($C11=$D$3,'FLETES (#) MAYO'!E11*E$3,IF($C11=$D$4,'FLETES (#) MAYO'!E11*E$4,IF($C11=$D$5,'FLETES (#) MAYO'!E11*E$5,0)))) -> #REF! | F11: =IF($C11=$D$2,'FLETES (#) MAYO'!F11*F$2,IF($C11=$D$3,'FLETES (#) MAYO'!F11*F$3,IF($C11=$D$4,'FLETES (#) MAYO'!F11*F$4,IF($C11=$D$5,'FLETES (#) MAYO'!F11*F$5,0)))) -> #REF! | G11: =IF($C11=$D$2,'FLETES (#) MAYO'!G11*G$2,IF($C11=$D$3,'FLETES (#) MAYO'!G11*G$3,IF($C11=$D$4,'FLETES (#) MAYO'!G11*G$4,IF($C11=$D$5,'FLETES (#) MAYO'!G11*G$5,0)))) -> #REF! | H11: =IF($C11=$D$2,'FLETES (#) MAYO'!H11*H$2,IF($C11=$D$3,'FLETES (#) MAYO'!H11*H$3,IF($C11=$D$4,'FLETES (#) MAYO'!H11*H$4,IF($C11=$D$5,'FLETES (#) MAYO'!H11*H$5,0)))) -> #REF! | I11: =IF($C11=$D$2,'FLETES (#) MAYO'!I11*I$2,IF($C11=$D$3,'FLETES (#) MAYO'!I11*I$3,IF($C11=$D$4,'FLETES (#) MAYO'!I11*I$4,IF($C11=$D$5,'FLETES (#) MAYO'!I11*I$5,0)))) -> #REF! | J11: =IF($C11=$D$2,'FLETES (#) MAYO'!J11*J$2,IF($C11=$D$3,'FLETES (#) MAYO'!J11*J$3,IF($C11=$D$4,'FLETES (#) MAYO'!J11*J$4,IF($C11=$D$5,'FLETES (#) MAYO'!J11*J$5,0)))) -> #REF! | K11: =IF($C11=$D$2,'FLETES (#) MAYO'!K11*K$2,IF($C11=$D$3,'FLETES (#) MAYO'!K11*K$3,IF($C11=$D$4,'FLETES (#) MAYO'!K11*K$4,IF($C11=$D$5,'FLETES (#) MAYO'!K11*K$5,0)))) -> #REF! | L11: =IF($C11=$D$2,'FLETES (#) MAYO'!L11*L$2,IF($C11=$D$3,'FLETES (#) MAYO'!L11*L$3,IF($C11=$D$4,'FLETES (#) MAYO'!L11*L$4,IF($C11=$D$5,'FLETES (#) MAYO'!L11*L$5,0)))) -> #REF! | ... AM11: =IF($C11=$D$2,'FLETES (#) MAYO'!AM11*AM$2,IF($C11=$D$3,'FLETES (#) MAYO'!AM11*AM$3,IF($C11=$D$4,'FLETES (#) MAYO'!AM11*AM$4,IF($C11=$D$5,'FLETES (#) MAYO'!AM11*AM$5,0)))) -> #REF!
A12: =IFERROR(__xludf.DUMMYFUNCTION("""COMPUTED_VALUE"""),"Cedeño Barveran Marcelo German") -> Cedeño Barveran Marcelo German | B12: =IFERROR(__xludf.DUMMYFUNCTION("""COMPUTED_VALUE"""),"MAP0286") -> MAP0286 | C12: =IFERROR(__xludf.DUMMYFUNCTION("""COMPUTED_VALUE"""),4) -> 4 | D12: =SUM(E12:AM12) -> #REF! | E12: =IF($C12=$D$2,'FLETES (#) MAYO'!E12*E$2,IF($C12=$D$3,'FLETES (#) MAYO'!E12*E$3,IF($C12=$D$4,'FLETES (#) MAYO'!E12*E$4,IF($C12=$D$5,'FLETES (#) MAYO'!E12*E$5,0)))) -> #REF! | F12: =IF($C12=$D$2,'FLETES (#) MAYO'!F12*F$2,IF($C12=$D$3,'FLETES (#) MAYO'!F12*F$3,IF($C12=$D$4,'FLETES (#) MAYO'!F12*F$4,IF($C12=$D$5,'FLETES (#) MAYO'!F12*F$5,0)))) -> #REF! | G12: =IF($C12=$D$2,'FLETES (#) MAYO'!G12*G$2,IF($C12=$D$3,'FLETES (#) MAYO'!G12*G$3,IF($C12=$D$4,'FLETES (#) MAYO'!G12*G$4,IF($C12=$D$5,'FLETES (#) MAYO'!G12*G$5,0)))) -> #REF! | H12: =IF($C12=$D$2,'FLETES (#) MAYO'!H12*H$2,IF($C12=$D$3,'FLETES (#) MAYO'!H12*H$3,IF($C12=$D$4,'FLETES (#) MAYO'!H12*H$4,IF($C12=$D$5,'FLETES (#) MAYO'!H12*H$5,0)))) -> #REF! | I12: =IF($C12=$D$2,'FLETES (#) MAYO'!I12*I$2,IF($C12=$D$3,'FLETES (#) MAYO'!I12*I$3,IF($C12=$D$4,'FLETES (#) MAYO'!I12*I$4,IF($C12=$D$5,'FLETES (#) MAYO'!I12*I$5,0)))) -> #REF! | J12: =IF($C12=$D$2,'FLETES (#) MAYO'!J12*J$2,IF($C12=$D$3,'FLETES (#) MAYO'!J12*J$3,IF($C12=$D$4,'FLETES (#) MAYO'!J12*J$4,IF($C12=$D$5,'FLETES (#) MAYO'!J12*J$5,0)))) -> #REF! | K12: =IF($C12=$D$2,'FLETES (#) MAYO'!K12*K$2,IF($C12=$D$3,'FLETES (#) MAYO'!K12*K$3,IF($C12=$D$4,'FLETES (#) MAYO'!K12*K$4,IF($C12=$D$5,'FLETES (#) MAYO'!K12*K$5,0)))) -> #REF! | L12: =IF($C12=$D$2,'FLETES (#) MAYO'!L12*L$2,IF($C12=$D$3,'FLETES (#) MAYO'!L12*L$3,IF($C12=$D$4,'FLETES (#) MAYO'!L12*L$4,IF($C12=$D$5,'FLETES (#) MAYO'!L12*L$5,0)))) -> #REF! | ... AM12: =IF($C12=$D$2,'FLETES (#) MAYO'!AM12*AM$2,IF($C12=$D$3,'FLETES (#) MAYO'!AM12*AM$3,IF($C12=$D$4,'FLETES (#) MAYO'!AM12*AM$4,IF($C12=$D$5,'FLETES (#) MAYO'!AM12*AM$5,0)))) -> #REF!
A13: =IFERROR(__xludf.DUMMYFUNCTION("""COMPUTED_VALUE"""),"Jonathan Alejandro Diaz Montes") -> Jonathan Alejandro Diaz Montes | B13: =IFERROR(__xludf.DUMMYFUNCTION("""COMPUTED_VALUE"""),"PQX0243") -> PQX0243 | C13: =IFERROR(__xludf.DUMMYFUNCTION("""COMPUTED_VALUE"""),4) -> 4 | D13: =SUM(E13:AM13) -> #REF! | E13: =IF($C13=$D$2,'FLETES (#) MAYO'!E13*E$2,IF($C13=$D$3,'FLETES (#) MAYO'!E13*E$3,IF($C13=$D$4,'FLETES (#) MAYO'!E13*E$4,IF($C13=$D$5,'FLETES (#) MAYO'!E13*E$5,0)))) -> #REF! | F13: =IF($C13=$D$2,'FLETES (#) MAYO'!F13*F$2,IF($C13=$D$3,'FLETES (#) MAYO'!F13*F$3,IF($C13=$D$4,'FLETES (#) MAYO'!F13*F$4,IF($C13=$D$5,'FLETES (#) MAYO'!F13*F$5,0)))) -> #REF! | G13: =IF($C13=$D$2,'FLETES (#) MAYO'!G13*G$2,IF($C13=$D$3,'FLETES (#) MAYO'!G13*G$3,IF($C13=$D$4,'FLETES (#) MAYO'!G13*G$4,IF($C13=$D$5,'FLETES (#) MAYO'!G13*G$5,0)))) -> #REF! | H13: =IF($C13=$D$2,'FLETES (#) MAYO'!H13*H$2,IF($C13=$D$3,'FLETES (#) MAYO'!H13*H$3,IF($C13=$D$4,'FLETES (#) MAYO'!H13*H$4,IF($C13=$D$5,'FLETES (#) MAYO'!H13*H$5,0)))) -> #REF! | I13: =IF($C13=$D$2,'FLETES (#) MAYO'!I13*I$2,IF($C13=$D$3,'FLETES (#) MAYO'!I13*I$3,IF($C13=$D$4,'FLETES (#) MAYO'!I13*I$4,IF($C13=$D$5,'FLETES (#) MAYO'!I13*I$5,0)))) -> #REF! | J13: =IF($C13=$D$2,'FLETES (#) MAYO'!J13*J$2,IF($C13=$D$3,'FLETES (#) MAYO'!J13*J$3,IF($C13=$D$4,'FLETES (#) MAYO'!J13*J$4,IF($C13=$D$5,'FLETES (#) MAYO'!J13*J$5,0)))) -> #REF! | K13: =IF($C13=$D$2,'FLETES (#) MAYO'!K13*K$2,IF($C13=$D$3,'FLETES (#) MAYO'!K13*K$3,IF($C13=$D$4,'FLETES (#) MAYO'!K13*K$4,IF($C13=$D$5,'FLETES (#) MAYO'!K13*K$5,0)))) -> #REF! | L13: =IF($C13=$D$2,'FLETES (#) MAYO'!L13*L$2,IF($C13=$D$3,'FLETES (#) MAYO'!L13*L$3,IF($C13=$D$4,'FLETES (#) MAYO'!L13*L$4,IF($C13=$D$5,'FLETES (#) MAYO'!L13*L$5,0)))) -> #REF! | ... AM13: =IF($C13=$D$2,'FLETES (#) MAYO'!AM13*AM$2,IF($C13=$D$3,'FLETES (#) MAYO'!AM13*AM$3,IF($C13=$D$4,'FLETES (#) MAYO'!AM13*AM$4,IF($C13=$D$5,'FLETES (#) MAYO'!AM13*AM$5,0)))) -> #REF!
A14: =IFERROR(__xludf.DUMMYFUNCTION("""COMPUTED_VALUE"""),"Freddy Amador Napa Rosado") -> Freddy Amador Napa Rosado | B14: =IFERROR(__xludf.DUMMYFUNCTION("""COMPUTED_VALUE"""),"PIB0529") -> PIB0529 | C14: =IFERROR(__xludf.DUMMYFUNCTION("""COMPUTED_VALUE"""),4) -> 4 | D14: =SUM(E14:AM14) -> #REF! | E14: =IF($C14=$D$2,'FLETES (#) MAYO'!E14*E$2,IF($C14=$D$3,'FLETES (#) MAYO'!E14*E$3,IF($C14=$D$4,'FLETES (#) MAYO'!E14*E$4,IF($C14=$D$5,'FLETES (#) MAYO'!E14*E$5,0)))) -> #REF! | F14: =IF($C14=$D$2,'FLETES (#) MAYO'!F14*F$2,IF($C14=$D$3,'FLETES (#) MAYO'!F14*F$3,IF($C14=$D$4,'FLETES (#) MAYO'!F14*F$4,IF($C14=$D$5,'FLETES (#) MAYO'!F14*F$5,0)))) -> #REF! | G14: =IF($C14=$D$2,'FLETES (#) MAYO'!G14*G$2,IF($C14=$D$3,'FLETES (#) MAYO'!G14*G$3,IF($C14=$D$4,'FLETES (#) MAYO'!G14*G$4,IF($C14=$D$5,'FLETES (#) MAYO'!G14*G$5,0)))) -> #REF! | H14: =IF($C14=$D$2,'FLETES (#) MAYO'!H14*H$2,IF($C14=$D$3,'FLETES (#) MAYO'!H14*H$3,IF($C14=$D$4,'FLETES (#) MAYO'!H14*H$4,IF($C14=$D$5,'FLETES (#) MAYO'!H14*H$5,0)))) -> #REF! | I14: =IF($C14=$D$2,'FLETES (#) MAYO'!I14*I$2,IF($C14=$D$3,'FLETES (#) MAYO'!I14*I$3,IF($C14=$D$4,'FLETES (#) MAYO'!I14*I$4,IF($C14=$D$5,'FLETES (#) MAYO'!I14*I$5,0)))) -> #REF! | J14: =IF($C14=$D$2,'FLETES (#) MAYO'!J14*J$2,IF($C14=$D$3,'FLETES (#) MAYO'!J14*J$3,IF($C14=$D$4,'FLETES (#) MAYO'!J14*J$4,IF($C14=$D$5,'FLETES (#) MAYO'!J14*J$5,0)))) -> #REF! | K14: =IF($C14=$D$2,'FLETES (#) MAYO'!K14*K$2,IF($C14=$D$3,'FLETES (#) MAYO'!K14*K$3,IF($C14=$D$4,'FLETES (#) MAYO'!K14*K$4,IF($C14=$D$5,'FLETES (#) MAYO'!K14*K$5,0)))) -> #REF! | L14: =IF($C14=$D$2,'FLETES (#) MAYO'!L14*L$2,IF($C14=$D$3,'FLETES (#) MAYO'!L14*L$3,IF($C14=$D$4,'FLETES (#) MAYO'!L14*L$4,IF($C14=$D$5,'FLETES (#) MAYO'!L14*L$5,0)))) -> #REF! | ... AM14: =IF($C14=$D$2,'FLETES (#) MAYO'!AM14*AM$2,IF($C14=$D$3,'FLETES (#) MAYO'!AM14*AM$3,IF($C14=$D$4,'FLETES (#) MAYO'!AM14*AM$4,IF($C14=$D$5,'FLETES (#) MAYO'!AM14*AM$5,0)))) -> #REF!
A15: =IFERROR(__xludf.DUMMYFUNCTION("""COMPUTED_VALUE"""),"Diego Adrian Mendoza Velez") -> Diego Adrian Mendoza Velez | B15: =IFERROR(__xludf.DUMMYFUNCTION("""COMPUTED_VALUE"""),"JAA3376") -> JAA3376 | C15: =IFERROR(__xludf.DUMMYFUNCTION("""COMPUTED_VALUE"""),4) -> 4 | D15: =SUM(E15:AM15) -> #REF! | E15: =IF($C15=$D$2,'FLETES (#) MAYO'!E15*E$2,IF($C15=$D$3,'FLETES (#) MAYO'!E15*E$3,IF($C15=$D$4,'FLETES (#) MAYO'!E15*E$4,IF($C15=$D$5,'FLETES (#) MAYO'!E15*E$5,0)))) -> #REF! | F15: =IF($C15=$D$2,'FLETES (#) MAYO'!F15*F$2,IF($C15=$D$3,'FLETES (#) MAYO'!F15*F$3,IF($C15=$D$4,'FLETES (#) MAYO'!F15*F$4,IF($C15=$D$5,'FLETES (#) MAYO'!F15*F$5,0)))) -> #REF! | G15: =IF($C15=$D$2,'FLETES (#) MAYO'!G15*G$2,IF($C15=$D$3,'FLETES (#) MAYO'!G15*G$3,IF($C15=$D$4,'FLETES (#) MAYO'!G15*G$4,IF($C15=$D$5,'FLETES (#) MAYO'!G15*G$5,0)))) -> #REF! | H15: =IF($C15=$D$2,'FLETES (#) MAYO'!H15*H$2,IF($C15=$D$3,'FLETES (#) MAYO'!H15*H$3,IF($C15=$D$4,'FLETES (#) MAYO'!H15*H$4,IF($C15=$D$5,'FLETES (#) MAYO'!H15*H$5,0)))) -> #REF! | I15: =IF($C15=$D$2,'FLETES (#) MAYO'!I15*I$2,IF($C15=$D$3,'FLETES (#) MAYO'!I15*I$3,IF($C15=$D$4,'FLETES (#) MAYO'!I15*I$4,IF($C15=$D$5,'FLETES (#) MAYO'!I15*I$5,0)))) -> #REF! | J15: =IF($C15=$D$2,'FLETES (#) MAYO'!J15*J$2,IF($C15=$D$3,'FLETES (#) MAYO'!J15*J$3,IF($C15=$D$4,'FLETES (#) MAYO'!J15*J$4,IF($C15=$D$5,'FLETES (#) MAYO'!J15*J$5,0)))) -> #REF! | K15: =IF($C15=$D$2,'FLETES (#) MAYO'!K15*K$2,IF($C15=$D$3,'FLETES (#) MAYO'!K15*K$3,IF($C15=$D$4,'FLETES (#) MAYO'!K15*K$4,IF($C15=$D$5,'FLETES (#) MAYO'!K15*K$5,0)))) -> #REF! | L15: =IF($C15=$D$2,'FLETES (#) MAYO'!L15*L$2,IF($C15=$D$3,'FLETES (#) MAYO'!L15*L$3,IF($C15=$D$4,'FLETES (#) MAYO'!L15*L$4,IF($C15=$D$5,'FLETES (#) MAYO'!L15*L$5,0)))) -> #REF! | ... AM15: =IF($C15=$D$2,'FLETES (#) MAYO'!AM15*AM$2,IF($C15=$D$3,'FLETES (#) MAYO'!AM15*AM$3,IF($C15=$D$4,'FLETES (#) MAYO'!AM15*AM$4,IF($C15=$D$5,'FLETES (#) MAYO'!AM15*AM$5,0)))) -> #REF!
A16: =IFERROR(__xludf.DUMMYFUNCTION("""COMPUTED_VALUE"""),"Oscar Jose Loor Basurto") -> Oscar Jose Loor Basurto | B16: =IFERROR(__xludf.DUMMYFUNCTION("""COMPUTED_VALUE"""),"PJB0702") -> PJB0702 | C16: =IFERROR(__xludf.DUMMYFUNCTION("""COMPUTED_VALUE"""),4) -> 4 | D16: =SUM(E16:AM16) -> #REF! | E16: =IF($C16=$D$2,'FLETES (#) MAYO'!E16*E$2,IF($C16=$D$3,'FLETES (#) MAYO'!E16*E$3,IF($C16=$D$4,'FLETES (#) MAYO'!E16*E$4,IF($C16=$D$5,'FLETES (#) MAYO'!E16*E$5,0)))) -> #REF! | F16: =IF($C16=$D$2,'FLETES (#) MAYO'!F16*F$2,IF($C16=$D$3,'FLETES (#) MAYO'!F16*F$3,IF($C16=$D$4,'FLETES (#) MAYO'!F16*F$4,IF($C16=$D$5,'FLETES (#) MAYO'!F16*F$5,0)))) -> #REF! | G16: =IF($C16=$D$2,'FLETES (#) MAYO'!G16*G$2,IF($C16=$D$3,'FLETES (#) MAYO'!G16*G$3,IF($C16=$D$4,'FLETES (#) MAYO'!G16*G$4,IF($C16=$D$5,'FLETES (#) MAYO'!G16*G$5,0)))) -> #REF! | H16: =IF($C16=$D$2,'FLETES (#) MAYO'!H16*H$2,IF($C16=$D$3,'FLETES (#) MAYO'!H16*H$3,IF($C16=$D$4,'FLETES (#) MAYO'!H16*H$4,IF($C16=$D$5,'FLETES (#) MAYO'!H16*H$5,0)))) -> #REF! | I16: =IF($C16=$D$2,'FLETES (#) MAYO'!I16*I$2,IF($C16=$D$3,'FLETES (#) MAYO'!I16*I$3,IF($C16=$D$4,'FLETES (#) MAYO'!I16*I$4,IF($C16=$D$5,'FLETES (#) MAYO'!I16*I$5,0)))) -> #REF! | J16: =IF($C16=$D$2,'FLETES (#) MAYO'!J16*J$2,IF($C16=$D$3,'FLETES (#) MAYO'!J16*J$3,IF($C16=$D$4,'FLETES (#) MAYO'!J16*J$4,IF($C16=$D$5,'FLETES (#) MAYO'!J16*J$5,0)))) -> #REF! | K16: =IF($C16=$D$2,'FLETES (#) MAYO'!K16*K$2,IF($C16=$D$3,'FLETES (#) MAYO'!K16*K$3,IF($C16=$D$4,'FLETES (#) MAYO'!K16*K$4,IF($C16=$D$5,'FLETES (#) MAYO'!K16*K$5,0)))) -> #REF! | L16: =IF($C16=$D$2,'FLETES (#) MAYO'!L16*L$2,IF($C16=$D$3,'FLETES (#) MAYO'!L16*L$3,IF($C16=$D$4,'FLETES (#) MAYO'!L16*L$4,IF($C16=$D$5,'FLETES (#) MAYO'!L16*L$5,0)))) -> #REF! | ... AM16: =IF($C16=$D$2,'FLETES (#) MAYO'!AM16*AM$2,IF($C16=$D$3,'FLETES (#) MAYO'!AM16*AM$3,IF($C16=$D$4,'FLETES (#) MAYO'!AM16*AM$4,IF($C16=$D$5,'FLETES (#) MAYO'!AM16*AM$5,0)))) -> #REF!
A17: =IFERROR(__xludf.DUMMYFUNCTION("""COMPUTED_VALUE"""),"Angulo Saltos Marlon Fabian") -> Angulo Saltos Marlon Fabian | B17: =IFERROR(__xludf.DUMMYFUNCTION("""COMPUTED_VALUE"""),"GKX0511") -> GKX0511 | C17: =IFERROR(__xludf.DUMMYFUNCTION("""COMPUTED_VALUE"""),4) -> 4 | D17: =SUM(E17:AM17) -> #REF! | E17: =IF($C17=$D$2,'FLETES (#) MAYO'!E17*E$2,IF($C17=$D$3,'FLETES (#) MAYO'!E17*E$3,IF($C17=$D$4,'FLETES (#) MAYO'!E17*E$4,IF($C17=$D$5,'FLETES (#) MAYO'!E17*E$5,0)))) -> #REF! | F17: =IF($C17=$D$2,'FLETES (#) MAYO'!F17*F$2,IF($C17=$D$3,'FLETES (#) MAYO'!F17*F$3,IF($C17=$D$4,'FLETES (#) MAYO'!F17*F$4,IF($C17=$D$5,'FLETES (#) MAYO'!F17*F$5,0)))) -> #REF! | G17: =IF($C17=$D$2,'FLETES (#) MAYO'!G17*G$2,IF($C17=$D$3,'FLETES (#) MAYO'!G17*G$3,IF($C17=$D$4,'FLETES (#) MAYO'!G17*G$4,IF($C17=$D$5,'FLETES (#) MAYO'!G17*G$5,0)))) -> #REF! | H17: =IF($C17=$D$2,'FLETES (#) MAYO'!H17*H$2,IF($C17=$D$3,'FLETES (#) MAYO'!H17*H$3,IF($C17=$D$4,'FLETES (#) MAYO'!H17*H$4,IF($C17=$D$5,'FLETES (#) MAYO'!H17*H$5,0)))) -> #REF! | I17: =IF($C17=$D$2,'FLETES (#) MAYO'!I17*I$2,IF($C17=$D$3,'FLETES (#) MAYO'!I17*I$3,IF($C17=$D$4,'FLETES (#) MAYO'!I17*I$4,IF($C17=$D$5,'FLETES (#) MAYO'!I17*I$5,0)))) -> #REF! | J17: =IF($C17=$D$2,'FLETES (#) MAYO'!J17*J$2,IF($C17=$D$3,'FLETES (#) MAYO'!J17*J$3,IF($C17=$D$4,'FLETES (#) MAYO'!J17*J$4,IF($C17=$D$5,'FLETES (#) MAYO'!J17*J$5,0)))) -> #REF! | K17: =IF($C17=$D$2,'FLETES (#) MAYO'!K17*K$2,IF($C17=$D$3,'FLETES (#) MAYO'!K17*K$3,IF($C17=$D$4,'FLETES (#) MAYO'!K17*K$4,IF($C17=$D$5,'FLETES (#) MAYO'!K17*K$5,0)))) -> #REF! | L17: =IF($C17=$D$2,'FLETES (#) MAYO'!L17*L$2,IF($C17=$D$3,'FLETES (#) MAYO'!L17*L$3,IF($C17=$D$4,'FLETES (#) MAYO'!L17*L$4,IF($C17=$D$5,'FLETES (#) MAYO'!L17*L$5,0)))) -> #REF! | ... AM17: =IF($C17=$D$2,'FLETES (#) MAYO'!AM17*AM$2,IF($C17=$D$3,'FLETES (#) MAYO'!AM17*AM$3,IF($C17=$D$4,'FLETES (#) MAYO'!AM17*AM$4,IF($C17=$D$5,'FLETES (#) MAYO'!AM17*AM$5,0)))) -> #REF!
A18: =IFERROR(__xludf.DUMMYFUNCTION("""COMPUTED_VALUE"""),"Enner Eliezer Cevallos Burgos") -> Enner Eliezer Cevallos Burgos | B18: =IFERROR(__xludf.DUMMYFUNCTION("""COMPUTED_VALUE"""),"PZI0105") -> PZI0105 | C18: =IFERROR(__xludf.DUMMYFUNCTION("""COMPUTED_VALUE"""),5) -> 5 | D18: =SUM(E18:AM18) -> #REF! | E18: =IF($C18=$D$2,'FLETES (#) MAYO'!E18*E$2,IF($C18=$D$3,'FLETES (#) MAYO'!E18*E$3,IF($C18=$D$4,'FLETES (#) MAYO'!E18*E$4,IF($C18=$D$5,'FLETES (#) MAYO'!E18*E$5,0)))) -> #REF! | F18: =IF($C18=$D$2,'FLETES (#) MAYO'!F18*F$2,IF($C18=$D$3,'FLETES (#) MAYO'!F18*F$3,IF($C18=$D$4,'FLETES (#) MAYO'!F18*F$4,IF($C18=$D$5,'FLETES (#) MAYO'!F18*F$5,0)))) -> #REF! | G18: =IF($C18=$D$2,'FLETES (#) MAYO'!G18*G$2,IF($C18=$D$3,'FLETES (#) MAYO'!G18*G$3,IF($C18=$D$4,'FLETES (#) MAYO'!G18*G$4,IF($C18=$D$5,'FLETES (#) MAYO'!G18*G$5,0)))) -> #REF! | H18: =IF($C18=$D$2,'FLETES (#) MAYO'!H18*H$2,IF($C18=$D$3,'FLETES (#) MAYO'!H18*H$3,IF($C18=$D$4,'FLETES (#) MAYO'!H18*H$4,IF($C18=$D$5,'FLETES (#) MAYO'!H18*H$5,0)))) -> #REF! | I18: =IF($C18=$D$2,'FLETES (#) MAYO'!I18*I$2,IF($C18=$D$3,'FLETES (#) MAYO'!I18*I$3,IF($C18=$D$4,'FLETES (#) MAYO'!I18*I$4,IF($C18=$D$5,'FLETES (#) MAYO'!I18*I$5,0)))) -> #REF! | J18: =IF($C18=$D$2,'FLETES (#) MAYO'!J18*J$2,IF($C18=$D$3,'FLETES (#) MAYO'!J18*J$3,IF($C18=$D$4,'FLETES (#) MAYO'!J18*J$4,IF($C18=$D$5,'FLETES (#) MAYO'!J18*J$5,0)))) -> #REF! | K18: =IF($C18=$D$2,'FLETES (#) MAYO'!K18*K$2,IF($C18=$D$3,'FLETES (#) MAYO'!K18*K$3,IF($C18=$D$4,'FLETES (#) MAYO'!K18*K$4,IF($C18=$D$5,'FLETES (#) MAYO'!K18*K$5,0)))) -> #REF! | L18: =IF($C18=$D$2,'FLETES (#) MAYO'!L18*L$2,IF($C18=$D$3,'FLETES (#) MAYO'!L18*L$3,IF($C18=$D$4,'FLETES (#) MAYO'!L18*L$4,IF($C18=$D$5,'FLETES (#) MAYO'!L18*L$5,0)))) -> #REF! | ... AM18: =IF($C18=$D$2,'FLETES (#) MAYO'!AM18*AM$2,IF($C18=$D$3,'FLETES (#) MAYO'!AM18*AM$3,IF($C18=$D$4,'FLETES (#) MAYO'!AM18*AM$4,IF($C18=$D$5,'FLETES (#) MAYO'!AM18*AM$5,0)))) -> #REF!
A19: =IFERROR(__xludf.DUMMYFUNCTION("""COMPUTED_VALUE"""),"Luis Javier Jaramillo Vera") -> Luis Javier Jaramillo Vera | B19: =IFERROR(__xludf.DUMMYFUNCTION("""COMPUTED_VALUE"""),"HAJ0694") -> HAJ0694 | C19: =IFERROR(__xludf.DUMMYFUNCTION("""COMPUTED_VALUE"""),5) -> 5 | D19: =SUM(E19:AM19) -> #REF! | E19: =IF($C19=$D$2,'FLETES (#) MAYO'!E19*E$2,IF($C19=$D$3,'FLETES (#) MAYO'!E19*E$3,IF($C19=$D$4,'FLETES (#) MAYO'!E19*E$4,IF($C19=$D$5,'FLETES (#) MAYO'!E19*E$5,0)))) -> #REF! | F19: =IF($C19=$D$2,'FLETES (#) MAYO'!F19*F$2,IF($C19=$D$3,'FLETES (#) MAYO'!F19*F$3,IF($C19=$D$4,'FLETES (#) MAYO'!F19*F$4,IF($C19=$D$5,'FLETES (#) MAYO'!F19*F$5,0)))) -> #REF! | G19: =IF($C19=$D$2,'FLETES (#) MAYO'!G19*G$2,IF($C19=$D$3,'FLETES (#) MAYO'!G19*G$3,IF($C19=$D$4,'FLETES (#) MAYO'!G19*G$4,IF($C19=$D$5,'FLETES (#) MAYO'!G19*G$5,0)))) -> #REF! | H19: =IF($C19=$D$2,'FLETES (#) MAYO'!H19*H$2,IF($C19=$D$3,'FLETES (#) MAYO'!H19*H$3,IF($C19=$D$4,'FLETES (#) MAYO'!H19*H$4,IF($C19=$D$5,'FLETES (#) MAYO'!H19*H$5,0)))) -> #REF! | I19: =IF($C19=$D$2,'FLETES (#) MAYO'!I19*I$2,IF($C19=$D$3,'FLETES (#) MAYO'!I19*I$3,IF($C19=$D$4,'FLETES (#) MAYO'!I19*I$4,IF($C19=$D$5,'FLETES (#) MAYO'!I19*I$5,0)))) -> #REF! | J19: =IF($C19=$D$2,'FLETES (#) MAYO'!J19*J$2,IF($C19=$D$3,'FLETES (#) MAYO'!J19*J$3,IF($C19=$D$4,'FLETES (#) MAYO'!J19*J$4,IF($C19=$D$5,'FLETES (#) MAYO'!J19*J$5,0)))) -> #REF! | K19: =IF($C19=$D$2,'FLETES (#) MAYO'!K19*K$2,IF($C19=$D$3,'FLETES (#) MAYO'!K19*K$3,IF($C19=$D$4,'FLETES (#) MAYO'!K19*K$4,IF($C19=$D$5,'FLETES (#) MAYO'!K19*K$5,0)))) -> #REF! | L19: =IF($C19=$D$2,'FLETES (#) MAYO'!L19*L$2,IF($C19=$D$3,'FLETES (#) MAYO'!L19*L$3,IF($C19=$D$4,'FLETES (#) MAYO'!L19*L$4,IF($C19=$D$5,'FLETES (#) MAYO'!L19*L$5,0)))) -> #REF! | ... AM19: =IF($C19=$D$2,'FLETES (#) MAYO'!AM19*AM$2,IF($C19=$D$3,'FLETES (#) MAYO'!AM19*AM$3,IF($C19=$D$4,'FLETES (#) MAYO'!AM19*AM$4,IF($C19=$D$5,'FLETES (#) MAYO'!AM19*AM$5,0)))) -> #REF!
