Workbook

Sheet ROL_UNIFICADO
A1: ROL UNIFICADO MES NOVIEMBRE 2020
F3: 1° QUINCENA | H3: 2° QUINCENA
A4: ÀREA DE PENDULA | C4: SUELDO BASICO | D4: SUELDO EXTRA | E4: DIAS SEG/SUELDO | F4: V. TRABAJOS FIJOS | G4: V. TRABAJOS EXTRAS | H4: V. TRABAJOS FIJOS | I4: V. TRABAJOS EXTRAS | J4: PERMISO IESS | K4: VACACIONES | L4: TOTAL BRUTO | M4: DSCTO 9,45% IESS | N4: SUB-TOTAL SUELDO | O4: DECIMO 3RO | P4: DECIMO 4TO | Q4: TOTAL BENEFICIOS | R4: FONDO RESERVA | S4: OTROS VALORES | T4: BONIFICACION | U4: TOTAL INGRESOS | V4: OTROS DSCTOS | W4: MULTA | X4: ANTICIPOS | Y4: ALIMENTACION | Z4: PRESTAMO QUIROGRA | AA4: TOTAL EGRESOS | AB4: VALOR NETO DEL MES | AC4: ABONO1 | AD4: ABONO2 | AE4: ABONO3 | AF4: SALDO A RECIBIR
A5: 1 | B5: BAQUE MERO ROBERTH DANIEL | C5: =IF(L5>=401.41,401.41,IF(L5<401.41,L5)) -> 401.41 | D5: =+L5-C5 -> 129.8231 | E5: =+C5/13.3803 -> 30.000075 | F5: =+'TALLER ACTIVOS'!BF7 -> 405.33568 | G5: =+[1]TALLER!BB7 -> 0 | H5: =+'TALLER ACTIVOS'!CX7 -> 125.89741 | I5: =+[1]TALLER!CT7 -> 0 | L5: =+F5+G5+H5+I5+K5+J5 -> 531.2331 | M5: =IF(L5>=401.41,37.933,IF(L5<401.41,L5*9.45%)) -> 37.933 | N5: =+L5-M5 -> 493.3001 | O5: =IF(E5>=30,33.45,IF(E5<30,E5*1.115)) -> 33.45 | P5: =IF(E5>=30,33.33,IF(E5<30,E5*1.111)) -> 33.33 | Q5: =+O5+P5 -> 66.78 | R5: =33.45/30*E5 -> 33.450083 | U5: =N5+Q5+R5+S5+T5 -> 593.53018 | Z5: 46.63 | AA5: =+W5+V5+X5+Y5+Z5 -> 46.63 | AB5: =+U5-AA5 -> 546.90018 | AF5: =+AB5-AC5-AD5-AE5 -> 546.90018
A6: =A5+1 -> 2 | B6: RISCO ZAMBRANO JEFFERSON CECILIO | C6: =IF(L6>=401.41,401.41,IF(L6<401.41,L6)) -> 401.41 | D6: =+L6-C6 -> 99.937188 | E6: =+C6/13.3803 -> 30.000075 | F6: =+'TALLER ACTIVOS'!BF8 -> 384.23382 | G6: =+[1]TALLER!BB8 -> 0 | H6: =+'TALLER ACTIVOS'!CX8 -> 117.11337 | I6: =+[1]TALLER!CT8 -> 0 | L6: =+F6+G6+H6+I6+K6+J6 -> 501.34719 | M6: =IF(L6>=401.41,37.933,IF(L6<401.41,L6*9.45%)) -> 37.933 | N6: =+L6-M6 -> 463.41419 | O6: =IF(E6>=30,33.45,IF(E6<30,E6*1.115)) -> 33.45 | P6: =IF(E6>=30,33.33,IF(E6<30,E6*1.111)) -> 33.33 | Q6: =+O6+P6 -> 66.78 | R6: =33.45/30*E6 -> 33.450083 | U6: =N6+Q6+R6+S6+T6 -> 563.64427 | AA6: =+W6+V6+X6+Y6+Z6 -> 0 | AB6: =+U6-AA6 -> 563.64427 | AF6: =+AB6-AC6-AD6-AE6 -> 563.64427
A7: =A6+1 -> 3 | B7: CHANALATA TONATO CESAR AUGUSTO | C7: =IF(L7>=401.41,401.41,IF(L7<401.41,L7)) -> 401.41 | D7: =+L7-C7 -> 110.26075 | E7: =+C7/13.3803 -> 30.000075 | F7: =+'TALLER ACTIVOS'!BF9 -> 375.89941 | G7: =+[1]TALLER!BB9 -> 0 | H7: =+'TALLER ACTIVOS'!CX9 -> 135.77134 | I7: =+[1]TALLER!CT9 -> 0 | L7: =+F7+G7+H7+I7+K7+J7 -> 511.67075 | M7: =IF(L7>=401.41,37.933,IF(L7<401.41,L7*9.45%)) -> 37.933 | N7: =+L7-M7 -> 473.73775 | O7: =IF(E7>=30,33.45,IF(E7<30,E7*1.115)) -> 33.45 | P7: =IF(E7>=30,33.33,IF(E7<30,E7*1.111)) -> 33.33 | Q7: =+O7+P7 -> 66.78 | R7: =33.45/30*E7 -> 33.450083 | U7: =N7+Q7+R7+S7+T7 -> 573.96783 | AA7: =+W7+V7+X7+Y7+Z7 -> 0 | AB7: =+U7-AA7 -> 573.96783 | AF7: =+AB7-AC7-AD7-AE7 -> 573.96783
A8: =A7+1 -> 4 | B8: JATIVA REINA LUIS ENRIQUE | C8: =IF(L8>=401.41,401.41,IF(L8<401.41,L8)) -> 401.41 | D8: =+L8-C8 -> 195.22121 | E8: =+C8/13.3803 -> 30.000075 | F8: =+'TALLER ACTIVOS'!BF10 -> 415.95953 | G8: =+[1]TALLER!BB10 -> 0 | H8: =+'TALLER ACTIVOS'!CX10 -> 180.67168 | I8: =+[1]TALLER!CT10 -> 0 | L8: =+F8+G8+H8+I8+K8+J8 -> 596.63121 | M8: =IF(L8>=401.41,37.933,IF(L8<401.41,L8*9.45%)) -> 37.933 | N8: =+L8-M8 -> 558.69821 | O8: =IF(E8>=30,33.45,IF(E8<30,E8*1.115)) -> 33.45 | P8: =IF(E8>=30,33.33,IF(E8<30,E8*1.111)) -> 33.33 | Q8: =+O8+P8 -> 66.78 | R8: =33.45/30*E8 -> 33.450083 | U8: =N8+Q8+R8+S8+T8 -> 658.92829 | AA8: =+W8+V8+X8+Y8+Z8 -> 0 | AB8: =+U8-AA8 -> 658.92829 | AF8: =+AB8-AC8-AD8-AE8 -> 658.92829
A9: =A8+1 -> 5 | B9: FERNANDEZ RISCO ALEX BLADIMIR | C9: =IF(L9>=401.41,401.41,IF(L9<401.41,L9)) -> 401.41 | D9: =+L9-C9 -> 184.20984 | E9: =+C9/13.3803 -> 30.000075 | F9: =+'TALLER ACTIVOS'!BF11 -> 416.88156 | G9: =+[1]TALLER!BB11 -> 0 | H9: =+'TALLER ACTIVOS'!CX11 -> 168.73828 | I9: =+[1]TALLER!CT11 -> 0 | L9: =+F9+G9+H9+I9+K9+J9 -> 585.61984 | M9: =IF(L9>=401.41,37.933,IF(L9<401.41,L9*9.45%)) -> 37.933 | N9: =+L9-M9 -> 547.68684 | O9: =IF(E9>=30,33.45,IF(E9<30,E9*1.115)) -> 33.45 | P9: =IF(E9>=30,33.33,IF(E9<30,E9*1.111)) -> 33.33 | Q9: =+O9+P9 -> 66.78 | R9: =33.45/30*E9 -> 33.450083 | U9: =N9+Q9+R9+S9+T9 -> 647.91692 | AA9: =+W9+V9+X9+Y9+Z9 -> 0 | AB9: =+U9-AA9 -> 647.91692 | AF9: =+AB9-AC9-AD9-AE9 -> 647.91692
A10: =A9+1 -> 6 | B10: LOOR TONATO JESUS MANUEL | C10: =IF(L10>=401.41,401.41,IF(L10<401.41,L10)) -> 401.41 | D10: =+L10-C10 -> 131.67328 | E10: =+C10/13.3803 -> 30.000075 | F10: =+'TALLER ACTIVOS'!BF12 -> 365.44755 | G10: =+[1]TALLER!BB12 -> 0 | H10: =+'TALLER ACTIVOS'!CX12 -> 167.63573 | I10: =+[1]TALLER!CT12 -> 0 | L10: =+F10+G10+H10+I10+K10+J10 -> 533.08328 | M10: =IF(L10>=401.41,37.933,IF(L10<401.41,L10*9.45%)) -> 37.933 | N10: =+L10-M10 -> 495.15028 | O10: =IF(E10>=30,33.45,IF(E10<30,E10*1.115)) -> 33.45 | P10: =IF(E10>=30,33.33,IF(E10<30,E10*1.111)) -> 33.33 | Q10: =+O10+P10 -> 66.78 | R10: =33.45/30*E10 -> 33.450083 | U10: =N10+Q10+R10+S10+T10 -> 595.38037 | AA10: =+W10+V10+X10+Y10+Z10 -> 0 | AB10: =+U10-AA10 -> 595.38037 | AF10: =+AB10-AC10-AD10-AE10 -> 595.38037
A11: =A10+1 -> 7 | B11: HERRERA PEÑARRIETA ARIEL GABRIEL | C11: =IF(L11>=401.41,401.41,IF(L11<401.41,L11)) -> 401.41 | D11: =+L11-C11 -> 196.59178 | E11: =+C11/13.3803 -> 30.000075 | F11: =+'TALLER ACTIVOS'!BF13 -> 416.51127 | G11: =+[1]TALLER!BB13 -> 0 | H11: =+'TALLER ACTIVOS'!CX13 -> 181.49052 | I11: =+[1]TALLER!CT13 -> 0 | L11: =+F11+G11+H11+I11+K11+J11 -> 598.00178 | M11: =IF(L11>=401.41,37.933,IF(L11<401.41,L11*9.45%)) -> 37.933 | N11: =+L11-M11 -> 560.06878 | O11: =IF(E11>=30,33.45,IF(E11<30,E11*1.115)) -> 33.45 | P11: =IF(E11>=30,33.33,IF(E11<30,E11*1.111)) -> 33.33 | Q11: =+O11+P11 -> 66.78 | R11: =33.45/30*E11 -> 33.450083 | U11: =N11+Q11+R11+S11+T11 -> 660.29887 | AA11: =+W11+V11+X11+Y11+Z11 -> 0 | AB11: =+U11-AA11 -> 660.29887 | AF11: =+AB11-AC11-AD11-AE11 -> 660.29887
A12: =A11+1 -> 8 | B12: SANCHEZ TES JUAN CARLOS | C12: =IF(L12>=401.41,401.41,IF(L12<401.41,L12)) -> 401.41 | D12: =+L12-C12 -> 89.639273 | E12: =+C12/13.3803 -> 30.000075 | F12: =+'TALLER ACTIVOS'!BF14 -> 379.64569 | G12: =+[1]TALLER!BB16 -> 0 | H12: =+'TALLER ACTIVOS'!CX14 -> 111.40358 | I12: =+[1]TALLER!CT16 -> 0 | L12: =+F12+G12+H12+I12+K12+J12 -> 491.04927 | M12: =IF(L12>=401.41,37.933,IF(L12<401.41,L12*9.45%)) -> 37.933 | N12: =+L12-M12 -> 453.11627 | O12: =IF(E12>=30,33.45,IF(E12<30,E12*1.115)) -> 33.45 | P12: =IF(E12>=30,33.33,IF(E12<30,E12*1.111)) -> 33.33 | Q12: =+O12+P12 -> 66.78 | R12: =33.45/30*E12 -> 33.450083 | U12: =N12+Q12+R12+S12+T12 -> 553.34636 | AA12: =+W12+V12+X12+Y12+Z12 -> 0 | AB12: =+U12-AA12 -> 553.34636 | AF12: =+AB12-AC12-AD12-AE12 -> 553.34636
A13: =A12+1 -> 9 | B13: VERA SALDARRIAGA EDISON ADOLFO | C13: =IF(L13>=401.41,401.41,IF(L13<401.41,L13)) -> 401.41 | D13: =+L13-C13 -> 114.52123 | E13: =+C13/13.3803 -> 30.000075 | F13: =+'TALLER ACTIVOS'!BF15 -> 381.99346 | G13: =+[1]TALLER!BB19 -> 0 | H13: =+'TALLER ACTIVOS'!CX15 -> 133.93777 | I13: =+[1]TALLER!CT10 -> 0 | L13: =+F13+G13+H13+I13+K13+J13 -> 515.93123 | M13: =IF(L13>=401.41,37.933,IF(L13<401.41,L13*9.45%)) -> 37.933 | N13: =+L13-M13 -> 477.99823 | O13: =IF(E13>=30,33.45,IF(E13<30,E13*1.115)) -> 33.45 | P13: =IF(E13>=30,33.33,IF(E13<30,E13*1.111)) -> 33.33 | Q13: =+O13+P13 -> 66.78 | U13: =N13+Q13+R13+S13+T13 -> 544.77823 | AA13: =+W13+V13+X13+Y13+Z13 -> 0 | AB13: =+U13-AA13 -> 544.77823 | AF13: =+AB13-AC13-AD13-AE13 -> 544.77823
A14: DESVINCULADOS
A15: =A13+1 -> 10 | B15: CEVALLOS RODRIGUEZ EVER LEONEL | C15: =IF(L15>=401.41,401.41,IF(L15<401.41,L15)) -> 401.41 | D15: =+L15-C15 -> 99.473403 | E15: =+C15/13.3803 -> 30.000075 | F15: =+'TALLER RETIRADOS'!BF7 -> 343.44812 | G15: =+[1]TALLER!BB20 -> 0 | H15: =+'TALLER RETIRADOS'!CX7 -> 157.43529 | I15: =+[1]TALLER!CT11 -> 0 | L15: =+F15+G15+H15+I15+K15+J15 -> 500.8834 | M15: =IF(L15>=401.41,37.933,IF(L15<401.41,L15*9.45%)) -> 37.933 | N15: =+L15-M15 -> 462.9504 | O15: =IF(E15>=30,33.45,IF(E15<30,E15*1.115)) -> 33.45 | P15: =IF(E15>=30,33.33,IF(E15<30,E15*1.111)) -> 33.33 | Q15: =+O15+P15 -> 66.78 | U15: =N15+Q15+R15+S15+T15 -> 529.7304 | V15: 529.7304 | AA15: =+W15+V15+X15+Y15+Z15 -> 529.7304 | AB15: =+U15-AA15 -> 0 | AF15: =+AB15-AC15-AD15-AE15 -> 0
A16: =A15+1 -> 11 | B16: CEVALLOS RODRIGUEZ JOSE VINICIO | C16: =IF(L16>=401.41,401.41,IF(L16<401.41,L16)) -> 401.41 | D16: =+L16-C16 -> 84.43436 | E16: =+C16/13.3803 -> 30.000075 | F16: =+'TALLER RETIRADOS'!BF8 -> 351.90659 | G16: =+[1]TALLER!BB21 -> 0 | H16: =+'TALLER RETIRADOS'!CX8 -> 133.93777 | I16: =+[1]TALLER!CT12 -> 0 | L16: =+F16+G16+H16+I16+K16+J16 -> 485.84436 | M16: =IF(L16>=401.41,37.933,IF(L16<401.41,L16*9.45%)) -> 37.933 | N16: =+L16-M16 -> 447.91136 | O16: =IF(E16>=30,33.45,IF(E16<30,E16*1.115)) -> 33.45 | P16: =IF(E16>=30,33.33,IF(E16<30,E16*1.111)) -> 33.33 | Q16: =+O16+P16 -> 66.78 | U16: =N16+Q16+R16+S16+T16 -> 514.69136 | V16: 514.69136 | AA16: =+W16+V16+X16+Y16+Z16 -> 514.69136 | AB16: =+U16-AA16 -> 0 | AF16: =+AB16-AC16-AD16-AE16 -> 0
A17: =A16+1 -> 12 | B17: GARCIA VERA EGDO BRYAN | C17: =IF(L17>=401.41,401.41,IF(L17<401.41,L17)) -> 401.41 | D17: =+L17-C17 -> 96.798315 | E17: =+C17/13.3803 -> 30.000075 | F17: =+'TALLER RETIRADOS'!BF9 -> 340.77303 | G17: =+[1]TALLER!BB15 -> 0 | H17: =+'TALLER RETIRADOS'!CX9 -> 157.43529 | I17: =+[1]TALLER!CT15 -> 0 | L17: =+F17+G17+H17+I17+K17+J17 -> 498.20832 | M17: =IF(L17>=401.41,37.933,IF(L17<401.41,L17*9.45%)) -> 37.933 | N17: =+L17-M17 -> 460.27532 | O17: =IF(E17>=30,33.45,IF(E17<30,E17*1.115)) -> 33.45 | P17: =IF(E17>=30,33.33,IF(E17<30,E17*1.111)) -> 33.33 | Q17: =+O17+P17 -> 66.78 | R17: =33.45/30*E17 -> 33.450083 | U17: =N17+Q17+R17+S17+T17 -> 560.5054 | V17: 560.5054 | AA17: =+W17+V17+X17+Y17+Z17 -> 560.5054 | AB17: =+U17-AA17 -> 0 | AF17: =+AB17-AC17-AD17-AE17 -> 0
A18: =A17+1 -> 13 | B18: MENDOZA ROSADO ANTENOR ALBERTO | C18: =IF(L18>=401.41,401.41,IF(L18<401.41,L18)) -> 401.41 | D18: =+L18-C18 -> 99.223695 | E18: =+C18/13.3803 -> 30.000075 | F18: =+'TALLER RETIRADOS'!BF10 -> 339.66244 | G18: =+[1]TALLER!BB23 -> 0 | H18: =+'TALLER RETIRADOS'!CX10 -> 160.97126 | I18: =+[1]TALLER!CT16 -> 0 | L18: =+F18+G18+H18+I18+K18+J18 -> 500.63369 | M18: =IF(L18>=401.41,37.933,IF(L18<401.41,L18*9.45%)) -> 37.933 | N18: =+L18-M18 -> 462.70069 | O18: =IF(E18>=30,33.45,IF(E18<30,E18*1.115)) -> 33.45 | P18: =IF(E18>=30,33.33,IF(E18<30,E18*1.111)) -> 33.33 | Q18: =+O18+P18 -> 66.78 | R18: =33.45/30*E18 -> 33.450083 | U18: =N18+Q18+R18+S18+T18 -> 562.93078 | V18: 562.93078 | AA18: =+W18+V18+X18+Y18+Z18 -> 562.93078 | AB18: =+U18-AA18 -> 0 | AF18: =+AB18-AC18-AD18-AE18 -> 0
A19: =A18+1 -> 14 | B19: ACOSTA ZAMBRANO EFFREN EULICE | C19: =IF(L19>=401.41,401.41,IF(L19<401.41,L19)) -> 401.41 | D19: =+L19-C19 -> 182.8242 | E19: =+C19/13.3803 -> 30.000075 | F19: =+'TALLER RETIRADOS'!BF77 -> 321.34295 | G19: =+[1]TALLER!BB18 -> 0 | H19: ='TALLER RETIRADOS'!CX77+'TALLER RETIRADOS'!DC77 -> 262.89125 | I19: =+[1]TALLER!CT17 -> 0 | L19: =+F19+G19+H19+I19+K19+J19 -> 584.2342 | M19: =IF(L19>=401.41,37.933,IF(L19<401.41,L19*9.45%)) -> 37.933 | N19: =+L19-M19 -> 546.3012 | O19: =IF(E19>=30,33.45,IF(E19<30,E19*1.115)) -> 33.45 | P19: =IF(E19>=30,33.33,IF(E19<30,E19*1.111)) -> 33.33 | Q19: =+O19+P19 -> 66.78 | R19: =33.45/30*E19 -> 33.450083 | U19: =N19+Q19+R19+S19+T19 -> 646.53129 | V19: 646.53129 | AA19: =+W19+V19+X19+Y19+Z19 -> 646.53129 | AB19: =+U19-AA19 -> 0 | AF19: =+AB19-AC19-AD19-AE19 -> 0
A20: =A19+1 -> 15 | B20: ALCIVAR CEDEÑO CALIXTO PRIMITIVO | C20: =IF(L20>=401.41,401.41,IF(L20<401.41,L20)) -> 401.41 | D20: =+L20-C20 -> 189.88416 | E20: =+C20/13.3803 -> 30.000075 | F20: =+'TALLER RETIRADOS'!BF78 -> 379.64569 | G20: =+[1]TALLER!BB14 -> 0 | H20: ='TALLER RETIRADOS'!CX78+'TALLER RETIRADOS'!DC78 -> 211.64847 | I20: =+[1]TALLER!CT18 -> 0 | L20: =+F20+G20+H20+I20+K20+J20 -> 591.29416 | M20: =IF(L20>=401.41,37.933,IF(L20<401.41,L20*9.45%)) -> 37.933 | N20: =+L20-M20 -> 553.36116 | O20: =IF(E20>=30,33.45,IF(E20<30,E20*1.115)) -> 33.45 | P20: =IF(E20>=30,33.33,IF(E20<30,E20*1.111)) -> 33.33 | Q20: =+O20+P20 -> 66.78 | R20: =33.45/30*E20 -> 33.450083 | U20: =N20+Q20+R20+S20+T20 -> 653.59124 | V20: 653.59124 | AA20: =+W20+V20+X20+Y20+Z20 -> 653.59124 | AB20: =+U20-AA20 -> 0 | AF20: =+AB20-AC20-AD20-AE20 -> 0
A21: 16 | B21: CRUZATTE MUÑOZ PEDRO ANTONIO | C21: =IF(L21>=401.41,401.41,IF(L21<401.41,L21)) -> 401.41 | D21: =+L21-C21 -> 194.89029 | E21: =+C21/13.3803 -> 30.000075 | F21: =+'TALLER RETIRADOS'!BF79 -> 356.94754 | G21: =+[1]TALLER!BB22 -> 0 | H21: ='TALLER RETIRADOS'!CX79+'TALLER RETIRADOS'!DC79 -> 239.35274 | I21: =+[1]TALLER!CT19 -> 0 | L21: =+F21+G21+H21+I21+K21+J21 -> 596.30029 | M21: =IF(L21>=401.41,37.933,IF(L21<401.41,L21*9.45%)) -> 37.933 | N21: =+L21-M21 -> 558.36729 | O21: =IF(E21>=30,33.45,IF(E21<30,E21*1.115)) -> 33.45 | P21: =IF(E21>=30,33.33,IF(E21<30,E21*1.111)) -> 33.33 | Q21: =+O21+P21 -> 66.78 | R21: =33.45/30*E21 -> 33.450083 | U21: =N21+Q21+R21+S21+T21 -> 658.59737 | V21: 658.59737 | AA21: =+W21+V21+X21+Y21+Z21 -> 658.59737 | AB21: =+U21-AA21 -> 0 | AF21: =+AB21-AC21-AD21-AE21 -> 0
A22: =A21+1 -> 17 | B22: LUDEÑA MORALES SANTOS NARCISO | C22: =IF(L22>=401.41,401.41,IF(L22<401.41,L22)) -> 401.41 | D22: =+L22-C22 -> 193.01323 | E22: =+C22/13.3803 -> 30.000075 | F22: =+'TALLER RETIRADOS'!BF80 -> 377.90637 | G22: =+[1]TALLER!BB17 -> 0 | H22: ='TALLER RETIRADOS'!CX80+'TALLER RETIRADOS'!DC80 -> 216.51687 | I22: =+[1]TALLER!CT20 -> 0 | L22: =+F22+G22+H22+I22+K22+J22 -> 594.42323 | M22: =IF(L22>=401.41,37.933,IF(L22<401.41,L22*9.45%)) -> 37.933 | N22: =+L22-M22 -> 556.49023 | O22: =IF(E22>=30,33.45,IF(E22<30,E22*1.115)) -> 33.45 | P22: =IF(E22>=30,33.33,IF(E22<30,E22*1.111)) -> 33.33 | Q22: =+O22+P22 -> 66.78 | R22: =33.45/30*E22 -> 33.450083 | U22: =N22+Q22+R22+S22+T22 -> 656.72032 | V22: 656.72032 | AA22: =+W22+V22+X22+Y22+Z22 -> 656.72032 | AB22: =+U22-AA22 -> 0 | AF22: =+AB22-AC22-AD22-AE22 -> 0
A23: ÀREA DE SIERRA DE MESA O CANTEADORA
A24: =A22+1 -> 18 | B24: PACHECO MONTOYA JENIFFER KATHERINE | C24: =IF(L24>=401.41,401.41,IF(L24<401.41,L24)) -> 401.41 | D24: =+L24-C24 -> 98.617095 | E24: =+C24/13.3803 -> 30.000075 | F24: =+'TALLER ACTIVOS'!BF19 -> 326.43248 | G24: 0 | H24: =+'TALLER ACTIVOS'!CX19 -> 173.59461 | I24: 0 | L24: =+F24+G24+H24+I24+K24+J24 -> 500.0271 | M24: =IF(L24>=401.41,37.933,IF(L24<401.41,L24*9.45%)) -> 37.933 | N24: =+L24-M24 -> 462.0941 | O24: =IF(E24>=30,33.45,IF(E24<30,E24*1.115)) -> 33.45 | P24: =IF(E24>=30,33.33,IF(E24<30,E24*1.111)) -> 33.33 | Q24: =+O24+P24 -> 66.78 | U24: =N24+Q24+R24+S24+T24 -> 528.8741 | AA24: =+W24+V24+X24+Y24+Z24 -> 0 | AB24: =+U24-AA24 -> 528.8741 | AF24: =+AB24-AC24-AD24-AE24 -> 528.8741
A25: =A24+1 -> 19 | B25: RUIZ MAYOR ENRIQUE GABRIEL | C25: =IF(L25>=401.41,401.41,IF(L25<401.41,L25)) -> 401.41 | D25: =+L25-C25 -> 38.893759 | E25: =+C25/13.3803 -> 30.000075 | F25: =+'TALLER ACTIVOS'!BF20 -> 314 | G25: 0 | H25: =+'TALLER ACTIVOS'!CX20 -> 126.30376 | I25: 0 | L25: =+F25+G25+H25+I25+K25+J25 -> 440.30376 | M25: =IF(L25>=401.41,37.933,IF(L25<401.41,L25*9.45%)) -> 37.933 | N25: =+L25-M25 -> 402.37076 | O25: =IF(E25>=30,33.45,IF(E25<30,E25*1.115)) -> 33.45 | P25: =IF(E25>=30,33.33,IF(E25<30,E25*1.111)) -> 33.33 | Q25: =+O25+P25 -> 66.78 | U25: =N25+Q25+R25+S25+T25 -> 469.15076 | Z25: 77.04 | AA25: =+W25+V25+X25+Y25+Z25 -> 77.04 | AB25: =+U25-AA25 -> 392.11076 | AF25: =+AB25-AC25-AD25-AE25 -> 392.11076
A26: =A25+1 -> 20 | B26: VALENCIA ORTEGA JORGE LUIS | C26: =IF(L26>=401.41,401.41,IF(L26<401.41,L26)) -> 401.41 | D26: =+L26-C26 -> 117.66716 | E26: =+C26/13.3803 -> 30.000075 | F26: =+'TALLER ACTIVOS'!BF21 -> 314 | G26: 0 | H26: =+'TALLER ACTIVOS'!CX21 -> 205.07716 | I26: 0 | L26: =+F26+G26+H26+I26+K26+J26 -> 519.07716 | M26: =IF(L26>=401.41,37.933,IF(L26<401.41,L26*9.45%)) -> 37.933 | N26: =+L26-M26 -> 481.14416 | O26: =IF(E26>=30,33.45,IF(E26<30,E26*1.115)) -> 33.45 | P26: =IF(E26>=30,33.33,IF(E26<30,E26*1.111)) -> 33.33 | Q26: =+O26+P26 -> 66.78 | R26: =33.45/30*E26 -> 33.450083 | U26: =N26+Q26+R26+S26+T26 -> 581.37425 | AA26: =+W26+V26+X26+Y26+Z26 -> 0 | AB26: =+U26-AA26 -> 581.37425 | AF26: =+AB26-AC26-AD26-AE26 -> 581.37425
A27: =A26+1 -> 21 | B27: BARREIRO VELEZ CRISTHIAN GEOVANNY | C27: =IF(L27>=401.41,401.41,IF(L27<401.41,L27)) -> 401.41 | D27: =+L27-C27 -> 234.11507 | E27: =+C27/13.3803 -> 30.000075 | F27: =+'TALLER ACTIVOS'!BF22 -> 402.90766 | G27: 0 | H27: =+'TALLER ACTIVOS'!CX22 -> 232.61741 | I27: 0 | L27: =+F27+G27+H27+I27+K27+J27 -> 635.52507 | M27: =IF(L27>=401.41,37.933,IF(L27<401.41,L27*9.45%)) -> 37.933 | N27: =+L27-M27 -> 597.59207 | O27: =IF(E27>=30,33.45,IF(E27<30,E27*1.115)) -> 33.45 | P27: =IF(E27>=30,33.33,IF(E27<30,E27*1.111)) -> 33.33 | Q27: =+O27+P27 -> 66.78 | R27: =33.45/30*E27 -> 33.450083 | U27: =N27+Q27+R27+S27+T27 -> 697.82215 | AA27: =+W27+V27+X27+Y27+Z27 -> 0 | AB27: =+U27-AA27 -> 697.82215 | AF27: =+AB27-AC27-AD27-AE27 -> 697.82215
A28: =A27+1 -> 22 | B28: ZAMBRANO VARGAS YORDI EMEREGILDO | C28: =IF(L28>=401.41,401.41,IF(L28<401.41,L28)) -> 401.41 | D28: =+L28-C28 -> 199.59194 | E28: =+C28/13.3803 -> 30.000075 | F28: =+'TALLER ACTIVOS'!BF23 -> 394.18846 | G28: 0 | H28: =+'TALLER ACTIVOS'!CX23 -> 206.81348 | I28: 0 | L28: =+F28+G28+H28+I28+K28+J28 -> 601.00194 | M28: =IF(L28>=401.41,37.933,IF(L28<401.41,L28*9.45%)) -> 37.933 | N28: =+L28-M28 -> 563.06894 | O28: =IF(E28>=30,33.45,IF(E28<30,E28*1.115)) -> 33.45 | P28: =IF(E28>=30,33.33,IF(E28<30,E28*1.111)) -> 33.33 | Q28: =+O28+P28 -> 66.78 | R28: =33.45/30*E28 -> 33.450083 | U28: =N28+Q28+R28+S28+T28 -> 663.29902 | AA28: =+W28+V28+X28+Y28+Z28 -> 0 | AB28: =+U28-AA28 -> 663.29902 | AF28: =+AB28-AC28-AD28-AE28 -> 663.29902
A29: =A28+1 -> 23 | B29: ZAMBRANO ROSADO SOFIA LUCIOLA | C29: =IF(L29>=401.41,401.41,IF(L29<401.41,L29)) -> 401.41 | D29: =+L29-C29 -> 308.66551 | E29: =+C29/13.3803 -> 30.000075 | F29: =+'TALLER ACTIVOS'!BF24 -> 432.73997 | G29: 0 | H29: =+'TALLER ACTIVOS'!CX24 -> 277.33554 | I29: 0 | L29: =+F29+G29+H29+I29+K29+J29 -> 710.07551 | M29: =IF(L29>=401.41,37.933,IF(L29<401.41,L29*9.45%)) -> 37.933 | N29: =+L29-M29 -> 672.14251 | O29: =IF(E29>=30,33.45,IF(E29<30,E29*1.115)) -> 33.45 | P29: =IF(E29>=30,33.33,IF(E29<30,E29*1.111)) -> 33.33 | Q29: =+O29+P29 -> 66.78 | U29: =N29+Q29+R29+S29+T29 -> 738.92251 | AA29: =+W29+V29+X29+Y29+Z29 -> 0 | AB29: =+U29-AA29 -> 738.92251 | AF29: =+AB29-AC29-AD29-AE29 -> 738.92251
A30: =A29+1 -> 24 | B30: MANZABA BRAVO LIDER ANTONIO | C30: =IF(L30>=401.41,401.41,IF(L30<401.41,L30)) -> 401.41 | D30: =+L30-C30 -> 14.641908 | E30: =+C30/13.3803 -> 30.000075 | F30: =+'TALLER ACTIVOS'!BF25 -> 260 | G30: 0 | H30: =+'TALLER ACTIVOS'!CX25 -> 156.05191 | I30: 0 | L30: =+F30+G30+H30+I30+K30+J30 -> 416.05191 | M30: =IF(L30>=401.41,37.933,IF(L30<401.41,L30*9.45%)) -> 37.933 | N30: =+L30-M30 -> 378.11891 | O30: =IF(E30>=30,33.45,IF(E30<30,E30*1.115)) -> 33.45 | P30: =IF(E30>=30,33.33,IF(E30<30,E30*1.111)) -> 33.33 | Q30: =+O30+P30 -> 66.78 | R30: =33.45/30*E30 -> 33.450083 | U30: =N30+Q30+R30+S30+T30 -> 478.34899 | AA30: =+W30+V30+X30+Y30+Z30 -> 0 | AB30: =+U30-AA30 -> 478.34899 | AF30: =+AB30-AC30-AD30-AE30 -> 478.34899
A31: =A30+1 -> 25 | B31: BAZURTO PARRAGA JUBER JAIR | C31: =IF(L31>=401.41,401.41,IF(L31<401.41,L31)) -> 401.41 | D31: =+L31-C31 -> 209.93919 | E31: =+C31/13.3803 -> 30.000075 | F31: =+'TALLER ACTIVOS'!BF26 -> 475.7927 | G31: 0 | H31: =+'TALLER ACTIVOS'!CX26 -> 135.55649 | I31: 0 | L31: =+F31+G31+H31+I31+K31+J31 -> 611.34919 | M31: =IF(L31>=401.41,37.933,IF(L31<401.41,L31*9.45%)) -> 37.933 | N31: =+L31-M31 -> 573.41619 | O31: =IF(E31>=30,33.45,IF(E31<30,E31*1.115)) -> 33.45 | P31: =IF(E31>=30,33.33,IF(E31<30,E31*1.111)) -> 33.33 | Q31: =+O31+P31 -> 66.78 | R31: =33.45/30*E31 -> 33.450083 | U31: =N31+Q31+R31+S31+T31 -> 673.64627 | AA31: =+W31+V31+X31+Y31+Z31 -> 0 | AB31: =+U31-AA31 -> 673.64627 | AF31: =+AB31-AC31-AD31-AE31 -> 673.64627
A32: =A31+1 -> 26 | B32: VIVAS MACIAS LISBETH ALEXANDRA | C32: =IF(L32>=401.41,401.41,IF(L32<401.41,L32)) -> 401.41 | D32: =+L32-C32 -> 39.693156 | E32: =+C32/13.3803 -> 30.000075 | F32: =+'TALLER ACTIVOS'!BF27 -> 348.27059 | G32: 0 | H32: =+'TALLER ACTIVOS'!CX27 -> 92.832563 | I32: 0 | L32: =+F32+G32+H32+I32+K32+J32 -> 441.10316 | M32: =IF(L32>=401.41,37.933,IF(L32<401.41,L32*9.45%)) -> 37.933 | N32: =+L32-M32 -> 403.17016 | O32: =IF(E32>=30,33.45,IF(E32<30,E32*1.115)) -> 33.45 | P32: =IF(E32>=30,33.33,IF(E32<30,E32*1.111)) -> 33.33 | Q32: =+O32+P32 -> 66.78 | R32: =33.45/30*E32 -> 33.450083 | U32: =N32+Q32+R32+S32+T32 -> 503.40024 | AA32: =+W32+V32+X32+Y32+Z32 -> 0 | AB32: =+U32-AA32 -> 503.40024 | AF32: =+AB32-AC32-AD32-AE32 -> 503.40024
A33: =A32+1 -> 27 | B33: PILOSO MANZABA YORGEN JAVIER | C33: =IF(L33>=401.41,401.41,IF(L33<401.41,L33)) -> 401.41 | D33: =+L33-C33 -> 187.09408 | E33: =+C33/13.3803 -> 30.000075 | F33: =+'TALLER ACTIVOS'!BF28 -> 375.49479 | G33: 0 | H33: =+'TALLER ACTIVOS'!CX28 -> 213.00929 | I33: 0 | L33: =+F33+G33+H33+I33+K33+J33 -> 588.50408 | M33: =IF(L33>=401.41,37.933,IF(L33<401.41,L33*9.45%)) -> 37.933 | N33: =+L33-M33 -> 550.57108 | O33: =IF(E33>=30,33.45,IF(E33<30,E33*1.115)) -> 33.45 | P33: =IF(E33>=30,33.33,IF(E33<30,E33*1.111)) -> 33.33 | Q33: =+O33+P33 -> 66.78 | R33: =33.45/30*E33 -> 33.450083 | U33: =N33+Q33+R33+S33+T33 -> 650.80116 | Z33: 49.87 | AA33: =+W33+V33+X33+Y33+Z33 -> 49.87 | AB33: =+U33-AA33 -> 600.93116 | AF33: =+AB33-AC33-AD33-AE33 -> 600.93116
A34: =A33+1 -> 28 | B34: ALVARADO MACIAS KAREN ELIZABETH | C34: =IF(L34>=401.41,401.41,IF(L34<401.41,L34)) -> 401.41 | D34: =+L34-C34 -> 101.13433 | E34: =+C34/13.3803 -> 30.000075 | F34: =+'TALLER ACTIVOS'!BF29 -> 254.63615 | G34: 0 | H34: =+'TALLER ACTIVOS'!CX29 -> 227.83818 | I34: 0 | J34: =13.38*3*50% -> 20.07 | L34: =+F34+G34+H34+I34+K34+J34 -> 502.54433 | M34: =IF(L34>=401.41,37.933,IF(L34<401.41,L34*9.45%)) -> 37.933 | N34: =+L34-M34 -> 464.61133 | O34: =IF(E34>=30,33.45,IF(E34<30,E34*1.115)) -> 33.45 | P34: =IF(E34>=30,33.33,IF(E34<30,E34*1.111)) -> 33.33 | Q34: =+O34+P34 -> 66.78 | R34: =33.45/30*E34 -> 33.450083 | U34: =N34+Q34+R34+S34+T34 -> 564.84141 | Z34: 23.36 | AA34: =+W34+V34+X34+Y34+Z34 -> 23.36 | AB34: =+U34-AA34 -> 541.48141 | AF34: =+AB34-AC34-AD34-AE34 -> 541.48141
A35: =A34+1 -> 29 | B35: NAVARRETE ALCIVAR BYRON ANDRES | C35: =IF(L35>=401.41,401.41,IF(L35<401.41,L35)) -> 401.41 | D35: =+L35-C35 -> 233.21661 | E35: =+C35/13.3803 -> 30.000075 | F35: =+'TALLER ACTIVOS'!BF30 -> 403.39775 | G35: 0 | H35: =+'TALLER ACTIVOS'!CX30 -> 231.22886 | I35: 0 | L35: =+F35+G35+H35+I35+K35+J35 -> 634.62661 | M35: =IF(L35>=401.41,37.933,IF(L35<401.41,L35*9.45%)) -> 37.933 | N35: =+L35-M35 -> 596.69361 | O35: =IF(E35>=30,33.45,IF(E35<30,E35*1.115)) -> 33.45 | P35: =IF(E35>=30,33.33,IF(E35<30,E35*1.111)) -> 33.33 | Q35: =+O35+P35 -> 66.78 | R35: =33.45/30*E35 -> 33.450083 | U35: =N35+Q35+R35+S35+T35 -> 696.9237 | AA35: =+W35+V35+X35+Y35+Z35 -> 0 | AB35: =+U35-AA35 -> 696.9237 | AF35: =+AB35-AC35-AD35-AE35 -> 696.9237
A36: =A35+1 -> 30 | B36: CHICA VERA STEVEN MANUEL | C36: =IF(L36>=401.41,401.41,IF(L36<401.41,L36)) -> 401.41 | D36: =+L36-C36 -> 148.01726 | E36: =+C36/13.3803 -> 30.000075 | F36: =+'TALLER ACTIVOS'!BF31 -> 375.76191 | G36: 0 | H36: =+'TALLER ACTIVOS'!CX31 -> 173.66535 | I36: 0 | L36: =+F36+G36+H36+I36+K36+J36 -> 549.42726 | M36: =IF(L36>=401.41,37.933,IF(L36<401.41,L36*9.45%)) -> 37.933 | N36: =+L36-M36 -> 511.49426 | O36: =IF(E36>=30,33.45,IF(E36<30,E36*1.115)) -> 33.45 | P36: =IF(E36>=30,33.33,IF(E36<30,E36*1.111)) -> 33.33 | Q36: =+O36+P36 -> 66.78 | R36: =33.45/30*E36 -> 33.450083 | U36: =N36+Q36+R36+S36+T36 -> 611.72434 | AA36: =+W36+V36+X36+Y36+Z36 -> 0 | AB36: =+U36-AA36 -> 611.72434 | AF36: =+AB36-AC36-AD36-AE36 -> 611.72434
A37: =A36+1 -> 31 | B37: RAMOS CACIQUE MARIA BEATRIZ | C37: =IF(L37>=401.41,401.41,IF(L37<401.41,L37)) -> 401.41 | D37: =+L37-C37 -> 216.13334 | E37: =+C37/13.3803 -> 30.000075 | F37: =+'TALLER ACTIVOS'!BF32 -> 388.28166 | G37: 0 | H37: =+'TALLER ACTIVOS'!CX32 -> 229.26168 | I37: 0 | L37: =+F37+G37+H37+I37+K37+J37 -> 617.54334 | M37: =IF(L37>=401.41,37.933,IF(L37<401.41,L37*9.45%)) -> 37.933 | N37: =+L37-M37 -> 579.61034 | O37: =IF(E37>=30,33.45,IF(E37<30,E37*1.115)) -> 33.45 | P37: =IF(E37>=30,33.33,IF(E37<30,E37*1.111)) -> 33.33 | Q37: =+O37+P37 -> 66.78 | R37: =33.45/30*E37 -> 33.450083 | U37: =N37+Q37+R37+S37+T37 -> 679.84042 | AA37: =+W37+V37+X37+Y37+Z37 -> 0 | AB37: =+U37-AA37 -> 679.84042 | AF37: =+AB37-AC37-AD37-AE37 -> 679.84042
A38: =A37+1 -> 32 | B38: CEDEÑO MUÑOZ HEINER JESUS | C38: =IF(L38>=401.41,401.41,IF(L38<401.41,L38)) -> 401.41 | D38: =+L38-C38 -> 224.01726 | E38: =+C38/13.3803 -> 30.000075 | F38: =+'TALLER ACTIVOS'!BF33 -> 375.76191 | G38: 0 | H38: =+'TALLER ACTIVOS'!CX33 -> 249.66535 | I38: 0 | L38: =+F38+G38+H38+I38+K38+J38 -> 625.42726 | M38: =IF(L38>=401.41,37.933,IF(L38<401.41,L38*9.45%)) -> 37.933 | N38: =+L38-M38 -> 587.49426 | O38: =IF(E38>=30,33.45,IF(E38<30,E38*1.115)) -> 33.45 | P38: =IF(E38>=30,33.33,IF(E38<30,E38*1.111)) -> 33.33 | Q38: =+O38+P38 -> 66.78 | R38: =33.45/30*E38 -> 33.450083 | U38: =N38+Q38+R38+S38+T38 -> 687.72434 | AA38: =+W38+V38+X38+Y38+Z38 -> 0 | AB38: =+U38-AA38 -> 687.72434 | AF38: =+AB38-AC38-AD38-AE38 -> 687.72434
A39: =A38+1 -> 33 | B39: SOLORZANO INTRIAGO JUAN CARLOS | C39: =IF(L39>=401.41,401.41,IF(L39<401.41,L39)) -> 401.41 | D39: =+L39-C39 -> 179.83008 | E39: =+C39/13.3803 -> 30.000075 | F39: =+'TALLER ACTIVOS'!BF34 -> 396.16583 | G39: 0 | H39: =+'TALLER ACTIVOS'!CX34 -> 185.07425 | I39: 0 | L39: =+F39+G39+H39+I39+K39+J39 -> 581.24008 | M39: =IF(L39>=401.41,37.933,IF(L39<401.41,L39*9.45%)) -> 37.933 | N39: =+L39-M39 -> 543.30708 | O39: =IF(E39>=30,33.45,IF(E39<30,E39*1.115)) -> 33.45 | P39: =IF(E39>=30,33.33,IF(E39<30,E39*1.111)) -> 33.33 | Q39: =+O39+P39 -> 66.78 | U39: =N39+Q39+R39+S39+T39 -> 610.08708 | AA39: =+W39+V39+X39+Y39+Z39 -> 0 | AB39: =+U39-AA39 -> 610.08708 | AF39: =+AB39-AC39-AD39-AE39 -> 610.08708
A40: =A39+1 -> 34 | B40: BRAVO LUCAS YANINE MARIUXI | C40: =IF(L40>=401.41,401.41,IF(L40<401.41,L40)) -> 401.41 | D40: =+L40-C40 -> 236.82253 | E40: =+C40/13.3803 -> 30.000075 | F40: =+'TALLER ACTIVOS'!BF35 -> 399.56864 | G40: 0 | H40: =+'TALLER ACTIVOS'!CX35 -> 238.6639 | I40: 0 | L40: =+F40+G40+H40+I40+K40+J40 -> 638.23253 | M40: =IF(L40>=401.41,37.933,IF(L40<401.41,L40*9.45%)) -> 37.933 | N40: =+L40-M40 -> 600.29953 | O40: =IF(E40>=30,33.45,IF(E40<30,E40*1.115)) -> 33.45 | P40: =IF(E40>=30,33.33,IF(E40<30,E40*1.111)) -> 33.33 | Q40: =+O40+P40 -> 66.78 | U40: =N40+Q40+R40+S40+T40 -> 667.07953 | Z40: 57.98 | AA40: =+W40+V40+X40+Y40+Z40 -> 57.98 | AB40: =+U40-AA40 -> 609.09953 | AF40: =+AB40-AC40-AD40-AE40 -> 609.09953
A41: =A40+1 -> 35 | B41: ANDRADE ZAMBRANO JESUS DANIEL | C41: =IF(L41>=401.41,401.41,IF(L41<401.41,L41)) -> 401.41 | D41: =+L41-C41 -> 293.37866 | E41: =+C41/13.3803 -> 30.000075 | F41: =+'TALLER ACTIVOS'!BF36 -> 462.37439 | G41: 0 | H41: =+'TALLER ACTIVOS'!CX36 -> 232.41427 | I41: 0 | L41: =+F41+G41+H41+I41+K41+J41 -> 694.78866 | M41: =IF(L41>=401.41,37.933,IF(L41<401.41,L41*9.45%)) -> 37.933 | N41: =+L41-M41 -> 656.85566 | O41: =IF(E41>=30,33.45,IF(E41<30,E41*1.115)) -> 33.45 | P41: =IF(E41>=30,33.33,IF(E41<30,E41*1.111)) -> 33.33 | Q41: =+O41+P41 -> 66.78 | U41: =N41+Q41+R41+S41+T41 -> 723.63566 | AA41: =+W41+V41+X41+Y41+Z41 -> 0 | AB41: =+U41-AA41 -> 723.63566 | AF41: =+AB41-AC41-AD41-AE41 -> 723.63566
A42: =A41+1 -> 36 | B42: VARELA ANDRADE JIMY FABRICIO | C42: =IF(L42>=401.41,401.41,IF(L42<401.41,L42)) -> 401.41 | D42: =+L42-C42 -> 231.25902 | E42: =+C42/13.3803 -> 30.000075 | F42: =+'TALLER ACTIVOS'!BF37 -> 416.02769 | G42: 0 | H42: =+'TALLER ACTIVOS'!CX37 -> 216.64133 | I42: 0 | L42: =+F42+G42+H42+I42+K42+J42 -> 632.66902 | M42: =IF(L42>=401.41,37.933,IF(L42<401.41,L42*9.45%)) -> 37.933 | N42: =+L42-M42 -> 594.73602 | O42: =IF(E42>=30,33.45,IF(E42<30,E42*1.115)) -> 33.45 | P42: =IF(E42>=30,33.33,IF(E42<30,E42*1.111)) -> 33.33 | Q42: =+O42+P42 -> 66.78 | R42: =33.45/30*E42 -> 33.450083 | U42: =N42+Q42+R42+S42+T42 -> 694.9661 | Z42: 132.27 | AA42: =+W42+V42+X42+Y42+Z42 -> 132.27 | AB42: =+U42-AA42 -> 562.6961 | AF42: =+AB42-AC42-AD42-AE42 -> 562.6961
A43: =A42+1 -> 37 | B43: MURILLO VARGAS MARITZA LILIANA | C43: =IF(L43>=401.41,401.41,IF(L43<401.41,L43)) -> 401.41 | D43: =+L43-C43 -> 299.29202 | E43: =+C43/13.3803 -> 30.000075 | F43: =+'TALLER ACTIVOS'!BF38 -> 451.43432 | G43: 0 | H43: =+'TALLER ACTIVOS'!CX38 -> 249.2677 | I43: 0 | L43: =+F43+G43+H43+I43+K43+J43 -> 700.70202 | M43: =IF(L43>=401.41,37.933,IF(L43<401.41,L43*9.45%)) -> 37.933 | N43: =+L43-M43 -> 662.76902 | O43: =IF(E43>=30,33.45,IF(E43<30,E43*1.115)) -> 33.45 | P43: =IF(E43>=30,33.33,IF(E43<30,E43*1.111)) -> 33.33 | Q43: =+O43+P43 -> 66.78 | R43: =33.45/30*E43 -> 33.450083 | U43: =N43+Q43+R43+S43+T43 -> 762.99911 | V43: 100 | Z43: 100.81 | AA43: =+W43+V43+X43+Y43+Z43 -> 200.81 | AB43: =+U43-AA43 -> 562.18911 | AF43: =+AB43-AC43-AD43-AE43 -> 562.18911
A44: =A43+1 -> 38 | B44: NAPA CEVALLOS FRIXON ARIEL | C44: =IF(L44>=401.41,401.41,IF(L44<401.41,L44)) -> 401.41 | D44: =+L44-C44 -> 67.444432 | E44: =+C44/13.3803 -> 30.000075 | F44: =+'TALLER ACTIVOS'!BF39 -> 320.92109 | G44: 0 | H44: =+'TALLER ACTIVOS'!CX39 -> 147.93335 | I44: 0 | L44: =+F44+G44+H44+I44+K44+J44 -> 468.85443 | M44: =IF(L44>=401.41,37.933,IF(L44<401.41,L44*9.45%)) -> 37.933 | N44: =+L44-M44 -> 430.92143 | O44: =IF(E44>=30,33.45,IF(E44<30,E44*1.115)) -> 33.45 | P44: =IF(E44>=30,33.33,IF(E44<30,E44*1.111)) -> 33.33 | Q44: =+O44+P44 -> 66.78 | R44: =33.45/30*E44 -> 33.450083 | U44: =N44+Q44+R44+S44+T44 -> 531.15152 | AA44: =+W44+V44+X44+Y44+Z44 -> 0 | AB44: =+U44-AA44 -> 531.15152 | AF44: =+AB44-AC44-AD44-AE44 -> 531.15152
A45: =A44+1 -> 39 | B45: ZAMBRANO QUIJIJE LUCIO GASTON | C45: =IF(L45>=401.41,401.41,IF(L45<401.41,L45)) -> 401.41 | D45: =+L45-C45 -> 40.657779 | E45: =+C45/13.3803 -> 30.000075 | F45: =+'TALLER ACTIVOS'!BF40 -> 319.984 | G45: 0 | H45: =+'TALLER ACTIVOS'!CX40 -> 122.08378 | I45: 0 | L45: =+F45+G45+H45+I45+K45+J45 -> 442.06778 | M45: =IF(L45>=401.41,37.933,IF(L45<401.41,L45*9.45%)) -> 37.933 | N45: =+L45-M45 -> 404.13478 | O45: =IF(E45>=30,33.45,IF(E45<30,E45*1.115)) -> 33.45 | P45: =IF(E45>=30,33.33,IF(E45<30,E45*1.111)) -> 33.33 | Q45: =+O45+P45 -> 66.78 | R45: =33.45/30*E45 -> 33.450083 | U45: =N45+Q45+R45+S45+T45 -> 504.36486 | AA45: =+W45+V45+X45+Y45+Z45 -> 0 | AB45: =+U45-AA45 -> 504.36486 | AF45: =+AB45-AC45-AD45-AE45 -> 504.36486
A46: =A45+1 -> 40 | B46: VILLALVA MAZAMBA RAMON OMAR | C46: =IF(L46>=401.41,401.41,IF(L46<401.41,L46)) -> 401.41 | D46: =+L46-C46 -> 272.47254 | E46: =+C46/13.3803 -> 30.000075 | F46: =+'TALLER ACTIVOS'!BF54 -> 492.53651 | G46: 0 | H46: =+'TALLER ACTIVOS'!CX54 -> 181.34603 | I46: 0 | L46: =+F46+G46+H46+I46+K46+J46 -> 673.88254 | M46: =IF(L46>=401.41,37.933,IF(L46<401.41,L46*9.45%)) -> 37.933 | N46: =+L46-M46 -> 635.94954 | O46: =IF(E46>=30,33.45,IF(E46<30,E46*1.115)) -> 33.45 | P46: =IF(E46>=30,33.33,IF(E46<30,E46*1.111)) -> 33.33 | Q46: =+O46+P46 -> 66.78 | R46: =33.45/30*E46 -> 33.450083 | U46: =N46+Q46+R46+S46+T46 -> 736.17962 | AA46: =+W46+V46+X46+Y46+Z46 -> 0 | AB46: =+U46-AA46 -> 736.17962 | AF46: =+AB46-AC46-AD46-AE46 -> 736.17962
A47: =A46+1 -> 41 | B47: ZAMBRANO INTRIAGO ANGEL AGUSTIN | C47: =IF(L47>=401.41,401.41,IF(L47<401.41,L47)) -> 333 | D47: =+L47-C47 -> 0 | E47: =+C47/13.3803 -> 24.887334 | F47: =+'TALLER ACTIVOS'!BF55 -> 225 | G47: 0 | H47: =+'TALLER ACTIVOS'!CX55 -> 108 | I47: 0 | L47: =+F47+G47+H47+I47+K47+J47 -> 333 | M47: =IF(L47>=401.41,37.933,IF(L47<401.41,L47*9.45%)) -> 31.4685 | N47: =+L47-M47 -> 301.5315 | O47: =IF(E47>=30,33.45,IF(E47<30,E47*1.115)) -> 27.749378 | P47: =IF(E47>=30,33.33,IF(E47<30,E47*1.111)) -> 27.649828 | Q47: =+O47+P47 -> 55.399206 | U47: =N47+Q47+R47+S47+T47 -> 356.93071 | AA47: =+W47+V47+X47+Y47+Z47 -> 0 | AB47: =+U47-AA47 -> 356.93071 | AF47: =+AB47-AC47-AD47-AE47 -> 356.93071
A48: =A47+1 -> 42 | B48: ALCIVAR VALENCIA ELIZABETH ESTEFANIA | C48: =IF(L48>=401.41,401.41,IF(L48<401.41,L48)) -> 401.41 | D48: =+L48-C48 -> 204.82222 | E48: =+C48/13.3803 -> 30.000075 | F48: =+'TALLER ACTIVOS'!BF56 -> 376.18912 | G48: 0 | H48: =+'TALLER ACTIVOS'!CX56 -> 230.0431 | I48: 0 | L48: =+F48+G48+H48+I48+K48+J48 -> 606.23222 | M48: =IF(L48>=401.41,37.933,IF(L48<401.41,L48*9.45%)) -> 37.933 | N48: =+L48-M48 -> 568.29922 | O48: =IF(E48>=30,33.45,IF(E48<30,E48*1.115)) -> 33.45 | P48: =IF(E48>=30,33.33,IF(E48<30,E48*1.111)) -> 33.33 | Q48: =+O48+P48 -> 66.78 | R48: =33.45/30*E48 -> 33.450083 | U48: =N48+Q48+R48+S48+T48 -> 668.5293 | Z48: 66.55 | AA48: =+W48+V48+X48+Y48+Z48 -> 66.55 | AB48: =+U48-AA48 -> 601.9793 | AF48: =+AB48-AC48-AD48-AE48 -> 601.9793
A49: =A48+1 -> 43 | B49: ANDRADE ZAMBRANO LUIS ALFREDO | C49: =IF(L49>=401.41,401.41,IF(L49<401.41,L49)) -> 401.41 | D49: =+L49-C49 -> 321.82805 | E49: =+C49/13.3803 -> 30.000075 | F49: =+'TALLER ACTIVOS'!BF57 -> 497.90234 | G49: 0 | H49: =+'TALLER ACTIVOS'!CX57 -> 225.33572 | I49: 0 | L49: =+F49+G49+H49+I49+K49+J49 -> 723.23805 | M49: =IF(L49>=401.41,37.933,IF(L49<401.41,L49*9.45%)) -> 37.933 | N49: =+L49-M49 -> 685.30505 | O49: =IF(E49>=30,33.45,IF(E49<30,E49*1.115)) -> 33.45 | P49: =IF(E49>=30,33.33,IF(E49<30,E49*1.111)) -> 33.33 | Q49: =+O49+P49 -> 66.78 | R49: =33.45/30*E49 -> 33.450083 | U49: =N49+Q49+R49+S49+T49 -> 785.53514 | Z49: 68.75 | AA49: =+W49+V49+X49+Y49+Z49 -> 68.75 | AB49: =+U49-AA49 -> 716.78514 | AF49: =+AB49-AC49-AD49-AE49 -> 716.78514
A50: =A49+1 -> 44 | B50: CORNEJO QUIROZ HOLGER ALADINO | C50: =IF(L50>=401.41,401.41,IF(L50<401.41,L50)) -> 401.41 | D50: =+L50-C50 -> 278.94263 | E50: =+C50/13.3803 -> 30.000075 | F50: =+'TALLER ACTIVOS'!BF58 -> 457.70916 | G50: 0 | H50: =+'TALLER ACTIVOS'!CX58 -> 222.64347 | I50: 0 | L50: =+F50+G50+H50+I50+K50+J50 -> 680.35263 | M50: =IF(L50>=401.41,37.933,IF(L50<401.41,L50*9.45%)) -> 37.933 | N50: =+L50-M50 -> 642.41963 | O50: =IF(E50>=30,33.45,IF(E50<30,E50*1.115)) -> 33.45 | P50: =IF(E50>=30,33.33,IF(E50<30,E50*1.111)) -> 33.33 | Q50: =+O50+P50 -> 66.78 | R50: =33.45/30*E50 -> 33.450083 | U50: =N50+Q50+R50+S50+T50 -> 742.64972 | Z50: 53.18 | AA50: =+W50+V50+X50+Y50+Z50 -> 53.18 | AB50: =+U50-AA50 -> 689.46972 | AF50: =+AB50-AC50-AD50-AE50 -> 689.46972
A51: =A50+1 -> 45 | B51: ESMERALDA GANCHOZO ANGEL MAURICIO | C51: =IF(L51>=401.41,401.41,IF(L51<401.41,L51)) -> 401.41 | D51: =+L51-C51 -> 43.637767 | E51: =+C51/13.3803 -> 30.000075 | F51: =+'TALLER ACTIVOS'!BF59 -> 249.27188 | G51: 0 | H51: =+'TALLER ACTIVOS'!CX59 -> 195.77589 | I51: 0 | L51: =+F51+G51+H51+I51+K51+J51 -> 445.04777 | M51: =IF(L51>=401.41,37.933,IF(L51<401.41,L51*9.45%)) -> 37.933 | N51: =+L51-M51 -> 407.11477 | O51: =IF(E51>=30,33.45,IF(E51<30,E51*1.115)) -> 33.45 | P51: =IF(E51>=30,33.33,IF(E51<30,E51*1.111)) -> 33.33 | Q51: =+O51+P51 -> 66.78 | R51: =33.45/30*E51 -> 33.450083 | U51: =N51+Q51+R51+S51+T51 -> 507.34485 | AA51: =+W51+V51+X51+Y51+Z51 -> 0 | AB51: =+U51-AA51 -> 507.34485 | AF51: =+AB51-AC51-AD51-AE51 -> 507.34485
A52: =A51+1 -> 46 | B52: FARIAS DELGADO JESSENIA JOHANNA | C52: =IF(L52>=401.41,401.41,IF(L52<401.41,L52)) -> 401.41 | D52: =+L52-C52 -> 303.7987 | E52: =+C52/13.3803 -> 30.000075 | F52: =+'TALLER ACTIVOS'!BF60 -> 487.21911 | G52: 0 | H52: =+'TALLER ACTIVOS'!CX60 -> 217.9896 | I52: 0 | L52: =+F52+G52+H52+I52+K52+J52 -> 705.2087 | M52: =IF(L52>=401.41,37.933,IF(L52<401.41,L52*9.45%)) -> 37.933 | N52: =+L52-M52 -> 667.2757 | Q52: =+O52+P52 -> 0 | R52: =33.45/30*E52 -> 33.450083 | U52: =N52+Q52+R52+S52+T52 -> 700.72579 | Z52: 47.92 | AA52: =+W52+V52+X52+Y52+Z52 -> 47.92 | AB52: =+U52-AA52 -> 652.80579 | AF52: =+AB52-AC52-AD52-AE52 -> 652.80579
A53: =A52+1 -> 47 | B53: MACIAS CRUZATTE RAMONA CONCEPCION | C53: =IF(L53>=401.41,401.41,IF(L53<401.41,L53)) -> 401.41 | D53: =+L53-C53 -> 340.75012 | E53: =+C53/13.3803 -> 30.000075 | F53: =+'TALLER ACTIVOS'!BF61 -> 527.06079 | G53: 0 | H53: =+'TALLER ACTIVOS'!CX61 -> 215.09933 | I53: 0 | L53: =+F53+G53+H53+I53+K53+J53 -> 742.16012 | M53: =IF(L53>=401.41,37.933,IF(L53<401.41,L53*9.45%)) -> 37.933 | N53: =+L53-M53 -> 704.22712 | O53: =IF(E53>=30,33.45,IF(E53<30,E53*1.115)) -> 33.45 | P53: =IF(E53>=30,33.33,IF(E53<30,E53*1.111)) -> 33.33 | Q53: =+O53+P53 -> 66.78 | R53: =33.45/30*E53 -> 33.450083 | U53: =N53+Q53+R53+S53+T53 -> 804.4572 | AA53: =+W53+V53+X53+Y53+Z53 -> 0 | AB53: =+U53-AA53 -> 804.4572 | AF53: =+AB53-AC53-AD53-AE53 -> 804.4572
A54: =A53+1 -> 48 | B54: OSTAIZA SOLORZANO UBALDO JAIR | C54: =IF(L54>=401.41,401.41,IF(L54<401.41,L54)) -> 401.41 | D54: =+L54-C54 -> 307.12588 | E54: =+C54/13.3803 -> 30.000075 | F54: =+'TALLER ACTIVOS'!BF62 -> 504.00687 | G54: 0 | H54: =+'TALLER ACTIVOS'!CX62 -> 204.52901 | I54: 0 | L54: =+F54+G54+H54+I54+K54+J54 -> 708.53588 | M54: =IF(L54>=401.41,37.933,IF(L54<401.41,L54*9.45%)) -> 37.933 | N54: =+L54-M54 -> 670.60288 | O54: =IF(E54>=30,33.45,IF(E54<30,E54*1.115)) -> 33.45 | P54: =IF(E54>=30,33.33,IF(E54<30,E54*1.111)) -> 33.33 | Q54: =+O54+P54 -> 66.78 | R54: =33.45/30*E54 -> 33.450083 | U54: =N54+Q54+R54+S54+T54 -> 770.83296 | V54: 100 | AA54: =+W54+V54+X54+Y54+Z54 -> 100 | AB54: =+U54-AA54 -> 670.83296 | AF54: =+AB54-AC54-AD54-AE54 -> 670.83296
A55: =A54+1 -> 49 | B55: SANTOS NAVARRETE LUIS GUSTAVO | C55: =IF(L55>=401.41,401.41,IF(L55<401.41,L55)) -> 401.41 | D55: =+L55-C55 -> 152.99595 | E55: =+C55/13.3803 -> 30.000075 | F55: =+'TALLER ACTIVOS'!BF63 -> 359.24695 | G55: 0 | H55: =+'TALLER ACTIVOS'!CX63 -> 195.15899 | I55: 0 | L55: =+F55+G55+H55+I55+K55+J55 -> 554.40595 | M55: =IF(L55>=401.41,37.933,IF(L55<401.41,L55*9.45%)) -> 37.933 | N55: =+L55-M55 -> 516.47295 | O55: =IF(E55>=30,33.45,IF(E55<30,E55*1.115)) -> 33.45 | P55: =IF(E55>=30,33.33,IF(E55<30,E55*1.111)) -> 33.33 | Q55: =+O55+P55 -> 66.78 | R55: =33.45/30*E55 -> 33.450083 | U55: =N55+Q55+R55+S55+T55 -> 616.70303 | Z55: 88.09 | AA55: =+W55+V55+X55+Y55+Z55 -> 88.09 | AB55: =+U55-AA55 -> 528.61303 | AF55: =+AB55-AC55-AD55-AE55 -> 528.61303
A56: =A55+1 -> 50 | B56: ZAMBRANO REINA NESTOR OCTAVIO | C56: =IF(L56>=401.41,401.41,IF(L56<401.41,L56)) -> 401.41 | D56: =+L56-C56 -> 259.53543 | E56: =+C56/13.3803 -> 30.000075 | F56: =+'TALLER ACTIVOS'!BF64 -> 447.27578 | G56: 0 | H56: =+'TALLER ACTIVOS'!CX64 -> 213.66965 | I56: 0 | L56: =+F56+G56+H56+I56+K56+J56 -> 660.94543 | M56: =IF(L56>=401.41,37.933,IF(L56<401.41,L56*9.45%)) -> 37.933 | N56: =+L56-M56 -> 623.01243 | O56: =IF(E56>=30,33.45,IF(E56<30,E56*1.115)) -> 33.45 | P56: =IF(E56>=30,33.33,IF(E56<30,E56*1.111)) -> 33.33 | Q56: =+O56+P56 -> 66.78 | R56: =33.45/30*E56 -> 33.450083 | U56: =N56+Q56+R56+S56+T56 -> 723.24251 | AA56: =+W56+V56+X56+Y56+Z56 -> 0 | AB56: =+U56-AA56 -> 723.24251 | AF56: =+AB56-AC56-AD56-AE56 -> 723.24251
A57: =A56+1 -> 51 | B57: BARRE MARQUEZ JORGE LUIS | C57: =IF(L57>=401.41,401.41,IF(L57<401.41,L57)) -> 401.41 | D57: =+L57-C57 -> 205.52174 | E57: =+C57/13.3803 -> 30.000075 | F57: =+'TALLER ACTIVOS'!BF65 -> 496.87674 | G57: 0 | H57: =+'TALLER ACTIVOS'!CX65 -> 110.05499 | I57: 0 | L57: =+F57+G57+H57+I57+K57+J57 -> 606.93174 | M57: =IF(L57>=401.41,37.933,IF(L57<401.41,L57*9.45%)) -> 37.933 | N57: =+L57-M57 -> 568.99874 | O57: =IF(E57>=30,33.45,IF(E57<30,E57*1.115)) -> 33.45 | P57: =IF(E57>=30,33.33,IF(E57<30,E57*1.111)) -> 33.33 | Q57: =+O57+P57 -> 66.78 | R57: =33.45/30*E57 -> 33.450083 | U57: =N57+Q57+R58+S57+T57 -> 658.11157 | Z57: 66.74 | AA57: =+W57+V57+X57+Y57+Z57 -> 66.74 | AB57: =+U57-AA57 -> 591.37157 | AF57: =+AB57-AC57-AD57-AE57 -> 591.37157
A58: =A57+1 -> 52 | B58: MACIAS LUCAS ANGELA MARIA | C58: =IF(L58>=401.41,401.41,IF(L58<401.41,L58)) -> 268 | D58: =+L58-C58 -> 0 | E58: =+C58/13.3803 -> 20.029446 | F58: =+'TALLER ACTIVOS'!BF66 -> 222 | G58: 0 | H58: =+'TALLER ACTIVOS'!CX66 -> 46 | I58: 0 | L58: =+F58+G58+H58+I58+K58+J58 -> 268 | M58: =IF(L58>=401.41,37.933,IF(L58<401.41,L58*9.45%)) -> 25.326 | N58: =+L58-M58 -> 242.674 | O58: =IF(E58>=30,33.45,IF(E58<30,E58*1.115)) -> 22.332833 | P58: =IF(E58>=30,33.33,IF(E58<30,E58*1.111)) -> 22.252715 | Q58: =+O58+P58 -> 44.585547 | R58: =33.45/30*E58 -> 22.332833 | U58: =N58+Q58+R117+S58+T58 -> 320.70963 | AA58: =+W58+V58+X58+Y58+Z58 -> 0 | AB58: =+U58-AA58 -> 320.70963 | AF58: =+AB58-AC58-AD58-AE58 -> 320.70963
A59: =A58+1 -> 53 | B59: ZAMBRANO ALCIVAR JORGE LUIS | C59: =IF(L59>=401.41,401.41,IF(L59<401.41,L59)) -> 401.41 | D59: =+L59-C59 -> 144.06084 | E59: =+C59/13.3803 -> 30.000075 | F59: =+'TALLER ACTIVOS'!BF67 -> 291.87224 | G59: 0 | H59: =+'TALLER ACTIVOS'!CX67 -> 253.5986 | I59: 0 | L59: =+F59+G59+H59+I59+K59+J59 -> 545.47084 | M59: =IF(L59>=401.41,37.933,IF(L59<401.41,L59*9.45%)) -> 37.933 | N59: =+L59-M59 -> 507.53784 | O59: =IF(E59>=30,33.45,IF(E59<30,E59*1.115)) -> 33.45 | P59: =IF(E59>=30,33.33,IF(E59<30,E59*1.111)) -> 33.33 | Q59: =+O59+P59 -> 66.78 | U59: =N59+Q59+R59+S59+T59 -> 574.31784 | AA59: =+W59+V59+X59+Y59+Z59 -> 0 | AB59: =+U59-AA59 -> 574.31784 | AF59: =+AB59-AC59-AD59-AE59 -> 574.31784
A60: =A59+1 -> 54 | B60: ZAVALA CATAGUA RAMON ORLANDO | C60: =IF(L60>=401.41,401.41,IF(L60<401.41,L60)) -> 401.41 | D60: =+L60-C60 -> 159.65681 | E60: =+C60/13.3803 -> 30.000075 | F60: =+'TALLER ACTIVOS'!BF68 -> 371.15735 | G60: 0 | H60: =+'TALLER ACTIVOS'!CX68 -> 189.90947 | I60: 0 | L60: =+F60+G60+H60+I60+K60+J60 -> 561.06681 | M60: =IF(L60>=401.41,37.933,IF(L60<401.41,L60*9.45%)) -> 37.933 | N60: =+L60-M60 -> 523.13381 | O60: =IF(E60>=30,33.45,IF(E60<30,E60*1.115)) -> 33.45 | P60: =IF(E60>=30,33.33,IF(E60<30,E60*1.111)) -> 33.33 | Q60: =+O60+P60 -> 66.78 | R60: =33.45/30*E60 -> 33.450083 | U60: =N60+Q60+R60+S60+T60 -> 623.3639 | Z60: 38.24 | AA60: =+W60+V60+X60+Y60+Z60 -> 38.24 | AB60: =+U60-AA60 -> 585.1239 | AF60: =+AB60-AC60-AD60-AE60 -> 585.1239
A61: =A60+1 -> 55 | B61: MECIAS PONCE MILENA ABIGAIL | C61: =IF(L61>=401.41,401.41,IF(L61<401.41,L61)) -> 100.35 | D61: =+L61-C61 -> 0 | E61: =+C61/13.3803 -> 7.4998318 | F61: =+'TALLER ACTIVOS'!BF69 -> 0 | G61: 0 | H61: =+'TALLER ACTIVOS'!CX69 -> 0 | I61: 0 | J61: =13.38*30*25% -> 100.35 | L61: =+F61+G61+H61+I61+K61+J61 -> 100.35 | M61: =IF(L61>=401.41,37.933,IF(L61<401.41,L61*9.45%)) -> 9.483075 | N61: =+L61-M61 -> 90.866925 | O61: =IF(E61>=30,33.45,IF(E61<30,E61*1.115)) -> 8.3623125 | P61: =IF(E61>=30,33.33,IF(E61<30,E61*1.111)) -> 8.3323132 | Q61: =+O61+P61 -> 16.694626 | U61: =N61+Q61+R61+S61+T61 -> 107.56155 | AA61: =+W61+V61+X61+Y61+Z61 -> 0 | AB61: =+U61-AA61 -> 107.56155 | AF61: =+AB61-AC61-AD61-AE61 -> 107.56155
A62: =A61+1 -> 56 | B62: CONFORME CONFORME JIMMY ALBERTO | C62: =IF(L62>=401.41,401.41,IF(L62<401.41,L62)) -> 100.35 | D62: =+L62-C62 -> 0 | E62: =+C62/13.3803 -> 7.4998318 | F62: =+'TALLER ACTIVOS'!BF70 -> 0 | G62: 0 | H62: =+'TALLER ACTIVOS'!CX70 -> 0 | I62: 0 | J62: =13.38*30*25% -> 100.35 | L62: =+F62+G62+H62+I62+K62+J62 -> 100.35 | M62: =IF(L62>=401.41,37.933,IF(L62<401.41,L62*9.45%)) -> 9.483075 | N62: =+L62-M62 -> 90.866925 | O62: =IF(E62>=30,33.45,IF(E62<30,E62*1.115)) -> 8.3623125 | P62: =IF(E62>=30,33.33,IF(E62<30,E62*1.111)) -> 8.3323132 | Q62: =+O62+P62 -> 16.694626 | U62: =N62+Q62+R62+S62+T62 -> 107.56155 | AA62: =+W62+V62+X62+Y62+Z62 -> 0 | AB62: =+U62-AA62 -> 107.56155 | AF62: =+AB62-AC62-AD62-AE62 -> 107.56155
A63: =A62+1 -> 57 | B63: PARRAGA ZAMBRANO JESSICA YARITZA | C63: =IF(L63>=401.41,401.41,IF(L63<401.41,L63)) -> 100.35 | D63: =+L63-C63 -> 0 | E63: =+C63/13.3803 -> 7.4998318 | F63: =+'TALLER ACTIVOS'!BF71 -> 0 | G63: 0 | H63: =+'TALLER ACTIVOS'!CX71 -> 0 | I63: 0 | J63: =13.38*30*25% -> 100.35 | L63: =+F63+G63+H63+I63+K63+J63 -> 100.35 | M63: =IF(L63>=401.41,37.933,IF(L63<401.41,L63*9.45%)) -> 9.483075 | N63: =+L63-M63 -> 90.866925 | O63: =IF(E63>=30,33.45,IF(E63<30,E63*1.115)) -> 8.3623125 | P63: =IF(E63>=30,33.33,IF(E63<30,E63*1.111)) -> 8.3323132 | Q63: =+O63+P63 -> 16.694626 | R63: =33.45/30*E63 -> 8.3623125 | U63: =N63+Q63+R63+S63+T63 -> 115.92386 | AA63: =+W63+V63+X63+Y63+Z63 -> 0 | AB63: =+U63-AA63 -> 115.92386 | AF63: =+AB63-AC63-AD63-AE63 -> 115.92386
A64: =A63+1 -> 58 | B64: RONQUILLO CACUANGO NANCY VANESA | C64: =IF(L64>=401.41,401.41,IF(L64<401.41,L64)) -> 100.35 | D64: =+L64-C64 -> 0 | E64: =+C64/13.3803 -> 7.4998318 | F64: =+'TALLER ACTIVOS'!BF72 -> 0 | G64: 0 | H64: =+'TALLER ACTIVOS'!CX72 -> 0 | I64: 0 | J64: =13.38*30*25% -> 100.35 | L64: =+F64+G64+H64+I64+K64+J64 -> 100.35 | M64: =IF(L64>=401.41,37.933,IF(L64<401.41,L64*9.45%)) -> 9.483075 | N64: =+L64-M64 -> 90.866925 | O64: =IF(E64>=30,33.45,IF(E64<30,E64*1.115)) -> 8.3623125 | P64: =IF(E64>=30,33.33,IF(E64<30,E64*1.111)) -> 8.3323132 | Q64: =+O64+P64 -> 16.694626 | U64: =N64+Q64+R64+S64+T64 -> 107.56155 | AA64: =+W64+V64+X64+Y64+Z64 -> 0 | AB64: =+U64-AA64 -> 107.56155 | AF64: =+AB64-AC64-AD64-AE64 -> 107.56155
A65: SECRETARIA, SUPERVISORES MECANICOS Y LIMPIEZA
A66: =A64+1 -> 59 | B66: VIDAL GONGORA JESSICA VERONICA | C66: =IF(L66>=401.41,401.41,IF(L66<401.41,L66)) -> 400 | D66: =+L66-C66 -> 0 | E66: =+C66/13.3803 -> 29.894696 | F66: =+'TALLER ACTIVOS'!BF41 -> 200 | G66: 0 | H66: =+'TALLER ACTIVOS'!CX41 -> 200 | I66: 0 | L66: =+F66+G66+H66+I66+K66+J66 -> 400 | M66: =IF(L66>=401.41,37.933,IF(L66<401.41,L66*9.45%)) -> 37.8 | N66: =+L66-M66 -> 362.2 | O66: =IF(E66>=30,33.45,IF(E66<30,E66*1.115)) -> 33.332586 | P66: =IF(E66>=30,33.33,IF(E66<30,E66*1.111)) -> 33.213007 | Q66: =+O66+P66 -> 66.545593 | U66: =N66+Q66+R66+S66+T66 -> 428.74559 | AA66: =+W66+V66+X66+Y66+Z66 -> 0 | AB66: =+U66-AA66 -> 428.74559 | AF66: =+AB66-AC66-AD66-AE66 -> 428.74559
A67: =A66+1 -> 60 | B67: PINCAY MUÑOZ GEMA LISBEL | C67: =IF(L67>=401.41,401.41,IF(L67<401.41,L67)) -> 401.41 | D67: =+L67-C67 -> 26.477679 | E67: =+C67/13.3803 -> 30.000075 | F67: =+'TALLER ACTIVOS'!BF42 -> 254.90277 | G67: 0 | H67: =+'TALLER ACTIVOS'!CX42 -> 172.98491 | I67: 0 | L67: =+F67+G67+H67+I67+K67+J67 -> 427.88768 | M67: =IF(L67>=401.41,37.933,IF(L67<401.41,L67*9.45%)) -> 37.933 | N67: =+L67-M67 -> 389.95468 | O67: =IF(E67>=30,33.45,IF(E67<30,E67*1.115)) -> 33.45 | P67: =IF(E67>=30,33.33,IF(E67<30,E67*1.111)) -> 33.33 | Q67: =+O67+P67 -> 66.78 | U67: =N67+Q67+R67+S67+T67 -> 456.73468 | V67: 75 | Z67: 23.74 | AA67: =+W67+V67+X67+Y67+Z67 -> 98.74 | AB67: =+U67-AA67 -> 357.99468 | AF67: =+AB67-AC67-AD67-AE67 -> 357.99468
A68: =A67+1 -> 61 | B68: BRAVO LUCAS ROSARIO MARIANELA | C68: =IF(L68>=401.41,401.41,IF(L68<401.41,L68)) -> 401.41 | D68: =+L68-C68 -> 62.761989 | E68: =+C68/13.3803 -> 30.000075 | F68: =+'TALLER ACTIVOS'!BF43 -> 256.18708 | G68: 0 | H68: =+'TALLER ACTIVOS'!CX43 -> 207.98491 | I68: 0 | L68: =+F68+G68+H68+I68+K68+J68 -> 464.17199 | M68: =IF(L68>=401.41,37.933,IF(L68<401.41,L68*9.45%)) -> 37.933 | N68: =+L68-M68 -> 426.23899 | O68: =IF(E68>=30,33.45,IF(E68<30,E68*1.115)) -> 33.45 | P68: =IF(E68>=30,33.33,IF(E68<30,E68*1.111)) -> 33.33 | Q68: =+O68+P68 -> 66.78 | U68: =N68+Q68+R68+S68+T68 -> 493.01899 | Z68: 97.27 | AA68: =+W68+V68+X68+Y68+Z68 -> 97.27 | AB68: =+U68-AA68 -> 395.74899 | AF68: =+AB68-AC68-AD68-AE68 -> 395.74899
A69: =A68+1 -> 62 | B69: MENENDEZ BASURTO JOSE LUIS | C69: =IF(L69>=401.41,401.41,IF(L69<401.41,L69)) -> 401.41 | D69: =+L69-C69 -> 66.477679 | E69: =+C69/13.3803 -> 30.000075 | F69: =+'TALLER ACTIVOS'!BF44 -> 254.90277 | G69: 0 | H69: =+'TALLER ACTIVOS'!CX44 -> 212.98491 | I69: 0 | L69: =+F69+G69+H69+I69+K69+J69 -> 467.88768 | M69: =IF(L69>=401.41,37.933,IF(L69<401.41,L69*9.45%)) -> 37.933 | N69: =+L69-M69 -> 429.95468 | O69: =IF(E69>=30,33.45,IF(E69<30,E69*1.115)) -> 33.45 | P69: =IF(E69>=30,33.33,IF(E69<30,E69*1.111)) -> 33.33 | Q69: =+O69+P69 -> 66.78 | R69: =33.45/30*E69 -> 33.450083 | U69: =N69+Q69+R69+S69+T69 -> 530.18476 | AA69: =+W69+V69+X69+Y69+Z69 -> 0 | AB69: =+U69-AA69 -> 530.18476 | AF69: =+AB69-AC69-AD69-AE69 -> 530.18476
A70: =A69+1 -> 63 | B70: BRAVO LUCAS RODDY LENIN | C70: =IF(L70>=401.41,401.41,IF(L70<401.41,L70)) -> 401.41 | D70: =+L70-C70 -> 39.687145 | E70: =+C70/13.3803 -> 30.000075 | F70: =+'TALLER ACTIVOS'!BF45 -> 228.11224 | G70: 0 | H70: =+'TALLER ACTIVOS'!CX45 -> 212.98491 | I70: 0 | L70: =+F70+G70+H70+I70+K70+J70 -> 441.09714 | M70: =IF(L70>=401.41,37.933,IF(L70<401.41,L70*9.45%)) -> 37.933 | N70: =+L70-M70 -> 403.16414 | O70: =IF(E70>=30,33.45,IF(E70<30,E70*1.115)) -> 33.45 | P70: =IF(E70>=30,33.33,IF(E70<30,E70*1.111)) -> 33.33 | Q70: =+O70+P70 -> 66.78 | U70: =N70+Q70+R70+S70+T70 -> 469.94414 | Z70: 66.46 | AA70: =+W70+V70+X70+Y70+Z70 -> 66.46 | AB70: =+U70-AA70 -> 403.48414 | AF70: =+AB70-AC70-AD70-AE70 -> 403.48414
A71: =A70+1 -> 64 | B71: CEDEÑO GARCIA CARLOS ANDRES | C71: =IF(L71>=401.41,401.41,IF(L71<401.41,L71)) -> 401.41 | D71: =+L71-C71 -> 28.977679 | E71: =+C71/13.3803 -> 30.000075 | F71: =+'TALLER ACTIVOS'!BF46 -> 229.90277 | G71: 0 | H71: =+'TALLER ACTIVOS'!CX46 -> 200.48491 | I71: 0 | L71: =+F71+G71+H71+I71+K71+J71 -> 430.38768 | M71: =IF(L71>=401.41,37.933,IF(L71<401.41,L71*9.45%)) -> 37.933 | N71: =+L71-M71 -> 392.45468 | O71: =IF(E71>=30,33.45,IF(E71<30,E71*1.115)) -> 33.45 | P71: =IF(E71>=30,33.33,IF(E71<30,E71*1.111)) -> 33.33 | Q71: =+O71+P71 -> 66.78 | R71: =33.45/30*E71 -> 33.450083 | U71: =N71+Q71+R71+S71+T71 -> 492.68476 | V71: 482.68476 | X71: 10 | AA71: =+W71+V71+X71+Y71+Z71 -> 492.68476 | AB71: =+U71-AA71 -> 0 | AF71: =+AB71-AC71-AD71-AE71 -> 0
A72: =A71+1 -> 65 | B72: PINARGOTE TORALES ROSA ENILDA | C72: =IF(L72>=401.41,401.41,IF(L72<401.41,L72)) -> 401.41 | D72: =+L72-C72 -> 111.47768 | E72: =+C72/13.3803 -> 30.000075 | F72: =+'TALLER ACTIVOS'!BF47 -> 299.90277 | G72: 0 | H72: =+'TALLER ACTIVOS'!CX47 -> 212.98491 | I72: 0 | L72: =+F72+G72+H72+I72+K72+J72 -> 512.88768 | M72: =IF(L72>=401.41,37.933,IF(L72<401.41,L72*9.45%)) -> 37.933 | N72: =+L72-M72 -> 474.95468 | O72: =IF(E72>=30,33.45,IF(E72<30,E72*1.115)) -> 33.45 | P72: =IF(E72>=30,33.33,IF(E72<30,E72*1.111)) -> 33.33 | Q72: =+O72+P72 -> 66.78 | R72: =33.45/30*E72 -> 33.450083 | U72: =N72+Q72+R72+S72+T72 -> 575.18476 | AA72: =+W72+V72+X72+Y72+Z72 -> 0 | AB72: =+U72-AA72 -> 575.18476 | AF72: =+AB72-AC72-AD72-AE72 -> 575.18476
A73: =A72+1 -> 66 | B73: SALTOS ZAMBRANO YASMANI FABRICIO | C73: =IF(L73>=401.41,401.41,IF(L73<401.41,L73)) -> 401.41 | D73: =+L73-C73 -> 136.47768 | E73: =+C73/13.3803 -> 30.000075 | F73: =+'TALLER ACTIVOS'!BF48 -> 324.90277 | G73: 0 | H73: =+'TALLER ACTIVOS'!CX48 -> 212.98491 | I73: 0 | L73: =+F73+G73+H73+I73+K73+J73 -> 537.88768 | M73: =IF(L73>=401.41,37.933,IF(L73<401.41,L73*9.45%)) -> 37.933 | N73: =+L73-M73 -> 499.95468 | O73: =IF(E73>=30,33.45,IF(E73<30,E73*1.115)) -> 33.45 | P73: =IF(E73>=30,33.33,IF(E73<30,E73*1.111)) -> 33.33 | Q73: =+O73+P73 -> 66.78 | R73: =33.45/30*E73 -> 33.450083 | U73: =N73+Q73+R73+S73+T73 -> 600.18476 | X73: 20 | AA73: =+W73+V73+X73+Y73+Z73 -> 20 | AB73: =+U73-AA73 -> 580.18476 | AF73: =+AB73-AC73-AD73-AE73 -> 580.18476
A74: =A73+1 -> 67 | B74: MALA CEDEÑO RAMON ALONSO | C74: =IF(L74>=401.41,401.41,IF(L74<401.41,L74)) -> 399.23077 | D74: =+L74-C74 -> 0 | E74: =+C74/13.3803 -> 29.837206 | F74: =+'TALLER ACTIVOS'!BF49 -> 220 | G74: 0 | H74: =+'TALLER ACTIVOS'!CX49 -> 179.23077 | I74: 0 | L74: =+F74+G74+H74+I74+K74+J74 -> 399.23077 | M74: =IF(L74>=401.41,37.933,IF(L74<401.41,L74*9.45%)) -> 37.727308 | N74: =+L74-M74 -> 361.50346 | O74: =IF(E74>=30,33.45,IF(E74<30,E74*1.115)) -> 33.268485 | P74: =IF(E74>=30,33.33,IF(E74<30,E74*1.111)) -> 33.149136 | Q74: =+O74+P74 -> 66.417621 | R74: =33.45/30*E74 -> 33.268485 | U74: =N74+Q74+R74+S74+T74 -> 461.18957 | AA74: =+W74+V74+X74+Y74+Z74 -> 0 | AB74: =+U74-AA74 -> 461.18957 | AF74: =+AB74-AC74-AD74-AE74 -> 461.18957
A75: =A74+1 -> 68 | B75: VERA FELIPE JAVIER | C75: =IF(L75>=401.41,401.41,IF(L75<401.41,L75)) -> 401.41 | D75: =+L75-C75 -> 13.205385 | E75: =+C75/13.3803 -> 30.000075 | F75: =+'TALLER ACTIVOS'!BF50 -> 220 | G75: 0 | H75: =+'TALLER ACTIVOS'!CX50 -> 194.61538 | I75: 0 | L75: =+F75+G75+H75+I75+K75+J75 -> 414.61538 | M75: =IF(L75>=401.41,37.933,IF(L75<401.41,L75*9.45%)) -> 37.933 | N75: =+L75-M75 -> 376.68238 | O75: =IF(E75>=30,33.45,IF(E75<30,E75*1.115)) -> 33.45 | P75: =IF(E75>=30,33.33,IF(E75<30,E75*1.111)) -> 33.33 | Q75: =+O75+P75 -> 66.78 | R75: =33.45/30*E75 -> 33.450083 | U75: =N75+Q75+R75+S75+T75 -> 476.91247 | Z75: 19.54 | AA75: =+W75+V75+X75+Y75+Z75 -> 19.54 | AB75: =+U75-AA75 -> 457.37247 | AF75: =+AB75-AC75-AD75-AE75 -> 457.37247
A76: DESVINCULADOS
A77: =A75+1 -> 69 | B77: ALCIVAR MACIAS DIEGO ARMANDO | C77: =IF(L77>=401.41,401.41,IF(L77<401.41,L77)) -> 401.41 | D77: =+L77-C77 -> 16.819294 | E77: =+C77/13.3803 -> 30.000075 | F77: =+'TALLER RETIRADOS'!BF29 -> 92.776812 | G77: 0 | H77: =+'TALLER RETIRADOS'!CX29 -> 124.75248 | I77: 0 | J77: =13.38*15 -> 200.7 | L77: =+F77+G77+H77+I77+K77+J77 -> 418.22929 | M77: =IF(L77>=401.41,37.933,IF(L77<401.41,L77*9.45%)) -> 37.933 | N77: =+L77-M77 -> 380.29629 | O77: =IF(E77>=30,33.45,IF(E77<30,E77*1.115)) -> 33.45 | P77: =IF(E77>=30,33.33,IF(E77<30,E77*1.111)) -> 33.33 | Q77: =+O77+P77 -> 66.78 | R77: =33.45/30*E77 -> 33.450083 | U77: =N77+Q77+R77+S77+T77 -> 480.52638 | V77: 480.52638 | AA77: =+W77+V77+X77+Y77+Z77 -> 480.52638 | AB77: =+U77-AA77 -> 0 | AF77: =+AB77-AC77-AD77-AE77 -> 0
A78: =A77+1 -> 70 | B78: ALVARADO CRUZ JOEL EMILIANO | C78: =IF(L78>=401.41,401.41,IF(L78<401.41,L78)) -> 401.41 | D78: =+L78-C78 -> 73.627733 | E78: =+C78/13.3803 -> 30.000075 | F78: =+'TALLER RETIRADOS'!BF30 -> 317.31952 | G78: 0 | H78: =+'TALLER RETIRADOS'!CX30 -> 157.71822 | I78: 0 | L78: =+F78+G78+H78+I78+K78+J78 -> 475.03773 | M78: =IF(L78>=401.41,37.933,IF(L78<401.41,L78*9.45%)) -> 37.933 | N78: =+L78-M78 -> 437.10473 | O78: =IF(E78>=30,33.45,IF(E78<30,E78*1.115)) -> 33.45 | P78: =IF(E78>=30,33.33,IF(E78<30,E78*1.111)) -> 33.33 | Q78: =+O78+P78 -> 66.78 | R78: =33.45/30*E78 -> 33.450083 | U78: =N78+Q78+R78+S78+T78 -> 537.33482 | V78: 537.33482 | AA78: =+W78+V78+X78+Y78+Z78 -> 537.33482 | AB78: =+U78-AA78 -> 0 | AF78: =+AB78-AC78-AD78-AE78 -> 0
A79: =A78+1 -> 71 | B79: ARCENTALES MOREIRA NARCISA CECIBEL | C79: =IF(L79>=401.41,401.41,IF(L79<401.41,L79)) -> 401.41 | D79: =+L79-C79 -> 75.551954 | E79: =+C79/13.3803 -> 30.000075 | F79: =+'TALLER RETIRADOS'!BF31 -> 265 | G79: 0 | H79: =+'TALLER RETIRADOS'!CX31 -> 211.96195 | I79: 0 | L79: =+F79+G79+H79+I79+K79+J79 -> 476.96195 | M79: =IF(L79>=401.41,37.933,IF(L79<401.41,L79*9.45%)) -> 37.933 | N79: =+L79-M79 -> 439.02895 | O79: =IF(E79>=30,33.45,IF(E79<30,E79*1.115)) -> 33.45 | P79: =IF(E79>=30,33.33,IF(E79<30,E79*1.111)) -> 33.33 | Q79: =+O79+P79 -> 66.78 | R79: =33.45/30*E79 -> 33.450083 | U79: =N79+Q79+R79+S79+T79 -> 539.25904 | V79: 539.25904 | AA79: =+W79+V79+X79+Y79+Z79 -> 539.25904 | AB79: =+U79-AA79 -> 0 | AF79: =+AB79-AC79-AD79-AE79 -> 0
A80: =A79+1 -> 72 | B80: BAQUE CEDEÑO BLADIMIR ARTEMIRES | C80: =IF(L80>=401.41,401.41,IF(L80<401.41,L80)) -> 401.41 | D80: =+L80-C80 -> 30.694716 | E80: =+C80/13.3803 -> 30.000075 | F80: =+'TALLER RETIRADOS'!BF32 -> 269.55811 | G80: 0 | H80: =+'TALLER RETIRADOS'!CX32 -> 162.54661 | I80: 0 | L80: =+F80+G80+H80+I80+K80+J80 -> 432.10472 | M80: =IF(L80>=401.41,37.933,IF(L80<401.41,L80*9.45%)) -> 37.933 | N80: =+L80-M80 -> 394.17172 | O80: =IF(E80>=30,33.45,IF(E80<30,E80*1.115)) -> 33.45 | P80: =IF(E80>=30,33.33,IF(E80<30,E80*1.111)) -> 33.33 | Q80: =+O80+P80 -> 66.78 | U80: =N80+Q80+R80+S80+T80 -> 460.95172 | V80: 460.95172 | AA80: =+W80+V80+X80+Y80+Z80 -> 460.95172 | AB80: =+U80-AA80 -> 0 | AF80: =+AB80-AC80-AD80-AE80 -> 0
A81: =A80+1 -> 73 | B81: BASURTO ACOSTA EDISON MANUEL | C81: =IF(L81>=401.41,401.41,IF(L81<401.41,L81)) -> 401.41 | D81: =+L81-C81 -> 231.32391 | E81: =+C81/13.3803 -> 30.000075 | F81: =+'TALLER RETIRADOS'!BF33 -> 481.28788 | G81: 0 | H81: =+'TALLER RETIRADOS'!CX33 -> 151.44603 | I81: 0 | L81: =+F81+G81+H81+I81+K81+J81 -> 632.73391 | M81: =IF(L81>=401.41,37.933,IF(L81<401.41,L81*9.45%)) -> 37.933 | N81: =+L81-M81 -> 594.80091 | O81: =IF(E81>=30,33.45,IF(E81<30,E81*1.115)) -> 33.45 | P81: =IF(E81>=30,33.33,IF(E81<30,E81*1.111)) -> 33.33 | Q81: =+O81+P81 -> 66.78 | R81: =33.45/30*E81 -> 33.450083 | U81: =N81+Q81+R81+S81+T81 -> 695.031 | V81: 695.031 | AA81: =+W81+V81+X81+Y81+Z81 -> 695.031 | AB81: =+U81-AA81 -> 0 | AF81: =+AB81-AC81-AD81-AE81 -> 0
A82: =A81+1 -> 74 | B82: BASURTO MACAY LUIS HERNAN | C82: =IF(L82>=401.41,401.41,IF(L82<401.41,L82)) -> 401.41 | D82: =+L82-C82 -> 154.74784 | E82: =+C82/13.3803 -> 30.000075 | F82: =+'TALLER RETIRADOS'!BF34 -> 369.87428 | G82: 0 | H82: =+'TALLER RETIRADOS'!CX34 -> 186.28356 | I82: 0 | L82: =+F82+G82+H82+I82+K82+J82 -> 556.15784 | M82: =IF(L82>=401.41,37.933,IF(L82<401.41,L82*9.45%)) -> 37.933 | N82: =+L82-M82 -> 518.22484 | O82: =IF(E82>=30,33.45,IF(E82<30,E82*1.115)) -> 33.45 | P82: =IF(E82>=30,33.33,IF(E82<30,E82*1.111)) -> 33.33 | Q82: =+O82+P82 -> 66.78 | R82: =33.45/30*E82 -> 33.450083 | U82: =N82+Q82+R82+S82+T82 -> 618.45492 | V82: 618.45492 | AA82: =+W82+V82+X82+Y82+Z82 -> 618.45492 | AB82: =+U82-AA82 -> 0 | AF82: =+AB82-AC82-AD82-AE82 -> 0
A83: =A82+1 -> 75 | B83: BASURTO MERA YANDRI LEUDALDO | C83: =IF(L83>=401.41,401.41,IF(L83<401.41,L83)) -> 401.41 | D83: =+L83-C83 -> 57.432332 | E83: =+C83/13.3803 -> 30.000075 | F83: =+'TALLER RETIRADOS'!BF35 -> 265 | G83: 0 | H83: =+'TALLER RETIRADOS'!CX35 -> 193.84233 | I83: 0 | L83: =+F83+G83+H83+I83+K83+J83 -> 458.84233 | M83: =IF(L83>=401.41,37.933,IF(L83<401.41,L83*9.45%)) -> 37.933 | N83: =+L83-M83 -> 420.90933 | O83: =IF(E83>=30,33.45,IF(E83<30,E83*1.115)) -> 33.45 | P83: =IF(E83>=30,33.33,IF(E83<30,E83*1.111)) -> 33.33 | Q83: =+O83+P83 -> 66.78 | R83: =33.45/30*E83 -> 33.450083 | U83: =N83+Q83+R83+S83+T83 -> 521.13941 | V83: 521.13941 | AA83: =+W83+V83+X83+Y83+Z83 -> 521.13941 | AB83: =+U83-AA83 -> 0 | AF83: =+AB83-AC83-AD83-AE83 -> 0
A84: =A83+1 -> 76 | B84: BRAVO RISCO WILMER EVIDIO | C84: =IF(L84>=401.41,401.41,IF(L84<401.41,L84)) -> 401.41 | D84: =+L84-C84 -> 51.59 | E84: =+C84/13.3803 -> 30.000075 | F84: =+'TALLER RETIRADOS'!BF36 -> 283 | G84: 0 | H84: =+'TALLER RETIRADOS'!CX36 -> 170 | I84: 0 | L84: =+F84+G84+H84+I84+K84+J84 -> 453 | M84: =IF(L84>=401.41,37.933,IF(L84<401.41,L84*9.45%)) -> 37.933 | N84: =+L84-M84 -> 415.067 | O84: =IF(E84>=30,33.45,IF(E84<30,E84*1.115)) -> 33.45 | P84: =IF(E84>=30,33.33,IF(E84<30,E84*1.111)) -> 33.33 | Q84: =+O84+P84 -> 66.78 | U84: =N84+Q84+R84+S84+T84 -> 481.847 | V84: 481.847 | AA84: =+W84+V84+X84+Y84+Z84 -> 481.847 | AB84: =+U84-AA84 -> 0 | AF84: =+AB84-AC84-AD84-AE84 -> 0
A85: =A84+1 -> 77 | B85: CADENA MONTES MARIA AUXILIADORA | C85: =IF(L85>=401.41,401.41,IF(L85<401.41,L85)) -> 401.41 | D85: =+L85-C85 -> 16.222667 | E85: =+C85/13.3803 -> 30.000075 | F85: =+'TALLER RETIRADOS'!BF37 -> 259.63267 | G85: 0 | H85: =+'TALLER RETIRADOS'!CX37 -> 158 | I85: 0 | L85: =+F85+G85+H85+I85+K85+J85 -> 417.63267 | M85: =IF(L85>=401.41,37.933,IF(L85<401.41,L85*9.45%)) -> 37.933 | N85: =+L85-M85 -> 379.69967 | O85: =IF(E85>=30,33.45,IF(E85<30,E85*1.115)) -> 33.45 | P85: =IF(E85>=30,33.33,IF(E85<30,E85*1.111)) -> 33.33 | Q85: =+O85+P85 -> 66.78 | R85: =33.45/30*E85 -> 33.450083 | U85: =N85+Q85+R85+S85+T85 -> 479.92975 | V85: 479.92975 | AA85: =+W85+V85+X85+Y85+Z85 -> 479.92975 | AB85: =+U85-AA85 -> 0 | AF85: =+AB85-AC85-AD85-AE85 -> 0
A86: =A85+1 -> 78 | B86: CEDEÑO BASURTO ROSARIO BEATRIZ | C86: =IF(L86>=401.41,401.41,IF(L86<401.41,L86)) -> 401.41 | D86: =+L86-C86 -> 76.925429 | E86: =+C86/13.3803 -> 30.000075 | F86: =+'TALLER RETIRADOS'!BF38 -> 265 | G86: 0 | H86: =+'TALLER RETIRADOS'!CX38 -> 213.33543 | I86: 0 | L86: =+F86+G86+H86+I86+K86+J86 -> 478.33543 | M86: =IF(L86>=401.41,37.933,IF(L86<401.41,L86*9.45%)) -> 37.933 | N86: =+L86-M86 -> 440.40243 | O86: =IF(E86>=30,33.45,IF(E86<30,E86*1.115)) -> 33.45 | P86: =IF(E86>=30,33.33,IF(E86<30,E86*1.111)) -> 33.33 | Q86: =+O86+P86 -> 66.78 | R86: =33.45/30*E86 -> 33.450083 | U86: =N86+Q86+R86+S86+T86 -> 540.63251 | V86: 540.63251 | AA86: =+W86+V86+X86+Y86+Z86 -> 540.63251 | AB86: =+U86-AA86 -> 0 | AF86: =+AB86-AC86-AD86-AE86 -> 0
A87: =A86+1 -> 79 | B87: CEVALLOS REYNA TITO GUALBERTO | C87: =IF(L87>=401.41,401.41,IF(L87<401.41,L87)) -> 401.41 | D87: =+L87-C87 -> 8.3087136 | E87: =+C87/13.3803 -> 30.000075 | F87: =+'TALLER RETIRADOS'!BF39 -> 283.71871 | G87: 0 | H87: =+'TALLER RETIRADOS'!CX39 -> 126 | I87: 0 | L87: =+F87+G87+H87+I87+K87+J87 -> 409.71871 | M87: =IF(L87>=401.41,37.933,IF(L87<401.41,L87*9.45%)) -> 37.933 | N87: =+L87-M87 -> 371.78571 | O87: =IF(E87>=30,33.45,IF(E87<30,E87*1.115)) -> 33.45 | P87: =IF(E87>=30,33.33,IF(E87<30,E87*1.111)) -> 33.33 | Q87: =+O87+P87 -> 66.78 | R87: =33.45/30*E87 -> 33.450083 | U87: =N87+Q87+R87+S87+T87 -> 472.0158 | V87: 472.0158 | AA87: =+W87+V87+X87+Y87+Z87 -> 472.0158 | AB87: =+U87-AA87 -> 0 | AF87: =+AB87-AC87-AD87-AE87 -> 0
A88: =A87+1 -> 80 | B88: CHAVARRIA MUÑOZ ANA ELIZABETH | C88: =IF(L88>=401.41,401.41,IF(L88<401.41,L88)) -> 334.59679 | D88: =+L88-C88 -> 0 | E88: =+C88/13.3803 -> 25.006674 | F88: =+'TALLER RETIRADOS'!BF40 -> 175.84878 | G88: 0 | H88: =+'TALLER RETIRADOS'!CX40 -> 138.67801 | I88: 0 | J88: =13.38*6*25% -> 20.07 | L88: =+F88+G88+H88+I88+K88+J88 -> 334.59679 | M88: =IF(L88>=401.41,37.933,IF(L88<401.41,L88*9.45%)) -> 31.619397 | N88: =+L88-M88 -> 302.9774 | O88: =IF(E88>=30,33.45,IF(E88<30,E88*1.115)) -> 27.882441 | P88: =IF(E88>=30,33.33,IF(E88<30,E88*1.111)) -> 27.782414 | Q88: =+O88+P88 -> 55.664855 | U88: =N88+Q88+R88+S88+T88 -> 358.64225 | V88: 358.64225 | AA88: =+W88+V88+X88+Y88+Z88 -> 358.64225 | AB88: =+U88-AA88 -> 0 | AF88: =+AB88-AC88-AD88-AE88 -> 0
A89: =A88+1 -> 81 | B89: CHICA VELEZ MIGUEL ANGEL | C89: =IF(L89>=401.41,401.41,IF(L89<401.41,L89)) -> 401.41 | D89: =+L89-C89 -> 296.30001 | E89: =+C89/13.3803 -> 30.000075 | F89: =+'TALLER RETIRADOS'!BF41 -> 460.95424 | G89: 0 | H89: =+'TALLER RETIRADOS'!CX41 -> 236.75576 | I89: 0 | L89: =+F89+G89+H89+I89+K89+J89 -> 697.71001 | M89: =IF(L89>=401.41,37.933,IF(L89<401.41,L89*9.45%)) -> 37.933 | N89: =+L89-M89 -> 659.77701 | O89: =IF(E89>=30,33.45,IF(E89<30,E89*1.115)) -> 33.45 | P89: =IF(E89>=30,33.33,IF(E89<30,E89*1.111)) -> 33.33 | Q89: =+O89+P89 -> 66.78 | U89: =N89+Q89+R89+S89+T89 -> 726.55701 | V89: 726.55701 | AA89: =+W89+V89+X89+Y89+Z89 -> 726.55701 | AB89: =+U89-AA89 -> 0 | AF89: =+AB89-AC89-AD89-AE89 -> 0
A90: =A89+1 -> 82 | B90: CHILA QUIROZ MAIRA GISSELA | C90: =IF(L90>=401.41,401.41,IF(L90<401.41,L90)) -> 401.41 | D90: =+L90-C90 -> 34.656774 | E90: =+C90/13.3803 -> 30.000075 | F90: =+'TALLER RETIRADOS'!BF42 -> 299.85591 | G90: 0 | H90: =+'TALLER RETIRADOS'!CX42 -> 136.21086 | I90: 0 | L90: =+F90+G90+H90+I90+K90+J90 -> 436.06677 | M90: =IF(L90>=401.41,37.933,IF(L90<401.41,L90*9.45%)) -> 37.933 | N90: =+L90-M90 -> 398.13377 | O90: =IF(E90>=30,33.45,IF(E90<30,E90*1.115)) -> 33.45 | P90: =IF(E90>=30,33.33,IF(E90<30,E90*1.111)) -> 33.33 | Q90: =+O90+P90 -> 66.78 | R90: =33.45/30*E90 -> 33.450083 | U90: =N90+Q90+R90+S90+T90 -> 498.36386 | V90: 498.36386 | AA90: =+W90+V90+X90+Y90+Z90 -> 498.36386 | AB90: =+U90-AA90 -> 0 | AF90: =+AB90-AC90-AD90-AE90 -> 0
A91: =A90+1 -> 83 | B91: CUENCA VELEZ KEVIN JOSUE | C91: =IF(L91>=401.41,401.41,IF(L91<401.41,L91)) -> 401.41 | D91: =+L91-C91 -> 191.87079 | E91: =+C91/13.3803 -> 30.000075 | F91: =+'TALLER RETIRADOS'!BF43 -> 364.92387 | G91: 0 | H91: =+'TALLER RETIRADOS'!CX43 -> 228.35692 | I91: 0 | L91: =+F91+G91+H91+I91+K91+J91 -> 593.28079 | M91: =IF(L91>=401.41,37.933,IF(L91<401.41,L91*9.45%)) -> 37.933 | N91: =+L91-M91 -> 555.34779 | O91: =IF(E91>=30,33.45,IF(E91<30,E91*1.115)) -> 33.45 | P91: =IF(E91>=30,33.33,IF(E91<30,E91*1.111)) -> 33.33 | Q91: =+O91+P91 -> 66.78 | U91: =N91+Q91+R91+S91+T91 -> 622.12779 | V91: 622.12779 | AA91: =+W91+V91+X91+Y91+Z91 -> 622.12779 | AB91: =+U91-AA91 -> 0 | AF91: =+AB91-AC91-AD91-AE91 -> 0
A92: =A91+1 -> 84 | B92: ESTRADA FIGUEROA MARCO ANIBAL | C92: =IF(L92>=401.41,401.41,IF(L92<401.41,L92)) -> 401.41 | D92: =+L92-C92 -> 158.7109 | E92: =+C92/13.3803 -> 30.000075 | F92: =+'TALLER RETIRADOS'!BF44 -> 333.83734 | G92: 0 | H92: =+'TALLER RETIRADOS'!CX44 -> 226.28356 | I92: 0 | L92: =+F92+G92+H92+I92+K92+J92 -> 560.1209 | M92: =IF(L92>=401.41,37.933,IF(L92<401.41,L92*9.45%)) -> 37.933 | N92: =+L92-M92 -> 522.1879 | O92: =IF(E92>=30,33.45,IF(E92<30,E92*1.115)) -> 33.45 | P92: =IF(E92>=30,33.33,IF(E92<30,E92*1.111)) -> 33.33 | Q92: =+O92+P92 -> 66.78 | R92: =33.45/30*E92 -> 33.450083 | U92: =N92+Q92+R92+S92+T92 -> 622.41798 | V92: 622.41798 | AA92: =+W92+V92+X92+Y92+Z92 -> 622.41798 | AB92: =+U92-AA92 -> 0 | AF92: =+AB92-AC92-AD92-AE92 -> 0
A93: =A92+1 -> 85 | B93: GAVILANES LOOR LUIS ANTONIO | C93: =IF(L93>=401.41,401.41,IF(L93<401.41,L93)) -> 364.5793 | D93: =+L93-C93 -> 0 | E93: =+C93/13.3803 -> 27.247468 | F93: =+'TALLER RETIRADOS'!BF45 -> 267.8605 | G93: 0 | H93: =+'TALLER RETIRADOS'!CX45 -> 96.718794 | I93: 0 | L93: =+F93+G93+H93+I93+K93+J93 -> 364.5793 | M93: =IF(L93>=401.41,37.933,IF(L93<401.41,L93*9.45%)) -> 34.452744 | N93: =+L93-M93 -> 330.12655 | O93: =IF(E93>=30,33.45,IF(E93<30,E93*1.115)) -> 30.380927 | P93: =IF(E93>=30,33.33,IF(E93<30,E93*1.111)) -> 30.271937 | Q93: =+O93+P93 -> 60.652864 | R93: =33.45/30*E93 -> 30.380927 | U93: =N93+Q93+R93+S93+T93 -> 421.16034 | V93: 421.16034 | AA93: =+W93+V93+X93+Y93+Z93 -> 421.16034 | AB93: =+U93-AA93 -> 0 | AF93: =+AB93-AC93-AD93-AE93 -> 0
A94: =A93+1 -> 86 | B94: GILER CHEVEZ MARIA JESSENIA | C94: =IF(L94>=401.41,401.41,IF(L94<401.41,L94)) -> 401.41 | D94: =+L94-C94 -> 113.22636 | E94: =+C94/13.3803 -> 30.000075 | F94: =+'TALLER RETIRADOS'!BF46 -> 301.22565 | G94: 0 | H94: =+'TALLER RETIRADOS'!CX46 -> 213.41071 | I94: 0 | L94: =+F94+G94+H94+I94+K94+J94 -> 514.63636 | M94: =IF(L94>=401.41,37.933,IF(L94<401.41,L94*9.45%)) -> 37.933 | N94: =+L94-M94 -> 476.70336 | O94: =IF(E94>=30,33.45,IF(E94<30,E94*1.115)) -> 33.45 | P94: =IF(E94>=30,33.33,IF(E94<30,E94*1.111)) -> 33.33 | Q94: =+O94+P94 -> 66.78 | U94: =N94+Q94+R94+S94+T94 -> 543.48336 | V94: 543.48336 | AA94: =+W94+V94+X94+Y94+Z94 -> 543.48336 | AB94: =+U94-AA94 -> 0 | AF94: =+AB94-AC94-AD94-AE94 -> 0
A95: =A94+1 -> 87 | B95: LOOR GARZON JONATHAN ARIEL | C95: =IF(L95>=401.41,401.41,IF(L95<401.41,L95)) -> 401.41 | D95: =+L95-C95 -> 11.59 | E95: =+C95/13.3803 -> 30.000075 | F95: =+'TALLER RETIRADOS'!BF47 -> 273 | G95: 0 | H95: =+'TALLER RETIRADOS'!CX47 -> 140 | I95: 0 | L95: =+F95+G95+H95+I95+K95+J95 -> 413 | M95: =IF(L95>=401.41,37.933,IF(L95<401.41,L95*9.45%)) -> 37.933 | N95: =+L95-M95 -> 375.067 | O95: =IF(E95>=30,33.45,IF(E95<30,E95*1.115)) -> 33.45 | P95: =IF(E95>=30,33.33,IF(E95<30,E95*1.111)) -> 33.33 | Q95: =+O95+P95 -> 66.78 | U95: =N95+Q95+R95+S95+T95 -> 441.847 | V95: 441.847 | AA95: =+W95+V95+X95+Y95+Z95 -> 441.847 | AB95: =+U95-AA95 -> 0 | AF95: =+AB95-AC95-AD95-AE95 -> 0
A96: =A95+1 -> 88 | B96: LOOR RIVAS JUNIOR JOHAN | C96: =IF(L96>=401.41,401.41,IF(L96<401.41,L96)) -> 401.41 | D96: =+L96-C96 -> 52.488227 | E96: =+C96/13.3803 -> 30.000075 | F96: =+'TALLER RETIRADOS'!BF48 -> 254 | G96: 0 | H96: =+'TALLER RETIRADOS'!CX48 -> 199.89823 | I96: 0 | L96: =+F96+G96+H96+I96+K96+J96 -> 453.89823 | M96: =IF(L96>=401.41,37.933,IF(L96<401.41,L96*9.45%)) -> 37.933 | N96: =+L96-M96 -> 415.96523 | O96: =IF(E96>=30,33.45,IF(E96<30,E96*1.115)) -> 33.45 | P96: =IF(E96>=30,33.33,IF(E96<30,E96*1.111)) -> 33.33 | Q96: =+O96+P96 -> 66.78 | R96: =33.45/30*E96 -> 33.450083 | U96: =N96+Q96+R96+S96+T96 -> 516.19531 | V96: 516.19531 | AA96: =+W96+V96+X96+Y96+Z96 -> 516.19531 | AB96: =+U96-AA96 -> 0 | AF96: =+AB96-AC96-AD96-AE96 -> 0
A97: =A96+1 -> 89 | B97: LOOR ZAMBRANO LUIS ANGEL | C97: =IF(L97>=401.41,401.41,IF(L97<401.41,L97)) -> 401.41 | D97: =+L97-C97 -> 179.51412 | E97: =+C97/13.3803 -> 30.000075 | F97: =+'TALLER RETIRADOS'!BF49 -> 347.47836 | G97: 0 | H97: =+'TALLER RETIRADOS'!CX49 -> 233.44576 | I97: 0 | L97: =+F97+G97+H97+I97+K97+J97 -> 580.92412 | M97: =IF(L97>=401.41,37.933,IF(L97<401.41,L97*9.45%)) -> 37.933 | N97: =+L97-M97 -> 542.99112 | O97: =IF(E97>=30,33.45,IF(E97<30,E97*1.115)) -> 33.45 | P97: =IF(E97>=30,33.33,IF(E97<30,E97*1.111)) -> 33.33 | Q97: =+O97+P97 -> 66.78 | U97: =N97+Q97+R97+S97+T97 -> 609.77112 | V97: 609.77112 | AA97: =+W97+V97+X97+Y97+Z97 -> 609.77112 | AB97: =+U97-AA97 -> 0 | AF97: =+AB97-AC97-AD97-AE97 -> 0
A98: =A97+1 -> 90 | B98: MENDOZA MOREIRA FREMY JAVIER | C98: =IF(L98>=401.41,401.41,IF(L98<401.41,L98)) -> 248.175 | D98: =+L98-C98 -> 0 | E98: =+C98/13.3803 -> 18.54779 | F98: =+'TALLER RETIRADOS'!BF50 -> 40 | G98: 0 | H98: =+'TALLER RETIRADOS'!CX50 -> 158 | I98: 0 | J98: =13.38*15*25% -> 50.175 | L98: =+F98+G98+H98+I98+K98+J98 -> 248.175 | M98: =IF(L98>=401.41,37.933,IF(L98<401.41,L98*9.45%)) -> 23.452537 | N98: =+L98-M98 -> 224.72246 | O98: =IF(E98>=30,33.45,IF(E98<30,E98*1.115)) -> 20.680786 | P98: =IF(E98>=30,33.33,IF(E98<30,E98*1.111)) -> 20.606595 | Q98: =+O98+P98 -> 41.287381 | R98: =33.45/30*E98 -> 20.680786 | U98: =N98+Q98+R98+S98+T98 -> 286.69063 | V98: 286.69063 | AA98: =+W98+V98+X98+Y98+Z98 -> 286.69063 | AB98: =+U98-AA98 -> 0 | AF98: =+AB98-AC98-AD98-AE98 -> 0
A99: =A98+1 -> 91 | B99: MUÑOZ ARCENTALES YULEXI GISSELA | C99: =IF(L99>=401.41,401.41,IF(L99<401.41,L99)) -> 401.41 | D99: =+L99-C99 -> 28.968645 | E99: =+C99/13.3803 -> 30.000075 | F99: =+'TALLER RETIRADOS'!BF51 -> 290.85078 | G99: 0 | H99: =+'TALLER RETIRADOS'!CX51 -> 139.52786 | I99: 0 | L99: =+F99+G99+H99+I99+K99+J99 -> 430.37865 | M99: =IF(L99>=401.41,37.933,IF(L99<401.41,L99*9.45%)) -> 37.933 | N99: =+L99-M99 -> 392.44565 | O99: =IF(E99>=30,33.45,IF(E99<30,E99*1.115)) -> 33.45 | P99: =IF(E99>=30,33.33,IF(E99<30,E99*1.111)) -> 33.33 | Q99: =+O99+P99 -> 66.78 | U99: =N99+Q99+R99+S99+T99 -> 459.22565 | V99: 459.22565 | AA99: =+W99+V99+X99+Y99+Z99 -> 459.22565 | AB99: =+U99-AA99 -> 0 | AF99: =+AB99-AC99-AD99-AE99 -> 0
A100: =A99+1 -> 92 | B100: PASCAL ROMAN LUIS MIGUEL | C100: =IF(L100>=401.41,401.41,IF(L100<401.41,L100)) -> 382.75208 | D100: =+L100-C100 -> 0 | E100: =+C100/13.3803 -> 28.605643 | F100: =+'TALLER RETIRADOS'!BF52 -> 242 | G100: 0 | H100: =+'TALLER RETIRADOS'!CX52 -> 140.75208 | I100: 0 | L100: =+F100+G100+H100+I100+K100+J100 -> 382.75208 | M100: =IF(L100>=401.41,37.933,IF(L100<401.41,L100*9.45%)) -> 36.170072 | N100: =+L100-M100 -> 346.58201 | O100: =IF(E100>=30,33.45,IF(E100<30,E100*1.115)) -> 31.895292 | P100: =IF(E100>=30,33.33,IF(E100<30,E100*1.111)) -> 31.780869 | Q100: =+O100+P100 -> 63.676161 | U100: =N100+Q100+R100+S100+T100 -> 410.25817 | V100: 410.25817 | AA100: =+W100+V100+X100+Y100+Z100 -> 410.25817 | AB100: =+U100-AA100 -> 0 | AF100: =+AB100-AC100-AD100-AE100 -> 0
A101: =A100+1 -> 93 | B101: RAMIREZ PILOSO CRISTHIAN BENITO | C101: =IF(L101>=401.41,401.41,IF(L101<401.41,L101)) -> 387.15672 | D101: =+L101-C101 -> 0 | E101: =+C101/13.3803 -> 28.934831 | F101: =+'TALLER RETIRADOS'!BF53 -> 208.08672 | G101: 0 | H101: =+'TALLER RETIRADOS'!CX53 -> 159 | I101: 0 | J101: =13.38*3*50% -> 20.07 | L101: =+F101+G101+H101+I101+K101+J101 -> 387.15672 | M101: =IF(L101>=401.41,37.933,IF(L101<401.41,L101*9.45%)) -> 36.58631 | N101: =+L101-M101 -> 350.57041 | O101: =IF(E101>=30,33.45,IF(E101<30,E101*1.115)) -> 32.262337 | P101: =IF(E101>=30,33.33,IF(E101<30,E101*1.111)) -> 32.146597 | Q101: =+O101+P101 -> 64.408934 | U101: =N101+Q101+R101+S101+T101 -> 414.97935 | V101: 414.97935 | AA101: =+W101+V101+X101+Y101+Z101 -> 414.97935 | AB101: =+U101-AA101 -> 0 | AF101: =+AB101-AC101-AD101-AE101 -> 0
...

Sheet TALLER ACTIVOS
A1: MANTELLOD S.A | BB1: 1RA QUINCENA JUNIO | CT1: 2DA QUINCENA JUNIO | CY1: MES DE JUNIO
A5: Nº | B5: PERSONAL DE PENDULA | C5: Nº DE GRUPOS | D5: # CELULAR | E5: CORREO | F5: MIERCOLES 26-05-2021 | I5: JUEVES 27-05-2021 | L5: VIERNES 28-05-2021 | O5: SABADO 29-05-2021 | R5: LUNES 31-05-2021 | U5: MARTES 01-06-2021 | X5: MIERCOLES 02-06-2021 | AA5: JUEVES 03-06-2021 | AD5: VIERNES 04-06-2021 | AG5: SABADO 05-06-2021 | AJ5: LUNES 07-05-2021 | AM5: MARTES 08-06-2021 | AP5: MIERCOLES 09-06-2021 | AS5: JUEVES 10-06-2021 | BB5: TOTAL BFT QUINCENA | BC5: $ POR AVANCE | BD5: $ AL DIARIO | BE5: MULTA | BF5: VALOR TOTAL QUINCENA | BG5: VIERNES 11-06-2021 | BJ5: SABADO 12-06-2021 | BM5: LUNES 14-06-2021 | BP5: MARTES 15-06-2021 | BS5: MIERCOLES 16-06-2021 | BV5: JUEVES 17-06-2021 | BY5: VIERNES 18-06-2021 | CB5: SABADO 19-06-2021 | CE5: LUNES 21-06-2021 | CH5: MARTES 22-06-2021 | CK5: MIERCOLES 23-06-2021 | CN5: JUEVES 24-06-2021 | CQ5: VIERNES 25-06-2021 | CT5: TOTAL BFT QUINCENA | CU5: $ POR AVANCE | CV5: $ AL DIARIO | CW5: MULTA | CX5: VALOR TOTAL QUINCENA | CY5: TOTAL BFT | CZ5: $ POR AVANCE | DA5: $ AL DIARIO | DB5: TOTAL A PAGAR
F6: BTF | G6: $ | H6: TRABAJOS DIARIO | I6: BTF | J6: $ | K6: TRABAJOS DIARIO | L6: BTF | M6: $ | N6: TRABAJOS DIARIO | O6: BTF | P6: $ | Q6: TRABAJOS DIARIO | R6: BTF | S6: $ | T6: TRABAJOS DIARIO | U6: BTF | V6: $ | W6: TRABAJOS DIARIO | X6: BTF | Y6: $ | Z6: TRABAJOS DIARIO | AA6: BTF | AB6: $ | AC6: TRABAJOS DIARIO | AD6: BTF | AE6: $ | AF6: TRABAJOS DIARIO | AG6: BTF | AH6: $ | AI6: TRABAJOS DIARIO | AJ6: BTF | AK6: $ | AL6: TRABAJOS DIARIO | AM6: BTF | AN6: $ | AO6: TRABAJOS DIARIO | AP6: BTF | AQ6: $ | AR6: TRABAJOS DIARIO | AS6: BTF | AT6: $ | AU6: TRABAJOS DIARIO | AV6: BTF | AW6: $ | AX6: TRABAJOS DIARIO | AY6: BTF | AZ6: $ | BA6: TRABAJOS DIARIO | BG6: BTF | BH6: $ | BI6: TRABAJOS DIARIO | BJ6: BTF | BK6: $ | BL6: TRABAJOS DIARIO | BM6: BTF | BN6: $ | BO6: TRABAJOS DIARIO | BP6: BTF | BQ6: $ | BR6: TRABAJOS DIARIO | BS6: BTF | BT6: $ | BU6: TRABAJOS DIARIO | BV6: BTF | BW6: $ | BX6: TRABAJOS DIARIO | BY6: BTF | BZ6: $ | CA6: TRABAJOS DIARIO | CB6: BTF | CC6: $ | CD6: TRABAJOS DIARIO | CE6: BTF | CF6: $ | CG6: TRABAJOS DIARIO | CH6: BTF | CI6: $ | CJ6: TRABAJOS DIARIO | CK6: BTF | CL6: $ | CM6: TRABAJOS DIARIO | CN6: BTF | CO6: $ | CP6: TRABAJOS DIARIO | CQ6: BTF | CR6: $ | CS6: TRABAJOS DIARIO
A7: 1 | B7: BAQUE MERO ROBERTH DANIEL | C7: PENDULA 1 | F7: 11378.37 | G7: =+F7*0.0035 -> 39.824295 | I7: 9683.62 | J7: =+I7*0.0035 -> 33.89267 | L7: 15254 | M7: =+L7*0.0035 -> 53.389 | O7: 0 | P7: =+O7*0.0035 -> 0 | R7: 10997.34 | S7: =+R7*0.0035 -> 38.49069 | U7: 8380.25 | V7: =+U7*0.0035 -> 29.330875 | X7: 6018.95 | Y7: =+X7*0.0035 -> 21.066325 | AA7: 7872.55 | AB7: =+AA7*0.0035 -> 27.553925 | AD7: 15764.41 | AE7: =+AD7*0.0035 -> 55.175435 | AG7: 0 | AH7: =+AG7*0.0035 -> 0 | AJ7: 11545.34 | AK7: =+AJ7*0.0035 -> 40.40869 | AM7: 0 | AN7: =+AM7*0.0035 -> 0 | AO7: 20 | AP7: 0 | AQ7: =+AP7*0.0035 -> 0 | AS7: 13201.08 | AT7: =+AS7*0.0035 -> 46.20378 | AW7: =+AV7*0.0035 -> 0 | AZ7: =+AY7*0.0035 -> 0 | BB7: =+F7+I7+L7+O7+R7+U7+X7+AA7+AD7+AG7+AJ7+AM7+AP7+AS7+AV7+AY7 -> 110095.91 | BC7: =+G7+J7+M7+P7+S7+V7+Y7+AB7+AE7+AH7+AK7+AN7+AQ7+AT7+AW7+AZ7 -> 385.33568 | BD7: =+H7+K7+N7+Q7+T7+W7+Z7+AC7+AF7+AI7+AL7+AO7+AR7+AU7+AX7+BA7 -> 20 | BF7: =+BC7+BD7-BE7 -> 405.33568 | BG7: 5590.75 | BH7: =+BG7*0.0035 -> 19.567625 | BJ7: 0 | BK7: =+BJ7*0.0035 -> 0 | BM7: 7777.15 | BN7: =+BM7*0.0035 -> 27.220025 | BP7: 7895.73 | BQ7: =+BP7*0.0035 -> 27.635055 | BS7: 0 | BT7: =+BS7*0.0035 -> 0 | BV7: 6079.55 | BW7: =+BV7*0.0035 -> 21.278425 | BY7: 0 | BZ7: =+BY7*0.0035 -> 0 | CB7: 0 | CC7: =+CB7*0.0035 -> 0 | CE7: 8627.51 | CF7: =+CE7*0.0035 -> 30.196285 | CH7: 0 | CI7: =+CH7*0.0035 -> 0 | CK7: 0 | CL7: =+CK7*0.0035 -> 0 | CN7: 0 | CO7: =+CN7*0.0035 -> 0 | CQ7: 0 | CR7: =+CQ7*0.0035 -> 0 | CT7: =BG7+BJ7+BM7+BP7+BS7+BV7+BY7+CB7+CH7+CK7+CN7+CQ7+CE7 -> 35970.69 | CU7: =BH7+BK7+BN7+BQ7+BT7+BW7+BZ7+CC7+CI7+CL7+CO7+CR7+CF7 -> 125.89741 | CV7: =+BI7+BL7+BO7+BR7+BU7+BX7+CA7+CD7+CG7+CJ7+CM7+CP7+CS7 -> 0 | CX7: =+CU7+CV7-CW7 -> 125.89741 | CY7: =+BB7+CT7 -> 146066.6 | CZ7: =+BC7+CU7 -> 511.2331 | DA7: =+BD7+CV7 -> 20 | DB7: =+CZ7+DA7 -> 531.2331
A8: =+A7+1 -> 2 | B8: RISCO ZAMBRANO JEFFERSON CECILIO | C8: PENDULA 1 | F8: 0 | G8: =+F8*0.0035 -> 0 | H8: 20 | I8: 10491.62 | J8: =+I8*0.0035 -> 36.72067 | L8: 13725 | M8: =+L8*0.0035 -> 48.0375 | O8: 0 | P8: =+O8*0.0035 -> 0 | R8: 10269.35 | S8: =+R8*0.0035 -> 35.942725 | U8: 7115.23 | V8: =+U8*0.0035 -> 24.903305 | X8: 5956.95 | Y8: =+X8*0.0035 -> 20.849325 | AA8: 0 | AB8: =+AA8*0.0035 -> 0 | AC8: 20 | AD8: 15942.41 | AE8: =+AD8*0.0035 -> 55.798435 | AG8: 0 | AH8: =+AG8*0.0035 -> 0 | AJ8: 10588.34 | AK8: =+AJ8*0.0035 -> 37.05919 | AM8: 9423.54 | AN8: =+AM8*0.0035 -> 32.98239 | AP8: 0 | AQ8: =+AP8*0.0035 -> 0 | AS8: 14840.08 | AT8: =+AS8*0.0035 -> 51.94028 | AW8: =+AV8*0.0035 -> 0 | AZ8: =+AY8*0.0035 -> 0 | BB8: =+F8+I8+L8+O8+R8+U8+X8+AA8+AD8+AG8+AJ8+AM8+AP8+AS8+AV8+AY8 -> 98352.52 | BC8: =+G8+J8+M8+P8+S8+V8+Y8+AB8+AE8+AH8+AK8+AN8+AQ8+AT8+AW8+AZ8 -> 344.23382 | BD8: =+H8+K8+N8+Q8+T8+W8+Z8+AC8+AF8+AI8+AL8+AO8+AR8+AU8+AX8+BA8 -> 40 | BF8: =+BC8+BD8-BE8 -> 384.23382 | BG8: 5590.77 | BH8: =+BG8*0.0035 -> 19.567695 | BJ8: 0 | BK8: =+BJ8*0.0035 -> 0 | BM8: 37108.31 | BN8: =+BM8*0.02/29 -> 25.591938 | BP8: 8347.73 | BQ8: =+BP8*0.0035 -> 29.217055 | BS8: 3309.84 | BT8: =+BS8*0.0035 -> 11.58444 | BV8: 6969.55 | BW8: =+BV8*0.0035 -> 24.393425 | BY8: 1931.09 | BZ8: =+BY8*0.0035 -> 6.758815 | CB8: 0 | CC8: =+CB8*0.0035 -> 0 | CE8: 0 | CF8: =+CE8*0.0035 -> 0 | CH8: 0 | CI8: =+CH8*0.0035 -> 0 | CK8: 0 | CL8: =+CK8*0.0035 -> 0 | CN8: 0 | CO8: =+CN8*0.0035 -> 0 | CQ8: 0 | CR8: =+CQ8*0.0035 -> 0 | CT8: =BG8+BJ8+BM8+BP8+BS8+BV8+BY8+CB8+CH8+CK8+CN8+CQ8+CE8 -> 63257.29 | CU8: =BH8+BK8+BN8+BQ8+BT8+BW8+BZ8+CC8+CI8+CL8+CO8+CR8+CF8 -> 117.11337 | CV8: =+BI8+BL8+BO8+BR8+BU8+BX8+CA8+CD8+CG8+CJ8+CM8+CP8+CS8 -> 0 | CX8: =+CU8+CV8-CW8 -> 117.11337 | CY8: =+BB8+CT8 -> 161609.81 | CZ8: =+BC8+CU8 -> 461.34719 | DA8: =+BD8+CV8 -> 40 | DB8: =+CZ8+DA8 -> 501.34719
A9: =+A8+1 -> 3 | B9: CHANALATA TONATO CESAR AUGUSTO | C9: PENDULA 1 | D9: 0988142911 | E9: cesarchanalata@gmail.com | F9: 10422.37 | G9: =+F9*0.0035 -> 36.478295 | I9: 8366.63 | J9: =+I9*0.0035 -> 29.283205 | L9: 13995 | M9: =+L9*0.0035 -> 48.9825 | O9: 0 | P9: =+O9*0.0035 -> 0 | R9: 9084.34 | S9: =+R9*0.0035 -> 31.79519 | U9: 0 | V9: =+U9*0.0035 -> 0 | W9: 20 | X9: 0 | Y9: =+X9*0.0035 -> 0 | Z9: 20 | AA9: 6716.55 | AB9: =+AA9*0.0035 -> 23.507925 | AD9: 14893.41 | AE9: =+AD9*0.0035 -> 52.126935 | AG9: 0 | AH9: =+AG9*0.0035 -> 0 | AJ9: 10850.34 | AK9: =+AJ9*0.0035 -> 37.97619 | AM9: 8256.54 | AN9: =+AM9*0.0035 -> 28.89789 | AP9: 0 | AQ9: =+AP9*0.0035 -> 0 | AS9: 13386.08 | AT9: =+AS9*0.0035 -> 46.85128 | AW9: =+AV9*0.0035 -> 0 | AZ9: =+AY9*0.0035 -> 0 | BB9: =+F9+I9+L9+O9+R9+U9+X9+AA9+AD9+AG9+AJ9+AM9+AP9+AS9+AV9+AY9 -> 95971.26 | BC9: =+G9+J9+M9+P9+S9+V9+Y9+AB9+AE9+AH9+AK9+AN9+AQ9+AT9+AW9+AZ9 -> 335.89941 | BD9: =+H9+K9+N9+Q9+T9+W9+Z9+AC9+AF9+AI9+AL9+AO9+AR9+AU9+AX9+BA9 -> 40 | BF9: =+BC9+BD9-BE9 -> 375.89941 | BG9: 5590.77 | BH9: =+BG9*0.0035 -> 19.567695 | BJ9: 0 | BK9: =+BJ9*0.0035 -> 0 | BM9: 7762.16 | BN9: =+BM9*0.0035 -> 27.16756 | BP9: 8498.73 | BQ9: =+BP9*0.0035 -> 29.745555 | BS9: 0 | BT9: =+BS9*0.0035 -> 0 | BV9: 7348.55 | BW9: =+BV9*0.0035 -> 25.719925 | BY9: 1931.09 | BZ9: =+BY9*0.0035 -> 6.758815 | CB9: 0 | CC9: =+CB9*0.0035 -> 0 | CE9: 7660.51 | CF9: =+CE9*0.0035 -> 26.811785 | CH9: 0 | CI9: =+CH9*0.0035 -> 0 | CK9: 0 | CL9: =+CK9*0.0035 -> 0 | CN9: 0 | CO9: =+CN9*0.0035 -> 0 | CQ9: 0 | CR9: =+CQ9*0.0035 -> 0 | CT9: =BG9+BJ9+BM9+BP9+BS9+BV9+BY9+CB9+CH9+CK9+CN9+CQ9+CE9 -> 38791.81 | CU9: =BH9+BK9+BN9+BQ9+BT9+BW9+BZ9+CC9+CI9+CL9+CO9+CR9+CF9 -> 135.77134 | CV9: =+BI9+BL9+BO9+BR9+BU9+BX9+CA9+CD9+CG9+CJ9+CM9+CP9+CS9 -> 0 | CX9: =+CU9+CV9-CW9 -> 135.77134 | CY9: =+BB9+CT9 -> 134763.07 | CZ9: =+BC9+CU9 -> 471.67075 | DA9: =+BD9+CV9 -> 40 | DB9: =+CZ9+DA9 -> 511.67075
A10: =+A9+1 -> 4 | B10: JATIVA REINA LUIS ENRIQUE | C10: PENDULA 2 | D10: 0968953599 | E10: Jhonhenrry-1994@hotmail.con | F10: 0 | G10: =+F10*0.0035 -> 0 | H10: 25 | I10: 5087.62 | J10: =+I10*0.0035 -> 17.80667 | K10: =25-J10 -> 7.19333 | L10: 5610.59 | M10: =+L10*0.0035 -> 19.637065 | N10: =36.33-M10 -> 16.692935 | O10: 0 | P10: =+O10*0.0035 -> 0 | R10: 10997.34 | S10: =+R10*0.0065/2 -> 35.741355 | U10: 7799.23 | V10: =+U10*0.0035 -> 27.297305 | X10: 7999.93 | Y10: =+X10*0.0035 -> 27.999755 | AA10: 8566.56 | AB10: =+AA10*0.0035 -> 29.98296 | AD10: 19351.39 | AE10: =+AD10*0.0035 -> 67.729865 | AG10: 0 | AH10: =+AG10*0.0035 -> 0 | AJ10: 12609.34 | AK10: =+AJ10*0.0035 -> 44.13269 | AM10: 10939.52 | AN10: =+AM10*0.0035 -> 38.28832 | AP10: 0 | AQ10: =+AP10*0.0035 -> 0 | AS10: 16702.08 | AT10: =+AS10*0.0035 -> 58.45728 | AW10: =+AV10*0.0035 -> 0 | AZ10: =+AY10*0.0035 -> 0 | BB10: =+F10+I10+L10+O10+R10+U10+X10+AA10+AD10+AG10+AJ10+AM10+AP10+AS10+AV10+AY10 -> 105663.6 | BC10: =+G10+J10+M10+P10+S10+V10+Y10+AB10+AE10+AH10+AK10+AN10+AQ10+AT10+AW10+AZ10 -> 367.07327 | BD10: =+H10+K10+N10+Q10+T10+W10+Z10+AC10+AF10+AI10+AL10+AO10+AR10+AU10+AX10+BA10 -> 48.886265 | BF10: =+BC10+BD10-BE10 -> 415.95953 | BG10: 5590.77 | BH10: =+BG10*0.0035 -> 19.567695 | BJ10: 0 | BK10: =+BJ10*0.0035 -> 0 | BM10: 12355 | BN10: =+BM10*0.0035 -> 43.2425 | BP10: 10021.73 | BQ10: =+BP10*0.0035 -> 35.076055 | BS10: 3309.84 | BT10: =+BS10*0.0035 -> 11.58444 | BV10: 8555.54 | BW10: =+BV10*0.0035 -> 29.94439 | BY10: 1931.09 | BZ10: =+BY10*0.0035 -> 6.758815 | CB10: 0 | CC10: =+CB10*0.0035 -> 0 | CE10: 9856.51 | CF10: =+CE10*0.0035 -> 34.497785 | CH10: 0 | CI10: =+CH10*0.0035 -> 0 | CK10: 0 | CL10: =+CK10*0.0035 -> 0 | CN10: 0 | CO10: =+CN10*0.0035 -> 0 | CQ10: 0 | CR10: =+CQ10*0.0035 -> 0 | CT10: =BG10+BJ10+BM10+BP10+BS10+BV10+BY10+CB10+CH10+CK10+CN10+CQ10+CE10 -> 51620.48 | CU10: =BH10+BK10+BN10+BQ10+BT10+BW10+BZ10+CC10+CI10+CL10+CO10+CR10+CF10 -> 180.67168 | CV10: =+BI10+BL10+BO10+BR10+BU10+BX10+CA10+CD10+CG10+CJ10+CM10+CP10+CS10 -> 0 | CX10: =+CU10+CV10-CW10 -> 180.67168 | CY10: =+BB10+CT10 -> 157284.08 | CZ10: =+BC10+CU10 -> 547.74495 | DA10: =+BD10+CV10 -> 48.886265 | DB10: =+CZ10+DA10 -> 596.63121
A11: =+A10+1 -> 5 | B11: FERNANDEZ RISCO ALEX BLADIMIR | C11: PENDULA 2 | F11: 11821.35 | G11: =+F11*0.0035 -> 41.374725 | I11: 7931.62 | J11: =+I11*0.0035 -> 27.76067 | L11: 13425 | M11: =+L11*0.0035 -> 46.9875 | O11: 0 | P11: =+O11*0.0035 -> 0 | R11: 11472.34 | S11: =+R11*0.0035 -> 40.15319 | U11: 6185.23 | V11: =+U11*0.0035 -> 21.648305 | X11: 6192.95 | Y11: =+X11*0.0035 -> 21.675325 | AA11: 0 | AB11: =+AA11*0.0035 -> 0 | AC11: 20 | AD11: 15688.41 | AE11: =+AD11*0.0035 -> 54.909435 | AG11: 0 | AH11: =+AG11*0.0035 -> 0 | AJ11: 10228.34 | AK11: =+AJ11*0.0035 -> 35.79919 | AM11: 10939.52 | AN11: =+AM11*0.0065/2 -> 35.55344 | AP11: 0 | AQ11: =+AP11*0.0035 -> 0 | AR11: 20 | AS11: 14577.08 | AT11: =+AS11*0.0035 -> 51.01978 | AW11: =+AV11*0.0035 -> 0 | AZ11: =+AY11*0.0035 -> 0 | BB11: =+F11+I11+L11+O11+R11+U11+X11+AA11+AD11+AG11+AJ11+AM11+AP11+AS11+AV11+AY11 -> 108461.84 | BC11: =+G11+J11+M11+P11+S11+V11+Y11+AB11+AE11+AH11+AK11+AN11+AQ11+AT11+AW11+AZ11 -> 376.88156 | BD11: =+H11+K11+N11+Q11+T11+W11+Z11+AC11+AF11+AI11+AL11+AO11+AR11+AU11+AX11+BA11 -> 40 | BF11: =+BC11+BD11-BE11 -> 416.88156 | BG11: 0 | BH11: =+BG11*0.0035 -> 0 | BI11: 20 | BJ11: 0 | BK11: =+BJ11*0.0035 -> 0 | BM11: 10923 | BN11: =+BM11*0.0035 -> 38.2305 | BP11: 8533.73 | BQ11: =+BP11*0.0035 -> 29.868055 | BS11: 3309.84 | BT11: =+BS11*0.0035 -> 11.58444 | BV11: 0 | BW11: =+BV11*0.0035 -> 0 | BX11: 20 | BY11: 0 | BZ11: =+BY11*0.0035 -> 0 | CA11: 20 | CB11: 0 | CC11: =+CB11*0.0035 -> 0 | CE11: 8301.51 | CF11: =+CE11*0.0035 -> 29.055285 | CH11: 0 | CI11: =+CH11*0.0035 -> 0 | CK11: 0 | CL11: =+CK11*0.0035 -> 0 | CN11: 0 | CO11: =+CN11*0.0035 -> 0 | CQ11: 0 | CR11: =+CQ11*0.0035 -> 0 | CT11: =BG11+BJ11+BM11+BP11+BS11+BV11+BY11+CB11+CH11+CK11+CN11+CQ11+CE11 -> 31068.08 | CU11: =BH11+BK11+BN11+BQ11+BT11+BW11+BZ11+CC11+CI11+CL11+CO11+CR11+CF11 -> 108.73828 | CV11: =+BI11+BL11+BO11+BR11+BU11+BX11+CA11+CD11+CG11+CJ11+CM11+CP11+CS11 -> 60 | CX11: =+CU11+CV11-CW11 -> 168.73828 | CY11: =+BB11+CT11 -> 139529.92 | CZ11: =+BC11+CU11 -> 485.61984 | DA11: =+BD11+CV11 -> 100 | DB11: =+CZ11+DA11 -> 585.61984
A12: =+A11+1 -> 6 | B12: LOOR TONATO JESUS MANUEL | C12: PENDULA 2 | F12: 10979.37 | G12: =+F12*0.0035 -> 38.427795 | I12: 0 | J12: =+I12*0.0035 -> 0 | K12: 20 | L12: 0 | M12: =+L12*0.0035 -> 0 | N12: 20 | O12: 0 | P12: =+O12*0.0035 -> 0 | Q12: 20 | R12: 9295.34 | S12: =+R12*0.0035 -> 32.53369 | U12: 8249.23 | V12: =+U12*0.0035 -> 28.872305 | X12: 6976.95 | Y12: =+X12*0.0035 -> 24.419325 | AA12: 6386.55 | AB12: =+AA12*0.0035 -> 22.352925 | AD12: 13160.41 | AE12: =+AD12*0.0035 -> 46.061435 | AG12: 0 | AH12: =+AG12*0.0035 -> 0 | AJ12: 8782.34 | AK12: =+AJ12*0.0035 -> 30.73819 | AM12: 7440.54 | AN12: =+AM12*0.0035 -> 26.04189 | AP12: 0 | AQ12: =+AP12*0.0035 -> 0 | AS12: 9806.09 | AT12: =+AS12*0.0035 -> 34.321315 | AU12: =56-AT12 -> 21.678685 | AW12: =+AV12*0.0035 -> 0 | AZ12: =+AY12*0.0035 -> 0 | BB12: =+F12+I12+L12+O12+R12+U12+X12+AA12+AD12+AG12+AJ12+AM12+AP12+AS12+AV12+AY12 -> 81076.82 | BC12: =+G12+J12+M12+P12+S12+V12+Y12+AB12+AE12+AH12+AK12+AN12+AQ12+AT12+AW12+AZ12 -> 283.76887 | BD12: =+H12+K12+N12+Q12+T12+W12+Z12+AC12+AF12+AI12+AL12+AO12+AR12+AU12+AX12+BA12 -> 81.678685 | BF12: =+BC12+BD12-BE12 -> 365.44755 | BG12: 5590.77 | BH12: =+BG12*0.0035 -> 19.567695 | BJ12: 0 | BK12: =+BJ12*0.0035 -> 0 | BM12: 10544 | BN12: =+BM12*0.0035 -> 36.904 | BP12: 42210.15 | BQ12: =+BP12*0.02/34 -> 24.8295 | BS12: 3309.85 | BT12: =+BS12*0.0035 -> 11.584475 | BV12: 8452.55 | BW12: =+BV12*0.0035 -> 29.583925 | BY12: 1931.09 | BZ12: =+BY12*0.0035 -> 6.758815 | CB12: 0 | CC12: =+CB12*0.0035 -> 0 | CE12: 10973.52 | CF12: =+CE12*0.0035 -> 38.40732 | CH12: 0 | CI12: =+CH12*0.0035 -> 0 | CK12: 0 | CL12: =+CK12*0.0035 -> 0 | CN12: 0 | CO12: =+CN12*0.0035 -> 0 | CQ12: 0 | CR12: =+CQ12*0.0035 -> 0 | CT12: =BG12+BJ12+BM12+BP12+BS12+BV12+BY12+CB12+CH12+CK12+CN12+CQ12+CE12 -> 83011.93 | CU12: =BH12+BK12+BN12+BQ12+BT12+BW12+BZ12+CC12+CI12+CL12+CO12+CR12+CF12 -> 167.63573 | CV12: =+BI12+BL12+BO12+BR12+BU12+BX12+CA12+CD12+CG12+CJ12+CM12+CP12+CS12 -> 0 | CX12: =+CU12+CV12-CW12 -> 167.63573 | CY12: =+BB12+CT12 -> 164088.75 | CZ12: =+BC12+CU12 -> 451.4046 | DA12: =+BD12+CV12 -> 81.678685 | DB12: =+CZ12+DA12 -> 533.08328
A13: =+A12+1 -> 7 | B13: HERRERA PEÑARRIETA ARIEL GABRIEL | C13: PENDULA 3 | D13: 0967523410 | E13: arielcedeño003@gmail.com | F13: 0 | G13: =+F13*0.0065/2 -> 0 | H13: 25 | I13: 5087.62 | J13: =+I13*0.0065/2 -> 16.534765 | K13: =25-J13 -> 8.465235 | L13: 5610.59 | M13: =+L13*0.0065/2 -> 18.234417 | N13: =36.33-M13 -> 18.095582 | O13: 0 | P13: =+O13*0.0065/2 -> 0 | R13: 11472.34 | S13: =+R13*0.0065/2 -> 37.285105 | U13: 7799.23 | V13: =+U13*0.0065/2 -> 25.347497 | X13: 7999.93 | Y13: =+X13*0.0065/2 -> 25.999772 | AA13: 8566.56 | AB13: =+AA13*0.0065/2 -> 27.84132 | AD13: 19351.39 | AE13: =+AD13*0.0065/2 -> 62.892017 | AG13: 0 | AH13: =+AG13*0.0065/2 -> 0 | AJ13: 12609.34 | AK13: =+AJ13*0.0065/2 -> 40.980355 | AM13: 10939.52 | AN13: =+AM13*0.0065/2 -> 35.55344 | AP13: 0 | AQ13: =+AP13*0.0065/2 -> 0 | AR13: 20 | AS13: 16702.08 | AT13: =+AS13*0.0065/2 -> 54.28176 | AW13: =+AV13*0.0065/2 -> 0 | AZ13: =+AY13*0.0065/2 -> 0 | BB13: =+F13+I13+L13+O13+R13+U13+X13+AA13+AD13+AG13+AJ13+AM13+AP13+AS13+AV13+AY13 -> 106138.6 | BC13: =+G13+J13+M13+P13+S13+V13+Y13+AB13+AE13+AH13+AK13+AN13+AQ13+AT13+AW13+AZ13 -> 344.95045 | BD13: =+H13+K13+N13+Q13+T13+W13+Z13+AC13+AF13+AI13+AL13+AO13+AR13+AU13+AX13+BA13 -> 71.560817 | BF13: =+BC13+BD13-BE13 -> 416.51127 | BG13: 5590.77 | BH13: =+BG13*0.0065/2 -> 18.170002 | BJ13: 0 | BK13: =+BJ13*0.0065/2 -> 0 | BM13: 12355 | BN13: =+BM13*0.0065/2 -> 40.15375 | BP13: 10021.73 | BQ13: =+BP13*0.0065/2 -> 32.570622 | BS13: 3309.84 | BT13: =+BS13*0.0065/2 -> 10.75698 | BV13: 8555.54 | BW13: =+BV13*0.0065/2 -> 27.805505 | BY13: 0 | BZ13: =+BY13*0.0065/2 -> 0 | CA13: 20 | CB13: 0 | CC13: =+CB13*0.0065/2 -> 0 | CE13: 9856.51 | CF13: =+CE13*0.0065/2 -> 32.033657 | CH13: 0 | CI13: =+CH13*0.0065/2 -> 0 | CK13: 0 | CL13: =+CK13*0.0065/2 -> 0 | CN13: 0 | CO13: =+CN13*0.0065/2 -> 0 | CQ13: 0 | CR13: =+CQ13*0.0065/2 -> 0 | CT13: =BG13+BJ13+BM13+BP13+BS13+BV13+BY13+CB13+CH13+CK13+CN13+CQ13+CE13 -> 49689.39 | CU13: =BH13+BK13+BN13+BQ13+BT13+BW13+BZ13+CC13+CI13+CL13+CO13+CR13+CF13 -> 161.49052 | CV13: =+BI13+BL13+BO13+BR13+BU13+BX13+CA13+CD13+CG13+CJ13+CM13+CP13+CS13 -> 20 | CX13: =+CU13+CV13-CW13 -> 181.49052 | CY13: =+BB13+CT13 -> 155827.99 | CZ13: =+BC13+CU13 -> 506.44097 | DA13: =+BD13+CV13 -> 91.560817 | DB13: =+CZ13+DA13 -> 598.00179
A14: =+A13+1 -> 8 | B14: SANCHEZ TES JUAN CARLOS | C14: PENDULA 4 | D14: 0994783560 | E14: juantessanches21@gmail.com | F14: 0 | G14: =+F14*0.0065/2 -> 0 | H14: 20 | I14: 10491.62 | J14: =+I14*0.0065/2 -> 34.097765 | L14: 13725 | M14: =+L14*0.0065/2 -> 44.60625 | O14: 0 | P14: =+O14*0.0065/2 -> 0 | R14: 10269.35 | S14: =+R14*0.0065/2 -> 33.375388 | U14: 7115.23 | V14: =+U14*0.0065/2 -> 23.124497 | X14: 5956.95 | Y14: =+X14*0.0065/2 -> 19.360087 | AA14: 0 | AB14: =+AA14*0.0065/2 -> 0 | AC14: 20 | AD14: 15942.41 | AE14: =+AD14*0.0065/2 -> 51.812832 | AG14: 0 | AH14: =+AG14*0.0065/2 -> 0 | AJ14: 10588.34 | AK14: =+AJ14*0.0065/2 -> 34.412105 | AM14: 9423.54 | AN14: =+AM14*0.0065/2 -> 30.626505 | AP14: 0 | AQ14: =+AP14*0.0065/2 -> 0 | AR14: 20 | AS14: 14840.08 | AT14: =+AS14*0.0065/2 -> 48.23026 | AW14: =+AV14*0.0065/2 -> 0 | AZ14: =+AY14*0.0065/2 -> 0 | BB14: =+F14+I14+L14+O14+R14+U14+X14+AA14+AD14+AG14+AJ14+AM14+AP14+AS14+AV14+AY14 -> 98352.52 | BC14: =+G14+J14+M14+P14+S14+V14+Y14+AB14+AE14+AH14+AK14+AN14+AQ14+AT14+AW14+AZ14 -> 319.64569 | BD14: =+H14+K14+N14+Q14+T14+W14+Z14+AC14+AF14+AI14+AL14+AO14+AR14+AU14+AX14+BA14 -> 60 | BF14: =+BC14+BD14-BE14 -> 379.64569 | BG14: 5590.77 | BH14: =+BG14*0.0065/2 -> 18.170002 | BJ14: 0 | BK14: =+BJ14*0.0065/2 -> 0 | BM14: 37108.31 | BN14: =+BM14*0.02/29 -> 25.591938 | BP14: 8347.73 | BQ14: =+BP14*0.0065/2 -> 27.130122 | BS14: 3309.84 | BT14: =+BS14*0.0035 -> 11.58444 | BV14: 6969.55 | BW14: =+BV14*0.0065/2 -> 22.651038 | BY14: 1931.09 | BZ14: =+BY14*0.0065/2 -> 6.2760425 | CB14: 0 | CC14: =+CB14*0.0065/2 -> 0 | CE14: 0 | CF14: =+CE14*0.0065/2 -> 0 | CH14: 0 | CI14: =+CH14*0.0065/2 -> 0 | CK14: 0 | CL14: =+CK14*0.0065/2 -> 0 | CN14: 0 | CO14: =+CN14*0.0065/2 -> 0 | CQ14: 0 | CR14: =+CQ14*0.0065/2 -> 0 | CT14: =BG14+BJ14+BM14+BP14+BS14+BV14+BY14+CB14+CH14+CK14+CN14+CQ14+CE14 -> 63257.29 | CU14: =BH14+BK14+BN14+BQ14+BT14+BW14+BZ14+CC14+CI14+CL14+CO14+CR14+CF14 -> 111.40358 | CV14: =+BI14+BL14+BO14+BR14+BU14+BX14+CA14+CD14+CG14+CJ14+CM14+CP14+CS14 -> 0 | CX14: =+CU14+CV14-CW14 -> 111.40358 | CY14: =+BB14+CT14 -> 161609.81 | CZ14: =+BC14+CU14 -> 431.04927 | DA14: =+BD14+CV14 -> 60 | DB14: =+CZ14+DA14 -> 491.04927
A15: =+A14+1 -> 9 | B15: VERA SALDARRIAGA EDISON ADOLFO | C15: PENDULA | D15: 0981145232 | F15: 11378.37 | G15: =+F15*0.0065/2 -> 36.979703 | I15: 9683.62 | J15: =+I15*0.0065/2 -> 31.471765 | L15: 15254 | M15: =+L15*0.0065/2 -> 49.5755 | O15: 0 | P15: =+O15*0.0065/2 -> 0 | R15: 10997.34 | S15: =+R15*0.0065/2 -> 35.741355 | U15: 8380.25 | V15: =+U15*0.0065/2 -> 27.235812 | X15: 6018.95 | Y15: =+X15*0.0065/2 -> 19.561587 | AA15: 7872.55 | AB15: =+AA15*0.0065/2 -> 25.585787 | AD15: 15764.41 | AE15: =+AD15*0.0065/2 -> 51.234333 | AG15: 0 | AH15: =+AG15*0.0065/2 -> 0 | AJ15: 11545.34 | AK15: =+AJ15*0.0065/2 -> 37.522355 | AM15: 7440.54 | AN15: =+AM15*0.0065/2 -> 24.181755 | AP15: 0 | AQ15: =+AP15*0.0065/2 -> 0 | AS15: 13201.08 | AT15: =+AS15*0.0065/2 -> 42.90351 | AW15: =+AV15*0.0065/2 -> 0 | AZ15: =+AY15*0.0065/2 -> 0 | BB15: =+F15+I15+L15+O15+R15+U15+X15+AA15+AD15+AG15+AJ15+AM15+AP15+AS15+AV15+AY15 -> 117536.45 | BC15: =+G15+J15+M15+P15+S15+V15+Y15+AB15+AE15+AH15+AK15+AN15+AQ15+AT15+AW15+AZ15 -> 381.99346 | BD15: =+H15+K15+N15+Q15+T15+W15+Z15+AC15+AF15+AI15+AL15+AO15+AR15+AU15+AX15+BA15 -> 0 | BF15: =+BC15+BD15-BE15 -> 381.99346 | BG15: 5590.75 | BH15: =+BG15*0.0065/2 -> 18.169937 | BJ15: 0 | BK15: =+BJ15*0.0065/2 -> 0 | BM15: 7777.15 | BN15: =+BM15*0.0065/2 -> 25.275737 | BP15: 7895.73 | BQ15: =+BP15*0.0065/2 -> 25.661122 | BS15: 3309.84 | BT15: =+BS15*0.0065/2 -> 10.75698 | BV15: 6079.55 | BW15: =+BV15*0.0065/2 -> 19.758537 | BY15: 1931.09 | BZ15: =+BY15*0.0065/2 -> 6.2760425 | CB15: 0 | CC15: =+CB15*0.0065/2 -> 0 | CE15: 8627.51 | CF15: =+CE15*0.0065/2 -> 28.039407 | CH15: 0 | CI15: =+CH15*0.0065/2 -> 0 | CK15: 0 | CL15: =+CK15*0.0065/2 -> 0 | CN15: 0 | CO15: =+CN15*0.0065/2 -> 0 | CQ15: 0 | CR15: =+CQ15*0.0065/2 -> 0 | CT15: =BG15+BJ15+BM15+BP15+BS15+BV15+BY15+CB15+CH15+CK15+CN15+CQ15+CE15 -> 41211.62 | CU15: =BH15+BK15+BN15+BQ15+BT15+BW15+BZ15+CC15+CI15+CL15+CO15+CR15+CF15 -> 133.93777 | CV15: =+BI15+BL15+BO15+BR15+BU15+BX15+CA15+CD15+CG15+CJ15+CM15+CP15+CS15 -> 0 | CX15: =+CU15+CV15-CW15 -> 133.93777 | CY15: =+BB15+CT15 -> 158748.07 | CZ15: =+BC15+CU15 -> 515.93123 | DA15: =+BD15+CV15 -> 0 | DB15: =+CZ15+DA15 -> 515.93123
A16: TOTAL | BB16: =SUM(BB7:BB15) -> 921649.52 | BC16: =SUM(BC7:BC15) -> 3139.7822 | BD16: =SUM(BD7:BD15) -> 402.12577 | BE16: =SUM(BE7:BE15) -> 0 | BF16: =SUM(BF7:BF15) -> 3541.908 | CT16: =SUM(CT7:CT15) -> 457878.58 | CU16: =SUM(CU7:CU15) -> 1242.6597 | CV16: =SUM(CV7:CV15) -> 80 | CW16: =SUM(CW7:CW15) -> 0 | CX16: =SUM(CX7:CX15) -> 1322.6597 | CY16: =SUM(CY7:CY15) -> 1379528.1 | CZ16: =SUM(CZ7:CZ15) -> 4382.4419 | DA16: =SUM(DA7:DA15) -> 482.12577 | DB16: =SUM(DB7:DB15) -> 4864.5677 | DD16: =+CZ16+DD17 -> 7720.2098 | DE16: =+DA16+DE17 -> 1188.5457 | DF16: =+DB16+DF17 -> 8908.7555
A17: Nº | B17: PERSONAL DE SIERRA MESA DE LA MAÑANA | C17: Nº DE GRUPOS | D17: # CELULAR | E17: CORREO | F17: MIERCOLES 26-05-2021 | I17: JUEVES 27-05-2021 | L17: VIERNES 28-05-2021 | O17: SABADO 29-05-2021 | R17: LUNES 31-05-2021 | U17: MARTES 01-06-2021 | X17: MIERCOLES 02-06-2021 | AA17: JUEVES 03-06-2021 | AD17: VIERNES 04-06-2021 | AG17: SABADO 05-06-2021 | AJ17: LUNES 07-05-2021 | AM17: MARTES 08-06-2021 | AP17: MIERCOLES 09-06-2021 | AS17: JUEVES 10-06-2021 | BB17: TOTAL BFT QUINCENA | BC17: $ POR AVANCE | BD17: $ AL DIARIO | BE17: MULTA | BF17: VALOR TOTAL QUINCENA | BG17: VIERNES 11-06-2021 | BJ17: SABADO 12-06-2021 | BM17: LUNES 14-06-2021 | BP17: MARTES 15-06-2021 | BS17: MIERCOLES 16-06-2021 | BV17: JUEVES 17-06-2021 | BY17: VIERNES 18-06-2021 | CB17: SABADO 19-06-2021 | CE17: LUNES 21-06-2021 | CH17: MARTES 22-06-2021 | CK17: MIERCOLES 23-06-2021 | CN17: JUEVES 24-06-2021 | CQ17: VIERNES 25-06-2021 | CT17: TOTAL BFT QUINCENA | CU17: $ POR AVANCE | CV17: $ AL DIARIO | CW17: MULTA | CX17: VALOR TOTAL QUINCENA | CY17: TOTAL BFT | CZ17: $ POR AVANCE | DA17: $ AL DIARIO | DB17: TOTAL A PAGAR | DD17: 3337.7679 | DE17: 706.41989 | DF17: 4044.1878
F18: BTF | G18: $ | H18: TRABAJOS DIARIO | I18: BTF | J18: $ | K18: TRABAJOS DIARIO | L18: BTF | M18: $ | N18: TRABAJOS DIARIO | O18: BTF | P18: $ | Q18: TRABAJOS DIARIO | R18: BTF | S18: $ | T18: TRABAJOS DIARIO | U18: BTF | V18: $ | W18: TRABAJOS DIARIO | X18: BTF | Y18: $ | Z18: TRABAJOS DIARIO | AA18: BTF | AB18: $ | AC18: TRABAJOS DIARIO | AD18: BTF | AE18: $ | AF18: TRABAJOS DIARIO | AG18: BTF | AH18: $ | AI18: TRABAJOS DIARIO | AJ18: BTF | AK18: $ | AL18: TRABAJOS DIARIO | AM18: BTF | AN18: $ | AO18: TRABAJOS DIARIO | AP18: BTF | AQ18: $ | AR18: TRABAJOS DIARIO | AS18: BTF | AT18: $ | AU18: TRABAJOS DIARIO | AV18: BTF | AW18: $ | AX18: TRABAJOS DIARIO | AY18: BTF | AZ18: $ | BA18: TRABAJOS DIARIO | BG18: BTF | BH18: $ | BI18: TRABAJOS DIARIO | BJ18: BTF | BK18: $ | BL18: TRABAJOS DIARIO | BM18: BTF | BN18: $ | BO18: TRABAJOS DIARIO | BP18: BTF | BQ18: $ | BR18: TRABAJOS DIARIO | BS18: BTF | BT18: $ | BU18: TRABAJOS DIARIO | BV18: BTF | BW18: $ | BX18: TRABAJOS DIARIO | BY18: BTF | BZ18: $ | CA18: TRABAJOS DIARIO | CB18: BTF | CC18: $ | CD18: TRABAJOS DIARIO | CE18: BTF | CF18: $ | CG18: TRABAJOS DIARIO | CH18: BTF | CI18: $ | CJ18: TRABAJOS DIARIO | CK18: BTF | CL18: $ | CM18: TRABAJOS DIARIO | CN18: BTF | CO18: $ | CP18: TRABAJOS DIARIO | CQ18: BTF | CR18: $ | CS18: TRABAJOS DIARIO | DF18: =+DB16+DF17 -> 8908.7555
A19: =+A15+1 -> 10 | B19: PACHECO MONTOYA JENIFFER KATHERINE | C19: SIERRA 1 | D19: 0993763536 | E19: jenifferpacheco.1996luky@gmail.com | F19: 3114.9347 | G19: =IF(F19<2700,F19*0.007,IF(F19<3200,F19*0.008,IF(F19<3700,F19*0.0097,IF(F19>3699,F19*0.01095,"")))) -> 24.919477 | I19: 3233.608 | J19: =IF(I19<2700,I19*0.007,IF(I19<3200,I19*0.008,IF(I19<3700,I19*0.0097,IF(I19>3699,I19*0.01095,"")))) -> 31.365998 | L19: 3523.5377 | M19: =IF(L19<2700,L19*0.007,IF(L19<3200,L19*0.008,IF(L19<3700,L19*0.0097,IF(L19>3699,L19*0.01095,"")))) -> 34.178316 | P19: =IF(O19<2700,O19*0.0097,IF(O19<3200,O19*0.01095,IF(O19<3700,O19*0.0122,IF(O19>3699,O19*0.01345,"")))) -> 0 | R19: 3653.3065 | S19: =IF(R19<2700,R19*0.007,IF(R19<3200,R19*0.008,IF(R19<3700,R19*0.0097,IF(R19>3699,R19*0.01095,"")))) -> 35.437073 | U19: 0 | V19: =IF(U19<2700,U19*0.008,IF(U19<3200,U19*0.0097,IF(U19<3700,U19*0.01095,IF(U19>3699,U19*0.0122,"")))) -> 0 | W19: 20 | X19: 0 | Y19: =IF(X19<2700,X19*0.008,IF(X19<3200,X19*0.0097,IF(X19<3700,X19*0.01095,IF(X19>3699,X19*0.0122,"")))) -> 0 | Z19: 20 | AA19: 0 | AB19: =IF(AA19<2700,AA19*0.008,IF(AA19<3200,AA19*0.0097,IF(AA19<3700,AA19*0.01095,IF(AA19>3699,AA19*0.0122,"")))) -> 0 | AC19: 20 | AD19: 2742.5126 | AE19: =IF(AD19<2700,AD19*0.007,IF(AD19<3200,AD19*0.008,IF(AD19<3700,AD19*0.0097,IF(AD19>3699,AD19*0.01095,"")))) -> 21.940101 | AF19: 30 | AG19: 0 | AH19: =IF(AG19<2700,AG19*0.0097,IF(AG19<3200,AG19*0.01095,IF(AG19<3700,AG19*0.0122,IF(AG19>3699,AG19*0.01345,"")))) -> 0 | AJ19: 3461.3065 | AK19: =IF(AJ19<2700,AJ19*0.007,IF(AJ19<3200,AJ19*0.008,IF(AJ19<3700,AJ19*0.0097,IF(AJ19>3699,AJ19*0.01095,"")))) -> 33.574673 | AM19: 2877.1055 | AN19: =IF(AM19<2700,AM19*0.007,IF(AM19<3200,AM19*0.008,IF(AM19<3700,AM19*0.0097,IF(AM19>3699,AM19*0.01095,"")))) -> 23.016844 | AP19: 0 | AQ19: =IF(AP19<2700,AP19*0.0097,IF(AP19<3200,AP19*0.01095,IF(AP19<3700,AP19*0.0122,IF(AP19>3699,AP19*0.01345,"")))) -> 0 | AR19: 12 | AS19: 0 | AT19: =IF(AS19<2700,AS19*0.008,IF(AS19<3200,AS19*0.0097,IF(AS19<3700,AS19*0.01095,IF(AS19>3699,AS19*0.0122,"")))) -> 0 | AU19: 20 | AW19: =IF(AV19<2700,AV19*0.0097,IF(AV19<3200,AV19*0.01095,IF(AV19<3700,AV19*0.0122,IF(AV19>3699,AV19*0.01345,"")))) -> 0 | AZ19: =IF(AY19<2700,AY19*0.0097,IF(AY19<3200,AY19*0.01095,IF(AY19<3700,AY19*0.0122,IF(AY19>3699,AY19*0.01345,"")))) -> 0 | BB19: =+F19+I19+L19+O19+R19+U19+X19+AA19+AD19+AG19+AJ19+AM19+AP19+AS19+AV19+AY19 -> 22606.312 | BC19: =+G19+J19+M19+P19+S19+V19+Y19+AB19+AE19+AH19+AK19+AN19+AQ19+AT19+AW19+AZ19 -> 204.43248 | BD19: =+H19+K19+N19+Q19+T19+W19+Z19+AC19+AF19+AI19+AL19+AO19+AR19+AU19+AX19+BA19 -> 122 | BF19: =+BC19+BD19-BE19 -> 326.43248 | BG19: 0 | BH19: =IF(BG19<2700,BG19*0.008,IF(BG19<3200,BG19*0.0097,IF(BG19<3700,BG19*0.01095,IF(BG19>3699,BG19*0.0122,"")))) -> 0 | BI19: 18 | BJ19: 0 | BK19: =IF(BJ19<2700,BJ19*0.0097,IF(BJ19<3200,BJ19*0.01095,IF(BJ19<3700,BJ19*0.0122,IF(BJ19>3699,BJ19*0.01345,"")))) -> 0 | BL19: 12 | BM19: 2175.196 | BN19: =IF(BM19<2700,BM19*0.007,IF(BM19<3200,BM19*0.008,IF(BM19<3700,BM19*0.0097,IF(BM19>3699,BM19*0.01095,"")))) -> 15.226372 | BP19: 2744.9246 | BQ19: =IF(BP19<2700,BP19*0.007,IF(BP19<3200,BP19*0.008,IF(BP19<3700,BP19*0.0097,IF(BP19>3699,BP19*0.01095,"")))) -> 21.959397 | BS19: 2624.804 | BT19: =IF(BS19<2700,BS19*0.007,IF(BS19<3200,BS19*0.008,IF(BS19<3700,BS19*0.0097,IF(BS19>3699,BS19*0.01095,"")))) -> 18.373628 | BV19: 2994.3317 | BW19: =IF(BV19<2700,BV19*0.007,IF(BV19<3200,BV19*0.008,IF(BV19<3700,BV19*0.0097,IF(BV19>3699,BV19*0.01095,"")))) -> 23.954653 | BY19: 1798.4322 | BZ19: =IF(BY19<2700,BY19*0.007,IF(BY19<3200,BY19*0.008,IF(BY19<3700,BY19*0.0097,IF(BY19>3699,BY19*0.01095,"")))) -> 12.589025 | CB19: 0 | CC19: =IF(CB19<2700,CB19*0.0097,IF(CB19<3200,CB19*0.01095,IF(CB19<3700,CB19*0.0122,IF(CB19>3699,CB19*0.01345,"")))) -> 0 | CD19: 10 | CE19: 2936.4422 | CF19: =IF(CE19<2700,CE19*0.007,IF(CE19<3200,CE19*0.008,IF(CE19<3700,CE19*0.0097,IF(CE19>3699,CE19*0.01095,"")))) -> 23.491538 | CH19: 0 | CI19: =IF(CH19<2700,CH19*0.0097,IF(CH19<3200,CH19*0.01095,IF(CH19<3700,CH19*0.0122,IF(CH19>3699,CH19*0.01345,"")))) -> 0 | CJ19: 18 | CK19: 0 | CL19: =IF(CK19<2700,CK19*0.0097,IF(CK19<3200,CK19*0.01095,IF(CK19<3700,CK19*0.0122,IF(CK19>3699,CK19*0.01345,"")))) -> 0 | CM19: 0 | CN19: 0 | CO19: =IF(CN19<2700,CN19*0.0097,IF(CN19<3200,CN19*0.01095,IF(CN19<3700,CN19*0.0122,IF(CN19>3699,CN19*0.01345,"")))) -> 0 | CQ19: 0 | CR19: =IF(CQ19<2700,CQ19*0.0097,IF(CQ19<3200,CQ19*0.01095,IF(CQ19<3700,CQ19*0.0122,IF(CQ19>3699,CQ19*0.01345,"")))) -> 0 | CT19: =BG19+BJ19+BM19+BP19+BS19+BV19+BY19+CB19+CH19+CK19+CN19+CQ19+CE19 -> 15274.131 | CU19: =BH19+BK19+BN19+BQ19+BT19+BW19+BZ19+CC19+CI19+CL19+CO19+CR19+CF19 -> 115.59461 | CV19: =+BI19+BL19+BO19+BR19+BU19+BX19+CA19+CD19+CG19+CJ19+CM19+CP19+CS19 -> 58 | CX19: =+CU19+CV19-CW19 -> 173.59461 | CY19: =+BB19+CT19 -> 37880.442 | CZ19: =+BC19+CU19 -> 320.0271 | DA19: =+BD19+CV19 -> 180 | DB19: =+CZ19+DA19 -> 500.0271
A20: =+A19+1 -> 11 | B20: RUIZ MAYOR ENRIQUE GABRIEL | C20: SIERRA 2 | F20: 0 | G20: =IF(F20<2700,F20*0.0105,IF(F20<3200,F20*0.01175,IF(F20<3700,F20*0.013,IF(F20>3699,F20*0.01425,"")))) -> 0 | H20: 30 | I20: 0 | J20: =IF(I20<2700,I20*0.0105,IF(I20<3200,I20*0.01175,IF(I20<3700,I20*0.013,IF(I20>3699,I20*0.01425,"")))) -> 0 | K20: 30 | L20: 0 | M20: =IF(L20<2700,L20*0.0105,IF(L20<3200,L20*0.01175,IF(L20<3700,L20*0.013,IF(L20>3699,L20*0.01425,"")))) -> 0 | N20: 50 | P20: =IF(O20<2700,O20*0.0105,IF(O20<3200,O20*0.01175,IF(O20<3700,O20*0.013,IF(O20>3699,O20*0.01425,"")))) -> 0 | R20: 0 | S20: =IF(R20<2700,R20*0.0105,IF(R20<3200,R20*0.01175,IF(R20<3700,R20*0.013,IF(R20>3699,R20*0.01425,"")))) -> 0 | T20: 20 | U20: 0 | V20: =IF(U20<2700,U20*0.0105,IF(U20<3200,U20*0.01175,IF(U20<3700,U20*0.013,IF(U20>3699,U20*0.01425,"")))) -> 0 | W20: 22 | X20: 0 | Y20: =IF(X20<2700,X20*0.0105,IF(X20<3200,X20*0.01175,IF(X20<3700,X20*0.013,IF(X20>3699,X20*0.01425,"")))) -> 0 | Z20: 20 | AA20: 0 | AB20: =IF(AA20<2700,AA20*0.0105,IF(AA20<3200,AA20*0.01175,IF(AA20<3700,AA20*0.013,IF(AA20>3699,AA20*0.01425,"")))) -> 0 | AC20: 22 | AD20: 0 | AE20: =IF(AD20<2700,AD20*0.0105,IF(AD20<3200,AD20*0.01175,IF(AD20<3700,AD20*0.013,IF(AD20>3699,AD20*0.01425,"")))) -> 0 | AF20: 20 | AG20: 0 | AH20: =IF(AG20<2700,AG20*0.0105,IF(AG20<3200,AG20*0.01175,IF(AG20<3700,AG20*0.013,IF(AG20>3699,AG20*0.01425,"")))) -> 0 | AI20: 20 | AJ20: 0 | AK20: =IF(AJ20<2700,AJ20*0.0105,IF(AJ20<3200,AJ20*0.01175,IF(AJ20<3700,AJ20*0.013,IF(AJ20>3699,AJ20*0.01425,"")))) -> 0 | AL20: 20 | AM20: 0 | AN20: =IF(AM20<2700,AM20*0.0105,IF(AM20<3200,AM20*0.01175,IF(AM20<3700,AM20*0.013,IF(AM20>3699,AM20*0.01425,"")))) -> 0 | AO20: 20 | AP20: 0 | AQ20: =IF(AP20<2700,AP20*0.0105,IF(AP20<3200,AP20*0.01175,IF(AP20<3700,AP20*0.013,IF(AP20>3699,AP20*0.01425,"")))) -> 0 | AR20: 20 | AS20: 0 | AT20: =IF(AS20<2700,AS20*0.01,IF(AS20<3200,AS20*0.0105,IF(AS20<3700,AS20*0.01175,IF(AS20>3699,AS20*0.013,"")))) -> 0 | AU20: 20 | AW20: =IF(AV20<2700,AV20*0.0105,IF(AV20<3200,AV20*0.01175,IF(AV20<3700,AV20*0.013,IF(AV20>3699,AV20*0.01425,"")))) -> 0 | AZ20: =IF(AY20<2700,AY20*0.0105,IF(AY20<3200,AY20*0.01175,IF(AY20<3700,AY20*0.013,IF(AY20>3699,AY20*0.01425,"")))) -> 0 | BB20: =+F20+I20+L20+O20+R20+U20+X20+AA20+AD20+AG20+AJ20+AM20+AP20+AS20+AV20+AY20 -> 0 | BC20: =+G20+J20+M20+P20+S20+V20+Y20+AB20+AE20+AH20+AK20+AN20+AQ20+AT20+AW20+AZ20 -> 0 | BD20: =+H20+K20+N20+Q20+T20+W20+Z20+AC20+AF20+AI20+AL20+AO20+AR20+AU20+AX20+BA20 -> 314 | BF20: =+BC20+BD20-BE20 -> 314 | BG20: 0 | BH20: =IF(BG20<2700,BG20*0.0105,IF(BG20<3200,BG20*0.01175,IF(BG20<3700,BG20*0.013,IF(BG20>3699,BG20*0.01425,"")))) -> 0 | BI20: 18 | BJ20: 0 | BK20: =IF(BJ20<2700,BJ20*0.0105,IF(BJ20<3200,BJ20*0.01175,IF(BJ20<3700,BJ20*0.013,IF(BJ20>3699,BJ20*0.01425,"")))) -> 0 | BL20: 18 | BM20: 0 | BN20: =IF(BM20<2700,BM20*0.0105,IF(BM20<3200,BM20*0.01175,IF(BM20<3700,BM20*0.013,IF(BM20>3699,BM20*0.01425,"")))) -> 0 | BO20: 0 | BP20: 0 | BQ20: =IF(BP20<2700,BP20*0.0105,IF(BP20<3200,BP20*0.01175,IF(BP20<3700,BP20*0.013,IF(BP20>3699,BP20*0.01425,"")))) -> 0 | BR20: 0 | BS20: 0 | BT20: =IF(BS20<2700,BS20*0.0105,IF(BS20<3200,BS20*0.01175,IF(BS20<3700,BS20*0.013,IF(BS20>3699,BS20*0.01425,"")))) -> 0 | BU20: 0 | BV20: 0 | BW20: =IF(BV20<2700,BV20*0.0105,IF(BV20<3200,BV20*0.01175,IF(BV20<3700,BV20*0.013,IF(BV20>3699,BV20*0.01425,"")))) -> 0 | BX20: 0 | BY20: 0 | BZ20: =IF(BY20<2700,BY20*0.0105,IF(BY20<3200,BY20*0.01175,IF(BY20<3700,BY20*0.013,IF(BY20>3699,BY20*0.01425,"")))) -> 0 | CA20: 18 | CB20: 0 | CC20: =IF(CB20<2700,CB20*0.0105,IF(CB20<3200,CB20*0.01175,IF(CB20<3700,CB20*0.013,IF(CB20>3699,CB20*0.01425,"")))) -> 0 | CD20: 10 | CE20: 3770.5327 | CF20: =IF(CE20<2700,CE20*0.0085,IF(CE20<3200,CE20*0.01,IF(CE20<3700,CE20*0.0105,IF(CE20>3699,CE20*0.01175,"")))) -> 44.303759 | CH20: 0 | CI20: =IF(CH20<2700,CH20*0.0105,IF(CH20<3200,CH20*0.01175,IF(CH20<3700,CH20*0.013,IF(CH20>3699,CH20*0.01425,"")))) -> 0 | CJ20: 0 | CK20: 0 | CL20: =IF(CK20<2700,CK20*0.0105,IF(CK20<3200,CK20*0.01175,IF(CK20<3700,CK20*0.013,IF(CK20>3699,CK20*0.01425,"")))) -> 0 | CM20: 18 | CN20: 0 | CO20: =IF(CN20<2700,CN20*0.0105,IF(CN20<3200,CN20*0.01175,IF(CN20<3700,CN20*0.013,IF(CN20>3699,CN20*0.01425,"")))) -> 0 | CQ20: 0 | CR20: =IF(CQ20<2700,CQ20*0.0105,IF(CQ20<3200,CQ20*0.01175,IF(CQ20<3700,CQ20*0.013,IF(CQ20>3699,CQ20*0.01425,"")))) -> 0 | CT20: =BG20+BJ20+BM20+BP20+BS20+BV20+BY20+CB20+CH20+CK20+CN20+CQ20+CE20 -> 3770.5327 | CU20: =BH20+BK20+BN20+BQ20+BT20+BW20+BZ20+CC20+CI20+CL20+CO20+CR20+CF20 -> 44.303759 | CV20: =+BI20+BL20+BO20+BR20+BU20+BX20+CA20+CD20+CG20+CJ20+CM20+CP20+CS20 -> 82 | CX20: =+CU20+CV20-CW20 -> 126.30376 | CY20: =+BB20+CT20 -> 3770.5327 | CZ20: =+BC20+CU20 -> 44.303759 | DA20: =+BD20+CV20 -> 396 | DB20: =+CZ20+DA20 -> 440.30376
A21: =+A20+1 -> 12 | B21: VALENCIA ORTEGA JORGE LUIS | C21: SIERRA 2 | F21: 0 | G21: =IF(F21<2700,F21*0.0097,IF(F21<3200,F21*0.01095,IF(F21<3700,F21*0.0122,IF(F21>3699,F21*0.01345,"")))) -> 0 | H21: 30 | I21: 0 | J21: =IF(I21<2700,I21*0.0097,IF(I21<3200,I21*0.01095,IF(I21<3700,I21*0.0122,IF(I21>3699,I21*0.01345,"")))) -> 0 | K21: 30 | L21: 0 | M21: =IF(L21<2700,L21*0.0097,IF(L21<3200,L21*0.01095,IF(L21<3700,L21*0.0122,IF(L21>3699,L21*0.01345,"")))) -> 0 | N21: 50 | P21: =IF(O21<2700,O21*0.0097,IF(O21<3200,O21*0.01095,IF(O21<3700,O21*0.0122,IF(O21>3699,O21*0.01345,"")))) -> 0 | R21: 0 | S21: =IF(R21<2700,R21*0.0097,IF(R21<3200,R21*0.01095,IF(R21<3700,R21*0.0122,IF(R21>3699,R21*0.01345,"")))) -> 0 | T21: 20 | U21: 0 | V21: =IF(U21<2700,U21*0.0097,IF(U21<3200,U21*0.01095,IF(U21<3700,U21*0.0122,IF(U21>3699,U21*0.01345,"")))) -> 0 | W21: 22 | X21: 0 | Y21: =IF(X21<2700,X21*0.0097,IF(X21<3200,X21*0.01095,IF(X21<3700,X21*0.0122,IF(X21>3699,X21*0.01345,"")))) -> 0 | Z21: 20 | AA21: 0 | AB21: =IF(AA21<2700,AA21*0.0097,IF(AA21<3200,AA21*0.01095,IF(AA21<3700,AA21*0.0122,IF(AA21>3699,AA21*0.01345,"")))) -> 0 | AC21: 22 | AD21: 0 | AE21: =IF(AD21<2700,AD21*0.0097,IF(AD21<3200,AD21*0.01095,IF(AD21<3700,AD21*0.0122,IF(AD21>3699,AD21*0.01345,"")))) -> 0 | AF21: 20 | AG21: 0 | AH21: =IF(AG21<2700,AG21*0.0097,IF(AG21<3200,AG21*0.01095,IF(AG21<3700,AG21*0.0122,IF(AG21>3699,AG21*0.01345,"")))) -> 0 | AI21: 20 | AJ21: 0 | AK21: =IF(AJ21<2700,AJ21*0.0101,IF(AJ21<3200,AJ21*0.01135,IF(AJ21<3700,AJ21*0.0126,IF(AJ21>3699,AJ21*0.01385,"")))) -> 0 | AL21: 20 | AM21: 0 | AN21: =IF(AM21<2700,AM21*0.0101,IF(AM21<3200,AM21*0.01135,IF(AM21<3700,AM21*0.0126,IF(AM21>3699,AM21*0.01385,"")))) -> 0 | AO21: 20 | AP21: 0 | AQ21: =IF(AP21<2700,AP21*0.0101,IF(AP21<3200,AP21*0.01135,IF(AP21<3700,AP21*0.0126,IF(AP21>3699,AP21*0.01385,"")))) -> 0 | AR21: 20 | AS21: 0 | AT21: =IF(AS21<2700,AS21*0.008,IF(AS21<3200,AS21*0.0097,IF(AS21<3700,AS21*0.01095,IF(AS21>3699,AS21*0.0122,"")))) -> 0 | AU21: 20 | AW21: =IF(AV21<2700,AV21*0.0097,IF(AV21<3200,AV21*0.01095,IF(AV21<3700,AV21*0.0122,IF(AV21>3699,AV21*0.01345,"")))) -> 0 | AZ21: =IF(AY21<2700,AY21*0.0097,IF(AY21<3200,AY21*0.01095,IF(AY21<3700,AY21*0.0122,IF(AY21>3699,AY21*0.01345,"")))) -> 0 | BB21: =+F21+I21+L21+O21+R21+U21+X21+AA21+AD21+AG21+AJ21+AM21+AP21+AS21+AV21+AY21 -> 0 | BC21: =+G21+J21+M21+P21+S21+V21+Y21+AB21+AE21+AH21+AK21+AN21+AQ21+AT21+AW21+AZ21 -> 0 | BD21: =+H21+K21+N21+Q21+T21+W21+Z21+AC21+AF21+AI21+AL21+AO21+AR21+AU21+AX21+BA21 -> 314 | BF21: =+BC21+BD21-BE21 -> 314 | BG21: 0 | BH21: =IF(BG21<2700,BG21*0.0101,IF(BG21<3200,BG21*0.01135,IF(BG21<3700,BG21*0.0126,IF(BG21>3699,BG21*0.01385,"")))) -> 0 | BI21: 18 | BJ21: 0 | BK21: =IF(BJ21<2700,BJ21*0.0101,IF(BJ21<3200,BJ21*0.01135,IF(BJ21<3700,BJ21*0.0126,IF(BJ21>3699,BJ21*0.01385,"")))) -> 0 | BL21: 18 | BM21: 2688.4824 | BN21: =IF(BM21<2700,BM21*0.0085,IF(BM21<3200,BM21*0.01,IF(BM21<3700,BM21*0.0105,IF(BM21>3699,BM21*0.01175,"")))) -> 22.852101 | BP21: 2289.0452 | BQ21: =IF(BP21<2700,BP21*0.0085,IF(BP21<3200,BP21*0.01,IF(BP21<3700,BP21*0.0105,IF(BP21>3699,BP21*0.01175,"")))) -> 19.456884 | BS21: 2610.3317 | BT21: =IF(BS21<2700,BS21*0.0085,IF(BS21<3200,BS21*0.01,IF(BS21<3700,BS21*0.0105,IF(BS21>3699,BS21*0.01175,"")))) -> 22.187819 | BV21: 2656.1608 | BW21: =IF(BV21<2700,BV21*0.0085,IF(BV21<3200,BV21*0.01,IF(BV21<3700,BV21*0.0105,IF(BV21>3699,BV21*0.01175,"")))) -> 22.577367 | BY21: 1495.9598 | BZ21: =IF(BY21<2700,BY21*0.0085,IF(BY21<3200,BY21*0.01,IF(BY21<3700,BY21*0.0105,IF(BY21>3699,BY21*0.01175,"")))) -> 12.715658 | CB21: 0 | CC21: =IF(CB21<2700,CB21*0.0097,IF(CB21<3200,CB21*0.01095,IF(CB21<3700,CB21*0.0122,IF(CB21>3699,CB21*0.01345,"")))) -> 0 | CD21: 10 | CE21: 3770.5327 | CF21: =IF(CE21<2700,CE21*0.007,IF(CE21<3200,CE21*0.008,IF(CE21<3700,CE21*0.0097,IF(CE21>3699,CE21*0.01095,"")))) -> 41.287333 | CH21: 0 | CI21: =IF(CH21<2700,CH21*0.0097,IF(CH21<3200,CH21*0.01095,IF(CH21<3700,CH21*0.0122,IF(CH21>3699,CH21*0.01345,"")))) -> 0 | CJ21: 0 | CK21: 0 | CL21: =IF(CK21<2700,CK21*0.0097,IF(CK21<3200,CK21*0.01095,IF(CK21<3700,CK21*0.0122,IF(CK21>3699,CK21*0.01345,"")))) -> 0 | CM21: 18 | CN21: 0 | CO21: =IF(CN21<2700,CN21*0.0097,IF(CN21<3200,CN21*0.01095,IF(CN21<3700,CN21*0.0122,IF(CN21>3699,CN21*0.01345,"")))) -> 0 | CQ21: 0 | CR21: =IF(CQ21<2700,CQ21*0.0097,IF(CQ21<3200,CQ21*0.01095,IF(CQ21<3700,CQ21*0.0122,IF(CQ21>3699,CQ21*0.01345,"")))) -> 0 | CT21: =BG21+BJ21+BM21+BP21+BS21+BV21+BY21+CB21+CH21+CK21+CN21+CQ21+CE21 -> 15510.513 | CU21: =BH21+BK21+BN21+BQ21+BT21+BW21+BZ21+CC21+CI21+CL21+CO21+CR21+CF21 -> 141.07716 | CV21: =+BI21+BL21+BO21+BR21+BU21+BX21+CA21+CD21+CG21+CJ21+CM21+CP21+CS21 -> 64 | CX21: =+CU21+CV21-CW21 -> 205.07716 | CY21: =+BB21+CT21 -> 15510.513 | CZ21: =+BC21+CU21 -> 141.07716 | DA21: =+BD21+CV21 -> 378 | DB21: =+CZ21+DA21 -> 519.07716
A22: =+A21+1 -> 13 | B22: BARREIRO VELEZ CRISTHIAN GEOVANNY | C22: SIERRA 3 | D22: 0993779176 | E22: cristhianbarreiro35@gmail.com | F22: 3582.8744 | G22: =IF(F22<2700,F22*0.0085,IF(F22<3200,F22*0.01,IF(F22<3700,F22*0.0105,IF(F22>3699,F22*0.01175,"")))) -> 37.620181 | I22: 0 | J22: =IF(I22<2700,I22*0.0105,IF(I22<3200,I22*0.01175,IF(I22<3700,I22*0.013,IF(I22>3699,I22*0.01425,"")))) -> 0 | L22: 3431.397 | M22: =IF(L22<2700,L22*0.0085,IF(L22<3200,L22*0.01,IF(L22<3700,L22*0.0105,IF(L22>3699,L22*0.01175,"")))) -> 36.029668 | P22: =IF(O22<2700,O22*0.0105,IF(O22<3200,O22*0.01175,IF(O22<3700,O22*0.013,IF(O22>3699,O22*0.01425,"")))) -> 0 | R22: 4473.407 | S22: =IF(R22<2700,R22*0.0085,IF(R22<3200,R22*0.01,IF(R22<3700,R22*0.0105,IF(R22>3699,R22*0.01175,"")))) -> 52.562533 | U22: 3696.7236 | V22: =IF(U22<2700,U22*0.0085,IF(U22<3200,U22*0.01,IF(U22<3700,U22*0.0105,IF(U22>3699,U22*0.01175,"")))) -> 38.815598 | X22: 3216.7236 | Y22: =IF(X22<2700,X22*0.0085,IF(X22<3200,X22*0.01,IF(X22<3700,X22*0.0105,IF(X22>3699,X22*0.01175,"")))) -> 33.775598 | AA22: 1894.4322 | AB22: =IF(AA22<2700,AA22*0.0085,IF(AA22<3200,AA22*0.01,IF(AA22<3700,AA22*0.0105,IF(AA22>3699,AA22*0.01175,"")))) -> 16.102673 | AD22: 8091.0151 | AE22: =IF(AD22<2700,AD22*0.0085,IF(AD22<3200,AD22*0.01,IF(AD22<3700,AD22*0.0105,IF(AD22>3699,AD22*0.01175,"")))) -> 95.069427 | AG22: 0 | AH22: =IF(AG22<2700,AG22*0.0105,IF(AG22<3200,AG22*0.01175,IF(AG22<3700,AG22*0.013,IF(AG22>3699,AG22*0.01425,"")))) -> 0 | AJ22: 0 | AK22: =IF(AJ22<2700,AJ22*0.0105,IF(AJ22<3200,AJ22*0.01175,IF(AJ22<3700,AJ22*0.013,IF(AJ22>3699,AJ22*0.01425,"")))) -> 0 | AM22: 3446.8342 | AN22: =IF(AM22<2700,AM22*0.0085,IF(AM22<3200,AM22*0.01,IF(AM22<3700,AM22*0.0105,IF(AM22>3699,AM22*0.01175,"")))) -> 36.191759 | AP22: 0 | AQ22: =IF(AP22<2700,AP22*0.0105,IF(AP22<3200,AP22*0.01175,IF(AP22<3700,AP22*0.013,IF(AP22>3699,AP22*0.01425,"")))) -> 0 | AR22: 12 | AS22: 3807.6784 | AT22: =IF(AS22<2700,AS22*0.0085,IF(AS22<3200,AS22*0.01,IF(AS22<3700,AS22*0.0105,IF(AS22>3699,AS22*0.01175,"")))) -> 44.740221 | AW22: =IF(AV22<2700,AV22*0.0105,IF(AV22<3200,AV22*0.01175,IF(AV22<3700,AV22*0.013,IF(AV22>3699,AV22*0.01425,"")))) -> 0 | AZ22: =IF(AY22<2700,AY22*0.0105,IF(AY22<3200,AY22*0.01175,IF(AY22<3700,AY22*0.013,IF(AY22>3699,AY22*0.01425,"")))) -> 0 | BB22: =+F22+I22+L22+O22+R22+U22+X22+AA22+AD22+AG22+AJ22+AM22+AP22+AS22+AV22+AY22 -> 35641.085 | BC22: =+G22+J22+M22+P22+S22+V22+Y22+AB22+AE22+AH22+AK22+AN22+AQ22+AT22+AW22+AZ22 -> 390.90766 | BD22: =+H22+K22+N22+Q22+T22+W22+Z22+AC22+AF22+AI22+AL22+AO22+AR22+AU22+AX22+BA22 -> 12 | BF22: =+BC22+BD22-BE22 -> 402.90766 | BG22: 3813.4673 | BH22: =IF(BG22<2700,BG22*0.0085,IF(BG22<3200,BG22*0.01,IF(BG22<3700,BG22*0.0105,IF(BG22>3699,BG22*0.01175,"")))) -> 44.808241 | BJ22: 0 | BK22: =IF(BJ22<2700,BJ22*0.0105,IF(BJ22<3200,BJ22*0.01175,IF(BJ22<3700,BJ22*0.013,IF(BJ22>3699,BJ22*0.01425,"")))) -> 0 | BL22: 0 | BM22: 2916.6633 | BN22: =IF(BM22<2700,BM22*0.0085,IF(BM22<3200,BM22*0.01,IF(BM22<3700,BM22*0.0105,IF(BM22>3699,BM22*0.01175,"")))) -> 29.166633 | BP22: 3408.2412 | BQ22: =IF(BP22<2700,BP22*0.0085,IF(BP22<3200,BP22*0.01,IF(BP22<3700,BP22*0.0105,IF(BP22>3699,BP22*0.01175,"")))) -> 35.786533 | BS22: 3149.6683 | BT22: =IF(BS22<2700,BS22*0.0085,IF(BS22<3200,BS22*0.01,IF(BS22<3700,BS22*0.0105,IF(BS22>3699,BS22*0.01175,"")))) -> 31.496683 | BV22: 3216.2412 | BW22: =IF(BV22<2700,BV22*0.0085,IF(BV22<3200,BV22*0.01,IF(BV22<3700,BV22*0.0105,IF(BV22>3699,BV22*0.01175,"")))) -> 33.770533 | BY22: 1519.598 | BZ22: =IF(BY22<2700,BY22*0.0085,IF(BY22<3200,BY22*0.01,IF(BY22<3700,BY22*0.0105,IF(BY22>3699,BY22*0.01175,"")))) -> 12.916583 | CB22: 0 | CC22: =IF(CB22<2700,CB22*0.0105,IF(CB22<3200,CB22*0.01175,IF(CB22<3700,CB22*0.013,IF(CB22>3699,CB22*0.01425,"")))) -> 0 | CD22: 0 | CE22: 3801.8894 | CF22: =IF(CE22<2700,CE22*0.0085,IF(CE22<3200,CE22*0.01,IF(CE22<3700,CE22*0.0105,IF(CE22>3699,CE22*0.01175,"")))) -> 44.672201 | CH22: 0 | CI22: =IF(CH22<2700,CH22*0.0105,IF(CH22<3200,CH22*0.01175,IF(CH22<3700,CH22*0.013,IF(CH22>3699,CH22*0.01425,"")))) -> 0 | CJ22: 0 | CK22: 0 | CL22: =IF(CK22<2700,CK22*0.0105,IF(CK22<3200,CK22*0.01175,IF(CK22<3700,CK22*0.013,IF(CK22>3699,CK22*0.01425,"")))) -> 0 | CM22: 0 | CN22: 0 | CO22: =IF(CN22<2700,CN22*0.0105,IF(CN22<3200,CN22*0.01175,IF(CN22<3700,CN22*0.013,IF(CN22>3699,CN22*0.01425,"")))) -> 0 | CQ22: 0 | CR22: =IF(CQ22<2700,CQ22*0.0105,IF(CQ22<3200,CQ22*0.01175,IF(CQ22<3700,CQ22*0.013,IF(CQ22>3699,CQ22*0.01425,"")))) -> 0 | CT22: =BG22+BJ22+BM22+BP22+BS22+BV22+BY22+CB22+CH22+CK22+CN22+CQ22+CE22 -> 21825.769 | CU22: =BH22+BK22+BN22+BQ22+BT22+BW22+BZ22+CC22+CI22+CL22+CO22+CR22+CF22 -> 232.61741 | CV22: =+BI22+BL22+BO22+BR22+BU22+BX22+CA22+CD22+CG22+CJ22+CM22+CP22+CS22 -> 0 | CX22: =+CU22+CV22-CW22 -> 232.61741 | CY22: =+BB22+CT22 -> 57466.854 | CZ22: =+BC22+CU22 -> 623.52507 | DA22: =+BD22+CV22 -> 12 | DB22: =+CZ22+DA22 -> 635.52507 | DC22: Permiso Medico 1 dias, 07-06-2021
A23: =+A22+1 -> 14 | B23: ZAMBRANO VARGAS YORDI EMEREGILDO | C23: SIERRA 3 | D23: 0988642074 | E23: darelzambrano09@gmail.com | F23: 0 | G23: =IF(F23<2700,F23*0.008,IF(F23<3200,F23*0.0097,IF(F23<3700,F23*0.01095,IF(F23>3699,F23*0.0122,"")))) -> 0 | H23: 18 | I23: 0 | J23: =IF(I23<2700,I23*0.008,IF(I23<3200,I23*0.0097,IF(I23<3700,I23*0.01095,IF(I23>3699,I23*0.0122,"")))) -> 0 | K23: 18 | L23: 3418.3719 | M23: =IF(L23<2700,L23*0.007,IF(L23<3200,L23*0.008,IF(L23<3700,L23*0.0097,IF(L23>3699,L23*0.01095,"")))) -> 33.158207 | P23: =IF(O23<2700,O23*0.0097,IF(O23<3200,O23*0.01095,IF(O23<3700,O23*0.0122,IF(O23>3699,O23*0.01345,"")))) -> 0 | R23: 4473.407 | S23: =IF(R23<2700,R23*0.007,IF(R23<3200,R23*0.008,IF(R23<3700,R23*0.0097,IF(R23>3699,R23*0.01095,"")))) -> 48.983807 | U23: 3696.7236 | V23: =IF(U23<2700,U23*0.007,IF(U23<3200,U23*0.008,IF(U23<3700,U23*0.0097,IF(U23>3699,U23*0.01095,"")))) -> 35.858219 | X23: 3216.7236 | Y23: =IF(X23<2700,X23*0.007,IF(X23<3200,X23*0.008,IF(X23<3700,X23*0.0097,IF(X23>3699,X23*0.01095,"")))) -> 31.202219 | AA23: 1894.4322 | AB23: =IF(AA23<2700,AA23*0.007,IF(AA23<3200,AA23*0.008,IF(AA23<3700,AA23*0.0097,IF(AA23>3699,AA23*0.01095,"")))) -> 13.261025 | AD23: 8091.0151 | AE23: =IF(AD23<2700,AD23*0.007,IF(AD23<3200,AD23*0.008,IF(AD23<3700,AD23*0.0097,IF(AD23>3699,AD23*0.01095,"")))) -> 88.596615 | AG23: 0 | AH23: =IF(AG23<2700,AG23*0.0097,IF(AG23<3200,AG23*0.01095,IF(AG23<3700,AG23*0.0122,IF(AG23>3699,AG23*0.01345,"")))) -> 0 | AJ23: 0 | AK23: =IF(AJ23<2700,AJ23*0.008,IF(AJ23<3200,AJ23*0.0097,IF(AJ23<3700,AJ23*0.01095,IF(AJ23>3699,AJ23*0.0122,"")))) -> 0 | AL23: 20 | AM23: 3446.8342 | AN23: =IF(AM23<2700,AM23*0.007,IF(AM23<3200,AM23*0.008,IF(AM23<3700,AM23*0.0097,IF(AM23>3699,AM23*0.01095,"")))) -> 33.434291 | AP23: 0 | AQ23: =IF(AP23<2700,AP23*0.0097,IF(AP23<3200,AP23*0.01095,IF(AP23<3700,AP23*0.0122,IF(AP23>3699,AP23*0.01345,"")))) -> 0 | AR23: 12 | AS23: 3807.6784 | AT23: =IF(AS23<2700,AS23*0.007,IF(AS23<3200,AS23*0.008,IF(AS23<3700,AS23*0.0097,IF(AS23>3699,AS23*0.01095,"")))) -> 41.694078 | AW23: =IF(AV23<2700,AV23*0.0097,IF(AV23<3200,AV23*0.01095,IF(AV23<3700,AV23*0.0122,IF(AV23>3699,AV23*0.01345,"")))) -> 0 | AZ23: =IF(AY23<2700,AY23*0.0097,IF(AY23<3200,AY23*0.01095,IF(AY23<3700,AY23*0.0122,IF(AY23>3699,AY23*0.01345,"")))) -> 0 | BB23: =+F23+I23+L23+O23+R23+U23+X23+AA23+AD23+AG23+AJ23+AM23+AP23+AS23+AV23+AY23 -> 32045.186 | BC23: =+G23+J23+M23+P23+S23+V23+Y23+AB23+AE23+AH23+AK23+AN23+AQ23+AT23+AW23+AZ23 -> 326.18846 | BD23: =+H23+K23+N23+Q23+T23+W23+Z23+AC23+AF23+AI23+AL23+AO23+AR23+AU23+AX23+BA23 -> 68 | BF23: =+BC23+BD23-BE23 -> 394.18846 | BG23: 3813.4673 | BH23: =IF(BG23<2700,BG23*0.007,IF(BG23<3200,BG23*0.008,IF(BG23<3700,BG23*0.0097,IF(BG23>3699,BG23*0.01095,"")))) -> 41.757467 | BJ23: 0 | BK23: =IF(BJ23<2700,BJ23*0.0097,IF(BJ23<3200,BJ23*0.01095,IF(BJ23<3700,BJ23*0.0122,IF(BJ23>3699,BJ23*0.01345,"")))) -> 0 | BL23: 0 | BM23: 2916.6633 | BN23: =IF(BM23<2700,BM23*0.007,IF(BM23<3200,BM23*0.008,IF(BM23<3700,BM23*0.0097,IF(BM23>3699,BM23*0.01095,"")))) -> 23.333307 | BP23: 3408.2412 | BQ23: =IF(BP23<2700,BP23*0.007,IF(BP23<3200,BP23*0.008,IF(BP23<3700,BP23*0.0097,IF(BP23>3699,BP23*0.01095,"")))) -> 33.05994 | BS23: 3149.6683 | BT23: =IF(BS23<2700,BS23*0.007,IF(BS23<3200,BS23*0.008,IF(BS23<3700,BS23*0.0097,IF(BS23>3699,BS23*0.01095,"")))) -> 25.197347 | BV23: 3216.2412 | BW23: =IF(BV23<2700,BV23*0.007,IF(BV23<3200,BV23*0.008,IF(BV23<3700,BV23*0.0097,IF(BV23>3699,BV23*0.01095,"")))) -> 31.19754 | BY23: 1519.598 | BZ23: =IF(BY23<2700,BY23*0.007,IF(BY23<3200,BY23*0.008,IF(BY23<3700,BY23*0.0097,IF(BY23>3699,BY23*0.01095,"")))) -> 10.637186 | CB23: 0 | CC23: =IF(CB23<2700,CB23*0.0097,IF(CB23<3200,CB23*0.01095,IF(CB23<3700,CB23*0.0122,IF(CB23>3699,CB23*0.01345,"")))) -> 0 | CD23: 0 | CE23: 3801.8894 | CF23: =IF(CE23<2700,CE23*0.007,IF(CE23<3200,CE23*0.008,IF(CE23<3700,CE23*0.0097,IF(CE23>3699,CE23*0.01095,"")))) -> 41.630689 | CH23: 0 | CI23: =IF(CH23<2700,CH23*0.0097,IF(CH23<3200,CH23*0.01095,IF(CH23<3700,CH23*0.0122,IF(CH23>3699,CH23*0.01345,"")))) -> 0 | CJ23: 0 | CK23: 0 | CL23: =IF(CK23<2700,CK23*0.0097,IF(CK23<3200,CK23*0.01095,IF(CK23<3700,CK23*0.0122,IF(CK23>3699,CK23*0.01345,"")))) -> 0 | CM23: 0 | CN23: 0 | CO23: =IF(CN23<2700,CN23*0.0097,IF(CN23<3200,CN23*0.01095,IF(CN23<3700,CN23*0.0122,IF(CN23>3699,CN23*0.01345,"")))) -> 0 | CQ23: 0 | CR23: =IF(CQ23<2700,CQ23*0.0097,IF(CQ23<3200,CQ23*0.01095,IF(CQ23<3700,CQ23*0.0122,IF(CQ23>3699,CQ23*0.01345,"")))) -> 0 | CT23: =BG23+BJ23+BM23+BP23+BS23+BV23+BY23+CB23+CH23+CK23+CN23+CQ23+CE23 -> 21825.769 | CU23: =BH23+BK23+BN23+BQ23+BT23+BW23+BZ23+CC23+CI23+CL23+CO23+CR23+CF23 -> 206.81348 | CV23: =+BI23+BL23+BO23+BR23+BU23+BX23+CA23+CD23+CG23+CJ23+CM23+CP23+CS23 -> 0 | CX23: =+CU23+CV23-CW23 -> 206.81348 | CY23: =+BB23+CT23 -> 53870.955 | CZ23: =+BC23+CU23 -> 533.00194 | DA23: =+BD23+CV23 -> 68 | DB23: =+CZ23+DA23 -> 601.00194
A24: =+A23+1 -> 15 | B24: ZAMBRANO ROSADO SOFIA LUCIOLA | C24: SIERRA 3 | D24: 0991906778 | E24: Zambranosofia172@hotmail.com | F24: 3582.8744 | G24: =IF(F24<2700,F24*0.0075,IF(F24<3200,F24*0.009,IF(F24<3700,F24*0.0101,IF(F24>3699,F24*0.01135,"")))) -> 36.187031 | I24: 2377.809 | J24: =IF(I24<2700,I24*0.0075,IF(I24<3200,I24*0.009,IF(I24<3700,I24*0.0101,IF(I24>3699,I24*0.01135,"")))) -> 17.833568 | L24: 3431.397 | M24: =IF(L24<2700,L24*0.0075,IF(L24<3200,L24*0.009,IF(L24<3700,L24*0.0101,IF(L24>3699,L24*0.01135,"")))) -> 34.65711 | P24: =IF(O24<2700,O24*0.0101,IF(O24<3200,O24*0.01135,IF(O24<3700,O24*0.0126,IF(O24>3699,O24*0.01385,"")))) -> 0 | R24: 4473.407 | S24: =IF(R24<2700,R24*0.0075,IF(R24<3200,R24*0.009,IF(R24<3700,R24*0.0101,IF(R24>3699,R24*0.01135,"")))) -> 50.77317 | U24: 3696.7236 | V24: =IF(U24<2700,U24*0.0075,IF(U24<3200,U24*0.009,IF(U24<3700,U24*0.0101,IF(U24>3699,U24*0.01135,"")))) -> 37.336909 | X24: 3216.7236 | Y24: =IF(X24<2700,X24*0.0075,IF(X24<3200,X24*0.009,IF(X24<3700,X24*0.0101,IF(X24>3699,X24*0.01135,"")))) -> 32.488909 | AA24: 1894.4322 | AB24: =IF(AA24<2700,AA24*0.0075,IF(AA24<3200,AA24*0.009,IF(AA24<3700,AA24*0.0101,IF(AA24>3699,AA24*0.01135,"")))) -> 14.208241 | AD24: 8091.0151 | AE24: =IF(AD24<2700,AD24*0.0075,IF(AD24<3200,AD24*0.009,IF(AD24<3700,AD24*0.0101,IF(AD24>3699,AD24*0.01135,"")))) -> 91.833021 | AG24: 0 | AH24: =IF(AG24<2700,AG24*0.0101,IF(AG24<3200,AG24*0.01135,IF(AG24<3700,AG24*0.0126,IF(AG24>3699,AG24*0.01385,"")))) -> 0 | AJ24: 3043.5377 | AK24: =IF(AJ24<2700,AJ24*0.0075,IF(AJ24<3200,AJ24*0.009,IF(AJ24<3700,AJ24*0.0101,IF(AJ24>3699,AJ24*0.01135,"")))) -> 27.391839 | AM24: 3446.8342 | AN24: =IF(AM24<2700,AM24*0.0075,IF(AM24<3200,AM24*0.009,IF(AM24<3700,AM24*0.0101,IF(AM24>3699,AM24*0.01135,"")))) -> 34.813025 | AP24: 0 | AQ24: =IF(AP24<2700,AP24*0.0101,IF(AP24<3200,AP24*0.01135,IF(AP24<3700,AP24*0.0126,IF(AP24>3699,AP24*0.01385,"")))) -> 0 | AR24: 12 | AS24: 3807.6784 | AT24: =IF(AS24<2700,AS24*0.0075,IF(AS24<3200,AS24*0.009,IF(AS24<3700,AS24*0.0101,IF(AS24>3699,AS24*0.01135,"")))) -> 43.21715 | AW24: =IF(AV24<2700,AV24*0.0101,IF(AV24<3200,AV24*0.01135,IF(AV24<3700,AV24*0.0126,IF(AV24>3699,AV24*0.01385,"")))) -> 0 | AZ24: =IF(AY24<2700,AY24*0.0101,IF(AY24<3200,AY24*0.01135,IF(AY24<3700,AY24*0.0126,IF(AY24>3699,AY24*0.01385,"")))) -> 0 | BB24: =+F24+I24+L24+O24+R24+U24+X24+AA24+AD24+AG24+AJ24+AM24+AP24+AS24+AV24+AY24 -> 41062.432 | BC24: =+G24+J24+M24+P24+S24+V24+Y24+AB24+AE24+AH24+AK24+AN24+AQ24+AT24+AW24+AZ24 -> 420.73997 | BD24: =+H24+K24+N24+Q24+T24+W24+Z24+AC24+AF24+AI24+AL24+AO24+AR24+AU24+AX24+BA24 -> 12 | BF24: =+BC24+BD24-BE24 -> 432.73997 | BG24: 3813.4673 | BH24: =IF(BG24<2700,BG24*0.0075,IF(BG24<3200,BG24*0.009,IF(BG24<3700,BG24*0.0101,IF(BG24>3699,BG24*0.01135,"")))) -> 43.282854 | BJ24: 0 | BK24: =IF(BJ24<2700,BJ24*0.0101,IF(BJ24<3200,BJ24*0.01135,IF(BJ24<3700,BJ24*0.0126,IF(BJ24>3699,BJ24*0.01385,"")))) -> 0 | BL24: 12 | BM24: 2916.6633 | BN24: =IF(BM24<2700,BM24*0.0075,IF(BM24<3200,BM24*0.009,IF(BM24<3700,BM24*0.0101,IF(BM24>3699,BM24*0.01135,"")))) -> 26.24997 | BP24: 3408.2412 | BQ24: =IF(BP24<2700,BP24*0.0075,IF(BP24<3200,BP24*0.009,IF(BP24<3700,BP24*0.0101,IF(BP24>3699,BP24*0.01135,"")))) -> 34.423236 | BS24: 3149.6683 | BT24: =IF(BS24<2700,BS24*0.0075,IF(BS24<3200,BS24*0.009,IF(BS24<3700,BS24*0.0101,IF(BS24>3699,BS24*0.01135,"")))) -> 28.347015 | BV24: 3216.2412 | BW24: =IF(BV24<2700,BV24*0.0075,IF(BV24<3200,BV24*0.009,IF(BV24<3700,BV24*0.0101,IF(BV24>3699,BV24*0.01135,"")))) -> 32.484036 | BY24: 1519.598 | BZ24: =IF(BY24<2700,BY24*0.0075,IF(BY24<3200,BY24*0.009,IF(BY24<3700,BY24*0.0101,IF(BY24>3699,BY24*0.01135,"")))) -> 11.396985 | CB24: 0 | CC24: =IF(CB24<2700,CB24*0.0101,IF(CB24<3200,CB24*0.01135,IF(CB24<3700,CB24*0.0126,IF(CB24>3699,CB24*0.01385,"")))) -> 0 | CD24: 10 | CE24: 3801.8894 | CF24: =IF(CE24<2700,CE24*0.0075,IF(CE24<3200,CE24*0.009,IF(CE24<3700,CE24*0.0101,IF(CE24>3699,CE24*0.01135,"")))) -> 43.151445 | CH24: 0 | CI24: =IF(CH24<2700,CH24*0.0101,IF(CH24<3200,CH24*0.01135,IF(CH24<3700,CH24*0.0126,IF(CH24>3699,CH24*0.01385,"")))) -> 0 | CJ24: 18 | CK24: 0 | CL24: =IF(CK24<2700,CK24*0.0101,IF(CK24<3200,CK24*0.01135,IF(CK24<3700,CK24*0.0126,IF(CK24>3699,CK24*0.01385,"")))) -> 0 | CM24: 18 | CN24: 0 | CO24: =IF(CN24<2700,CN24*0.0101,IF(CN24<3200,CN24*0.01135,IF(CN24<3700,CN24*0.0126,IF(CN24>3699,CN24*0.01385,"")))) -> 0 | CQ24: 0 | CR24: =IF(CQ24<2700,CQ24*0.0101,IF(CQ24<3200,CQ24*0.01135,IF(CQ24<3700,CQ24*0.0126,IF(CQ24>3699,CQ24*0.01385,"")))) -> 0 | CT24: =BG24+BJ24+BM24+BP24+BS24+BV24+BY24+CB24+CH24+CK24+CN24+CQ24+CE24 -> 21825.769 | CU24: =BH24+BK24+BN24+BQ24+BT24+BW24+BZ24+CC24+CI24+CL24+CO24+CR24+CF24 -> 219.33554 | CV24: =+BI24+BL24+BO24+BR24+BU24+BX24+CA24+CD24+CG24+CJ24+CM24+CP24+CS24 -> 58 | CX24: =+CU24+CV24-CW24 -> 277.33554 | CY24: =+BB24+CT24 -> 62888.201 | CZ24: =+BC24+CU24 -> 640.07551 | DA24: =+BD24+CV24 -> 70 | DB24: =+CZ24+DA24 -> 710.07551
A25: =+A24+1 -> 16 | B25: MANZABA BRAVO LIDER ANTONIO | C25: SIERRA 4 | D25: 0987980050 | E25: antoniomanzababravo@gmail.com | F25: 0 | G25: =IF(F25<2700,F25*0.0097,IF(F25<3200,F25*0.01095,IF(F25<3700,F25*0.0122,IF(F25>3699,F25*0.01345,"")))) -> 0 | H25: 20 | I25: 0 | J25: =IF(I25<2700,I25*0.0097,IF(I25<3200,I25*0.01095,IF(I25<3700,I25*0.0122,IF(I25>3699,I25*0.01345,"")))) -> 0 | K25: 20 | L25: 0 | M25: =IF(L25<2700,L25*0.0097,IF(L25<3200,L25*0.01095,IF(L25<3700,L25*0.0122,IF(L25>3699,L25*0.01345,"")))) -> 0 | N25: 40 | P25: =IF(O25<2700,O25*0.0097,IF(O25<3200,O25*0.01095,IF(O25<3700,O25*0.0122,IF(O25>3699,O25*0.01345,"")))) -> 0 | R25: 0 | S25: =IF(R25<2700,R25*0.0097,IF(R25<3200,R25*0.01095,IF(R25<3700,R25*0.0122,IF(R25>3699,R25*0.01345,"")))) -> 0 | T25: 18 | U25: 0 | V25: =IF(U25<2700,U25*0.0097,IF(U25<3200,U25*0.01095,IF(U25<3700,U25*0.0122,IF(U25>3699,U25*0.01345,"")))) -> 0 | W25: 18 | X25: 0 | Y25: =IF(X25<2700,X25*0.0097,IF(X25<3200,X25*0.01095,IF(X25<3700,X25*0.0122,IF(X25>3699,X25*0.01345,"")))) -> 0 | Z25: 18 | AA25: 0 | AB25: =IF(AA25<2700,AA25*0.0097,IF(AA25<3200,AA25*0.01095,IF(AA25<3700,AA25*0.0122,IF(AA25>3699,AA25*0.01345,"")))) -> 0 | AC25: 18 | AD25: 0 | AE25: =IF(AD25<2700,AD25*0.0097,IF(AD25<3200,AD25*0.01095,IF(AD25<3700,AD25*0.0122,IF(AD25>3699,AD25*0.01345,"")))) -> 0 | AF25: 18 | AG25: 0 | AH25: =IF(AG25<2700,AG25*0.0097,IF(AG25<3200,AG25*0.01095,IF(AG25<3700,AG25*0.0122,IF(AG25>3699,AG25*0.01345,"")))) -> 0 | AI25: 18 | AJ25: 0 | AK25: =IF(AJ25<2700,AJ25*0.0097,IF(AJ25<3200,AJ25*0.01095,IF(AJ25<3700,AJ25*0.0122,IF(AJ25>3699,AJ25*0.01345,"")))) -> 0 | AL25: 18 | AM25: 0 | AN25: =IF(AM25<2700,AM25*0.007,IF(AM25<3200,AM25*0.008,IF(AM25<3700,AM25*0.0097,IF(AM25>3699,AM25*0.01095,"")))) -> 0 | AO25: 18 | AP25: 0 | AQ25: =IF(AP25<2700,AP25*0.0097,IF(AP25<3200,AP25*0.01095,IF(AP25<3700,AP25*0.0122,IF(AP25>3699,AP25*0.01345,"")))) -> 0 | AR25: 18 | AS25: 0 | AT25: =IF(AS25<2700,AS25*0.007,IF(AS25<3200,AS25*0.008,IF(AS25<3700,AS25*0.0097,IF(AS25>3699,AS25*0.01095,"")))) -> 0 | AU25: 18 | AW25: =IF(AV25<2700,AV25*0.0097,IF(AV25<3200,AV25*0.01095,IF(AV25<3700,AV25*0.0122,IF(AV25>3699,AV25*0.01345,"")))) -> 0 | AZ25: =IF(AY25<2700,AY25*0.0097,IF(AY25<3200,AY25*0.01095,IF(AY25<3700,AY25*0.0122,IF(AY25>3699,AY25*0.01345,"")))) -> 0 | BB25: =+F25+I25+L25+O25+R25+U25+X25+AA25+AD25+AG25+AJ25+AM25+AP25+AS25+AV25+AY25 -> 0 | BC25: =+G25+J25+M25+P25+S25+V25+Y25+AB25+AE25+AH25+AK25+AN25+AQ25+AT25+AW25+AZ25 -> 0 | BD25: =+H25+K25+N25+Q25+T25+W25+Z25+AC25+AF25+AI25+AL25+AO25+AR25+AU25+AX25+BA25 -> 260 | BF25: =+BC25+BD25-BE25 -> 260 | BG25: 0 | BH25: =IF(BG25<2700,BG25*0.007,IF(BG25<3200,BG25*0.008,IF(BG25<3700,BG25*0.0097,IF(BG25>3699,BG25*0.01095,"")))) -> 0 | BI25: 18 | BJ25: 0 | BK25: =IF(BJ25<2700,BJ25*0.0097,IF(BJ25<3200,BJ25*0.01095,IF(BJ25<3700,BJ25*0.0122,IF(BJ25>3699,BJ25*0.01345,"")))) -> 0 | BL25: 18 | BM25: 3126.0302 | BN25: =IF(BM25<2700,BM25*0.007,IF(BM25<3200,BM25*0.008,IF(BM25<3700,BM25*0.0097,IF(BM25>3699,BM25*0.01095,"")))) -> 25.008241 | BP25: 2573.1859 | BQ25: =IF(BP25<2700,BP25*0.007,IF(BP25<3200,BP25*0.008,IF(BP25<3700,BP25*0.0097,IF(BP25>3699,BP25*0.01095,"")))) -> 18.012302 | BS25: 2940.7839 | BT25: =IF(BS25<2700,BS25*0.008,IF(BS25<3200,BS25*0.0097,IF(BS25<3700,BS25*0.01095,IF(BS25>3699,BS25*0.0122,"")))) -> 28.525604 | BV25: 2406.2714 | BW25: =IF(BV25<2700,BV25*0.008,IF(BV25<3200,BV25*0.0097,IF(BV25<3700,BV25*0.01095,IF(BV25>3699,BV25*0.0122,"")))) -> 19.250171 | BY25: 0 | BZ25: =IF(BY25<2700,BY25*0.0097,IF(BY25<3200,BY25*0.01095,IF(BY25<3700,BY25*0.0122,IF(BY25>3699,BY25*0.01345,"")))) -> 0 | CB25: 0 | CC25: =IF(CB25<2700,CB25*0.0097,IF(CB25<3200,CB25*0.01095,IF(CB25<3700,CB25*0.0122,IF(CB25>3699,CB25*0.01345,"")))) -> 0 | CD25: 0 | CE25: 3016.0402 | CF25: =IF(CE25<2700,CE25*0.008,IF(CE25<3200,CE25*0.0097,IF(CE25<3700,CE25*0.01095,IF(CE25>3699,CE25*0.0122,"")))) -> 29.25559 | CH25: 0 | CI25: =IF(CH25<2700,CH25*0.0097,IF(CH25<3200,CH25*0.01095,IF(CH25<3700,CH25*0.0122,IF(CH25>3699,CH25*0.01345,"")))) -> 0 | CJ25: 0 | CK25: 0 | CL25: =IF(CK25<2700,CK25*0.0097,IF(CK25<3200,CK25*0.01095,IF(CK25<3700,CK25*0.0122,IF(CK25>3699,CK25*0.01345,"")))) -> 0 | CM25: 0 | CN25: 0 | CO25: =IF(CN25<2700,CN25*0.0097,IF(CN25<3200,CN25*0.01095,IF(CN25<3700,CN25*0.0122,IF(CN25>3699,CN25*0.01345,"")))) -> 0 | CQ25: 0 | CR25: =IF(CQ25<2700,CQ25*0.0097,IF(CQ25<3200,CQ25*0.01095,IF(CQ25<3700,CQ25*0.0122,IF(CQ25>3699,CQ25*0.01345,"")))) -> 0 | CT25: =BG25+BJ25+BM25+BP25+BS25+BV25+BY25+CB25+CH25+CK25+CN25+CQ25+CE25 -> 14062.312 | CU25: =BH25+BK25+BN25+BQ25+BT25+BW25+BZ25+CC25+CI25+CL25+CO25+CR25+CF25 -> 120.05191 | CV25: =+BI25+BL25+BO25+BR25+BU25+BX25+CA25+CD25+CG25+CJ25+CM25+CP25+CS25 -> 36 | CX25: =+CU25+CV25-CW25 -> 156.05191 | CY25: =+BB25+CT25 -> 14062.312 | CZ25: =+BC25+CU25 -> 120.05191 | DA25: =+BD25+CV25 -> 296 | DB25: =+CZ25+DA25 -> 416.05191 | DC25: Permiso Medico 2 dias, 18 al 19-06-2021
A26: =+A25+1 -> 17 | B26: BAZURTO PARRAGA JUBER JAIR | C26: SIERRA 5 | D26: 0985424177 | E26: juberbasurto97@gmail.com | F26: 0 | G26: =IF(F26<2700,F26*0.0097,IF(F26<3200,F26*0.01095,IF(F26<3700,F26*0.0122,IF(F26>3699,F26*0.01345,"")))) -> 0 | H26: 20 | I26: 2637.8291 | J26: =IF(I26<2700,I26*0.007,IF(I26<3200,I26*0.008,IF(I26<3700,I26*0.0097,IF(I26>3699,I26*0.01095,"")))) -> 18.464804 | K26: =35-J26 -> 16.535196 | L26: 4248.1206 | M26: =IF(L26<2700,L26*0.007,IF(L26<3200,L26*0.008,IF(L26<3700,L26*0.0097,IF(L26>3699,L26*0.01095,"")))) -> 46.516921 | P26: =IF(O26<2700,O26*0.0097,IF(O26<3200,O26*0.01095,IF(O26<3700,O26*0.0122,IF(O26>3699,O26*0.01345,"")))) -> 0 | R26: 4727.6382 | S26: =IF(R26<2700,R26*0.007,IF(R26<3200,R26*0.008,IF(R26<3700,R26*0.0097,IF(R26>3699,R26*0.01095,"")))) -> 51.767638 | U26: 4166.1106 | V26: =IF(U26<2700,U26*0.007,IF(U26<3200,U26*0.008,IF(U26<3700,U26*0.0097,IF(U26>3699,U26*0.01095,"")))) -> 45.618911 | X26: 2938.8543 | Y26: =IF(X26<2700,X26*0.007,IF(X26<3200,X26*0.008,IF(X26<3700,X26*0.0097,IF(X26>3699,X26*0.01095,"")))) -> 23.510834 | AA26: 2958.6332 | AB26: =IF(AA26<2700,AA26*0.007,IF(AA26<3200,AA26*0.008,IF(AA26<3700,AA26*0.0097,IF(AA26>3699,AA26*0.01095,"")))) -> 23.669065 | AD26: 7528.0402 | AE26: =IF(AD26<2700,AD26*0.007,IF(AD26<3200,AD26*0.008,IF(AD26<3700,AD26*0.0097,IF(AD26>3699,AD26*0.01095,"")))) -> 82.43204 | AG26: 0 | AH26: =IF(AG26<2700,AG26*0.0097,IF(AG26<3200,AG26*0.01095,IF(AG26<3700,AG26*0.0122,IF(AG26>3699,AG26*0.01345,"")))) -> 0 | AJ26: 4030.0704 | AK26: =IF(AJ26<2700,AJ26*0.007,IF(AJ26<3200,AJ26*0.008,IF(AJ26<3700,AJ26*0.0097,IF(AJ26>3699,AJ26*0.01095,"")))) -> 44.12927 | AM26: 3839.0352 | AN26: =IF(AM26<2700,AM26*0.007,IF(AM26<3200,AM26*0.008,IF(AM26<3700,AM26*0.0097,IF(AM26>3699,AM26*0.01095,"")))) -> 42.037435 | AP26: 0 | AQ26: =IF(AP26<2700,AP26*0.0097,IF(AP26<3200,AP26*0.01095,IF(AP26<3700,AP26*0.0122,IF(AP26>3699,AP26*0.01345,"")))) -> 0 | AR26: 12 | AS26: 4484.9849 | AT26: =IF(AS26<2700,AS26*0.007,IF(AS26<3200,AS26*0.008,IF(AS26<3700,AS26*0.0097,IF(AS26>3699,AS26*0.01095,"")))) -> 49.110585 | AW26: =IF(AV26<2700,AV26*0.0097,IF(AV26<3200,AV26*0.01095,IF(AV26<3700,AV26*0.0122,IF(AV26>3699,AV26*0.01345,"")))) -> 0 | AZ26: =IF(AY26<2700,AY26*0.0097,IF(AY26<3200,AY26*0.01095,IF(AY26<3700,AY26*0.0122,IF(AY26>3699,AY26*0.01345,"")))) -> 0 | BB26: =+F26+I26+L26+O26+R26+U26+X26+AA26+AD26+AG26+AJ26+AM26+AP26+AS26+AV26+AY26 -> 41559.317 | BC26: =+G26+J26+M26+P26+S26+V26+Y26+AB26+AE26+AH26+AK26+AN26+AQ26+AT26+AW26+AZ26 -> 427.2575 | BD26: =+H26+K26+N26+Q26+T26+W26+Z26+AC26+AF26+AI26+AL26+AO26+AR26+AU26+AX26+BA26 -> 48.535196 | BF26: =+BC26+BD26-BE26 -> 475.7927 | BG26: 3574.191 | BH26: =IF(BG26<2700,BG26*0.007,IF(BG26<3200,BG26*0.008,IF(BG26<3700,BG26*0.0097,IF(BG26>3699,BG26*0.01095,"")))) -> 34.669652 | BJ26: 0 | BK26: =IF(BJ26<2700,BJ26*0.0097,IF(BJ26<3200,BJ26*0.01095,IF(BJ26<3700,BJ26*0.0122,IF(BJ26>3699,BJ26*0.01345,"")))) -> 0 | BL26: 0 | BM26: 2417.8492 | BN26: =IF(BM26<2700,BM26*0.007,IF(BM26<3200,BM26*0.008,IF(BM26<3700,BM26*0.0097,IF(BM26>3699,BM26*0.01095,"")))) -> 16.924945 | BP26: 2535.0754 | BQ26: =IF(BP26<2700,BP26*0.007,IF(BP26<3200,BP26*0.008,IF(BP26<3700,BP26*0.0097,IF(BP26>3699,BP26*0.01095,"")))) -> 17.745528 | BS26: 2651.8191 | BT26: =IF(BS26<2700,BS26*0.007,IF(BS26<3200,BS26*0.008,IF(BS26<3700,BS26*0.0097,IF(BS26>3699,BS26*0.01095,"")))) -> 18.562734 | BV26: 2339.2161 | BW26: =IF(BV26<2700,BV26*0.007,IF(BV26<3200,BV26*0.008,IF(BV26<3700,BV26*0.0097,IF(BV26>3699,BV26*0.01095,"")))) -> 16.374513 | BY26: 1100.3819 | BZ26: =IF(BY26<2700,BY26*0.007,IF(BY26<3200,BY26*0.008,IF(BY26<3700,BY26*0.0097,IF(BY26>3699,BY26*0.01095,"")))) -> 7.7026734 | CB26: 0 | CC26: =IF(CB26<2700,CB26*0.0097,IF(CB26<3200,CB26*0.01095,IF(CB26<3700,CB26*0.0122,IF(CB26>3699,CB26*0.01345,"")))) -> 0 | CD26: 0 | CE26: 2947.0553 | CF26: =IF(CE26<2700,CE26*0.007,IF(CE26<3200,CE26*0.008,IF(CE26<3700,CE26*0.0097,IF(CE26>3699,CE26*0.01095,"")))) -> 23.576442 | CH26: 0 | CI26: =IF(CH26<2700,CH26*0.0097,IF(CH26<3200,CH26*0.01095,IF(CH26<3700,CH26*0.0122,IF(CH26>3699,CH26*0.01345,"")))) -> 0 | CK26: 0 | CL26: =IF(CK26<2700,CK26*0.0097,IF(CK26<3200,CK26*0.01095,IF(CK26<3700,CK26*0.0122,IF(CK26>3699,CK26*0.01345,"")))) -> 0 | CN26: 0 | CO26: =IF(CN26<2700,CN26*0.0097,IF(CN26<3200,CN26*0.01095,IF(CN26<3700,CN26*0.0122,IF(CN26>3699,CN26*0.01345,"")))) -> 0 | CQ26: 0 | CR26: =IF(CQ26<2700,CQ26*0.0097,IF(CQ26<3200,CQ26*0.01095,IF(CQ26<3700,CQ26*0.0122,IF(CQ26>3699,CQ26*0.01345,"")))) -> 0 | CT26: =BG26+BJ26+BM26+BP26+BS26+BV26+BY26+CB26+CH26+CK26+CN26+CQ26+CE26 -> 17565.588 | CU26: =BH26+BK26+BN26+BQ26+BT26+BW26+BZ26+CC26+CI26+CL26+CO26+CR26+CF26 -> 135.55649 | CV26: =+BI26+BL26+BO26+BR26+BU26+BX26+CA26+CD26+CG26+CJ26+CM26+CP26+CS26 -> 0 | CX26: =+CU26+CV26-CW26 -> 135.55649 | CY26: =+BB26+CT26 -> 59124.905 | CZ26: =+BC26+CU26 -> 562.81399 | DA26: =+BD26+CV26 -> 48.535196 | DB26: =+CZ26+DA26 -> 611.34919
A27: =+A26+1 -> 18 | B27: VIVAS MACIAS LISBETH ALEXANDRA | C27: SIERRA 5 | D27: 0989701317 | E27: alexandra04macias@gmail.com | F27: 0 | G27: =IF(F27<2700,F27*0.0101,IF(F27<3200,F27*0.01135,IF(F27<3700,F27*0.0126,IF(F27>3699,F27*0.01385,"")))) -> 0 | H27: 18 | I27: 2535.0754 | J27: =IF(I27<2700,I27*0.0075,IF(I27<3200,I27*0.009,IF(I27<3700,I27*0.0101,IF(I27>3699,I27*0.01135,"")))) -> 19.013065 | L27: 3418.3719 | M27: =IF(L27<2700,L27*0.0075,IF(L27<3200,L27*0.009,IF(L27<3700,L27*0.0101,IF(L27>3699,L27*0.01135,"")))) -> 34.525556 | P27: =IF(O27<2700,O27*0.0101,IF(O27<3200,O27*0.01135,IF(O27<3700,O27*0.0126,IF(O27>3699,O27*0.01385,"")))) -> 0 | R27: 3175.2362 | S27: =IF(R27<2700,R27*0.0075,IF(R27<3200,R27*0.009,IF(R27<3700,R27*0.0101,IF(R27>3699,R27*0.01135,"")))) -> 28.577126 | U27: 2730.9347 | V27: =IF(U27<2700,U27*0.0075,IF(U27<3200,U27*0.009,IF(U27<3700,U27*0.0101,IF(U27>3699,U27*0.01135,"")))) -> 24.578412 | X27: 2272.1608 | Y27: =IF(X27<2700,X27*0.0075,IF(X27<3200,X27*0.009,IF(X27<3700,X27*0.0101,IF(X27>3699,X27*0.01135,"")))) -> 17.041206 | AA27: 1748.7437 | AB27: =IF(AA27<2700,AA27*0.0075,IF(AA27<3200,AA27*0.009,IF(AA27<3700,AA27*0.0101,IF(AA27>3699,AA27*0.01135,"")))) -> 13.115578 | AD27: 6174.392 | AE27: =IF(AD27<2700,AD27*0.0075,IF(AD27<3200,AD27*0.009,IF(AD27<3700,AD27*0.0101,IF(AD27>3699,AD27*0.01135,"")))) -> 70.079349 | AG27: 0 | AH27: =IF(AG27<2700,AG27*0.0101,IF(AG27<3200,AG27*0.01135,IF(AG27<3700,AG27*0.0126,IF(AG27>3699,AG27*0.01385,"")))) -> 0 | AJ27: 3792.7236 | AK27: =IF(AJ27<2700,AJ27*0.0075,IF(AJ27<3200,AJ27*0.009,IF(AJ27<3700,AJ27*0.0101,IF(AJ27>3699,AJ27*0.01135,"")))) -> 43.047413 | AM27: 2992.402 | AN27: =IF(AM27<2700,AM27*0.0075,IF(AM27<3200,AM27*0.009,IF(AM27<3700,AM27*0.0101,IF(AM27>3699,AM27*0.01135,"")))) -> 26.931618 | AP27: 0 | AQ27: =IF(AP27<2700,AP27*0.0101,IF(AP27<3200,AP27*0.01135,IF(AP27<3700,AP27*0.0126,IF(AP27>3699,AP27*0.01385,"")))) -> 0 | AR27: 16 | AS27: 3699.1357 | AT27: =IF(AS27<2700,AS27*0.0075,IF(AS27<3200,AS27*0.009,IF(AS27<3700,AS27*0.0101,IF(AS27>3699,AS27*0.01135,"")))) -> 37.36127 | AW27: =IF(AV27<2700,AV27*0.0101,IF(AV27<3200,AV27*0.01135,IF(AV27<3700,AV27*0.0126,IF(AV27>3699,AV27*0.01385,"")))) -> 0 | AZ27: =IF(AY27<2700,AY27*0.0101,IF(AY27<3200,AY27*0.01135,IF(AY27<3700,AY27*0.0126,IF(AY27>3699,AY27*0.01385,"")))) -> 0 | BB27: =+F27+I27+L27+O27+R27+U27+X27+AA27+AD27+AG27+AJ27+AM27+AP27+AS27+AV27+AY27 -> 32539.176 | BC27: =+G27+J27+M27+P27+S27+V27+Y27+AB27+AE27+AH27+AK27+AN27+AQ27+AT27+AW27+AZ27 -> 314.27059 | BD27: =+H27+K27+N27+Q27+T27+W27+Z27+AC27+AF27+AI27+AL27+AO27+AR27+AU27+AX27+BA27 -> 34 | BF27: =+BC27+BD27-BE27 -> 348.27059 | BG27: 0 | BH27: =IF(BG27<2700,BG27*0.0101,IF(BG27<3200,BG27*0.01135,IF(BG27<3700,BG27*0.0126,IF(BG27>3699,BG27*0.01385,"")))) -> 0 | BJ27: 0 | BK27: =IF(BJ27<2700,BJ27*0.0101,IF(BJ27<3200,BJ27*0.01135,IF(BJ27<3700,BJ27*0.0126,IF(BJ27>3699,BJ27*0.01385,"")))) -> 0 | BL27: 0 | BM27: 2417.8492 | BN27: =IF(BM27<2700,BM27*0.0075,IF(BM27<3200,BM27*0.009,IF(BM27<3700,BM27*0.0101,IF(BM27>3699,BM27*0.01135,"")))) -> 18.133869 | BP27: 2535.0754 | BQ27: =IF(BP27<2700,BP27*0.0075,IF(BP27<3200,BP27*0.009,IF(BP27<3700,BP27*0.0101,IF(BP27>3699,BP27*0.01135,"")))) -> 19.013065 | BS27: 2651.8191 | BT27: =IF(BS27<2700,BS27*0.0075,IF(BS27<3200,BS27*0.009,IF(BS27<3700,BS27*0.0101,IF(BS27>3699,BS27*0.01135,"")))) -> 19.888643 | BV27: 2339.2161 | BW27: =IF(BV27<2700,BV27*0.0075,IF(BV27<3200,BV27*0.009,IF(BV27<3700,BV27*0.0101,IF(BV27>3699,BV27*0.01135,"")))) -> 17.544121 | BY27: 1100.3819 | BZ27: =IF(BY27<2700,BY27*0.0075,IF(BY27<3200,BY27*0.009,IF(BY27<3700,BY27*0.0101,IF(BY27>3699,BY27*0.01135,"")))) -> 8.2528643 | CB27: 0 | CC27: =IF(CB27<2700,CB27*0.0101,IF(CB27<3200,CB27*0.01135,IF(CB27<3700,CB27*0.0126,IF(CB27>3699,CB27*0.01385,"")))) -> 0 | CD27: 10 | CE27: 0 | CF27: =IF(CE27<2700,CE27*0.0101,IF(CE27<3200,CE27*0.01135,IF(CE27<3700,CE27*0.0126,IF(CE27>3699,CE27*0.01385,"")))) -> 0 | CH27: 0 | CI27: =IF(CH27<2700,CH27*0.0101,IF(CH27<3200,CH27*0.01135,IF(CH27<3700,CH27*0.0126,IF(CH27>3699,CH27*0.01385,"")))) -> 0 | CK27: 0 | CL27: =IF(CK27<2700,CK27*0.0101,IF(CK27<3200,CK27*0.01135,IF(CK27<3700,CK27*0.0126,IF(CK27>3699,CK27*0.01385,"")))) -> 0 | CN27: 0 | CO27: =IF(CN27<2700,CN27*0.0101,IF(CN27<3200,CN27*0.01135,IF(CN27<3700,CN27*0.0126,IF(CN27>3699,CN27*0.01385,"")))) -> 0 | CQ27: 0 | CR27: =IF(CQ27<2700,CQ27*0.0101,IF(CQ27<3200,CQ27*0.01135,IF(CQ27<3700,CQ27*0.0126,IF(CQ27>3699,CQ27*0.01385,"")))) -> 0 | CT27: =BG27+BJ27+BM27+BP27+BS27+BV27+BY27+CB27+CH27+CK27+CN27+CQ27+CE27 -> 11044.342 | CU27: =BH27+BK27+BN27+BQ27+BT27+BW27+BZ27+CC27+CI27+CL27+CO27+CR27+CF27 -> 82.832563 | CV27: =+BI27+BL27+BO27+BR27+BU27+BX27+CA27+CD27+CG27+CJ27+CM27+CP27+CS27 -> 10 | CX27: =+CU27+CV27-CW27 -> 92.832563 | CY27: =+BB27+CT27 -> 43583.518 | CZ27: =+BC27+CU27 -> 397.10316 | DA27: =+BD27+CV27 -> 44 | DB27: =+CZ27+DA27 -> 441.10316 | DC27: Permiso Medico 2 dias, 21 al 22-06-2021
A28: =+A27+1 -> 19 | B28: PILOSO MANZABA YORGEN JAVIER | C28: SIERRA 6 | D28: 09608014217 | E28: yorgenpilosomanzaba@hotmail.com | F28: 0 | G28: =IF(F28<2700,F28*0.01,IF(F28<3200,F28*0.0105,IF(F28<3700,F28*0.01175,IF(F28>3699,F28*0.013,"")))) -> 0 | H28: 18 | I28: 2535.0754 | J28: =IF(I28<2700,I28*0.0085,IF(I28<3200,I28*0.01,IF(I28<3700,I28*0.0105,IF(I28>3699,I28*0.01175,"")))) -> 21.548141 | L28: 3418.3719 | M28: =IF(L28<2700,L28*0.0085,IF(L28<3200,L28*0.01,IF(L28<3700,L28*0.0105,IF(L28>3699,L28*0.01175,"")))) -> 35.892905 | P28: =IF(O28<2700,O28*0.0105,IF(O28<3200,O28*0.01175,IF(O28<3700,O28*0.013,IF(O28>3699,O28*0.01425,"")))) -> 0 | R28: 3494.1106 | S28: =IF(R28<2700,R28*0.0085,IF(R28<3200,R28*0.01,IF(R28<3700,R28*0.0105,IF(R28>3699,R28*0.01175,"")))) -> 36.688161 | U28: 2730.9347 | V28: =IF(U28<2700,U28*0.0085,IF(U28<3200,U28*0.01,IF(U28<3700,U28*0.0105,IF(U28>3699,U28*0.01175,"")))) -> 27.309347 | X28: 2272.1608 | Y28: =IF(X28<2700,X28*0.0085,IF(X28<3200,X28*0.01,IF(X28<3700,X28*0.0105,IF(X28>3699,X28*0.01175,"")))) -> 19.313367 | AA28: 1748.7437 | AB28: =IF(AA28<2700,AA28*0.0085,IF(AA28<3200,AA28*0.01,IF(AA28<3700,AA28*0.0105,IF(AA28>3699,AA28*0.01175,"")))) -> 14.864322 | AD28: 6174.392 | AE28: =IF(AD28<2700,AD28*0.0085,IF(AD28<3200,AD28*0.01,IF(AD28<3700,AD28*0.0105,IF(AD28>3699,AD28*0.01175,"")))) -> 72.549106 | AG28: 0 | AH28: =IF(AG28<2700,AG28*0.0105,IF(AG28<3200,AG28*0.01175,IF(AG28<3700,AG28*0.013,IF(AG28>3699,AG28*0.01425,"")))) -> 0 | AJ28: 3792.7236 | AK28: =IF(AJ28<2700,AJ28*0.0085,IF(AJ28<3200,AJ28*0.01,IF(AJ28<3700,AJ28*0.0105,IF(AJ28>3699,AJ28*0.01175,"")))) -> 44.564503 | AM28: 2992.402 | AN28: =IF(AM28<2700,AM28*0.0085,IF(AM28<3200,AM28*0.01,IF(AM28<3700,AM28*0.0105,IF(AM28>3699,AM28*0.01175,"")))) -> 29.92402 | AP28: 0 | AQ28: =IF(AP28<2700,AP28*0.0105,IF(AP28<3200,AP28*0.01175,IF(AP28<3700,AP28*0.013,IF(AP28>3699,AP28*0.01425,"")))) -> 0 | AR28: 16 | AS28: 3699.1357 | AT28: =IF(AS28<2700,AS28*0.0085,IF(AS28<3200,AS28*0.01,IF(AS28<3700,AS28*0.0105,IF(AS28>3699,AS28*0.01175,"")))) -> 38.840925 | AW28: =IF(AV28<2700,AV28*0.0105,IF(AV28<3200,AV28*0.01175,IF(AV28<3700,AV28*0.013,IF(AV28>3699,AV28*0.01425,"")))) -> 0 | AZ28: =IF(AY28<2700,AY28*0.0105,IF(AY28<3200,AY28*0.01175,IF(AY28<3700,AY28*0.013,IF(AY28>3699,AY28*0.01425,"")))) -> 0 | BB28: =+F28+I28+L28+O28+R28+U28+X28+AA28+AD28+AG28+AJ28+AM28+AP28+AS28+AV28+AY28 -> 32858.05 | BC28: =+G28+J28+M28+P28+S28+V28+Y28+AB28+AE28+AH28+AK28+AN28+AQ28+AT28+AW28+AZ28 -> 341.49479 | BD28: =+H28+K28+N28+Q28+T28+W28+Z28+AC28+AF28+AI28+AL28+AO28+AR28+AU28+AX28+BA28 -> 34 | BF28: =+BC28+BD28-BE28 -> 375.49479 | BG28: 3354.6935 | BH28: =IF(BG28<2700,BG28*0.0085,IF(BG28<3200,BG28*0.01,IF(BG28<3700,BG28*0.0105,IF(BG28>3699,BG28*0.01175,"")))) -> 35.224281 | BJ28: 0 | BK28: =IF(BJ28<2700,BJ28*0.0105,IF(BJ28<3200,BJ28*0.01175,IF(BJ28<3700,BJ28*0.013,IF(BJ28>3699,BJ28*0.01425,"")))) -> 0 | BL28: 0 | BM28: 3140.0201 | BN28: =IF(BM28<2700,BM28*0.0085,IF(BM28<3200,BM28*0.01,IF(BM28<3700,BM28*0.0105,IF(BM28>3699,BM28*0.01175,"")))) -> 31.400201 | BP28: 3291.4975 | BQ28: =IF(BP28<2700,BP28*0.0085,IF(BP28<3200,BP28*0.01,IF(BP28<3700,BP28*0.0105,IF(BP28>3699,BP28*0.01175,"")))) -> 34.560724 | BS28: 3297.2864 | BT28: =IF(BS28<2700,BS28*0.0085,IF(BS28<3200,BS28*0.01,IF(BS28<3700,BS28*0.0105,IF(BS28>3699,BS28*0.01175,"")))) -> 34.621508 | BV28: 3263.5176 | BW28: =IF(BV28<2700,BV28*0.0085,IF(BV28<3200,BV28*0.01,IF(BV28<3700,BV28*0.0105,IF(BV28>3699,BV28*0.01175,"")))) -> 34.266935 | BY28: 1308.3015 | BZ28: =IF(BY28<2700,BY28*0.0085,IF(BY28<3200,BY28*0.01,IF(BY28<3700,BY28*0.0105,IF(BY28>3699,BY28*0.01175,"")))) -> 11.120563 | CB28: 0 | CC28: =IF(CB28<2700,CB28*0.0105,IF(CB28<3200,CB28*0.01175,IF(CB28<3700,CB28*0.013,IF(CB28>3699,CB28*0.01425,"")))) -> 0 | CD28: 0 | CE28: 3181.5075 | CF28: =IF(CE28<2700,CE28*0.0085,IF(CE28<3200,CE28*0.01,IF(CE28<3700,CE28*0.0105,IF(CE28>3699,CE28*0.01175,"")))) -> 31.815075 | CH28: 0 | CI28: =IF(CH28<2700,CH28*0.0105,IF(CH28<3200,CH28*0.01175,IF(CH28<3700,CH28*0.013,IF(CH28>3699,CH28*0.01425,"")))) -> 0 | CK28: 0 | CL28: =IF(CK28<2700,CK28*0.0105,IF(CK28<3200,CK28*0.01175,IF(CK28<3700,CK28*0.013,IF(CK28>3699,CK28*0.01425,"")))) -> 0 | CN28: 0 | CO28: =IF(CN28<2700,CN28*0.0105,IF(CN28<3200,CN28*0.01175,IF(CN28<3700,CN28*0.013,IF(CN28>3699,CN28*0.01425,"")))) -> 0 | CQ28: 0 | CR28: =IF(CQ28<2700,CQ28*0.0105,IF(CQ28<3200,CQ28*0.01175,IF(CQ28<3700,CQ28*0.013,IF(CQ28>3699,CQ28*0.01425,"")))) -> 0 | CT28: =BG28+BJ28+BM28+BP28+BS28+BV28+BY28+CB28+CH28+CK28+CN28+CQ28+CE28 -> 20836.824 | CU28: =BH28+BK28+BN28+BQ28+BT28+BW28+BZ28+CC28+CI28+CL28+CO28+CR28+CF28 -> 213.00929 | CV28: =+BI28+BL28+BO28+BR28+BU28+BX28+CA28+CD28+CG28+CJ28+CM28+CP28+CS28 -> 0 | CX28: =+CU28+CV28-CW28 -> 213.00929 | CY28: =+BB28+CT28 -> 53694.874 | CZ28: =+BC28+CU28 -> 554.50408 | DA28: =+BD28+CV28 -> 34 | DB28: =+CZ28+DA28 -> 588.50408
A29: =+A28+1 -> 20 | B29: ALVARADO MACIAS KAREN ELIZABETH | C29: SIERRA 6 | D29: 0998635201 | E29: karenalvarado0101@gmail.com | F29: 0 | G29: =IF(F29<2700,F29*0.008,IF(F29<3200,F29*0.0097,IF(F29<3700,F29*0.01095,IF(F29>3699,F29*0.0122,"")))) -> 0 | H29: 18 | I29: 2535.0754 | J29: =IF(I29<2700,I29*0.007,IF(I29<3200,I29*0.008,IF(I29<3700,I29*0.0097,IF(I29>3699,I29*0.01095,"")))) -> 17.745528 | L29: 3418.3719 | M29: =IF(L29<2700,L29*0.007,IF(L29<3200,L29*0.008,IF(L29<3700,L29*0.0097,IF(L29>3699,L29*0.01095,"")))) -> 33.158207 | P29: =IF(O29<2700,O29*0.0097,IF(O29<3200,O29*0.01095,IF(O29<3700,O29*0.0122,IF(O29>3699,O29*0.01345,"")))) -> 0 | R29: 0 | S29: =IF(R29<2700,R29*0.0097,IF(R29<3200,R29*0.01095,IF(R29<3700,R29*0.0122,IF(R29>3699,R29*0.01345,"")))) -> 0 | U29: 0 | V29: =IF(U29<2700,U29*0.0097,IF(U29<3200,U29*0.01095,IF(U29<3700,U29*0.0122,IF(U29>3699,U29*0.01345,"")))) -> 0 | X29: 0 | Y29: =IF(X29<2700,X29*0.0097,IF(X29<3200,X29*0.01095,IF(X29<3700,X29*0.0122,IF(X29>3699,X29*0.01345,"")))) -> 0 | AA29: 1748.7437 | AB29: =IF(AA29<2700,AA29*0.007,IF(AA29<3200,AA29*0.008,IF(AA29<3700,AA29*0.0097,IF(AA29>3699,AA29*0.01095,"")))) -> 12.241206 | AD29: 6174.392 | AE29: =IF(AD29<2700,AD29*0.007,IF(AD29<3200,AD29*0.008,IF(AD29<3700,AD29*0.0097,IF(AD29>3699,AD29*0.01095,"")))) -> 67.609592 | AG29: 0 | AH29: =IF(AG29<2700,AG29*0.0097,IF(AG29<3200,AG29*0.01095,IF(AG29<3700,AG29*0.0122,IF(AG29>3699,AG29*0.01345,"")))) -> 0 | AI29: 18 | AJ29: 0 | AK29: =IF(AJ29<2700,AJ29*0.008,IF(AJ29<3200,AJ29*0.0097,IF(AJ29<3700,AJ29*0.01095,IF(AJ29>3699,AJ29*0.0122,"")))) -> 0 | AL29: 18 | AM29: 0 | AN29: =IF(AM29<2700,AM29*0.008,IF(AM29<3200,AM29*0.0097,IF(AM29<3700,AM29*0.01095,IF(AM29>3699,AM29*0.0122,"")))) -> 0 | AO29: 18 | AP29: 0 | AQ29: =IF(AP29<2700,AP29*0.0097,IF(AP29<3200,AP29*0.01095,IF(AP29<3700,AP29*0.0122,IF(AP29>3699,AP29*0.01345,"")))) -> 0 | AR29: 16 | AS29: 3699.1357 | AT29: =IF(AS29<2700,AS29*0.007,IF(AS29<3200,AS29*0.008,IF(AS29<3700,AS29*0.0097,IF(AS29>3699,AS29*0.01095,"")))) -> 35.881616 | AW29: =IF(AV29<2700,AV29*0.0097,IF(AV29<3200,AV29*0.01095,IF(AV29<3700,AV29*0.0122,IF(AV29>3699,AV29*0.01345,"")))) -> 0 | AZ29: =IF(AY29<2700,AY29*0.0097,IF(AY29<3200,AY29*0.01095,IF(AY29<3700,AY29*0.0122,IF(AY29>3699,AY29*0.01345,"")))) -> 0 | BB29: =+F29+I29+L29+O29+R29+U29+X29+AA29+AD29+AG29+AJ29+AM29+AP29+AS29+AV29+AY29 -> 17575.719 | BC29: =+G29+J29+M29+P29+S29+V29+Y29+AB29+AE29+AH29+AK29+AN29+AQ29+AT29+AW29+AZ29 -> 166.63615 | BD29: =+H29+K29+N29+Q29+T29+W29+Z29+AC29+AF29+AI29+AL29+AO29+AR29+AU29+AX29+BA29 -> 88 | BF29: =+BC29+BD29-BE29 -> 254.63615 | BG29: 3354.6935 | BH29: =IF(BG29<2700,BG29*0.007,IF(BG29<3200,BG29*0.008,IF(BG29<3700,BG29*0.0097,IF(BG29>3699,BG29*0.01095,"")))) -> 32.540527 | BJ29: 0 | BK29: =IF(BJ29<2700,BJ29*0.0097,IF(BJ29<3200,BJ29*0.01095,IF(BJ29<3700,BJ29*0.0122,IF(BJ29>3699,BJ29*0.01345,"")))) -> 0 | BL29: 12 | BM29: 3140.0201 | BN29: =IF(BM29<2700,BM29*0.007,IF(BM29<3200,BM29*0.008,IF(BM29<3700,BM29*0.0097,IF(BM29>3699,BM29*0.01095,"")))) -> 25.120161 | BP29: 3291.4975 | BQ29: =IF(BP29<2700,BP29*0.007,IF(BP29<3200,BP29*0.008,IF(BP29<3700,BP29*0.0097,IF(BP29>3699,BP29*0.01095,"")))) -> 31.927526 | BS29: 3297.2864 | BT29: =IF(BS29<2700,BS29*0.007,IF(BS29<3200,BS29*0.008,IF(BS29<3700,BS29*0.0097,IF(BS29>3699,BS29*0.01095,"")))) -> 31.983678 | BV29: 3263.5176 | BW29: =IF(BV29<2700,BV29*0.007,IF(BV29<3200,BV29*0.008,IF(BV29<3700,BV29*0.0097,IF(BV29>3699,BV29*0.01095,"")))) -> 31.656121 | BY29: 1308.3015 | BZ29: =IF(BY29<2700,BY29*0.007,IF(BY29<3200,BY29*0.008,IF(BY29<3700,BY29*0.0097,IF(BY29>3699,BY29*0.01095,"")))) -> 9.1581106 | CB29: 0 | CC29: =IF(CB29<2700,CB29*0.0097,IF(CB29<3200,CB29*0.01095,IF(CB29<3700,CB29*0.0122,IF(CB29>3699,CB29*0.01345,"")))) -> 0 | CD29: 10 | CE29: 3181.5075 | CF29: =IF(CE29<2700,CE29*0.007,IF(CE29<3200,CE29*0.008,IF(CE29<3700,CE29*0.0097,IF(CE29>3699,CE29*0.01095,"")))) -> 25.45206 | CH29: 0 | CI29: =IF(CH29<2700,CH29*0.0097,IF(CH29<3200,CH29*0.01095,IF(CH29<3700,CH29*0.0122,IF(CH29>3699,CH29*0.01345,"")))) -> 0 | CJ29: 18 | CK29: 0 | CL29: =IF(CK29<2700,CK29*0.0097,IF(CK29<3200,CK29*0.01095,IF(CK29<3700,CK29*0.0122,IF(CK29>3699,CK29*0.01345,"")))) -> 0 | CN29: 0 | CO29: =IF(CN29<2700,CN29*0.0097,IF(CN29<3200,CN29*0.01095,IF(CN29<3700,CN29*0.0122,IF(CN29>3699,CN29*0.01345,"")))) -> 0 | CQ29: 0 | CR29: =IF(CQ29<2700,CQ29*0.0097,IF(CQ29<3200,CQ29*0.01095,IF(CQ29<3700,CQ29*0.0122,IF(CQ29>3699,CQ29*0.01345,"")))) -> 0 | CT29: =BG29+BJ29+BM29+BP29+BS29+BV29+BY29+CB29+CH29+CK29+CN29+CQ29+CE29 -> 20836.824 | CU29: =BH29+BK29+BN29+BQ29+BT29+BW29+BZ29+CC29+CI29+CL29+CO29+CR29+CF29 -> 187.83818 | CV29: =+BI29+BL29+BO29+BR29+BU29+BX29+CA29+CD29+CG29+CJ29+CM29+CP29+CS29 -> 40 | CX29: =+CU29+CV29-CW29 -> 227.83818 | CY29: =+BB29+CT29 -> 38412.543 | CZ29: =+BC29+CU29 -> 354.47433 | DA29: =+BD29+CV29 -> 128 | DB29: =+CZ29+DA29 -> 482.47433 | DC29: Permiso Medico 3 dias, 31 al 02-06-2021
A30: =+A29+1 -> 21 | B30: NAVARRETE ALCIVAR BYRON ANDRES | C30: SIERRA 7 | D30: 0939067178 | E30: byronandresnavarretealcivar@gmail.com | F30: 0 | G30: =IF(F30<2700,F30*0.0105,IF(F30<3200,F30*0.01175,IF(F30<3700,F30*0.013,IF(F30>3699,F30*0.01425,"")))) -> 0 | H30: 20 | I30: 0 | J30: =IF(I30<2700,I30*0.0105,IF(I30<3200,I30*0.01175,IF(I30<3700,I30*0.013,IF(I30>3699,I30*0.01425,"")))) -> 0 | K30: 20 | L30: 0 | M30: =IF(L30<2700,L30*0.0105,IF(L30<3200,L30*0.01175,IF(L30<3700,L30*0.013,IF(L30>3699,L30*0.01425,"")))) -> 0 | N30: 20 | P30: =IF(O30<2700,O30*0.0105,IF(O30<3200,O30*0.01175,IF(O30<3700,O30*0.013,IF(O30>3699,O30*0.01425,"")))) -> 0 | R30: 4296.8442 | S30: =IF(R30<2700,R30*0.0085,IF(R30<3200,R30*0.01,IF(R30<3700,R30*0.0105,IF(R30>3699,R30*0.01175,"")))) -> 50.48792 | U30: 3354.6935 | V30: =IF(U30<2700,U30*0.0085,IF(U30<3200,U30*0.01,IF(U30<3700,U30*0.0105,IF(U30>3699,U30*0.01175,"")))) -> 35.224281 | X30: 2617.0854 | Y30: =IF(X30<2700,X30*0.0085,IF(X30<3200,X30*0.01,IF(X30<3700,X30*0.0105,IF(X30>3699,X30*0.01175,"")))) -> 22.245226 | AA30: 2575.598 | AB30: =IF(AA30<2700,AA30*0.0085,IF(AA30<3200,AA30*0.01,IF(AA30<3700,AA30*0.0105,IF(AA30>3699,AA30*0.01175,"")))) -> 21.892583 | AD30: 6276.1809 | AE30: =IF(AD30<2700,AD30*0.0085,IF(AD30<3200,AD30*0.01,IF(AD30<3700,AD30*0.0105,IF(AD30>3699,AD30*0.01175,"")))) -> 73.745126 | AG30: 0 | AH30: =IF(AG30<2700,AG30*0.0105,IF(AG30<3200,AG30*0.01175,IF(AG30<3700,AG30*0.013,IF(AG30>3699,AG30*0.01425,"")))) -> 0 | AJ30: 3702.0302 | AK30: =IF(AJ30<2700,AJ30*0.0085,IF(AJ30<3200,AJ30*0.01,IF(AJ30<3700,AJ30*0.0105,IF(AJ30>3699,AJ30*0.01175,"")))) -> 43.498854 | AM30: 3237.4673 | AN30: =IF(AM30<2700,AM30*0.0085,IF(AM30<3200,AM30*0.01,IF(AM30<3700,AM30*0.0105,IF(AM30>3699,AM30*0.01175,"")))) -> 33.993407 | AP30: 0 | AQ30: =IF(AP30<2700,AP30*0.0105,IF(AP30<3200,AP30*0.01175,IF(AP30<3700,AP30*0.013,IF(AP30>3699,AP30*0.01425,"")))) -> 0 | AR30: 16 | AS30: 3941.3065 | AT30: =IF(AS30<2700,AS30*0.0085,IF(AS30<3200,AS30*0.01,IF(AS30<3700,AS30*0.0105,IF(AS30>3699,AS30*0.01175,"")))) -> 46.310352 | AW30: =IF(AV30<2700,AV30*0.0105,IF(AV30<3200,AV30*0.01175,IF(AV30<3700,AV30*0.013,IF(AV30>3699,AV30*0.01425,"")))) -> 0 | AZ30: =IF(AY30<2700,AY30*0.0105,IF(AY30<3200,AY30*0.01175,IF(AY30<3700,AY30*0.013,IF(AY30>3699,AY30*0.01425,"")))) -> 0 | BB30: =+F30+I30+L30+O30+R30+U30+X30+AA30+AD30+AG30+AJ30+AM30+AP30+AS30+AV30+AY30 -> 30001.206 | BC30: =+G30+J30+M30+P30+S30+V30+Y30+AB30+AE30+AH30+AK30+AN30+AQ30+AT30+AW30+AZ30 -> 327.39775 | BD30: =+H30+K30+N30+Q30+T30+W30+Z30+AC30+AF30+AI30+AL30+AO30+AR30+AU30+AX30+BA30 -> 76 | BF30: =+BC30+BD30-BE30 -> 403.39775 | BG30: 3807.196 | BH30: =IF(BG30<2700,BG30*0.0085,IF(BG30<3200,BG30*0.01,IF(BG30<3700,BG30*0.0105,IF(BG30>3699,BG30*0.01175,"")))) -> 44.734553 | BJ30: 0 | BK30: =IF(BJ30<2700,BJ30*0.0105,IF(BJ30<3200,BJ30*0.01175,IF(BJ30<3700,BJ30*0.013,IF(BJ30>3699,BJ30*0.01425,"")))) -> 0 | BL30: 0 | BM30: 2947.0553 | BN30: =IF(BM30<2700,BM30*0.0085,IF(BM30<3200,BM30*0.01,IF(BM30<3700,BM30*0.0105,IF(BM30>3699,BM30*0.01175,"")))) -> 29.470553 | BP30: 2849.1256 | BQ30: =IF(BP30<2700,BP30*0.0085,IF(BP30<3200,BP30*0.01,IF(BP30<3700,BP30*0.0105,IF(BP30>3699,BP30*0.01175,"")))) -> 28.491256 | BS30: 3192.603 | BT30: =IF(BS30<2700,BS30*0.0085,IF(BS30<3200,BS30*0.01,IF(BS30<3700,BS30*0.0105,IF(BS30>3699,BS30*0.01175,"")))) -> 31.92603 | BV30: 2590.5528 | BW30: =IF(BV30<2700,BV30*0.0085,IF(BV30<3200,BV30*0.01,IF(BV30<3700,BV30*0.0105,IF(BV30>3699,BV30*0.01175,"")))) -> 22.019698 | BY30: 1296.2412 | BZ30: =IF(BY30<2700,BY30*0.0085,IF(BY30<3200,BY30*0.01,IF(BY30<3700,BY30*0.0105,IF(BY30>3699,BY30*0.01175,"")))) -> 11.01805 | CB30: 0 | CC30: =IF(CB30<2700,CB30*0.0105,IF(CB30<3200,CB30*0.01175,IF(CB30<3700,CB30*0.013,IF(CB30>3699,CB30*0.01425,"")))) -> 0 | CD30: 10 | CE30: 3387.4975 | CF30: =IF(CE30<2700,CE30*0.0085,IF(CE30<3200,CE30*0.01,IF(CE30<3700,CE30*0.0105,IF(CE30>3699,CE30*0.01175,"")))) -> 35.568724 | CH30: 0 | CI30: =IF(CH30<2700,CH30*0.0105,IF(CH30<3200,CH30*0.01175,IF(CH30<3700,CH30*0.013,IF(CH30>3699,CH30*0.01425,"")))) -> 0 | CK30: 0 | CL30: =IF(CK30<2700,CK30*0.0105,IF(CK30<3200,CK30*0.01175,IF(CK30<3700,CK30*0.013,IF(CK30>3699,CK30*0.01425,"")))) -> 0 | CN30: 0 | CO30: =IF(CN30<2700,CN30*0.0105,IF(CN30<3200,CN30*0.01175,IF(CN30<3700,CN30*0.013,IF(CN30>3699,CN30*0.01425,"")))) -> 0 | CQ30: 0 | CR30: =IF(CQ30<2700,CQ30*0.0105,IF(CQ30<3200,CQ30*0.01175,IF(CQ30<3700,CQ30*0.013,IF(CQ30>3699,CQ30*0.01425,"")))) -> 0 | CS30: 18 | CT30: =BG30+BJ30+BM30+BP30+BS30+BV30+BY30+CB30+CH30+CK30+CN30+CQ30+CE30 -> 20070.271 | CU30: =BH30+BK30+BN30+BQ30+BT30+BW30+BZ30+CC30+CI30+CL30+CO30+CR30+CF30 -> 203.22886 | CV30: =+BI30+BL30+BO30+BR30+BU30+BX30+CA30+CD30+CG30+CJ30+CM30+CP30+CS30 -> 28 | CX30: =+CU30+CV30-CW30 -> 231.22886 | CY30: =+BB30+CT30 -> 50071.477 | CZ30: =+BC30+CU30 -> 530.62661 | DA30: =+BD30+CV30 -> 104 | DB30: =+CZ30+DA30 -> 634.62661
A31: =+A30+1 -> 22 | B31: CHICA VERA STEVEN MANUEL | C31: SIERRA 7 | D31: 0984156367 | E31: stevenverachica@gmail.com | F31: 0 | G31: =IF(F31<2700,F31*0.0097,IF(F31<3200,F31*0.01095,IF(F31<3700,F31*0.0122,IF(F31>3699,F31*0.01345,"")))) -> 0 | H31: 20 | I31: 0 | J31: =IF(I31<2700,I31*0.0097,IF(I31<3200,I31*0.01095,IF(I31<3700,I31*0.0122,IF(I31>3699,I31*0.01345,"")))) -> 0 | K31: 20 | L31: 0 | M31: =IF(L31<2700,L31*0.0097,IF(L31<3200,L31*0.01095,IF(L31<3700,L31*0.0122,IF(L31>3699,L31*0.01345,"")))) -> 0 | N31: 20 | P31: =IF(O31<2700,O31*0.0097,IF(O31<3200,O31*0.01095,IF(O31<3700,O31*0.0122,IF(O31>3699,O31*0.01345,"")))) -> 0 | R31: 4296.8442 | S31: =IF(R31<2700,R31*0.007,IF(R31<3200,R31*0.008,IF(R31<3700,R31*0.0097,IF(R31>3699,R31*0.01095,"")))) -> 47.050444 | U31: 3354.6935 | V31: =IF(U31<2700,U31*0.007,IF(U31<3200,U31*0.008,IF(U31<3700,U31*0.0097,IF(U31>3699,U31*0.01095,"")))) -> 32.540527 | X31: 2617.0854 | Y31: =IF(X31<2700,X31*0.007,IF(X31<3200,X31*0.008,IF(X31<3700,X31*0.0097,IF(X31>3699,X31*0.01095,"")))) -> 18.319598 | AA31: 2575.598 | AB31: =IF(AA31<2700,AA31*0.007,IF(AA31<3200,AA31*0.008,IF(AA31<3700,AA31*0.0097,IF(AA31>3699,AA31*0.01095,"")))) -> 18.029186 | AD31: 6276.1809 | AE31: =IF(AD31<2700,AD31*0.007,IF(AD31<3200,AD31*0.008,IF(AD31<3700,AD31*0.0097,IF(AD31>3699,AD31*0.01095,"")))) -> 68.724181 | AG31: 0 | AH31: =IF(AG31<2700,AG31*0.0097,IF(AG31<3200,AG31*0.01095,IF(AG31<3700,AG31*0.0122,IF(AG31>3699,AG31*0.01345,"")))) -> 0 | AJ31: 3702.0302 | AK31: =IF(AJ31<2700,AJ31*0.007,IF(AJ31<3200,AJ31*0.008,IF(AJ31<3700,AJ31*0.0097,IF(AJ31>3699,AJ31*0.01095,"")))) -> 40.53723 | AM31: 3237.4673 | AN31: =IF(AM31<2700,AM31*0.007,IF(AM31<3200,AM31*0.008,IF(AM31<3700,AM31*0.0097,IF(AM31>3699,AM31*0.01095,"")))) -> 31.403433 | AP31: 0 | AQ31: =IF(AP31<2700,AP31*0.0097,IF(AP31<3200,AP31*0.01095,IF(AP31<3700,AP31*0.0122,IF(AP31>3699,AP31*0.01345,"")))) -> 0 | AR31: 16 | AS31: 3941.3065 | AT31: =IF(AS31<2700,AS31*0.007,IF(AS31<3200,AS31*0.008,IF(AS31<3700,AS31*0.0097,IF(AS31>3699,AS31*0.01095,"")))) -> 43.157307 | AW31: =IF(AV31<2700,AV31*0.0097,IF(AV31<3200,AV31*0.01095,IF(AV31<3700,AV31*0.0122,IF(AV31>3699,AV31*0.01345,"")))) -> 0 | AZ31: =IF(AY31<2700,AY31*0.0097,IF(AY31<3200,AY31*0.01095,IF(AY31<3700,AY31*0.0122,IF(AY31>3699,AY31*0.01345,"")))) -> 0 | BB31: =+F31+I31+L31+O31+R31+U31+X31+AA31+AD31+AG31+AJ31+AM31+AP31+AS31+AV31+AY31 -> 30001.206 | BC31: =+G31+J31+M31+P31+S31+V31+Y31+AB31+AE31+AH31+AK31+AN31+AQ31+AT31+AW31+AZ31 -> 299.76191 | BD31: =+H31+K31+N31+Q31+T31+W31+Z31+AC31+AF31+AI31+AL31+AO31+AR31+AU31+AX31+BA31 -> 76 | BF31: =+BC31+BD31-BE31 -> 375.76191 | BG31: 3807.196 | BH31: =IF(BG31<2700,BG31*0.007,IF(BG31<3200,BG31*0.008,IF(BG31<3700,BG31*0.0097,IF(BG31>3699,BG31*0.01095,"")))) -> 41.688796 | BJ31: 0 | BK31: =IF(BJ31<2700,BJ31*0.0097,IF(BJ31<3200,BJ31*0.01095,IF(BJ31<3700,BJ31*0.0122,IF(BJ31>3699,BJ31*0.01345,"")))) -> 0 | BL31: 0 | BM31: 2947.0553 | BN31: =IF(BM31<2700,BM31*0.007,IF(BM31<3200,BM31*0.008,IF(BM31<3700,BM31*0.0097,IF(BM31>3699,BM31*0.01095,"")))) -> 23.576442 | BP31: 2849.1256 | BQ31: =IF(BP31<2700,BP31*0.007,IF(BP31<3200,BP31*0.008,IF(BP31<3700,BP31*0.0097,IF(BP31>3699,BP31*0.01095,"")))) -> 22.793005 | BS31: 3192.603 | BT31: =IF(BS31<2700,BS31*0.007,IF(BS31<3200,BS31*0.008,IF(BS31<3700,BS31*0.0097,IF(BS31>3699,BS31*0.01095,"")))) -> 25.540824 | BV31: 2590.5528 | BW31: =IF(BV31<2700,BV31*0.007,IF(BV31<3200,BV31*0.008,IF(BV31<3700,BV31*0.0097,IF(BV31>3699,BV31*0.01095,"")))) -> 18.133869 | BY31: 1296.2412 | BZ31: =IF(BY31<2700,BY31*0.007,IF(BY31<3200,BY31*0.008,IF(BY31<3700,BY31*0.0097,IF(BY31>3699,BY31*0.01095,"")))) -> 9.0736884 | CB31: 0 | CC31: =IF(CB31<2700,CB31*0.0097,IF(CB31<3200,CB31*0.01095,IF(CB31<3700,CB31*0.0122,IF(CB31>3699,CB31*0.01345,"")))) -> 0 | CD31: 0 | CE31: 3387.4975 | CF31: =IF(CE31<2700,CE31*0.007,IF(CE31<3200,CE31*0.008,IF(CE31<3700,CE31*0.0097,IF(CE31>3699,CE31*0.01095,"")))) -> 32.858726 | CH31: 0 | CI31: =IF(CH31<2700,CH31*0.0097,IF(CH31<3200,CH31*0.01095,IF(CH31<3700,CH31*0.0122,IF(CH31>3699,CH31*0.01345,"")))) -> 0 | CK31: 0 | CL31: =IF(CK31<2700,CK31*0.0097,IF(CK31<3200,CK31*0.01095,IF(CK31<3700,CK31*0.0122,IF(CK31>3699,CK31*0.01345,"")))) -> 0 | CN31: 0 | CO31: =IF(CN31<2700,CN31*0.0097,IF(CN31<3200,CN31*0.01095,IF(CN31<3700,CN31*0.0122,IF(CN31>3699,CN31*0.01345,"")))) -> 0 | CQ31: 0 | CR31: =IF(CQ31<2700,CQ31*0.0097,IF(CQ31<3200,CQ31*0.01095,IF(CQ31<3700,CQ31*0.0122,IF(CQ31>3699,CQ31*0.01345,"")))) -> 0 | CT31: =BG31+BJ31+BM31+BP31+BS31+BV31+BY31+CB31+CH31+CK31+CN31+CQ31+CE31 -> 20070.271 | CU31: =BH31+BK31+BN31+BQ31+BT31+BW31+BZ31+CC31+CI31+CL31+CO31+CR31+CF31 -> 173.66535 | CV31: =+BI31+BL31+BO31+BR31+BU31+BX31+CA31+CD31+CG31+CJ31+CM31+CP31+CS31 -> 0 | CX31: =+CU31+CV31-CW31 -> 173.66535 | CY31: =+BB31+CT31 -> 50071.477 | CZ31: =+BC31+CU31 -> 473.42726 | DA31: =+BD31+CV31 -> 76 | DB31: =+CZ31+DA31 -> 549.42726
A32: =+A31+1 -> 23 | B32: RAMOS CACIQUE MARIA BEATRIZ | C32: SIERRA 7 | D32: 0989841745 | E32: beatrizramoscacique@hotmail.com | F32: 0 | G32: =IF(F32<2700,F32*0.0101,IF(F32<3200,F32*0.01135,IF(F32<3700,F32*0.0126,IF(F32>3699,F32*0.01385,"")))) -> 0 | H32: 20 | I32: 0 | J32: =IF(I32<2700,I32*0.0101,IF(I32<3200,I32*0.01135,IF(I32<3700,I32*0.0126,IF(I32>3699,I32*0.01385,"")))) -> 0 | K32: 20 | L32: 0 | M32: =IF(L32<2700,L32*0.0101,IF(L32<3200,L32*0.01135,IF(L32<3700,L32*0.0126,IF(L32>3699,L32*0.01385,"")))) -> 0 | N32: 20 | P32: =IF(O32<2700,O32*0.0101,IF(O32<3200,O32*0.01135,IF(O32<3700,O32*0.0126,IF(O32>3699,O32*0.01385,"")))) -> 0 | R32: 4296.8442 | S32: =IF(R32<2700,R32*0.0075,IF(R32<3200,R32*0.009,IF(R32<3700,R32*0.0101,IF(R32>3699,R32*0.01135,"")))) -> 48.769182 | U32: 3354.6935 | V32: =IF(U32<2700,U32*0.0075,IF(U32<3200,U32*0.009,IF(U32<3700,U32*0.0101,IF(U32>3699,U32*0.01135,"")))) -> 33.882404 | X32: 2617.0854 | Y32: =IF(X32<2700,X32*0.0075,IF(X32<3200,X32*0.009,IF(X32<3700,X32*0.0101,IF(X32>3699,X32*0.01135,"")))) -> 19.628141 | AA32: 2575.598 | AB32: =IF(AA32<2700,AA32*0.0075,IF(AA32<3200,AA32*0.009,IF(AA32<3700,AA32*0.0101,IF(AA32>3699,AA32*0.01135,"")))) -> 19.316985 | AD32: 6276.1809 | AE32: =IF(AD32<2700,AD32*0.0075,IF(AD32<3200,AD32*0.009,IF(AD32<3700,AD32*0.0101,IF(AD32>3699,AD32*0.01135,"")))) -> 71.234653 | AG32: 0 | AH32: =IF(AG32<2700,AG32*0.0101,IF(AG32<3200,AG32*0.01135,IF(AG32<3700,AG32*0.0126,IF(AG32>3699,AG32*0.01385,"")))) -> 0 | AJ32: 3702.0302 | AK32: =IF(AJ32<2700,AJ32*0.0075,IF(AJ32<3200,AJ32*0.009,IF(AJ32<3700,AJ32*0.0101,IF(AJ32>3699,AJ32*0.01135,"")))) -> 42.018042 | AM32: 3237.4673 | AN32: =IF(AM32<2700,AM32*0.0075,IF(AM32<3200,AM32*0.009,IF(AM32<3700,AM32*0.0101,IF(AM32>3699,AM32*0.01135,"")))) -> 32.69842 | AP32: 0 | AQ32: =IF(AP32<2700,AP32*0.0101,IF(AP32<3200,AP32*0.01135,IF(AP32<3700,AP32*0.0126,IF(AP32>3699,AP32*0.01385,"")))) -> 0 | AR32: 16 | AS32: 3941.3065 | AT32: =IF(AS32<2700,AS32*0.0075,IF(AS32<3200,AS32*0.009,IF(AS32<3700,AS32*0.0101,IF(AS32>3699,AS32*0.01135,"")))) -> 44.733829 | AW32: =IF(AV32<2700,AV32*0.0101,IF(AV32<3200,AV32*0.01135,IF(AV32<3700,AV32*0.0126,IF(AV32>3699,AV32*0.01385,"")))) -> 0 | AZ32: =IF(AY32<2700,AY32*0.0101,IF(AY32<3200,AY32*0.01135,IF(AY32<3700,AY32*0.0126,IF(AY32>3699,AY32*0.01385,"")))) -> 0 | BB32: =+F32+I32+L32+O32+R32+U32+X32+AA32+AD32+AG32+AJ32+AM32+AP32+AS32+AV32+AY32 -> 30001.206 | BC32: =+G32+J32+M32+P32+S32+V32+Y32+AB32+AE32+AH32+AK32+AN32+AQ32+AT32+AW32+AZ32 -> 312.28166 | BD32: =+H32+K32+N32+Q32+T32+W32+Z32+AC32+AF32+AI32+AL32+AO32+AR32+AU32+AX32+BA32 -> 76 | BF32: =+BC32+BD32-BE32 -> 388.28166 | BG32: 3807.196 | BH32: =IF(BG32<2700,BG32*0.0075,IF(BG32<3200,BG32*0.009,IF(BG32<3700,BG32*0.0101,IF(BG32>3699,BG32*0.01135,"")))) -> 43.211674 | BJ32: 0 | BK32: =IF(BJ32<2700,BJ32*0.0101,IF(BJ32<3200,BJ32*0.01135,IF(BJ32<3700,BJ32*0.0126,IF(BJ32>3699,BJ32*0.01385,"")))) -> 0 | BL32: 12 | BM32: 2947.0553 | BN32: =IF(BM32<2700,BM32*0.0075,IF(BM32<3200,BM32*0.009,IF(BM32<3700,BM32*0.0101,IF(BM32>3699,BM32*0.01135,"")))) -> 26.523497 | BP32: 2849.1256 | BQ32: =IF(BP32<2700,BP32*0.0075,IF(BP32<3200,BP32*0.009,IF(BP32<3700,BP32*0.0101,IF(BP32>3699,BP32*0.01135,"")))) -> 25.642131 | BS32: 3192.603 | BT32: =IF(BS32<2700,BS32*0.0075,IF(BS32<3200,BS32*0.009,IF(BS32<3700,BS32*0.0101,IF(BS32>3699,BS32*0.01135,"")))) -> 28.733427 | BV32: 2590.5528 | BW32: =IF(BV32<2700,BV32*0.0075,IF(BV32<3200,BV32*0.009,IF(BV32<3700,BV32*0.0101,IF(BV32>3699,BV32*0.01135,"")))) -> 19.429146 | BY32: 1296.2412 | BZ32: =IF(BY32<2700,BY32*0.0075,IF(BY32<3200,BY32*0.009,IF(BY32<3700,BY32*0.0101,IF(BY32>3699,BY32*0.01135,"")))) -> 9.721809 | CB32: 0 | CC32: =IF(CB32<2700,CB32*0.0101,IF(CB32<3200,CB32*0.01135,IF(CB32<3700,CB32*0.0126,IF(CB32>3699,CB32*0.01385,"")))) -> 0 | CD32: 10 | CE32: 0 | CF32: =IF(CE32<2700,CE32*0.0075,IF(CE32<3200,CE32*0.009,IF(CE32<3700,CE32*0.0101,IF(CE32>3699,CE32*0.01135,"")))) -> 0 | CG32: 18 | CH32: 0 | CI32: =IF(CH32<2700,CH32*0.0101,IF(CH32<3200,CH32*0.01135,IF(CH32<3700,CH32*0.0126,IF(CH32>3699,CH32*0.01385,"")))) -> 0 | CJ32: 18 | CK32: 0 | CL32: =IF(CK32<2700,CK32*0.0101,IF(CK32<3200,CK32*0.01135,IF(CK32<3700,CK32*0.0126,IF(CK32>3699,CK32*0.01385,"")))) -> 0 | CN32: 0 | CO32: =IF(CN32<2700,CN32*0.0101,IF(CN32<3200,CN32*0.01135,IF(CN32<3700,CN32*0.0126,IF(CN32>3699,CN32*0.01385,"")))) -> 0 | CQ32: 0 | CR32: =IF(CQ32<2700,CQ32*0.0101,IF(CQ32<3200,CQ32*0.01135,IF(CQ32<3700,CQ32*0.0126,IF(CQ32>3699,CQ32*0.01385,"")))) -> 0 | CS32: 18 | CT32: =BG32+BJ32+BM32+BP32+BS32+BV32+BY32+CB32+CH32+CK32+CN32+CQ32+CE32 -> 16682.774 | CU32: =BH32+BK32+BN32+BQ32+BT32+BW32+BZ32+CC32+CI32+CL32+CO32+CR32+CF32 -> 153.26168 | CV32: =+BI32+BL32+BO32+BR32+BU32+BX32+CA32+CD32+CG32+CJ32+CM32+CP32+CS32 -> 76 | CX32: =+CU32+CV32-CW32 -> 229.26168 | CY32: =+BB32+CT32 -> 46683.98 | CZ32: =+BC32+CU32 -> 465.54334 | DA32: =+BD32+CV32 -> 152 | DB32: =+CZ32+DA32 -> 617.54334
A33: =+A32+1 -> 24 | B33: CEDEÑO MUÑOZ HEINER JESUS | C33: SIERRA 7 | D33: 0989934871 | E33: heinercede1999cm@gmail.com | F33: 0 | G33: =IF(F33<2700,F33*0.0097,IF(F33<3200,F33*0.01095,IF(F33<3700,F33*0.0122,IF(F33>3699,F33*0.01345,"")))) -> 0 | H33: 20 | I33: 0 | J33: =IF(I33<2700,I33*0.0097,IF(I33<3200,I33*0.01095,IF(I33<3700,I33*0.0122,IF(I33>3699,I33*0.01345,"")))) -> 0 | K33: 20 | L33: 0 | M33: =IF(L33<2700,L33*0.0097,IF(L33<3200,L33*0.01095,IF(L33<3700,L33*0.0122,IF(L33>3699,L33*0.01345,"")))) -> 0 | N33: 20 | P33: =IF(O33<2700,O33*0.0097,IF(O33<3200,O33*0.01095,IF(O33<3700,O33*0.0122,IF(O33>3699,O33*0.01345,"")))) -> 0 | R33: 4296.8442 | S33: =IF(R33<2700,R33*0.007,IF(R33<3200,R33*0.008,IF(R33<3700,R33*0.0097,IF(R33>3699,R33*0.01095,"")))) -> 47.050444 | U33: 3354.6935 | V33: =IF(U33<2700,U33*0.007,IF(U33<3200,U33*0.008,IF(U33<3700,U33*0.0097,IF(U33>3699,U33*0.01095,"")))) -> 32.540527 | X33: 2617.0854 | Y33: =IF(X33<2700,X33*0.007,IF(X33<3200,X33*0.008,IF(X33<3700,X33*0.0097,IF(X33>3699,X33*0.01095,"")))) -> 18.319598 | AA33: 2575.598 | AB33: =IF(AA33<2700,AA33*0.007,IF(AA33<3200,AA33*0.008,IF(AA33<3700,AA33*0.0097,IF(AA33>3699,AA33*0.01095,"")))) -> 18.029186 | AD33: 6276.1809 | AE33: =IF(AD33<2700,AD33*0.007,IF(AD33<3200,AD33*0.008,IF(AD33<3700,AD33*0.0097,IF(AD33>3699,AD33*0.01095,"")))) -> 68.724181 | AG33: 0 | AH33: =IF(AG33<2700,AG33*0.0097,IF(AG33<3200,AG33*0.01095,IF(AG33<3700,AG33*0.0122,IF(AG33>3699,AG33*0.01345,"")))) -> 0 | AJ33: 3702.0302 | AK33: =IF(AJ33<2700,AJ33*0.007,IF(AJ33<3200,AJ33*0.008,IF(AJ33<3700,AJ33*0.0097,IF(AJ33>3699,AJ33*0.01095,"")))) -> 40.53723 | AM33: 3237.4673 | AN33: =IF(AM33<2700,AM33*0.007,IF(AM33<3200,AM33*0.008,IF(AM33<3700,AM33*0.0097,IF(AM33>3699,AM33*0.01095,"")))) -> 31.403433 | AP33: 0 | AQ33: =IF(AP33<2700,AP33*0.0097,IF(AP33<3200,AP33*0.01095,IF(AP33<3700,AP33*0.0122,IF(AP33>3699,AP33*0.01345,"")))) -> 0 | AR33: 16 | AS33: 3941.3065 | AT33: =IF(AS33<2700,AS33*0.007,IF(AS33<3200,AS33*0.008,IF(AS33<3700,AS33*0.0097,IF(AS33>3699,AS33*0.01095,"")))) -> 43.157307 | AW33: =IF(AV33<2700,AV33*0.0097,IF(AV33<3200,AV33*0.01095,IF(AV33<3700,AV33*0.0122,IF(AV33>3699,AV33*0.01345,"")))) -> 0 | AZ33: =IF(AY33<2700,AY33*0.0097,IF(AY33<3200,AY33*0.01095,IF(AY33<3700,AY33*0.0122,IF(AY33>3699,AY33*0.01345,"")))) -> 0 | BB33: =+F33+I33+L33+O33+R33+U33+X33+AA33+AD33+AG33+AJ33+AM33+AP33+AS33+AV33+AY33 -> 30001.206 | BC33: =+G33+J33+M33+P33+S33+V33+Y33+AB33+AE33+AH33+AK33+AN33+AQ33+AT33+AW33+AZ33 -> 299.76191 | BD33: =+H33+K33+N33+Q33+T33+W33+Z33+AC33+AF33+AI33+AL33+AO33+AR33+AU33+AX33+BA33 -> 76 | BF33: =+BC33+BD33-BE33 -> 375.76191 | BG33: 3807.196 | BH33: =IF(BG33<2700,BG33*0.007,IF(BG33<3200,BG33*0.008,IF(BG33<3700,BG33*0.0097,IF(BG33>3699,BG33*0.01095,"")))) -> 41.688796 | BJ33: 0 | BK33: =IF(BJ33<2700,BJ33*0.0097,IF(BJ33<3200,BJ33*0.01095,IF(BJ33<3700,BJ33*0.0122,IF(BJ33>3699,BJ33*0.01345,"")))) -> 0 | BL33: 12 | BM33: 2947.0553 | BN33: =IF(BM33<2700,BM33*0.007,IF(BM33<3200,BM33*0.008,IF(BM33<3700,BM33*0.0097,IF(BM33>3699,BM33*0.01095,"")))) -> 23.576442 | BP33: 2849.1256 | BQ33: =IF(BP33<2700,BP33*0.007,IF(BP33<3200,BP33*0.008,IF(BP33<3700,BP33*0.0097,IF(BP33>3699,BP33*0.01095,"")))) -> 22.793005 | BS33: 3192.603 | BT33: =IF(BS33<2700,BS33*0.007,IF(BS33<3200,BS33*0.008,IF(BS33<3700,BS33*0.0097,IF(BS33>3699,BS33*0.01095,"")))) -> 25.540824 | BV33: 2590.5528 | BW33: =IF(BV33<2700,BV33*0.007,IF(BV33<3200,BV33*0.008,IF(BV33<3700,BV33*0.0097,IF(BV33>3699,BV33*0.01095,"")))) -> 18.133869 | BY33: 1296.2412 | BZ33: =IF(BY33<2700,BY33*0.007,IF(BY33<3200,BY33*0.008,IF(BY33<3700,BY33*0.0097,IF(BY33>3699,BY33*0.01095,"")))) -> 9.0736884 | CB33: 0 | CC33: =IF(CB33<2700,CB33*0.0097,IF(CB33<3200,CB33*0.01095,IF(CB33<3700,CB33*0.0122,IF(CB33>3699,CB33*0.01345,"")))) -> 0 | CD33: 10 | CE33: 3387.4975 | CF33: =IF(CE33<2700,CE33*0.007,IF(CE33<3200,CE33*0.008,IF(CE33<3700,CE33*0.0097,IF(CE33>3699,CE33*0.01095,"")))) -> 32.858726 | CH33: 0 | CI33: =IF(CH33<2700,CH33*0.0097,IF(CH33<3200,CH33*0.01095,IF(CH33<3700,CH33*0.0122,IF(CH33>3699,CH33*0.01345,"")))) -> 0 | CJ33: 18 | CK33: 0 | CL33: =IF(CK33<2700,CK33*0.0097,IF(CK33<3200,CK33*0.01095,IF(CK33<3700,CK33*0.0122,IF(CK33>3699,CK33*0.01345,"")))) -> 0 | CM33: 18 | CN33: 0 | CO33: =IF(CN33<2700,CN33*0.0097,IF(CN33<3200,CN33*0.01095,IF(CN33<3700,CN33*0.0122,IF(CN33>3699,CN33*0.01345,"")))) -> 0 | CQ33: 0 | CR33: =IF(CQ33<2700,CQ33*0.0097,IF(CQ33<3200,CQ33*0.01095,IF(CQ33<3700,CQ33*0.0122,IF(CQ33>3699,CQ33*0.01345,"")))) -> 0 | CS33: 18 | CT33: =BG33+BJ33+BM33+BP33+BS33+BV33+BY33+CB33+CH33+CK33+CN33+CQ33+CE33 -> 20070.271 | CU33: =BH33+BK33+BN33+BQ33+BT33+BW33+BZ33+CC33+CI33+CL33+CO33+CR33+CF33 -> 173.66535 | CV33: =+BI33+BL33+BO33+BR33+BU33+BX33+CA33+CD33+CG33+CJ33+CM33+CP33+CS33 -> 76 | CX33: =+CU33+CV33-CW33 -> 249.66535 | CY33: =+BB33+CT33 -> 50071.477 | CZ33: =+BC33+CU33 -> 473.42726 | DA33: =+BD33+CV33 -> 152 | DB33: =+CZ33+DA33 -> 625.42726
A34: =+A33+1 -> 25 | B34: SOLORZANO INTRIAGO JUAN CARLOS | C34: SIERRA 8 | D34: 0986245276 | E34: solorzanojuan61@gmail.com | F34: 0 | G34: =IF(F34<2700,F34*0.0105,IF(F34<3200,F34*0.01175,IF(F34<3700,F34*0.013,IF(F34>3699,F34*0.01425,"")))) -> 0 | H34: 20 | I34: 1612.7035 | J34: =IF(I34<2700,I34*0.0085,IF(I34<3200,I34*0.01,IF(I34<3700,I34*0.0105,IF(I34>3699,I34*0.01175,"")))) -> 13.70798 | K34: =30-J34 -> 16.29202 | L34: 0 | M34: =IF(L34<2700,L34*0.0105,IF(L34<3200,L34*0.01175,IF(L34<3700,L34*0.013,IF(L34>3699,L34*0.01425,"")))) -> 0 | N34: 20 | P34: =IF(O34<2700,O34*0.0105,IF(O34<3200,O34*0.01175,IF(O34<3700,O34*0.013,IF(O34>3699,O34*0.01425,"")))) -> 0 | R34: 3512.9246 | S34: =IF(R34<2700,R34*0.0085,IF(R34<3200,R34*0.01,IF(R34<3700,R34*0.0105,IF(R34>3699,R34*0.01175,"")))) -> 36.885709 | U34: 3316.1005 | V34: =IF(U34<2700,U34*0.0085,IF(U34<3200,U34*0.01,IF(U34<3700,U34*0.0105,IF(U34>3699,U34*0.01175,"")))) -> 34.819055 | X34: 2485.8693 | Y34: =IF(X34<2700,X34*0.0085,IF(X34<3200,X34*0.01,IF(X34<3700,X34*0.0105,IF(X34>3699,X34*0.01175,"")))) -> 21.129889 | AA34: 2361.407 | AB34: =IF(AA34<2700,AA34*0.0085,IF(AA34<3200,AA34*0.01,IF(AA34<3700,AA34*0.0105,IF(AA34>3699,AA34*0.01175,"")))) -> 20.07196 | AD34: 6922.1307 | AE34: =IF(AD34<2700,AD34*0.0085,IF(AD34<3200,AD34*0.01,IF(AD34<3700,AD34*0.0105,IF(AD34>3699,AD34*0.01175,"")))) -> 81.335035 | AG34: 0 | AH34: =IF(AG34<2700,AG34*0.0105,IF(AG34<3200,AG34*0.01175,IF(AG34<3700,AG34*0.013,IF(AG34>3699,AG34*0.01425,"")))) -> 0 | AJ34: 4146.8141 | AK34: =IF(AJ34<2700,AJ34*0.0085,IF(AJ34<3200,AJ34*0.01,IF(AJ34<3700,AJ34*0.0105,IF(AJ34>3699,AJ34*0.01175,"")))) -> 48.725065 | AM34: 3157.3869 | AN34: =IF(AM34<2700,AM34*0.0085,IF(AM34<3200,AM34*0.01,IF(AM34<3700,AM34*0.0105,IF(AM34>3699,AM34*0.01175,"")))) -> 31.573869 | AP34: 0 | AQ34: =IF(AP34<2700,AP34*0.0105,IF(AP34<3200,AP34*0.01175,IF(AP34<3700,AP34*0.013,IF(AP34>3699,AP34*0.01425,"")))) -> 0 | AR34: 14 | AS34: 3583.3568 | AT34: =IF(AS34<2700,AS34*0.0085,IF(AS34<3200,AS34*0.01,IF(AS34<3700,AS34*0.0105,IF(AS34>3699,AS34*0.01175,"")))) -> 37.625246 | AW34: =IF(AV34<2700,AV34*0.0105,IF(AV34<3200,AV34*0.01175,IF(AV34<3700,AV34*0.013,IF(AV34>3699,AV34*0.01425,"")))) -> 0 | AZ34: =IF(AY34<2700,AY34*0.0105,IF(AY34<3200,AY34*0.01175,IF(AY34<3700,AY34*0.013,IF(AY34>3699,AY34*0.01425,"")))) -> 0 | BB34: =+F34+I34+L34+O34+R34+U34+X34+AA34+AD34+AG34+AJ34+AM34+AP34+AS34+AV34+AY34 -> 31098.693 | BC34: =+G34+J34+M34+P34+S34+V34+Y34+AB34+AE34+AH34+AK34+AN34+AQ34+AT34+AW34+AZ34 -> 325.87381 | BD34: =+H34+K34+N34+Q34+T34+W34+Z34+AC34+AF34+AI34+AL34+AO34+AR34+AU34+AX34+BA34 -> 70.29202 | BF34: =+BC34+BD34-BE34 -> 396.16583 | BG34: 3196.9447 | BH34: =IF(BG34<2700,BG34*0.0085,IF(BG34<3200,BG34*0.01,IF(BG34<3700,BG34*0.0105,IF(BG34>3699,BG34*0.01175,"")))) -> 31.969447 | BJ34: 0 | BK34: =IF(BJ34<2700,BJ34*0.0105,IF(BJ34<3200,BJ34*0.01175,IF(BJ34<3700,BJ34*0.013,IF(BJ34>3699,BJ34*0.01425,"")))) -> 0 | BL34: 0 | BM34: 2853.4673 | BN34: =IF(BM34<2700,BM34*0.0085,IF(BM34<3200,BM34*0.01,IF(BM34<3700,BM34*0.0105,IF(BM34>3699,BM34*0.01175,"")))) -> 28.534673 | BP34: 3258.2111 | BQ34: =IF(BP34<2700,BP34*0.0085,IF(BP34<3200,BP34*0.01,IF(BP34<3700,BP34*0.0105,IF(BP34>3699,BP34*0.01175,"")))) -> 34.211216 | BS34: 0 | BT34: =IF(BS34<2700,BS34*0.0105,IF(BS34<3200,BS34*0.01175,IF(BS34<3700,BS34*0.013,IF(BS34>3699,BS34*0.01425,"")))) -> 0 | BU34: 18 | BV34: 0 | BW34: =IF(BV34<2700,BV34*0.0105,IF(BV34<3200,BV34*0.01175,IF(BV34<3700,BV34*0.013,IF(BV34>3699,BV34*0.01425,"")))) -> 0 | BX34: 18 | BY34: 0 | BZ34: =IF(BY34<2700,BY34*0.0105,IF(BY34<3200,BY34*0.01175,IF(BY34<3700,BY34*0.013,IF(BY34>3699,BY34*0.01425,"")))) -> 0 | CA34: 18 | CB34: 0 | CC34: =IF(CB34<2700,CB34*0.0105,IF(CB34<3200,CB34*0.01175,IF(CB34<3700,CB34*0.013,IF(CB34>3699,CB34*0.01425,"")))) -> 0 | CD34: 0 | CE34: 3462.7538 | CF34: =IF(CE34<2700,CE34*0.0085,IF(CE34<3200,CE34*0.01,IF(CE34<3700,CE34*0.0105,IF(CE34>3699,CE34*0.01175,"")))) -> 36.358915 | CH34: 0 | CI34: =IF(CH34<2700,CH34*0.0105,IF(CH34<3200,CH34*0.01175,IF(CH34<3700,CH34*0.013,IF(CH34>3699,CH34*0.01425,"")))) -> 0 | CK34: 0 | CL34: =IF(CK34<2700,CK34*0.0105,IF(CK34<3200,CK34*0.01175,IF(CK34<3700,CK34*0.013,IF(CK34>3699,CK34*0.01425,"")))) -> 0 | CN34: 0 | CO34: =IF(CN34<2700,CN34*0.0105,IF(CN34<3200,CN34*0.01175,IF(CN34<3700,CN34*0.013,IF(CN34>3699,CN34*0.01425,"")))) -> 0 | CQ34: 0 | CR34: =IF(CQ34<2700,CQ34*0.0105,IF(CQ34<3200,CQ34*0.01175,IF(CQ34<3700,CQ34*0.013,IF(CQ34>3699,CQ34*0.01425,"")))) -> 0 | CT34: =BG34+BJ34+BM34+BP34+BS34+BV34+BY34+CB34+CH34+CK34+CN34+CQ34+CE34 -> 12771.377 | CU34: =BH34+BK34+BN34+BQ34+BT34+BW34+BZ34+CC34+CI34+CL34+CO34+CR34+CF34 -> 131.07425 | CV34: =+BI34+BL34+BO34+BR34+BU34+BX34+CA34+CD34+CG34+CJ34+CM34+CP34+CS34 -> 54 | CX34: =+CU34+CV34-CW34 -> 185.07425 | CY34: =+BB34+CT34 -> 43870.07 | CZ34: =+BC34+CU34 -> 456.94806 | DA34: =+BD34+CV34 -> 124.29202 | DB34: =+CZ34+DA34 -> 581.24008
A35: =+A34+1 -> 26 | B35: BRAVO LUCAS YANINE MARIUXI | C35: SIERRA 8 | D35: 0990908974 | E35: janinebravo1995123@gmail.com | F35: 0 | G35: =IF(F35<2700,F35*0.0101,IF(F35<3200,F35*0.01135,IF(F35<3700,F35*0.0126,IF(F35>3699,F35*0.01385,"")))) -> 0 | H35: 20 | I35: 0 | J35: =IF(I35<2700,I35*0.009,IF(I35<3200,I35*0.0101,IF(I35<3700,I35*0.01135,IF(I35>3699,I35*0.0126,"")))) -> 0 | K35: 30 | L35: 0 | M35: =IF(L35<2700,L35*0.0101,IF(L35<3200,L35*0.01135,IF(L35<3700,L35*0.0126,IF(L35>3699,L35*0.01385,"")))) -> 0 | N35: 40 | P35: =IF(O35<2700,O35*0.0101,IF(O35<3200,O35*0.01135,IF(O35<3700,O35*0.0126,IF(O35>3699,O35*0.01385,"")))) -> 0 | R35: 3512.9246 | S35: =IF(R35<2700,R35*0.0075,IF(R35<3200,R35*0.009,IF(R35<3700,R35*0.0101,IF(R35>3699,R35*0.01135,"")))) -> 35.480539 | U35: 3316.1005 | V35: =IF(U35<2700,U35*0.0075,IF(U35<3200,U35*0.009,IF(U35<3700,U35*0.0101,IF(U35>3699,U35*0.01135,"")))) -> 33.492615 | X35: 2485.8693 | Y35: =IF(X35<2700,X35*0.0075,IF(X35<3200,X35*0.009,IF(X35<3700,X35*0.0101,IF(X35>3699,X35*0.01135,"")))) -> 18.64402 | AA35: 2361.407 | AB35: =IF(AA35<2700,AA35*0.0075,IF(AA35<3200,AA35*0.009,IF(AA35<3700,AA35*0.0101,IF(AA35>3699,AA35*0.01135,"")))) -> 17.710553 | AD35: 6922.1307 | AE35: =IF(AD35<2700,AD35*0.0075,IF(AD35<3200,AD35*0.009,IF(AD35<3700,AD35*0.0101,IF(AD35>3699,AD35*0.01135,"")))) -> 78.566183 | AG35: 0 | AH35: =IF(AG35<2700,AG35*0.0101,IF(AG35<3200,AG35*0.01135,IF(AG35<3700,AG35*0.0126,IF(AG35>3699,AG35*0.01385,"")))) -> 0 | AJ35: 4146.8141 | AK35: =IF(AJ35<2700,AJ35*0.0075,IF(AJ35<3200,AJ35*0.009,IF(AJ35<3700,AJ35*0.0101,IF(AJ35>3699,AJ35*0.01135,"")))) -> 47.06634 | AM35: 3157.3869 | AN35: =IF(AM35<2700,AM35*0.0075,IF(AM35<3200,AM35*0.009,IF(AM35<3700,AM35*0.0101,IF(AM35>3699,AM35*0.01135,"")))) -> 28.416482 | AP35: 0 | AQ35: =IF(AP35<2700,AP35*0.0101,IF(AP35<3200,AP35*0.01135,IF(AP35<3700,AP35*0.0126,IF(AP35>3699,AP35*0.01385,"")))) -> 0 | AR35: 14 | AS35: 3583.3568 | AT35: =IF(AS35<2700,AS35*0.0075,IF(AS35<3200,AS35*0.009,IF(AS35<3700,AS35*0.0101,IF(AS35>3699,AS35*0.01135,"")))) -> 36.191904 | AW35: =IF(AV35<2700,AV35*0.0101,IF(AV35<3200,AV35*0.01135,IF(AV35<3700,AV35*0.0126,IF(AV35>3699,AV35*0.01385,"")))) -> 0 | AZ35: =IF(AY35<2700,AY35*0.0101,IF(AY35<3200,AY35*0.01135,IF(AY35<3700,AY35*0.0126,IF(AY35>3699,AY35*0.01385,"")))) -> 0 | BB35: =+F35+I35+L35+O35+R35+U35+X35+AA35+AD35+AG35+AJ35+AM35+AP35+AS35+AV35+AY35 -> 29485.99 | BC35: =+G35+J35+M35+P35+S35+V35+Y35+AB35+AE35+AH35+AK35+AN35+AQ35+AT35+AW35+AZ35 -> 295.56864 | BD35: =+H35+K35+N35+Q35+T35+W35+Z35+AC35+AF35+AI35+AL35+AO35+AR35+AU35+AX35+BA35 -> 104 | BF35: =+BC35+BD35-BE35 -> 399.56864 | BG35: 3196.9447 | BH35: =IF(BG35<2700,BG35*0.0075,IF(BG35<3200,BG35*0.009,IF(BG35<3700,BG35*0.0101,IF(BG35>3699,BG35*0.01135,"")))) -> 28.772503 | BJ35: 0 | BK35: =IF(BJ35<2700,BJ35*0.0101,IF(BJ35<3200,BJ35*0.01135,IF(BJ35<3700,BJ35*0.0126,IF(BJ35>3699,BJ35*0.01385,"")))) -> 0 | BL35: 12 | BM35: 2853.4673 | BN35: =IF(BM35<2700,BM35*0.0075,IF(BM35<3200,BM35*0.009,IF(BM35<3700,BM35*0.0101,IF(BM35>3699,BM35*0.01135,"")))) -> 25.681206 | BP35: 3258.2111 | BQ35: =IF(BP35<2700,BP35*0.0075,IF(BP35<3200,BP35*0.009,IF(BP35<3700,BP35*0.0101,IF(BP35>3699,BP35*0.01135,"")))) -> 32.907932 | BS35: 0 | BT35: =IF(BS35<2700,BS35*0.0101,IF(BS35<3200,BS35*0.01135,IF(BS35<3700,BS35*0.0126,IF(BS35>3699,BS35*0.01385,"")))) -> 0 | BU35: 18 | BV35: 0 | BW35: =IF(BV35<2700,BV35*0.0101,IF(BV35<3200,BV35*0.01135,IF(BV35<3700,BV35*0.0126,IF(BV35>3699,BV35*0.01385,"")))) -> 0 | BX35: 18 | BY35: 0 | BZ35: =IF(BY35<2700,BY35*0.0101,IF(BY35<3200,BY35*0.01135,IF(BY35<3700,BY35*0.0126,IF(BY35>3699,BY35*0.01385,"")))) -> 0 | CA35: 18 | CB35: 0 | CC35: =IF(CB35<2700,CB35*0.0101,IF(CB35<3200,CB35*0.01135,IF(CB35<3700,CB35*0.0126,IF(CB35>3699,CB35*0.01385,"")))) -> 0 | CD35: 10 | CE35: 3462.7538 | CF35: =IF(CE35<2700,CE35*0.009,IF(CE35<3200,CE35*0.0101,IF(CE35<3700,CE35*0.01135,IF(CE35>3699,CE35*0.0126,"")))) -> 39.302255 | CH35: 0 | CI35: =IF(CH35<2700,CH35*0.0101,IF(CH35<3200,CH35*0.01135,IF(CH35<3700,CH35*0.0126,IF(CH35>3699,CH35*0.01385,"")))) -> 0 | CJ35: 18 | CK35: 0 | CL35: =IF(CK35<2700,CK35*0.0101,IF(CK35<3200,CK35*0.01135,IF(CK35<3700,CK35*0.0126,IF(CK35>3699,CK35*0.01385,"")))) -> 0 | CM35: 18 | CN35: 0 | CO35: =IF(CN35<2700,CN35*0.0101,IF(CN35<3200,CN35*0.01135,IF(CN35<3700,CN35*0.0126,IF(CN35>3699,CN35*0.01385,"")))) -> 0 | CQ35: 0 | CR35: =IF(CQ35<2700,CQ35*0.0101,IF(CQ35<3200,CQ35*0.01135,IF(CQ35<3700,CQ35*0.0126,IF(CQ35>3699,CQ35*0.01385,"")))) -> 0 | CT35: =BG35+BJ35+BM35+BP35+BS35+BV35+BY35+CB35+CH35+CK35+CN35+CQ35+CE35 -> 12771.377 | CU35: =BH35+BK35+BN35+BQ35+BT35+BW35+BZ35+CC35+CI35+CL35+CO35+CR35+CF35 -> 126.6639 | CV35: =+BI35+BL35+BO35+BR35+BU35+BX35+CA35+CD35+CG35+CJ35+CM35+CP35+CS35 -> 112 | CX35: =+CU35+CV35-CW35 -> 238.6639 | CY35: =+BB35+CT35 -> 42257.367 | CZ35: =+BC35+CU35 -> 422.23253 | DA35: =+BD35+CV35 -> 216 | DB35: =+CZ35+DA35 -> 638.23253
A36: =+A35+1 -> 27 | B36: ANDRADE ZAMBRANO JESUS DANIEL | C36: SIERRA 9 | D36: 0997555720 | E36: dany1997111@hotmail.com | F36: 0 | G36: =IF(F36<2700,F36*0.0105,IF(F36<3200,F36*0.01175,IF(F36<3700,F36*0.013,IF(F36>3699,F36*0.01425,"")))) -> 0 | H36: 20 | I36: 2625.7688 | J36: =IF(I36<2700,I36*0.0085,IF(I36<3200,I36*0.01,IF(I36<3700,I36*0.0105,IF(I36>3699,I36*0.01175,"")))) -> 22.319035 | K36: =30-J36 -> 7.6809648 | L36: 3790.794 | M36: =IF(L36<2700,L36*0.0085,IF(L36<3200,L36*0.01,IF(L36<3700,L36*0.0105,IF(L36>3699,L36*0.01175,"")))) -> 44.541829 | P36: =IF(O36<2700,O36*0.0105,IF(O36<3200,O36*0.01175,IF(O36<3700,O36*0.013,IF(O36>3699,O36*0.01425,"")))) -> 0 | R36: 4258.2513 | S36: =IF(R36<2700,R36*0.0085,IF(R36<3200,R36*0.01,IF(R36<3700,R36*0.0105,IF(R36>3699,R36*0.01175,"")))) -> 50.034452 | U36: 3747.8593 | V36: =IF(U36<2700,U36*0.0085,IF(U36<3200,U36*0.01,IF(U36<3700,U36*0.0105,IF(U36>3699,U36*0.01175,"")))) -> 44.037347 | X36: 3012.1809 | Y36: =IF(X36<2700,X36*0.0085,IF(X36<3200,X36*0.01,IF(X36<3700,X36*0.0105,IF(X36>3699,X36*0.01175,"")))) -> 30.121809 | AA36: 2680.7638 | AB36: =IF(AA36<2700,AA36*0.0085,IF(AA36<3200,AA36*0.01,IF(AA36<3700,AA36*0.0105,IF(AA36>3699,AA36*0.01175,"")))) -> 22.786492 | AD36: 7911.0754 | AE36: =IF(AD36<2700,AD36*0.0085,IF(AD36<3200,AD36*0.01,IF(AD36<3700,AD36*0.0105,IF(AD36>3699,AD36*0.01175,"")))) -> 92.955136 | AG36: 0 | AH36: =IF(AG36<2700,AG36*0.0105,IF(AG36<3200,AG36*0.01175,IF(AG36<3700,AG36*0.013,IF(AG36>3699,AG36*0.01425,"")))) -> 0 | AJ36: 4200.8442 | AK36: =IF(AJ36<2700,AJ36*0.0085,IF(AJ36<3200,AJ36*0.01,IF(AJ36<3700,AJ36*0.0105,IF(AJ36>3699,AJ36*0.01175,"")))) -> 49.35992 | AM36: 0 | AN36: =IF(AM36<2700,AM36*0.01,IF(AM36<3200,AM36*0.0105,IF(AM36<3700,AM36*0.01175,IF(AM36>3699,AM36*0.013,"")))) -> 0 | AO36: 18 | AP36: 0 | AQ36: =IF(AP36<2700,AP36*0.0105,IF(AP36<3200,AP36*0.01175,IF(AP36<3700,AP36*0.013,IF(AP36>3699,AP36*0.01425,"")))) -> 0 | AS36: 4656.7236 | AT36: =IF(AS36<2700,AS36*0.01,IF(AS36<3200,AS36*0.0105,IF(AS36<3700,AS36*0.01175,IF(AS36>3699,AS36*0.013,"")))) -> 60.537407 | AW36: =IF(AV36<2700,AV36*0.0105,IF(AV36<3200,AV36*0.01175,IF(AV36<3700,AV36*0.013,IF(AV36>3699,AV36*0.01425,"")))) -> 0 | AZ36: =IF(AY36<2700,AY36*0.0105,IF(AY36<3200,AY36*0.01175,IF(AY36<3700,AY36*0.013,IF(AY36>3699,AY36*0.01425,"")))) -> 0 | BB36: =+F36+I36+L36+O36+R36+U36+X36+AA36+AD36+AG36+AJ36+AM36+AP36+AS36+AV36+AY36 -> 36884.261 | BC36: =+G36+J36+M36+P36+S36+V36+Y36+AB36+AE36+AH36+AK36+AN36+AQ36+AT36+AW36+AZ36 -> 416.69343 | BD36: =+H36+K36+N36+Q36+T36+W36+Z36+AC36+AF36+AI36+AL36+AO36+AR36+AU36+AX36+BA36 -> 45.680965 | BF36: =+BC36+BD36-BE36 -> 462.37439 | BG36: 4331.0955 | BH36: =IF(BG36<2700,BG36*0.0085,IF(BG36<3200,BG36*0.01,IF(BG36<3700,BG36*0.0105,IF(BG36>3699,BG36*0.01175,"")))) -> 50.890372 | BJ36: 0 | BK36: =IF(BJ36<2700,BJ36*0.0105,IF(BJ36<3200,BJ36*0.01175,IF(BJ36<3700,BJ36*0.013,IF(BJ36>3699,BJ36*0.01425,"")))) -> 0 | BL36: 0 | BM36: 3048.8442 | BN36: =IF(BM36<2700,BM36*0.0085,IF(BM36<3200,BM36*0.01,IF(BM36<3700,BM36*0.0105,IF(BM36>3699,BM36*0.01175,"")))) -> 30.488442 | BP36: 3343.598 | BQ36: =IF(BP36<2700,BP36*0.0085,IF(BP36<3200,BP36*0.01,IF(BP36<3700,BP36*0.0105,IF(BP36>3699,BP36*0.01175,"")))) -> 35.107779 | BS36: 0 | BT36: =IF(BS36<2700,BS36*0.0105,IF(BS36<3200,BS36*0.01175,IF(BS36<3700,BS36*0.013,IF(BS36>3699,BS36*0.01425,"")))) -> 0 | BU36: 18 | BV36: 0 | BW36: =IF(BV36<2700,BV36*0.0105,IF(BV36<3200,BV36*0.01175,IF(BV36<3700,BV36*0.013,IF(BV36>3699,BV36*0.01425,"")))) -> 0 | BX36: 18 | BY36: 0 | BZ36: =IF(BY36<2700,BY36*0.0105,IF(BY36<3200,BY36*0.01175,IF(BY36<3700,BY36*0.013,IF(BY36>3699,BY36*0.01425,"")))) -> 0 | CA36: 18 | CB36: 0 | CC36: =IF(CB36<2700,CB36*0.0105,IF(CB36<3200,CB36*0.01175,IF(CB36<3700,CB36*0.013,IF(CB36>3699,CB36*0.01425,"")))) -> 0 | CD36: 10 | CE36: 4419.3769 | CF36: =IF(CE36<2700,CE36*0.0085,IF(CE36<3200,CE36*0.01,IF(CE36<3700,CE36*0.0105,IF(CE36>3699,CE36*0.01175,"")))) -> 51.927678 | CH36: 0 | CI36: =IF(CH36<2700,CH36*0.0105,IF(CH36<3200,CH36*0.01175,IF(CH36<3700,CH36*0.013,IF(CH36>3699,CH36*0.01425,"")))) -> 0 | CK36: 0 | CL36: =IF(CK36<2700,CK36*0.0105,IF(CK36<3200,CK36*0.01175,IF(CK36<3700,CK36*0.013,IF(CK36>3699,CK36*0.01425,"")))) -> 0 | CN36: 0 | CO36: =IF(CN36<2700,CN36*0.0105,IF(CN36<3200,CN36*0.01175,IF(CN36<3700,CN36*0.013,IF(CN36>3699,CN36*0.01425,"")))) -> 0 | CQ36: 0 | CR36: =IF(CQ36<2700,CQ36*0.0105,IF(CQ36<3200,CQ36*0.01175,IF(CQ36<3700,CQ36*0.013,IF(CQ36>3699,CQ36*0.01425,"")))) -> 0 | CT36: =BG36+BJ36+BM36+BP36+BS36+BV36+BY36+CB36+CH36+CK36+CN36+CQ36+CE36 -> 15142.915 | CU36: =BH36+BK36+BN36+BQ36+BT36+BW36+BZ36+CC36+CI36+CL36+CO36+CR36+CF36 -> 168.41427 | CV36: =+BI36+BL36+BO36+BR36+BU36+BX36+CA36+CD36+CG36+CJ36+CM36+CP36+CS36 -> 64 | CX36: =+CU36+CV36-CW36 -> 232.41427 | CY36: =+BB36+CT36 -> 52027.176 | CZ36: =+BC36+CU36 -> 585.1077 | DA36: =+BD36+CV36 -> 109.68096 | DB36: =+CZ36+DA36 -> 694.78866
A37: =+A36+1 -> 28 | B37: VARELA ANDRADE JIMY FABRICIO | C37: SIERRA 9 | D37: 0989671159 | E37: jimyvarelaandrade@hotmail.com | F37: 0 | G37: =IF(F37<2700,F37*0.0097,IF(F37<3200,F37*0.01095,IF(F37<3700,F37*0.0122,IF(F37>3699,F37*0.01345,"")))) -> 0 | H37: 20 | I37: 2625.7688 | J37: =IF(I37<2700,I37*0.007,IF(I37<3200,I37*0.008,IF(I37<3700,I37*0.0097,IF(I37>3699,I37*0.01095,"")))) -> 18.380382 | K37: =30-J37 -> 11.619618 | L37: 3790.794 | M37: =IF(L37<2700,L37*0.007,IF(L37<3200,L37*0.008,IF(L37<3700,L37*0.0097,IF(L37>3699,L37*0.01095,"")))) -> 41.509194 | P37: =IF(O37<2700,O37*0.0097,IF(O37<3200,O37*0.01095,IF(O37<3700,O37*0.0122,IF(O37>3699,O37*0.01345,"")))) -> 0 | R37: 0 | S37: =IF(R37<2700,R37*0.008,IF(R37<3200,R37*0.0097,IF(R37<3700,R37*0.01095,IF(R37>3699,R37*0.0122,"")))) -> 0 | T37: 25 | U37: 3747.8593 | V37: =IF(U37<2700,U37*0.007,IF(U37<3200,U37*0.008,IF(U37<3700,U37*0.0097,IF(U37>3699,U37*0.01095,"")))) -> 41.039059 | X37: 3012.1809 | Y37: =IF(X37<2700,X37*0.007,IF(X37<3200,X37*0.008,IF(X37<3700,X37*0.0097,IF(X37>3699,X37*0.01095,"")))) -> 24.097447 | AA37: 2680.7638 | AB37: =IF(AA37<2700,AA37*0.007,IF(AA37<3200,AA37*0.008,IF(AA37<3700,AA37*0.0097,IF(AA37>3699,AA37*0.01095,"")))) -> 18.765347 | AD37: 7911.0754 | AE37: =IF(AD37<2700,AD37*0.007,IF(AD37<3200,AD37*0.008,IF(AD37<3700,AD37*0.0097,IF(AD37>3699,AD37*0.01095,"")))) -> 86.626275 | AG37: 0 | AH37: =IF(AG37<2700,AG37*0.0097,IF(AG37<3200,AG37*0.01095,IF(AG37<3700,AG37*0.0122,IF(AG37>3699,AG37*0.01345,"")))) -> 0 | AJ37: 4200.8442 | AK37: =IF(AJ37<2700,AJ37*0.007,IF(AJ37<3200,AJ37*0.008,IF(AJ37<3700,AJ37*0.0097,IF(AJ37>3699,AJ37*0.01095,"")))) -> 45.999244 | AM37: 0 | AN37: =IF(AM37<2700,AM37*0.008,IF(AM37<3200,AM37*0.0097,IF(AM37<3700,AM37*0.01095,IF(AM37>3699,AM37*0.0122,"")))) -> 0 | AO37: 20 | AP37: 0 | AQ37: =IF(AP37<2700,AP37*0.0097,IF(AP37<3200,AP37*0.01095,IF(AP37<3700,AP37*0.0122,IF(AP37>3699,AP37*0.01345,"")))) -> 0 | AR37: 12 | AS37: 4656.7236 | AT37: =IF(AS37<2700,AS37*0.007,IF(AS37<3200,AS37*0.008,IF(AS37<3700,AS37*0.0097,IF(AS37>3699,AS37*0.01095,"")))) -> 50.991124 | AW37: =IF(AV37<2700,AV37*0.0097,IF(AV37<3200,AV37*0.01095,IF(AV37<3700,AV37*0.0122,IF(AV37>3699,AV37*0.01345,"")))) -> 0 | AZ37: =IF(AY37<2700,AY37*0.0097,IF(AY37<3200,AY37*0.01095,IF(AY37<3700,AY37*0.0122,IF(AY37>3699,AY37*0.01345,"")))) -> 0 | BB37: =+F37+I37+L37+O37+R37+U37+X37+AA37+AD37+AG37+AJ37+AM37+AP37+AS37+AV37+AY37 -> 32626.01 | BC37: =+G37+J37+M37+P37+S37+V37+Y37+AB37+AE37+AH37+AK37+AN37+AQ37+AT37+AW37+AZ37 -> 327.40807 | BD37: =+H37+K37+N37+Q37+T37+W37+Z37+AC37+AF37+AI37+AL37+AO37+AR37+AU37+AX37+BA37 -> 88.619618 | BF37: =+BC37+BD37-BE37 -> 416.02769 | BG37: 4331.0955 | BH37: =IF(BG37<2700,BG37*0.007,IF(BG37<3200,BG37*0.008,IF(BG37<3700,BG37*0.0097,IF(BG37>3699,BG37*0.01095,"")))) -> 47.425495 | BJ37: 0 | BK37: =IF(BJ37<2700,BJ37*0.0097,IF(BJ37<3200,BJ37*0.01095,IF(BJ37<3700,BJ37*0.0122,IF(BJ37>3699,BJ37*0.01345,"")))) -> 0 | BL37: 0 | BM37: 3048.8442 | BN37: =IF(BM37<2700,BM37*0.007,IF(BM37<3200,BM37*0.008,IF(BM37<3700,BM37*0.0097,IF(BM37>3699,BM37*0.01095,"")))) -> 24.390754 | BP37: 3343.598 | BQ37: =IF(BP37<2700,BP37*0.007,IF(BP37<3200,BP37*0.008,IF(BP37<3700,BP37*0.0097,IF(BP37>3699,BP37*0.01095,"")))) -> 32.432901 | BS37: 0 | BT37: =IF(BS37<2700,BS37*0.0097,IF(BS37<3200,BS37*0.01095,IF(BS37<3700,BS37*0.0122,IF(BS37>3699,BS37*0.01345,"")))) -> 0 | BU37: 18 | BV37: 0 | BW37: =IF(BV37<2700,BV37*0.0097,IF(BV37<3200,BV37*0.01095,IF(BV37<3700,BV37*0.0122,IF(BV37>3699,BV37*0.01345,"")))) -> 0 | BX37: 18 | BY37: 0 | BZ37: =IF(BY37<2700,BY37*0.0097,IF(BY37<3200,BY37*0.01095,IF(BY37<3700,BY37*0.0122,IF(BY37>3699,BY37*0.01345,"")))) -> 0 | CA37: 18 | CB37: 0 | CC37: =IF(CB37<2700,CB37*0.0097,IF(CB37<3200,CB37*0.01095,IF(CB37<3700,CB37*0.0122,IF(CB37>3699,CB37*0.01345,"")))) -> 0 | CD37: 10 | CE37: 4419.3769 | CF37: =IF(CE37<2700,CE37*0.007,IF(CE37<3200,CE37*0.008,IF(CE37<3700,CE37*0.0097,IF(CE37>3699,CE37*0.01095,"")))) -> 48.392177 | CH37: 0 | CI37: =IF(CH37<2700,CH37*0.0097,IF(CH37<3200,CH37*0.01095,IF(CH37<3700,CH37*0.0122,IF(CH37>3699,CH37*0.01345,"")))) -> 0 | CK37: 0 | CL37: =IF(CK37<2700,CK37*0.0097,IF(CK37<3200,CK37*0.01095,IF(CK37<3700,CK37*0.0122,IF(CK37>3699,CK37*0.01345,"")))) -> 0 | CN37: 0 | CO37: =IF(CN37<2700,CN37*0.0097,IF(CN37<3200,CN37*0.01095,IF(CN37<3700,CN37*0.0122,IF(CN37>3699,CN37*0.01345,"")))) -> 0 | CQ37: 0 | CR37: =IF(CQ37<2700,CQ37*0.0097,IF(CQ37<3200,CQ37*0.01095,IF(CQ37<3700,CQ37*0.0122,IF(CQ37>3699,CQ37*0.01345,"")))) -> 0 | CT37: =BG37+BJ37+BM37+BP37+BS37+BV37+BY37+CB37+CH37+CK37+CN37+CQ37+CE37 -> 15142.915 | CU37: =BH37+BK37+BN37+BQ37+BT37+BW37+BZ37+CC37+CI37+CL37+CO37+CR37+CF37 -> 152.64133 | CV37: =+BI37+BL37+BO37+BR37+BU37+BX37+CA37+CD37+CG37+CJ37+CM37+CP37+CS37 -> 64 | CX37: =+CU37+CV37-CW37 -> 216.64133 | CY37: =+BB37+CT37 -> 47768.925 | CZ37: =+BC37+CU37 -> 480.0494 | DA37: =+BD37+CV37 -> 152.61962 | DB37: =+CZ37+DA37 -> 632.66902
A38: =+A37+1 -> 29 | B38: MURILLO VARGAS MARITZA LILIANA | C38: SIERRA 9 | D38: 0989405423 | E38: murillovargas95@gmail.com | F38: 0 | G38: =IF(F38<2700,F38*0.0101,IF(F38<3200,F38*0.01135,IF(F38<3700,F38*0.0126,IF(F38>3699,F38*0.01385,"")))) -> 0 | H38: 20 | I38: 2625.7688 | J38: =IF(I38<2700,I38*0.0075,IF(I38<3200,I38*0.009,IF(I38<3700,I38*0.0101,IF(I38>3699,I38*0.01135,"")))) -> 19.693266 | K38: =30-J38 -> 10.306734 | L38: 3790.794 | M38: =IF(L38<2700,L38*0.0075,IF(L38<3200,L38*0.009,IF(L38<3700,L38*0.0101,IF(L38>3699,L38*0.01135,"")))) -> 43.025512 | P38: =IF(O38<2700,O38*0.0101,IF(O38<3200,O38*0.01135,IF(O38<3700,O38*0.0126,IF(O38>3699,O38*0.01385,"")))) -> 0 | R38: 4258.2513 | S38: =IF(R38<2700,R38*0.0075,IF(R38<3200,R38*0.009,IF(R38<3700,R38*0.0101,IF(R38>3699,R38*0.01135,"")))) -> 48.331152 | U38: 3747.8593 | V38: =IF(U38<2700,U38*0.0075,IF(U38<3200,U38*0.009,IF(U38<3700,U38*0.0101,IF(U38>3699,U38*0.01135,"")))) -> 42.538203 | X38: 3012.1809 | Y38: =IF(X38<2700,X38*0.0075,IF(X38<3200,X38*0.009,IF(X38<3700,X38*0.0101,IF(X38>3699,X38*0.01135,"")))) -> 27.109628 | AA38: 2680.7638 | AB38: =IF(AA38<2700,AA38*0.0075,IF(AA38<3200,AA38*0.009,IF(AA38<3700,AA38*0.0101,IF(AA38>3699,AA38*0.01135,"")))) -> 20.105729 | AD38: 7911.0754 | AE38: =IF(AD38<2700,AD38*0.0075,IF(AD38<3200,AD38*0.009,IF(AD38<3700,AD38*0.0101,IF(AD38>3699,AD38*0.01135,"")))) -> 89.790706 | AG38: 0 | AH38: =IF(AG38<2700,AG38*0.0101,IF(AG38<3200,AG38*0.01135,IF(AG38<3700,AG38*0.0126,IF(AG38>3699,AG38*0.01385,"")))) -> 0 | AJ38: 4200.8442 | AK38: =IF(AJ38<2700,AJ38*0.0075,IF(AJ38<3200,AJ38*0.009,IF(AJ38<3700,AJ38*0.0101,IF(AJ38>3699,AJ38*0.01135,"")))) -> 47.679582 | AM38: 0 | AN38: =IF(AM38<2700,AM38*0.009,IF(AM38<3200,AM38*0.0101,IF(AM38<3700,AM38*0.01135,IF(AM38>3699,AM38*0.0126,"")))) -> 0 | AO38: 18 | AP38: 0 | AQ38: =IF(AP38<2700,AP38*0.0101,IF(AP38<3200,AP38*0.01135,IF(AP38<3700,AP38*0.0126,IF(AP38>3699,AP38*0.01385,"")))) -> 0 | AR38: 12 | AS38: 4656.7236 | AT38: =IF(AS38<2700,AS38*0.0075,IF(AS38<3200,AS38*0.009,IF(AS38<3700,AS38*0.0101,IF(AS38>3699,AS38*0.01135,"")))) -> 52.853813 | AW38: =IF(AV38<2700,AV38*0.0101,IF(AV38<3200,AV38*0.01135,IF(AV38<3700,AV38*0.0126,IF(AV38>3699,AV38*0.01385,"")))) -> 0 | AZ38: =IF(AY38<2700,AY38*0.0101,IF(AY38<3200,AY38*0.01135,IF(AY38<3700,AY38*0.0126,IF(AY38>3699,AY38*0.01385,"")))) -> 0 | BB38: =+F38+I38+L38+O38+R38+U38+X38+AA38+AD38+AG38+AJ38+AM38+AP38+AS38+AV38+AY38 -> 36884.261 | BC38: =+G38+J38+M38+P38+S38+V38+Y38+AB38+AE38+AH38+AK38+AN38+AQ38+AT38+AW38+AZ38 -> 391.12759 | BD38: =+H38+K38+N38+Q38+T38+W38+Z38+AC38+AF38+AI38+AL38+AO38+AR38+AU38+AX38+BA38 -> 60.306734 | BF38: =+BC38+BD38-BE38 -> 451.43432 | BG38: 4331.0955 | BH38: =IF(BG38<2700,BG38*0.0075,IF(BG38<3200,BG38*0.009,IF(BG38<3700,BG38*0.0101,IF(BG38>3699,BG38*0.01135,"")))) -> 49.157934 | BJ38: 0 | BK38: =IF(BJ38<2700,BJ38*0.0101,IF(BJ38<3200,BJ38*0.01135,IF(BJ38<3700,BJ38*0.0126,IF(BJ38>3699,BJ38*0.01385,"")))) -> 0 | BL38: 12 | BM38: 0 | BN38: =IF(BM38<2700,BM38*0.0101,IF(BM38<3200,BM38*0.01135,IF(BM38<3700,BM38*0.0126,IF(BM38>3699,BM38*0.01385,"")))) -> 0 | BP38: 3343.598 | BQ38: =IF(BP38<2700,BP38*0.009,IF(BP38<3200,BP38*0.0101,IF(BP38<3700,BP38*0.01135,IF(BP38>3699,BP38*0.0126,"")))) -> 37.949837 | BS38: 0 | BT38: =IF(BS38<2700,BS38*0.0101,IF(BS38<3200,BS38*0.01135,IF(BS38<3700,BS38*0.0126,IF(BS38>3699,BS38*0.01385,"")))) -> 0 | BU38: 18 | BV38: 0 | BW38: =IF(BV38<2700,BV38*0.0101,IF(BV38<3200,BV38*0.01135,IF(BV38<3700,BV38*0.0126,IF(BV38>3699,BV38*0.01385,"")))) -> 0 | BX38: 18 | BY38: 0 | BZ38: =IF(BY38<2700,BY38*0.0101,IF(BY38<3200,BY38*0.01135,IF(BY38<3700,BY38*0.0126,IF(BY38>3699,BY38*0.01385,"")))) -> 0 | CA38: 18 | CB38: 0 | CC38: =IF(CB38<2700,CB38*0.0101,IF(CB38<3200,CB38*0.01135,IF(CB38<3700,CB38*0.0126,IF(CB38>3699,CB38*0.01385,"")))) -> 0 | CD38: 10 | CE38: 4419.3769 | CF38: =IF(CE38<2700,CE38*0.0075,IF(CE38<3200,CE38*0.009,IF(CE38<3700,CE38*0.0101,IF(CE38>3699,CE38*0.01135,"")))) -> 50.159928 | CH38: 0 | CI38: =IF(CH38<2700,CH38*0.0101,IF(CH38<3200,CH38*0.01135,IF(CH38<3700,CH38*0.0126,IF(CH38>3699,CH38*0.01385,"")))) -> 0 | CJ38: 18 | CK38: 0 | CL38: =IF(CK38<2700,CK38*0.0101,IF(CK38<3200,CK38*0.01135,IF(CK38<3700,CK38*0.0126,IF(CK38>3699,CK38*0.01385,"")))) -> 0 | CM38: 18 | CN38: 0 | CO38: =IF(CN38<2700,CN38*0.0101,IF(CN38<3200,CN38*0.01135,IF(CN38<3700,CN38*0.0126,IF(CN38>3699,CN38*0.01385,"")))) -> 0 | CQ38: 0 | CR38: =IF(CQ38<2700,CQ38*0.0101,IF(CQ38<3200,CQ38*0.01135,IF(CQ38<3700,CQ38*0.0126,IF(CQ38>3699,CQ38*0.01385,"")))) -> 0 | CT38: =BG38+BJ38+BM38+BP38+BS38+BV38+BY38+CB38+CH38+CK38+CN38+CQ38+CE38 -> 12094.07 | CU38: =BH38+BK38+BN38+BQ38+BT38+BW38+BZ38+CC38+CI38+CL38+CO38+CR38+CF38 -> 137.2677 | CV38: =+BI38+BL38+BO38+BR38+BU38+BX38+CA38+CD38+CG38+CJ38+CM38+CP38+CS38 -> 112 | CX38: =+CU38+CV38-CW38 -> 249.2677 | CY38: =+BB38+CT38 -> 48978.332 | CZ38: =+BC38+CU38 -> 528.39529 | DA38: =+BD38+CV38 -> 172.30673 | DB38: =+CZ38+DA38 -> 700.70202
A39: =+A38+1 -> 30 | B39: NAPA CEVALLOS FRIXON ARIEL | C39: SIERRA 10 | D39: 0994471277 | E39: napaariel140@gmail.com | F39: 3383.6382 | G39: =IF(F39<2700,F39*0.0085,IF(F39<3200,F39*0.01,IF(F39<3700,F39*0.0105,IF(F39>3699,F39*0.01175,"")))) -> 35.528201 | I39: 2919.0754 | J39: =IF(I39<2700,I39*0.0085,IF(I39<3200,I39*0.01,IF(I39<3700,I39*0.0105,IF(I39>3699,I39*0.01175,"")))) -> 29.190754 | L39: 3692.8643 | M39: =IF(L39<2700,L39*0.0085,IF(L39<3200,L39*0.01,IF(L39<3700,L39*0.0105,IF(L39>3699,L39*0.01175,"")))) -> 38.775075 | P39: =IF(O39<2700,O39*0.0105,IF(O39<3200,O39*0.01175,IF(O39<3700,O39*0.013,IF(O39>3699,O39*0.01425,"")))) -> 0 | R39: 3653.3065 | S39: =IF(R39<2700,R39*0.0085,IF(R39<3200,R39*0.01,IF(R39<3700,R39*0.0105,IF(R39>3699,R39*0.01175,"")))) -> 38.359719 | U39: 0 | V39: =IF(U39<2700,U39*0.01,IF(U39<3200,U39*0.0105,IF(U39<3700,U39*0.01175,IF(U39>3699,U39*0.013,"")))) -> 0 | W39: 20 | X39: 0 | Y39: =IF(X39<2700,X39*0.01,IF(X39<3200,X39*0.0105,IF(X39<3700,X39*0.01175,IF(X39>3699,X39*0.013,"")))) -> 0 | Z39: 20 | AA39: 0 | AB39: =IF(AA39<2700,AA39*0.01,IF(AA39<3200,AA39*0.0105,IF(AA39<3700,AA39*0.01175,IF(AA39>3699,AA39*0.013,"")))) -> 0 | AC39: 18 | AD39: 0 | AE39: =IF(AD39<2700,AD39*0.01,IF(AD39<3200,AD39*0.0105,IF(AD39<3700,AD39*0.01175,IF(AD39>3699,AD39*0.013,"")))) -> 0 | AF39: 18 | AG39: 0 | AH39: =IF(AG39<2700,AG39*0.0105,IF(AG39<3200,AG39*0.01175,IF(AG39<3700,AG39*0.013,IF(AG39>3699,AG39*0.01425,"")))) -> 0 | AI39: 18 | AJ39: 0 | AK39: =IF(AJ39<2700,AJ39*0.01,IF(AJ39<3200,AJ39*0.0105,IF(AJ39<3700,AJ39*0.01175,IF(AJ39>3699,AJ39*0.013,"")))) -> 0 | AL39: 18 | AM39: 0 | AN39: =IF(AM39<2700,AM39*0.01,IF(AM39<3200,AM39*0.0105,IF(AM39<3700,AM39*0.01175,IF(AM39>3699,AM39*0.013,"")))) -> 0 | AO39: 18 | AP39: 0 | AQ39: =IF(AP39<2700,AP39*0.0105,IF(AP39<3200,AP39*0.01175,IF(AP39<3700,AP39*0.013,IF(AP39>3699,AP39*0.01425,"")))) -> 0 | AR39: 18 | AS39: 3106.7337 | AT39: =IF(AS39<2700,AS39*0.0085,IF(AS39<3200,AS39*0.01,IF(AS39<3700,AS39*0.0105,IF(AS39>3699,AS39*0.01175,"")))) -> 31.067337 | AW39: =IF(AV39<2700,AV39*0.0105,IF(AV39<3200,AV39*0.01175,IF(AV39<3700,AV39*0.013,IF(AV39>3699,AV39*0.01425,"")))) -> 0 | AZ39: =IF(AY39<2700,AY39*0.0105,IF(AY39<3200,AY39*0.01175,IF(AY39<3700,AY39*0.013,IF(AY39>3699,AY39*0.01425,"")))) -> 0 | BB39: =+F39+I39+L39+O39+R39+U39+X39+AA39+AD39+AG39+AJ39+AM39+AP39+AS39+AV39+AY39 -> 16755.618 | BC39: =+G39+J39+M39+P39+S39+V39+Y39+AB39+AE39+AH39+AK39+AN39+AQ39+AT39+AW39+AZ39 -> 172.92109 | BD39: =+H39+K39+N39+Q39+T39+W39+Z39+AC39+AF39+AI39+AL39+AO39+AR39+AU39+AX39+BA39 -> 148 | BF39: =+BC39+BD39-BE39 -> 320.92109 | BG39: 3482.0503 | BH39: =IF(BG39<2700,BG39*0.0085,IF(BG39<3200,BG39*0.01,IF(BG39<3700,BG39*0.0105,IF(BG39>3699,BG39*0.01175,"")))) -> 36.561528 | BJ39: 0 | BK39: =IF(BJ39<2700,BJ39*0.0105,IF(BJ39<3200,BJ39*0.01175,IF(BJ39<3700,BJ39*0.013,IF(BJ39>3699,BJ39*0.01425,"")))) -> 0 | BL39: 0 | BM39: 2514.3317 | BN39: =IF(BM39<2700,BM39*0.0085,IF(BM39<3200,BM39*0.01,IF(BM39<3700,BM39*0.0105,IF(BM39>3699,BM39*0.01175,"")))) -> 21.371819 | BP39: 0 | BQ39: =IF(BP39<2700,BP39*0.0105,IF(BP39<3200,BP39*0.01175,IF(BP39<3700,BP39*0.013,IF(BP39>3699,BP39*0.01425,"")))) -> 0 | BR39: 18 | BS39: 0 | BT39: =IF(BS39<2700,BS39*0.0105,IF(BS39<3200,BS39*0.01175,IF(BS39<3700,BS39*0.013,IF(BS39>3699,BS39*0.01425,"")))) -> 0 | BU39: 18 | BV39: 0 | BW39: =IF(BV39<2700,BV39*0.0105,IF(BV39<3200,BV39*0.01175,IF(BV39<3700,BV39*0.013,IF(BV39>3699,BV39*0.01425,"")))) -> 0 | BX39: 18 | BY39: 0 | BZ39: =IF(BY39<2700,BY39*0.0105,IF(BY39<3200,BY39*0.01175,IF(BY39<3700,BY39*0.013,IF(BY39>3699,BY39*0.01425,"")))) -> 0 | CA39: 18 | CB39: 0 | CC39: =IF(CB39<2700,CB39*0.0105,IF(CB39<3200,CB39*0.01175,IF(CB39<3700,CB39*0.013,IF(CB39>3699,CB39*0.01425,"")))) -> 0 | CD39: 0 | CE39: 0 | CF39: =IF(CE39<2700,CE39*0.0105,IF(CE39<3200,CE39*0.01175,IF(CE39<3700,CE39*0.013,IF(CE39>3699,CE39*0.01425,"")))) -> 0 | CG39: 18 | CH39: 0 | CI39: =IF(CH39<2700,CH39*0.0105,IF(CH39<3200,CH39*0.01175,IF(CH39<3700,CH39*0.013,IF(CH39>3699,CH39*0.01425,"")))) -> 0 | CJ39: 0 | CK39: 0 | CL39: =IF(CK39<2700,CK39*0.0105,IF(CK39<3200,CK39*0.01175,IF(CK39<3700,CK39*0.013,IF(CK39>3699,CK39*0.01425,"")))) -> 0 | CN39: 0 | CO39: =IF(CN39<2700,CN39*0.0105,IF(CN39<3200,CN39*0.01175,IF(CN39<3700,CN39*0.013,IF(CN39>3699,CN39*0.01425,"")))) -> 0 | CQ39: 0 | CR39: =IF(CQ39<2700,CQ39*0.0105,IF(CQ39<3200,CQ39*0.01175,IF(CQ39<3700,CQ39*0.013,IF(CQ39>3699,CQ39*0.01425,"")))) -> 0 | CT39: =BG39+BJ39+BM39+BP39+BS39+BV39+BY39+CB39+CH39+CK39+CN39+CQ39+CE39 -> 5996.3819 | CU39: =BH39+BK39+BN39+BQ39+BT39+BW39+BZ39+CC39+CI39+CL39+CO39+CR39+CF39 -> 57.933347 | CV39: =+BI39+BL39+BO39+BR39+BU39+BX39+CA39+CD39+CG39+CJ39+CM39+CP39+CS39 -> 90 | CX39: =+CU39+CV39-CW39 -> 147.93335 | CY39: =+BB39+CT39 -> 22752 | CZ39: =+BC39+CU39 -> 230.85443 | DA39: =+BD39+CV39 -> 238 | DB39: =+CZ39+DA39 -> 468.85443
